Workbook

Sheet README
A1: TITLE | B1: Conservation agriculture meta-analysis - NEW data extraction workbook (structure of META_ANALYSIS_MASTER updated 53, no previous data)
A2: NEW SERIES | B2: Started 2026-10-05. All data rows of the old master were removed at the author's request; serials continue from the old master, starting at 164, so the two files can be merged. The history entries further down describe the OLD master (updated 53) and are kept only as the rulebook.
A3: PARTIAL CA COLUMNS | B3: Every parameter sheet has <prefix>pCA, pZT, pMT, pMTR (olive-green headers) after <prefix>DTR: puddled / conventional rice + ZT wheat with residue (pCA) / without residue (pZT), + MT wheat without (pMT) / with residue (pMTR). See Codes and RULES.
A4: LAT_LONG | B4: One row per study x site: coordinates as reported and in decimal degrees, source (paper / Google Maps), climate class.
A6: HOW TO USE | B6: Upload ONE research paper at a time. Data are extracted and appended to the relevant parameter sheets only. Sheets for parameters absent from a paper are left untouched.
A8: SHEET TYPES
A9: Study_Info | B9: One row per study x site. Master record of coordinates, climate, initial soil properties, management. Fill this FIRST for every new paper.
A10: Treatment_Mapping | B10: Log of every treatment in every paper and the code it was assigned. Any treatment that is unclear is logged here with status NEEDS CONFIRMATION and left out of the data sheets.
A11: Codes | B11: Treatment codes + all reclassification rules (climate, texture, duration, depth).
A12: Parameter sheets | B12: One sheet per measured parameter (BD, SOC, MWD, PR, YIELD, ...). Unit for each sheet is written in the orange note to the right of the header row AND in the UNIT column.
A14: COLUMN COLOUR KEY
A15: Dark blue | B15: Study identification
A16: Teal | B16: Soil depth (reclassified + as reported)
A17: Green | B17: Treatment mean values
A18: Amber | B18: Obs / Rep / SD
A19: Grey | B19: Site covariates (climate, initial soil)
A20: Purple | B20: Unit, treatment mapping, management, data source, notes
A22: RULES APPLIED
A23: Rep | B23: Always 3 unless the paper clearly states otherwise.
A24: Obs | B24: Number of paper-level data points collapsed into that row for that depth class: years x sub-treatments x original depths falling in the class. e.g. 3 years x 1 depth = 3; 3 years x 2 original depths in the same class x 2 qualifying treatments = 12.
A25: SD | B25: SD = SQRT(2*Obs/Rep) - the formula used in the original workbook. Written as a live formula so it updates if Obs changes. Overwritten with the real value when the paper reports SD (or SE, converted as SD = SE*sqrt(Rep)).
A26: Season | B26: Soil parameters are taken from the WHEAT season, not the rice season.
A27: Coordinates | B27: Decimal degrees. Taken from the paper; if absent, looked up from the stated location and flagged in Notes.
A28: Figures | B28: Values read off figures are digitised (WebPlotDigitizer style) and marked 'Figure' in Data source.
A29: Supplementary | B29: Supplementary files are searched for online and extracted; marked 'Supplementary' in Data source.
A30: Multi-year / multi-site | B30: Every year and every site is entered - separate rows, Site/Location and YEAR OF DATA distinguish them.
A31: Doubtful treatments | B31: Left blank in the data sheets and raised with you; logged in Treatment_Mapping.
A32: Porosity | B32: Where a paper reports total porosity it is entered as printed (studies 5 and 11). Everywhere else it is DERIVED as porosity (%) = (1 - BD / PD) x 100, using the TREATMENT bulk density from the BD sheet - as a live cross-sheet formula, so correcting a bulk density corrects the porosity - and PD = 2.65 Mg/m3, since no study with bulk-density data reports its own particle density. That default reproduces both measured porosities in this workbook to within 0.1 percentage points. Derived rows say DERIVED in Data source; replace 2.65 in the formulas to change the assumption.
A33: EXAMPLE ROW (BD sheet) | B33: Do not keep this in the data sheets - shown here only as a format guide.
A35: No. | B35: SERIAL NO | C35: Authors | D35: Year | E35: Journal | F35: Country | G35: Site/Location | H35: latitude | I35: longitude | J35: CLIMATE | K35: year of data collection/experiment | L35: DURATION | M35: SOIL | N35: DEPTH | O35: DEPTH (as reported in paper) | P35: BD_CA | Q35: BD_CT | R35: BD_ZT | S35: Obs | T35: Rep | U35: SD | V35: CLAY | W35: RAIN FALL | X35: ph (initial) | Y35: UNIT | Z35: Treatment mapping (paper's name -> code) | AA35: Data source
A36: 1 | B36: 1 | C36: Roy D. et al. | D36: 2021 | E36: Geoderma | F36: India | G36: Karnal, Haryana | H36: 29.42 | I36: 76.57 | J36: ST | K36: 10 | L36: 4-10 Y | M36: LOAMY | N36: 0-15 CM | O36: 0-5 + 5-15 cm pooled | P36: 1.39 | Q36: 1.5 | R36: 1.44 | S36: 2 | T36: 3 | U36: SD = SQRT(2*Obs/Rep) (live formula in the data sheets) | V36: 19.89 | W36: 670 | X36: 8 | Y36: Mg/m3 | Z36: ZT+R (ZTW with full residue) -> CA; CTW no residue -> CT; ZTW no residue -> ZT | AA36: Table 3
A38: SHEET SET | B38: Sheets are added only when you ask for them. Six were added on 2026-10-01 at your request: WSC, LFC-LFOC, LFON, PON, cPOM-C and fPOM-C - each carries its full form in the purple note to the right of its header row. For any OTHER parameter this workbook does not carry, values are kept in the Notes/Doubts column of the closest existing sheet. Those still parked in notes are listed below.
A39: SOC(active C pool) | B39: Soil organic carbon as the papers report it - in most papers simply "SOC" or "organic carbon", measured by Walkley-Black wet oxidation, i.e. the oxidisable / labile fraction rather than total carbon. ALL studies that report treatment-level SOC go on this sheet. Total carbon by dry combustion goes on TC(total c); inorganic carbon on SIC.
A40: ACTIVE C-MACRO / MICRO | B40: Active carbon pool associated with macroaggregates (>0.25 mm) and microaggregates (<0.25 mm), g/kg - these live on the macro c and micro c sheets, no separate sheets.
A41: Still parked in Notes | B41: DOC (dissolved organic carbon), KMnO4-oxidisable carbon, the Chan et al. very-labile / labile / less-labile / non-labile pools P1-P4, cumulative CO2-C, sorptivity, cumulative infiltration, stratification ratios, energy-budget terms, and the 0-90 cm carbon stocks of study 25. Say the word and any of these becomes a sheet.
A45: Derived-value rule | B45: Anything computed rather than printed carries its formula and inputs in the Notes column and names its Data source as DERIVED.
A46: ROOT sheets (added 2026-10-03) | B46: On author instruction, root parameters of rice and wheat are entered as DENSITIES plus diameter: RLD(CM-CM3), RVD(cm3-cm3), RMD(mg-cm3) and two new sheets RSD(cm2-cm3) (root surface area density) and ROOT DIA(mm) (average root diameter). Per-sample root values are converted with the sampled soil volume (formula and assumption in Notes). _W = wheat, _R = rice columns.
A47: New sheets (updated 8, 2026-10-03) | B47: Carbon/soil sheets added for Gupta et al. 2022 (study 75 companion) and Kahlon 2014 (study 74): POXC(KMnO4-C) mg/kg; the Chan et al. (2001) oxidisable C fractions VLC(Cfrac1), LC(Cfrac2), LLC(Cfrac3), NLC(Cfrac4) g/kg (VLC + LC + LLC + NLC = TOC); Fungal count and Cellulolytic count (CFU/g, multiplier in UNIT); Moisture storage (mm, soil-profile water storage). Same column layout as every parameter sheet.
A48: IR sheet (2026-10-03) | B48: IR_ columns = STEADY-STATE infiltration rate; IIR_ columns = INITIAL infiltration rate (both cm/hr). Final, basic and quasi-steady rates go in IR_; the first-reading rate goes in IIR_.
A49: FORMULAS sheet + NET RETURN sheet (2026-10-04) | B49: Every derivation used in the workbook is listed on the FORMULAS sheet (straw = biomass - grain, HI = grain / biomass, CL/LI/CPI/CMI, GHGI = GWP / grain, porosity, SD, unit conversions). NET RETURN sheet = net return per ha in the printed currency (W / R / SYS groups, as BC ratio). DERIVED rows reference their source cells with live formulas and say so in Data source.
A50: Soil-water sheets (2026-10-04) | B50: GWC (gravimetric water content), AWC (weight basis), AWC (volume basis), WHC (Keen box only), FC (weight basis), PWP (weight basis). See Codes and FORMULAS.
A51: Soil-water re-check (2026-10-05) | B51: All previous studies re-checked against Methods; WATER-QUANTITY CHECK notes added; new rows: GWC studies 11 (Table 3), 12 (Fig. 4), 18 (Fig. 6), 62 (Fig. 2); FC / PWP / AWC study 9 (Figs 3-6).
A52: Batch ext\221-225 (2026-10-05) | B52: 102 (companion 3) Yu 2026; 129 (companion) Guo 2026 yields; 134 Rana 2023 (rice, red); 136 Hou 2026 (W0); 28 (companion) re-submission; 133 Yan 2018 and 135 Li 2026 excluded.
... A58: Batch 111-113 (2026-10-05) | B58: Files 112.pdf, 113_rqal.pdf, 113.pdf, 111_real.pdf, 112_real.pdf -> serials 164 Yadav 2000 (7 sites; 100F CT vs 50F+CR CTR flagged; year-wise yields digitised from Fig. 2), 165 Davari 2012 (organic RW / RWM; RR CT vs RI CTR), 166 Das 2014 (T2 CT vs T8 CTR flagged), 167 Naz 2023 EXCLUDED (rice-berseem GM trial), 168 Dhaliwal 2020 (CT/CTR/ZT/CA; rice-season red rows). No supplementary files found. Digitisation scripts and outputs in the repo folder digitised/.

Sheet RULES
A1: RULES - consolidated extraction, coding and analysis rules of this workbook (author-confirmed unless marked). Updated 2026-10-05
A3: No. | B3: Category | C3: Rule | D3: Details / worked examples | E3: Source / date | F3: Status
A4: WORKFLOW & DATA MANAGEMENT
A5: 1 | B5: Workflow & data management | C5: Existing entries are correct and are not recalculated or 'fixed'. | D5: New rules apply to new papers. Earlier rows are changed only when the author asks (e.g. an entry shown to be wrong against its source: study 59 in updated 17; rotary-rule recoding in updated 47). | E5: Author 2026-10-03 | F5: IN FORCE
A6: 2 | B6: Workflow & data management | C6: Every batch is saved as a new numbered version (META_ANALYSIS_MASTER updated NN.xlsx); the previous file is never overwritten. | D6: Each build is checked cell-by-cell against the previous version (only intended cells may change, 0 formula errors). | E6: Workbook convention | F6: IN FORCE
A7: 3 | B7: Workflow & data management | C7: Ask the author whenever in doubt. | D7: Unclear treatments are left out of the data sheets and raised with the author; doubts are written in Notes/Doubts. | E7: Author | F7: IN FORCE
A8: 4 | B8: Workflow & data management | C8: Fill Study_Info first; log EVERY treatment of every paper in Treatment_Mapping with its code (or EXCLUDED) and rationale; excluded data go to EXCLUDED_rows. | D8: Check Study_Info for duplicates (DOI, title, authors, year) before adding a paper. | E8: Workbook convention | F8: IN FORCE
A9: 5 | B9: Workflow & data management | C9: Same experiment reported in two papers = ONE serial; same site but a different experiment = separate serials. | D9: Different papers of one trial are filed as 'NN (companion)', 'NN (companion 2)' ... | E9: Codes - SAME-EXPERIMENT RULE | F9: IN FORCE
A10: 6 | B10: Workflow & data management | C10: A re-submitted paper that is already in the workbook is entered AGAIN as 'NN (companion)' (duplicate-flagged); the original study is not changed. | D10: Two identical files in the SAME batch: enter once, record the duplicate in EXCLUDED_rows. Same-trial papers reporting the same seasons: keep both, flag duplicate seasons. | E10: Author 2026-10-03 / 2026-10-05 | F10: IN FORCE
A11: 7 | B11: Workflow & data management | C11: Look for supplementary material online for every paper and report what was found (or 'none found' and where searched); extract its data (Data source = 'Supplementary ...'). | D11: Downloading a supplement needs the author's permission. CAPTCHA pages are never bypassed - the file is fetched from the publisher's direct link only after permission, or the author supplies it (Desktop\SUPP DATA). | E11: Author 2026-10-03 | F11: IN FORCE
A12: 8 | B12: Workflow & data management | C12: Extract everything: tables, text AND figures (digitised; approximate values flagged). | D12: End each batch with a list of anything not extracted. Figures: vector paths read exactly where possible, raster figures by calibrated colour digitising. | E12: Author 2026-10-03 | F12: IN FORCE
A13: 9 | B13: Workflow & data management | C13: The author wants MORE data: enter every parameter that has a sheet, even when it must be derived or has a non-standard definition/unit (flagged). | D13: When unsure whether something goes in notes or on a sheet, lean to a sheet. Parameters with NO sheet are not entered unless the author asks for a new sheet (e.g. PLFA not entered). | E13: Author 2026-10-03 / 2026-10-04 | F13: IN FORCE
A14: 10 | B14: Workflow & data management | C14: Every data sheet carries 'Treatment details (from paper)' and 'Method used (from paper)' right after Notes/Doubts. | D14: Treatment details = Study_Info treatments + every Treatment_Mapping line of the study (so treatments can be re-classified). Method = analytical method auto-detected from the paper's Methods with a quoted context (verify). Filled for every new row of every build. | E14: Author 2026-10-05 | F14: IN FORCE
A15: 11 | B15: Workflow & data management | C15: Data source tags: Text / Table n / Figure n (digitised) / Supplementary / Calculated / DERIVED / MODEL OUTPUT / Author-reported. | E15: Codes | F15: IN FORCE
A16: TREATMENT CODES
A17: 12 | B17: Treatment codes | C17: CA = zero tillage + residue; ZT = zero tillage, no residue; CT = conventional tillage, no residue; CTR = conventional + residue; MT = minimum/reduced tillage, no residue; MTR = minimum/reduced + residue; DT = deep tillage, no residue; DTR = deep tillage + residue. | D17: Typical descriptions of each code are on the Codes sheet. | E17: Codes | F17: IN FORCE
A18: 13 | B18: Treatment codes | C18: ROTARY / ROTAVATOR RULE: full-width rotary or rotavator tillage to >=10 cm, OR >=2 full-width passes = CT (CTR with residue), whatever the paper calls it. Rotary <=8 cm, a single-pass rotary till-drill, Super Seeder / Roto Seeder, or strip / zone rotary (only the seed rows tilled) = MT (MTR with residue). | D18: Rotavator = rotary tillage (same rule). 8-10 cm, or depth unstated and not clearly full-width primary tillage -> ask. Applied to old studies in updated 47: 25 T6/T7 -> CT/CTR (row b), 41 Rot+R100 -> MTR (row b), 64 + 64 (companion) RT -> CTR (row b), 69 AR -> CT (study excluded, no contrast), 74 RT -> CTR, 82 rotavator -> CT/CTR (row a, depth not stated - flag). | E18: Author 2026-10-05 | F18: IN FORCE
A19: 14 | B19: Treatment codes | C19: Deep tillage: ploughing / chiselling / sub-soiling >= 25 cm, or straw buried to 30 cm -> DT (no straw) / DTR (straw). | D19: Studies 9, 65, 108. | E19: Author 2026-10-03 | F19: IN FORCE
A20: 15 | B20: Treatment codes | C20: Bed systems: permanent beds + residue -> CA; permanent beds without residue -> ZT; freshly made beds each season -> MT; VMP beds re-formed + non-puddled transplanting -> MTR. | E20: Codes; author 2026-10-04 | F20: IN FORCE
A21: 16 | B21: Treatment codes | C21: Strip tillage, zone-disc tiller or strip drill + residue -> MTR, even when the paper calls it CA. | D21: Studies 124, 125, 127. | E21: Author 2026-10-03 / 2026-10-04 | F21: IN FORCE
A22: 17 | B22: Treatment codes | C22: Shallow rotary 3-5 cm stubble breaking + surface straw -> MTR; shallow rotary 6-7 cm + straw mulch -> MTR. | D22: Guo 2026 'NT' (129 companion); Kong 121 STS. | E22: Author 2026-10-04 / 2026-10-05 | F22: IN FORCE
A23: 18 | B23: Treatment codes | C23: Low residue (about 20 % stubble, farmer practice) counts as residue -> CTR / MTR. | D23: Rows pair like residue levels (as study 40). | E23: Author 2026-10-04 | F23: IN FORCE
A24: 19 | B24: Treatment codes | C24: Tillage ~25 cm with a 'conventional tiller' + straw -> CT / CTR; PTOS (power-tiller-operated seeder, full tillage) -> CTR. | E24: Author 2026-10-04 / 2026-10-05 | F24: IN FORCE
A25: 20 | B25: Treatment codes | C25: Several of the paper's treatments under ONE code -> one row per treatment (rows a, b, c ...), the other codes repeated in each row. | D25: Obs adds T = number of treatments under that code (see Statistics). | E25: Author 2026-10-03 | F25: IN FORCE
A26: 21 | B26: Treatment codes | C26: Inclusion threshold: a study is included if it yields ANY TWO usable codes; a CT reference is not required. | D26: A study left with one code after the rotation rule contributes nothing (e.g. study 69 after the rotary rule). | E26: Codes - INCLUSION THRESHOLD | F26: IN FORCE
A27: ROTATION MATCHING (RICE + WHEAT PHASES)
A28: 22 | B28: Rotation matching (rice + wheat phases) | C28: Rice tillage stated: the rice and wheat phases of a treatment must be the SAME type of tillage; a mismatched treatment is EXCLUDED, in either direction. | D28: Excluded: no-till rice + conventional wheat (RNT-WCT); puddled rice + ZT / bed wheat; alternate tillage. Logged in Treatment_Mapping as EXCLUDED. | E28: Codes - STANDING RULE 1 | F28: IN FORCE
A29: 23 | B29: Rotation matching (rice + wheat phases) | C29: Rice tillage NOT stated: classify on the wheat-phase tillage alone (do not assume a puddled rice phase). | D29: Studies 9, 11, 12, 41. | E29: Codes - STANDING RULE 2 | F29: IN FORCE
A30: 24 | B30: Rotation matching (rice + wheat phases) | C30: Author exceptions: puddled rice + conservation wheat INCLUDED and flagged 'PUDDLED RICE PHASE'. | D30: Kahlon 2014 (74), 34 (companion), Yangzhou group 126-128, 130, 132 - filter on the flag for sensitivity analysis. | E30: Author 2026-10-03 / 2026-10-04 | F30: IN FORCE
A31: 25 | B31: Rotation matching (rice + wheat phases) | C31: Tilled UNPUDDLED rice (dry tillage, transplanted or direct-seeded) + ZT wheat: without residue -> ZT, with residue -> CA (flagged). | D31: UPTR-ZTW, MTR/DSR-ZTW, CT-DDSR fb ZT -> ZT; study 29 family T6 -> CA. Puddled / wet-tilled rice + ZTW stays a mismatch. | E31: Author 2026-10-03 / 2026-10-04 | F31: IN FORCE
A32: 26 | B32: Rotation matching (rice + wheat phases) | C32: Zero-till DSR + one-pass rotary till-drill wheat -> MT; tilled DSR + reduced-till wheat -> MT (+ residue -> MTR). | D32: Studies 76, 79, 113. | E32: Author 2026-10-03 / 2026-10-04 | F32: IN FORCE
A33: 27 | B33: Rotation matching (rice + wheat phases) | C33: Unpuddled (aerobic) rice = reduced tillage -> MT. | D33: Study 69 AR. Superseded on 2026-10-05: AR land preparation was disc plough + rotavator = CT under the rotary rule, so study 69 is excluded (rows in EXCLUDED_rows). | E33: Author 2026-10-03 | F33: SUPERSEDED (rotary rule)
A34: 28 | B34: Rotation matching (rice + wheat phases) | C34: Puddled drum-seeded rice + CT wheat -> CT; SRI fb SWI -> CT; SRI-SWI with a different nutrient regime is excluded when a proper CT exists; CT dry-seeded unpuddled rice + CT wheat -> CT / CTR (flagged). | E34: Author 2026-10-03 / 2026-10-04 | F34: IN FORCE
A35: 29 | B35: Rotation matching (rice + wheat phases) | C35: When papers of one trial disagree on puddling, follow the main paper. | D35: Mishra Table 1 used over Saurabh for study 29 T3. | E35: Author 2026-10-04 | F35: IN FORCE
A36: CROPPING SYSTEM & DESIGN
A37: 30 | B37: Cropping system & design | C37: Third crop grown in EVERY treatment -> included; added in some treatments only -> those treatments excluded; with a mixed rotation history -> include flagged. | D37: When a third crop is present only in some treatments, use the treatment with the same rotation as the CT reference (Chaki CS1 vs CS2/CS3). | E37: Codes; author 2026-10-04 | F37: IN FORCE
A38: 31 | B38: Cropping system & design | C38: Excluded systems: rice-maize, wheat-maize, soybean-wheat, double rice, rice-only or rice-rice TRIALS. | D38: Exception: a rice-season-only paper from a genuine rice-wheat CA trial -> red rice rows (Rana 2023, Bazaya 2009). | E38: Author 2026-10-03 / 2026-10-05 | F38: IN FORCE
A39: 32 | B39: Cropping system & design | C39: Factorial / split-plot papers: use the interaction (cell) means; papers with only marginal / mixed-rotation means -> excluded, values in notes. | D39: Tripathi 2007 (72). | E39: Codes | F39: IN FORCE
A40: 33 | B40: Cropping system & design | C40: Non-tillage factors (N dose, irrigation, nutrient source, variety, density, rotation ...) crossed with tillage -> one row per factor level (cell means), level named in Notes and 'Fertilizer dose & other management'. | D40: Only if no cell means are printed, the main-effect mean is used and flagged. From serial 76 onward (not retroactive). Main-effect means pooled over residue -> entered flagged. | E40: Author 2026-10-03 / 2026-10-04 | F40: IN FORCE
A41: 34 | B41: Cropping system & design | C41: Amendments and confounded treatments are excluded: biochar, compost added, INM / nutrient-management trials with identical tillage, unfertilised control or undefined farmer practice when a fertilised tier exists, rotation treatments. | D41: Artificial warming: ambient (W0) rows only, warmed rows in notes. Rhizosphere devices / simulated tillage soil excluded. | E41: Author 2026-10-03 / 2026-10-05 | F41: IN FORCE
A42: SEASONS, YEARS & ROWS
A43: 35 | B43: Seasons, years & rows | C43: Wheat season is the default for soil parameters. | D43: Rice-season soil values that duplicate a wheat-season parameter -> Notes only. | E43: Codes | F43: IN FORCE
A44: 36 | B44: Seasons, years & rows | C44: Rice-season fallback: a parameter reported ONLY for the rice season is entered with the WHOLE ROW in RED and 'RICE SEASON' at the start of 'Crop/season of sampling'. | D44: Filter on font colour or that column to include / exclude. | E44: Codes - RICE-SEASON FALLBACK | F44: IN FORCE
A45: 37 | B45: Seasons, years & rows | C45: Year-wise data always: every year a paper gives (table or figure) is a separate row; the multi-year mean goes to Notes. | D45: From study 101 onward. | E45: Author 2026-10-03 | F45: IN FORCE
A46: 38 | B46: Seasons, years & rows | C46: Soil sampled at several crop stages in one season -> one row per stage (stage in 'Crop/season of sampling'). | E46: Author 2026-10-03 | F46: IN FORCE
A47: 39 | B47: Seasons, years & rows | C47: Box plots: not entered by default; box-plot means entered when the author asks or when they are the only data for a parameter (flagged). | D47: Studies 101, 388. | E47: Author 2026-10-03 | F47: IN FORCE
A48: SITE CLASSIFICATION
A49: 40 | B49: Site classification | C49: Climate: latitude > 30 deg -> TEMP; <= 30 deg -> ST. | D49: Pittelkow et al. 2015; Mondal et al. 2018. | E49: Codes | F49: IN FORCE
A50: 41 | B50: Site classification | C50: Texture: SCL, SiCL, CL, Si, SiL, L, SL -> LOAMY; LS, S -> SANDY; SC, SiC, C -> CLAYEY; class not stated -> USDA triangle from sand/silt/clay. | D50: Shirazi et al. 2001. | E50: Codes | F50: IN FORCE
A51: 42 | B51: Site classification | C51: Duration: 0-3 Y / 4-10 Y / >10 Y = years since the trial was established at sampling. | E51: Codes | F51: IN FORCE
A52: 43 | B52: Site classification | C52: Depth classes 0-15 / 15-30 / 30-45 / 45-60 / >60 CM by maximum overlap: 0-10 -> 0-15; 10-20 and 20-30 -> 15-30 (separate rows, D=2); 20-40 -> 30-45; 0-30 -> 0-15; 30-60 -> 30-45; 60-90 -> >60. | D52: Penetration resistance: 0-10 ... 50-60 CM classes. C stock / sequestration: cumulative 0-10, 0-20 ... 0-60 CM (0-15 -> 0-20, 0-45 -> 0-50). | E52: Codes; author 2026-10-03 | F52: IN FORCE
A53: STATISTICS (OBS, REP, SD)
A54: 44 | B54: Statistics (Obs, Rep, SD) | C54: Rep = 3 unless the paper states a different number of replications. | E54: Codes | F54: IN FORCE
A55: 45 | B55: Statistics (Obs, Rep, SD) | C55: Obs (new papers) = additive per row: Y (years in that row's mean) + T (paper treatments under one code) + D (depths inside the depth class); a factor equal to 1 adds nothing; minimum 1. | D55: 3 years -> 3; 2 treatments -> 2; 3 depths -> 3; all three -> 8. No-depth parameters (yield, WUE, uptake, GHG): D = 0. Row-b recoding adds T=2 to rows a and b. | E55: Author 2026-10-03 | F55: IN FORCE
A56: 46 | B56: Statistics (Obs, Rep, SD) | C56: SD = workbook formula SQRT(2*Obs/Rep) when the paper gives no SD/SE; a reported SD (or SE x SQRT(Rep)) replaces it. | D56: Paper-reported SD kept in Notes when the single SD column keeps the formula. | E56: Codes; author 2026-10-03 | F56: IN FORCE
A57: PARAMETER-SPECIFIC
A58: 47 | B58: Parameter-specific | C58: Carbon: oxidisable / labile organic C as most papers report it (SOC, Walkley-Black, OM/1.724) -> 'SOC (active C pool)' in g/kg; TOC = labile + non-labile or C by dry combustion. | D58: Every paper's SOC must appear on one concentration sheet (derive from content/stock with BD, flagged). | E58: Author 2026-10-03 | F58: IN FORCE
A59: 48 | B59: Parameter-specific | C59: SOC stock = SOC (g/kg) x BD x thickness (cm) x 0.1, cumulative from the surface, live cross-sheet formulas; sequestration rate = (treatment stock - initial stock) / years from the same initial SOC x initial BD. | D59: Only where SOC and treatment BD share a layer; do not duplicate printed stocks; skipped when the baseline is implausible. | E59: Author 2026-10-03 | F59: IN FORCE
A60: 49 | B60: Parameter-specific | C60: Soil water: GWC = gravimetric water content at any instant (v/v / BD); AWC (FC - PWP) on BOTH 'AWC (weight basis)' and 'AWC (volume basis)'; field capacity -> 'FC (weight basis)'; wilting point -> 'PWP (weight basis)'; WHC only for Keen-Raczkowski box; saturated WC -> 'SAT WC'; profile storage (mm) -> 'Moisture storage'. | D60: Each soil-water row carries a 'WATER-QUANTITY CHECK' note from the paper's Methods. BD for conversions: same study/depth/treatment from the BD sheet, else the paper's own layer BD, else 1.35 Mg/m3. Basis not stated -> GWC, flagged. | E60: Author 2026-10-04 / 2026-10-05 | F60: IN FORCE
A61: 50 | B61: Parameter-specific | C61: Infiltration: IR_ = steady-state (final / basic) rate, IIR_ = initial rate, both cm/hr on the IR sheet; cumulative infiltration in Notes. | E61: Author 2026-10-03 | F61: IN FORCE
A62: 51 | B62: Parameter-specific | C62: Roots as densities: RLD (cm/cm3), RVD (cm3/cm3), RMD (mg/cm3), RSD (cm2/cm3); ROOT DIA (mm); per-sample values converted with the sampled soil volume (live formula, assumption in Notes). | E62: Author 2026-10-03 | F62: IN FORCE
A63: 52 | B63: Parameter-specific | C63: Derived values (live formulas, flagged DERIVED): straw = biomass - grain; HI = grain / (grain + straw); GHGI = GWP / (grain t/ha x 1000); CL / LI / CPI / CMI with CT as reference; porosity = (1 - BD/PD) x 100 with PD 2.65 default. | D63: A printed value always wins over a derived one. Every derivation is documented on the FORMULAS sheet. | E63: Author 2026-10-04 | F63: IN FORCE
A64: 53 | B64: Parameter-specific | C64: %-variation tables: treatment value = reference x (1 + VR/100) as a live formula; ratio-only papers: concentration = ratio x SOC (flagged). | D64: Studies 64, 90, 102. | E64: Author default 2026-10-03 | F64: IN FORCE
A65: 54 | B65: Parameter-specific | C65: System values (system / rice-equivalent yield, system B:C, WP, GWP, uptake) go in the SYS columns; flagged if they include a third crop. | D65: The paper's own system value replaces a derived rice + wheat sum. | E65: Author 2026-10-03 | F65: IN FORCE
A66: 55 | B66: Parameter-specific | C66: Model / simulation output (APSIM, DSSAT) IS entered when available or asked for, every row flagged 'MODEL OUTPUT' in Notes and Data source. | D66: Studies 28 (DSSAT Table 6), 78 and 117 (companion) (APSIM). Input-based LCA GWP entered flagged. | E66: Author 2026-10-03 / 2026-10-05 | F66: IN FORCE
A67: 56 | B67: Parameter-specific | C67: Simulated output is not entered. | D67: Original Codes rule. | E67: Codes (old) | F67: SUPERSEDED (model output now entered)
A68: 57 | B68: Parameter-specific | C68: Economics: paper B:C defined as gross/cost is converted to net/cost (B:C - 1); NET RETURN sheet in the printed currency (gross margin and model rows flagged). | E68: Author 2026-10-03 / 2026-10-04 | F68: IN FORCE
A69: 58 | B69: Parameter-specific | C69: Unit conversions: GHG kg CH4 -> kg C (x 12/16), kg N2O -> kg N (x 28/44); P mg/kg x 2.25 -> kg/ha; available N/P/K and NO3 in mg/kg kept as printed when no layer BD; enzyme rates converted to the sheet unit (e.g. per day / 24). | D69: Penetration resistance in non-convertible units (N/cm) entered as printed, flagged. | E69: Workbook practice | F69: IN FORCE
A70: 59 | B70: Parameter-specific | C70: Kept in Notes only (no sheet): soil temperature, crop growth, energy, water footprint, relative water content (% of FC), site-level FC/PWP profiles. | E70: Author 2026-10-03 / 2026-10-05 | F70: IN FORCE
A71: FORMATTING & BUILD
A72: 60 | B72: Formatting & build | C72: Arial 10; Notes/Doubts fill FFF2CC; rice-season rows whole row red; the orange 'UNIT FOR THIS SHEET' note column is never restyled; formulas stay live and their values are cached after every save. | D72: fullCalcOnLoad is set so Excel recalculates on opening. | E72: Workbook convention | F72: IN FORCE
A73: 61 | B73: Formatting & build | C73: Every recoded or added row states what was done at the start of Notes ('RECODED <date> ...', 'ROW b (added <date>) ...', 'DUPLICATE RE-SUBMISSION ...', 'MODEL OUTPUT ...'). | D73: Lets any decision be filtered and reversed. | E73: Workbook convention | F73: IN FORCE
A74: 62 | B74: Cropping system & design | C74: A straw-return treatment whose mineral fertiliser was cut to offset straw nutrients is coded CTR (or MTR / CA by tillage) and FLAGGED. | D74: He et al. 2021 (145) OF+S: rice N 182 vs 225, wheat 189 vs 210 kg/ha. Drop the flagged rows for a fertiliser-matched sensitivity check. | E74: Author 2026-10-05 | F74: IN FORCE
A75: 63 | B75: Parameter-specific | C75: Plant height, glycine aminopeptidase, mycorrhizal spore counts, net GWP (NGWP) and net economic benefit get their own sheets; root length per plant is converted to root length density (assumptions in the formula, flagged). | D75: Sheets PLANT HEIGHT, GAP, MYCORRHIZAL SPORES, NGWP, NET ECONOMIC BENEFIT (first filled from ext\241-250). | E75: Author 2026-10-05 | F75: IN FORCE
A76: 64 | B76: Coding | C76: Permanent raised beds WITH residue retention = CA (flagged) in companion papers even when the main study coded the bed treatment ZT. | D76: 71 (companion), 71 (companion 2) | E76: Author 2026-10-05 | F76: IN FORCE
A77: 65 | B77: Pooled means | C77: Main effects pooled over a factor level that would itself be excluded (e.g. shallow wheat tillage after puddled rice) go to Notes only; enter only rotation-matched cells. | D77: 163 Sarkar & Kar 2011 | E77: Author 2026-10-05 | F77: IN FORCE
A78: 66 | B78: Parameter-specific | C78: Earthworm density and dissolved organic C get their own sheets (EARTHWORM, DOC); DOC printed per litre of extract is entered as printed and flagged. | D78: 156, 161 | E78: Author 2026-10-05 | F78: IN FORCE
A79: NEW WORKBOOK SERIES (2026-10-05)
A80: 67 | B80: Workflow & data management | C80: NEW workbook: built on the updated 53 structure with NO previous data carried over. Serial numbers CONTINUE from the old master: the first new study is 164 (old master ends at 163), so the two files can be merged. Each upload is saved as a new numbered version (META_ANALYSIS_NEW_updated_NN.xlsx). | D80: README, RULES, Codes and FORMULAS are kept as the rulebook; worked examples there cite the OLD master's serials (updated 53), not studies of this workbook. | E80: Author 2026-10-05 | F80: IN FORCE
A81: 68 | B81: Treatment codes | C81: PARTIAL CA CODES: pCA = puddled / conventional rice + ZT wheat WITH residue; pZT = puddled / conventional rice + ZT wheat, residue removed; pMT = puddled / conventional rice + MT wheat, no residue; pMTR = puddled / conventional rice + MT wheat WITH residue. | D81: Every parameter sheet carries <prefix>pCA, pZT, pMT, pMTR right after <prefix>DTR (olive-green headers). These treatments are NO LONGER excluded under the rotation-matching rule (rule 22) and are NOT entered in the CA / ZT / MT / MTR columns; they go to the p-columns. The reverse mismatch (ZT / no-till rice + conventional wheat, RNT-WCT) stays EXCLUDED (author re-confirmed). MT vs MTR for the wheat phase follows the rotary rule (rule 13). | E81: Author 2026-10-05 | F81: IN FORCE
A82: 69 | B82: Treatment codes | C82: Rotary rule restated: full-width rotary to >= 10 cm, or >= 2 full-width passes = CT / CTR whatever the paper calls it; rotary <= 8 cm, single-pass till-drill, Super / Roto Seeder, strip or zone rotary = MT / MTR. | D82: 8-10 cm or depth unstated -> ask the author. | E82: Author 2026-10-05 | F82: IN FORCE
A83: 70 | B83: Treatment codes | C83: Same treatment type in rice and wheat = include (e.g. puddled transplanted rice + CT wheat = CT). Rice tillage not stated -> classify on the wheat tillage alone. | D83: Rules 22-23 unchanged except for the partial-CA codes above. | E83: Author 2026-10-05 | F83: IN FORCE
A84: 71 | B84: Cropping system & design | C84: Green manuring / a third crop (mungbean, Sesbania, etc.) in a rice-wheat system: study included. Green manuring is a SUPPLEMENTARY condition for CA, NOT a necessary one: ZT + residue = CA with or without green manure. | D84: A green manure / third crop grown only in the CA treatment does not exclude that treatment and does not change its code; the crop is named in Notes and 'Fertilizer dose & other management' ('GREEN MANURE'). Green manure never turns a non-CA treatment into CA (e.g. ZT without residue + green manure stays ZT). | E84: Author 2026-10-05 | F84: IN FORCE
A85: 72 | B85: Cropping system & design | C85: Inclusion: any study with ANY TWO of CT, ZT, CA, DT, MT, MTR, CTR, DTR, pCA, pZT, pMT, pMTR is included. Not restricted to South Asia. | D85: Rule 21 extended to the partial-CA codes. | E85: Author 2026-10-05 | F85: IN FORCE
A86: 73 | B86: Parameter-specific | C86: Porosity (%) = (1 - BD / PD) x 100 from the TREATMENT BD (changed BD). PD = the treatment's PD if reported, else the paper's initial PD, else 2.65 Mg/m3 (flagged). | D86: Live formula linking the BD sheet (and PD sheet where used). A printed total porosity is entered as printed. | E86: Author 2026-10-05 | F86: IN FORCE
A87: 74 | B87: Parameter-specific | C87: WSA = sum of ALL water-stable aggregate fractions > 0.053 mm, in g/g of soil (0-1). A printed WSA in % is divided by 100; when the paper gives only the fractions, WSA is their sum (DERIVED, flagged). | D87: The silt + clay fraction (< 0.053 mm) is never included. The old master (updated 53) holds WSA in % - divide by 100 when merging. | E87: Author 2026-10-05 | F87: IN FORCE
A88: 75 | B88: Parameter-specific | C88: Penetration resistance: 10 cm classes 0-10, 10-20, 20-30, 30-40, 40-50, 50-60 CM (and >60 CM) - do NOT stop at 30 cm. C stock and sequestration: cumulative 0-10 ... 0-60 CM. | D88: Rule 43 restated. | E88: Author 2026-10-05 | F88: IN FORCE
A89: 76 | B89: Parameter-specific | C89: SOC (Walkley-Black / 'SOC' / OM/1.724) of every paper goes to SOC(active C pool); every other carbon pool reported (TOC, TC, POXC, PSOC, MOC, WSC, DOC, LFOC, HFOC, Chan fractions, macro/micro-aggregate C, stocks) goes to its own sheet. | D89: Rule 47 restated. | E89: Author 2026-10-05 | F89: IN FORCE
A90: 77 | B90: Parameter-specific | C90: Soil water: AWC (FC - PWP) on BOTH AWC sheets (converted with BD); water content at sampling -> GWC (weight basis; v/v / BD); FC (-33 kPa) -> FC (weight basis); PWP (-1500 kPa) -> PWP (weight basis); Keen box -> WHC; saturated WC -> SAT WC. | D90: Rule 49 restated. | E90: Author 2026-10-05 | F90: IN FORCE
A91: 78 | B91: Treatment codes | C91: INM papers with a crop-residue treatment: 100% NPK (CT) vs reduced NPK + straw substituting the cut N (CTR), FLAGGED under rule 62. | D91: Applied to Yadav 2000 (164: 100F vs 50F+CR, 50% NPK + wheat straw to rice only) and Das 2014 (166: T2 vs T8, 25% N via straw to both crops). FYM / press mud / green manure / unfertilised tiers excluded. | E91: Default 2026-10-05 | F91: PENDING CONFIRMATION
... A96: 83 | B96: Seasons, years & rows | C96: Year-wise yields digitised from multi-site trend figures; where a treatment's panel plots fewer seasons, seasons are paired by matching the series and checked against the printed site means. | D96: Yadav 2000 (164) Fig. 2: Faizabad wheat (12 CR seasons), Jabalpur wheat (12 seasons, one of 1988-89/1989-90 unlabelled), Sabour (one unlabelled season 1993-96). | E96: Default 2026-10-05 (rule 37) | F96: IN FORCE

Sheet Codes
A1: TREATMENT CODES
A2: Code | B2: Meaning | C2: Typical descriptions in papers
A3: CA | B3: Zero tillage + residue retention | C3: ZT+R, ZTW with residue, permanent beds with residue, NT + mulch, CA-based scenario
A4: CT | B4: Conventional tillage, NO residue | C4: CT, farmers practice, puddled transplanted rice - conventional till wheat, residue removed/burnt
A5: ZT | B5: Zero tillage only, no residue | C5: ZT, NT, direct drilled without residue
A6: DT | B6: Deep tillage only, no residue | C6: deep ploughing, sub-soiling, chiselling without residue
A7: MTR | B7: Minimum / reduced tillage WITH residue | C7: RT+R, reduced till (power tiller 2 passes, 0.08-0.10 m) + residue, rotary till drill + residue, reduced puddling + residue, unpuddled harrowing+rotavator + residue
A8: MT | B8: Minimum / reduced tillage only, no residue | C8: RT, reduced till, rotary till drill, reduced puddling, 2 passes power tiller, unpuddled rice without residue
A9: CTR | B9: Conventional tillage WITH residue | C9: CT+R, conventional till with residue incorporated
A10: DTR | B10: Deep tillage WITH residue | C10: deep tillage + residue incorporation
A11: pCA | B11: PARTIAL CA: puddled / conventional-till rice + ZERO-TILL wheat WITH residue retained | C11: PTR-ZTW+R, TPR fb ZTW (Happy Seeder / Turbo Happy Seeder into rice residue), puddled rice + ZT wheat with mulch
A12: pZT | B12: PARTIAL ZT: puddled / conventional-till rice + ZERO-TILL wheat, residue REMOVED / burnt | C12: PTR-ZTW, TPR fb ZTW (no residue), puddled rice + ZT drill wheat
A13: pMT | B13: PARTIAL MT: puddled / conventional-till rice + MINIMUM / REDUCED-till wheat, NO residue | C13: PTR + rotary till-drill / Super Seeder / strip-till wheat (rotary <= 8 cm or single pass), no residue
... A18: NOTE | B18: Unclear treatments | C18: Left out of the data sheets and raised with you.
A20: RECLASSIFICATION
A21: Climate | B21: latitude > 30 deg -> TEMP (temperate) | C21: Pittelkow et al. 2015; Mondal et al. 2018
A22: Climate | B22: latitude <= 30 deg -> ST (sub-tropical)
A23: Texture | B23: Sandy clay loam, silty clay loam, clay loam, silt, silt loam, loam, sandy loam -> LOAMY | C23: Shirazi et al. 2001
A24: Texture | B24: Loamy sand, sand -> SANDY
A25: Texture | B25: Sandy clay, silty clay, clay -> CLAYEY
A26: Texture | B26: Class not stated -> derive from sand/silt/clay using the USDA texture triangle, then reclassify
A27: Duration | B27: 0-3 Y / 4-10 Y / >10 Y | C27: Years since the trial was established at the time of sampling
A28: Depth (general) | B28: 0-15, 15-30, 30-45, 45-60, >60 CM | C28: Reported depth reassigned by MAXIMUM OVERLAP, applied SEQUENTIALLY so consecutive reported layers fall in consecutive classes. Worked rules agreed with author: (a) paper reports 0-20 / 20-40 cm -> 0-20 = 0-15 CM, 20-40 = 15-30 CM. (b) paper reports 0-10 / 10-20 / 20-40 cm -> 0-10 = 0-15 CM, 10-20 = 15-30 CM, 20-40 = 30-45 CM. Original depth always kept in 'DEPTH (as reported in paper)'. If a paper genuinely reports >1 layer inside one class, all are entered and Obs increases.
A29: Depth (PR) | B29: 0-10, 10-20, 20-30, 30-40, 40-50, 50-60 CM | C29: Penetration resistance only
A30: Depth (C stock / sequestration) | B30: 0-10, 0-20, 0-30, 0-40, 0-50, 0-60 CM | C30: Cumulative depths
A32: DATA SOURCE TAGS | B32: Text / Table n / Figure n (digitised) / Supplementary / Calculated / Author-reported
A34: DECISIONS (author-confirmed)
A35: EXCLUDED | B35: No-till rice + conventional-till wheat (RNT-WCT, AT1 type) | C35: Excluded from the meta-analysis entirely. Log in Treatment_Mapping with ASSIGNED CODE = EXCLUDED, Status = EXCLUDED.
A36: SD | B36: SD = SQRT(2*Obs/Rep) | C36: Formula carried over from the original workbook; replaced by the real SD when a paper reports SD or SE (SD = SE*SQRT(Rep)).
A37: Rep | B37: Always 3 | C37: Unless the paper explicitly states a different number of replications.
A38: Season | B38: Wheat season only | C38: Soil parameters measured in the rice season are not entered.
A40: ROTATION-MATCHING RULE
A41: Rule | B41: Within a SINGLE treatment, the rice phase and the wheat phase must be the SAME type of tillage. If one phase is conventional and the other is conservation (or vice versa), that treatment is EXCLUDED. | C41: INCLUDE: puddled transplanted rice + conventional tillage wheat = CT. ZT/unpuddled/DSR rice + ZT wheat, residue in both = CA. ZT rice + ZT wheat, no residue = ZT. EXCLUDE: no-till rice + conventional-till wheat (RNT-WCT). EXCLUDE: conventionally puddled transplanted rice + zero-till wheat. EXCLUDE: conventional-till DSR + reduced-till wheat (CTDSR-RTW).
A42: Consequence | B42: Any treatment with contrasting tillage between the two phases is dropped, in either direction. | C42: Log it in Treatment_Mapping with ASSIGNED CODE = EXCLUDED. If this leaves a study with no CA-vs-CT (or other-vs-CT) pair, the whole study contributes nothing and its rows are moved to EXCLUDED_rows.
A43: Factorial / split-plot papers | B43: Use the INTERACTION (cell) means so the rice and wheat phase are matched, not the marginal means of one factor. | C43: A marginal mean for a wheat treatment is averaged across every rice treatment, so its rice phase is a mixture. If the paper reports only marginal means and no cell means, note it in Notes/Doubts and flag the row.
A45: RULE AMENDMENT - WITHDRAWN
A46: WITHDRAWN | B46: A short-lived amendment exempted wheat-phase-only experiments from the rotation-matching rule. It has been WITHDRAWN at the author's instruction. | C46: The rule applies in full again: the previous crop's tillage counts, and only treatments with the SAME type of treatment in the rice and the wheat phase are included (e.g. puddled transplanted rice + conventional tillage wheat = CT). Reversed for Singh & Singh 2021 (ZT removed again) and Kumar et al. 2012 (all rows moved to EXCLUDED_rows).
A47: IN FORCE | B47: Any treatment whose rice and wheat phases differ in tillage type is excluded, whether or not the contrast was part of the experimental design. | C47: Excludes: no-till rice + conventional-till wheat (RNT-WCT); conventionally puddled rice + zero-till or bed-planted wheat; conventional-till DSR + reduced-till wheat.
A48: CONSISTENT | B48: Sharma et al. 2022 (study 1) stays excluded - its ZTWR0 and ZTWR100 follow a conventionally puddled rice phase. | C48: Its 22 rows remain in EXCLUDED_rows. Consistent with Singh & Singh 2021 ZT, Kumar et al. 2012, Bachchan et al. 2018 and Paliwal et al. TPR-ZTW-ZTS.
A50: RULE REFINEMENT (author instruction)
A51: When the rice phase is NOT described | B51: Classify on the WHEAT-phase tillage alone. Do not assume the preceding rice was conventionally puddled. | C51: Applied to Balwinder-Singh et al. 2011 (study 12): mulch -> CA, non-mulch -> ZT. The rule in full still applies wherever the paper DOES state the rice establishment.
A52: Still excluded | B52: Papers that state a conventional/puddled rice phase alongside conservation wheat. | C52: Sharma et al. 2022 (PTR stated); Paliwal et al. TPR-ZTW-ZTS (transplanted rice stated); Choudhury & Singh 2013 (TPR stated).
A53: OPEN - needs your decision | B53: Two studies already excluded also do NOT describe the rice phase. | C53: Singh & Singh 2021 (study 9) ZT - would return as CA; Kumar et al. 2012 (study 11) ZT and CT - would return the whole study with BD, porosity, Ksat, infiltration, PAWC and penetration resistance. Say the word and I will restore them from EXCLUDED_rows.
A55: STANDING RULE (current)
A56: 1. Rice tillage IS stated | B56: The rice and wheat phases must be the SAME type of tillage within a treatment. | C56: e.g. puddled transplanted rice + conventional tillage wheat = CT. Puddled rice + zero-till wheat = EXCLUDED.
A57: 2. Rice tillage NOT stated | B57: Classify on the WHEAT-phase tillage alone; do not assume a conventional rice phase. | C57: Applied to Balwinder-Singh et al. 2011 (study 12), Singh & Singh 2021 ZT -> CA (study 9) and Kumar et al. 2012 (study 11), all restored.
A58: 3. Still excluded | B58: Studies that explicitly state a conventional/puddled rice phase alongside conservation wheat. | C58: Sharma et al. 2022 (study 1, PTR stated); Paliwal et al. TPR-ZTW-ZTS (study 7); Choudhury & Singh 2013 bed/ZT variants (study 6); Gathala et al. T2 (study 15); Aryal et al. 2015 (study 17).
A60: INCLUSION THRESHOLD (author instruction)
A61: Any TWO codes is enough | B61: A study is included if it yields ANY TWO of CT, ZT, CA, DT, MT, MTR, DTR (and CTR). A conventional-tillage reference is NOT required. | C61: e.g. CA vs ZT (Balwinder-Singh et al. 2011, study 12); CT vs CTR (Bandyopadhyay et al. 2011, study 3; Akwakwa & Wang 2023, study 18); ZT vs CT (Aryal et al. 2015, study 17, brought back in on this rule).
A62: Still excluded on one code | B62: A study left with only ONE usable code after the rotation rule contributes no contrast. | C62: Sharma et al. 2022 (study 1): CTWR0 is rotation-matched CT, but ZTWR0 and ZTWR100 follow an explicitly puddled rice phase and are excluded, leaving one code.
A63: Still excluded for no data | B63: Treatment codes are irrelevant if the paper publishes no values. | C63: Nandipamu et al. 2025 (study 13, energy indices only, though CT/CTR/CA are all matched); Biswas et al. 2024 (study 14, raw values not released); Bachchan et al. 2018 (study 10, data duplicate Kumar et al. 2012); Lou et al. 2024 (study 16, no tillage treatment).
A65: SAME-EXPERIMENT RULE
A66: Two papers, one experiment -> ONE serial | B66: When two papers report the SAME trial, they share a serial number so the experiment is counted once and no pseudo-replication is introduced. Parameters are split between them, never duplicated. | C66: Applied to: Jat H.S. et al. 2022 (Front. Microbiol.) + Jat H.S. et al. 2021 (Eur. J. Soil Biol.) = study 23, CSSRI Karnal scenarios; Choudhury & Singh 2013 + Choudhury, Bouman & Singh 2007 = study 6, IARI New Delhi.
A67: Same site, different experiment -> SEPARATE serials | B67: Trials at the same location and start year but with different designs are separate studies. | C67: Author-confirmed for study 19 (Choudhary K.M. et al. 2018, 8 treatments) and study 24 (Choudhary M. et al. 2018, 14 treatments), both at Taraori, Karnal, both established 2012.
A69: THIRD CROP IN THE ROTATION
A70: Common to every treatment -> IN | B70: A rice-wheat system carrying a third crop is included when that crop is grown in EVERY treatment, because it then does not confound the tillage contrast. The study is flagged in Study_Info and in every row's Notes, and only the rice and wheat figures are entered - system-level figures that bundle the third crop are left out. | C70: Mishra et al. 2021 (study 29): rice-wheat-greengram, zero-till greengram in all seven treatments. Rice and wheat yields, water productivity, BCR and GWP entered; rice-equivalent system yield, system water productivity, system BCR and system GWP left out.
A71: Varies between treatments -> OUT | B71: When the third crop is added to some treatments and not others, rotation is confounded with tillage and those treatments are excluded. | C71: Raj et al. 2023 (study 22): CA4 and CA5 insert zero-till mungbean while CA1-CA3 and CT do not, so both are excluded while the rest of the study is kept.
A73: MODELLED AND LCA-ESTIMATED VALUES
A74: Simulated output -> not entered | B74: Crop-model output is not a measurement and does not go on the data sheets. | C74: Vashisht et al. 2025 (study 28) Table 6: DSSAT CERES-rice and CERES-wheat yields, water balance and water productivity - left out, recorded in the BC ratio notes.
A75: Input-based LCA -> entered, flagged | B75: GWP built from activity data and emission factors includes embedded upstream emissions (fertiliser manufacture, diesel, electricity) that a chamber measurement does not. Entered, but flagged on the row so it is not pooled blind with measured flux. | C75: Mishra et al. 2021 (study 29) Table 8 - fertiliser manufacture alone is 670 of its ~900 kg CO2-eq/ha, against chamber-measured GWP in Hu et al. 2016 (study 26).
A77: RICE-SEASON FALLBACK (author instruction)
A78: Rule | B78: Wheat season stays the default. If a study reports a parameter ONLY for the preceding rice season (no wheat-season value of that parameter in that study), the rice-season value is entered. | C78: Applied only where the wheat-season value is absent - rice-season duplicates of parameters that already have a wheat-season value are still left out.
A79: Formatting | B79: The WHOLE ROW is written in RED text, and Crop/season of sampling starts with "RICE SEASON". | C79: Filter on font colour or on that column to include/exclude these rows in the analysis.
A80: Applied to | B80: Choudhury & Singh 2013 (study 6): rice root weight density at flowering, Fig. 3 -> RMD(mg-cm3), rice columns, 6 rows. | C80: Checked and NOT needed: Suryawanshi 2018 (study 2, kharif BD/N/total N - rabi values present); Choudhury & Singh 2013 BD and Ks (wheat values present); Paliwal 2017 (study 7, after-rice BD and moisture - after-wheat values present); Sanketh 2026 (study 38, rice MBC/FDA - wheat values present).
A82: AUTHOR EXCEPTIONS (updated 8, 2026-10-03)
A83: Kahlon 2014 (study 74) | B83: INCLUDED although rice is puddled transplanted in every treatment (NT -> ZT, RT -> MTR, HS -> CA). | C83: Author instruction 2026-10-03; every row flagged 'FLAG - PUDDLED RICE PHASE' in Notes - filter SERIAL NO 74 for sensitivity analysis.
A84: Unpuddled transplanted rice + ZT wheat | B84: Coded ZT (Jat et al. 2011, study 71, UPTR-ZTW). | C84: Dry tillage without puddling treated as compatible with ZT wheat (author approved).
A85: Marginal means | B85: Tripathi et al. 2007 (study 72) has only marginal / mixed-rotation means -> EXCLUDED, values kept in notes. | C85: Codes rule 'Factorial / split-plot papers'.
A86: Model output exception (2026-10-03) | B86: Bana et al. 2023 (study 78) APSIM simulated values ENTERED on author instruction. | C86: Every row starts 'MODEL OUTPUT (APSIM)' in Notes and Data source; filter on it for sensitivity analysis.
A87: New sheets (updated 10) | B87: SYS STRAW, C input, C output, CSI, CER, GHG intensity | C87: Added for Chaudhary et al. 2025 (study 76) on author instruction; system-level values, same column layout as the uptake sheets.
A88: Multi-experiment papers (2026-10-03) | B88: Tomar 2008 lecture split into serials 80-84, one per experiment; serial 84 is secondary data (Aslam et al. 1993). | C88: Included in full on author instruction ('involve all'); flags in Notes.
A89: Zero-till rice + reduced-till wheat | B89: Applied to study 79 (P1T1 rotavator, P1T3 strip till) as MT, following the author decision for study 76 ZTDSR-RTW.
A90: Dry-tilled non-puddled rice + ZT wheat (2026-10-03) | B90: Coded ZT (studies 86 MTR/DSR-ZTW, 87 CT-DDSR fb ZT), consistent with study 71 UPTR-ZTW; flagged because the rice phase is tilled, not zero-till. | C90: Author decision; supersedes the older 'conventional-till DSR + reduced-till wheat -> exclude' note for ZT wheat. SRI fb SWI -> CT.
A91: Depth class of a 20-30 cm layer (2026-10-03) | B91: A reported 20-30 cm layer -> 15-30 CM (NOT 30-45 CM). With 10-20 cm also in 15-30 CM, the two layers are separate rows and D=2 is added to Obs. | C91: Author correction; applied to studies 80, 91, 92 in updated 15.
A92: Infiltration (IR sheet, 2026-10-03) | B92: IR_ = steady-state infiltration rate (final, basic or quasi-steady rate); IIR_ = initial infiltration rate (first reading). Both in cm/hr on the IR sheet. | C92: Author definition. Steady-state and initial rates stay as two column groups on the one IR sheet; cumulative infiltration is kept in Notes.
A93: Depth class of a 20-40 cm layer (2026-10-03) | B93: A reported 20-40 cm layer -> 30-45 CM (author decision, study 97). | C93: Contrast: a 20-30 cm layer -> 15-30 CM.
A94: Puddled rice + ZT Happy-Seeder wheat - 34 (companion) (2026-10-03) | B94: Included flagged on author instruction (Kahlon-type exception): M1-M3 -> CA, M4 -> CTR. | C94: Study 34 itself stays excluded.
A95: Depth classes 0-30 / 30-60 / 60-90 cm (2026-10-03) | B95: 0-30 -> 0-15 CM, 30-60 -> 30-45 CM, 60-90 -> >60 CM (existing precedent applied to study 101).
A96: New K-pool sheets (updated 21) | B96: WS-K (water-soluble K), EX-K (exchangeable K), NEX-K (non-exchangeable K) - added for Rattan et al. 2025 (study 101). | C96: Lean-to-sheet rule.
A97: Year-wise data (author instruction 2026-10-03) | B97: When a paper gives year-wise values (tables or figures), enter every year as a separate row - not only the multi-year mean. | C97: Applies from study 101 onward; means then go in notes to avoid double counting.
A98: Box plots on request | B98: Box-plot mean markers entered for study 101 on author request (pooled over N); default remains: box plots not entered unless the author asks.
A99: Several sampling stages in one season (author 2026-10-03) | B99: When a paper samples soil at several crop stages (e.g. heading, grain filling, maturity), each stage is entered as its own row with the stage named in 'Crop/season of sampling'. | C99: Applied to 102 (companion) = Chen et al. 2022.
A100: Parameters without a sheet (author 2026-10-03) | B100: Extract only parameters that already have a sheet unless the author asks for a new one (PLFA of study 105 not entered).
A101: Deep burying of straw to 30 cm (author 2026-10-03) | B101: Plough + rake burying straw to 30 cm counts as deep tillage: no-straw control -> DT, straw treatments -> DTR (study 108). | C101: Consistent with the >= 25 cm deep-tillage threshold (study 9).
A102: Duplicate files within one batch (author 2026-10-03) | B102: When two files in the same batch are the same paper, enter it once and record the duplicate in EXCLUDED_rows (390 = 388).
A103: System values in SYS columns (author 2026-10-03) | B103: Paper-reported SYSTEM values (rice-equivalent / system yield, system B:C, system WP, system GWP, system nutrient uptake) are entered in the SYS columns, flagged when they include a third crop. Supersedes the study-29 rule that kept them in the notes. | C103: Applied retroactively to studies 29, 29 (companion 2), 45, 48, 56 (uptake sheets got new SYS columns). Studies 22 (CA4/CA5) and 50 have system values that are not recorded in the notes - need the papers.
A104: Tilled unpuddled rice + ZT wheat, by residue (author 2026-10-04) | B104: Dry-tilled (cultivator / harrow / rotavator) UNPUDDLED rice - transplanted or direct-seeded - followed by zero-till wheat: WITHOUT residue -> ZT (flagged); WITH residue retained -> CA (flagged, tilled rice phase). If the rice is wet-tilled/puddled it remains a rotation mismatch (excluded). Where two papers of one trial disagree on puddling, follow the main paper. | C104: Applied to study 29 family (T6 CTDSR-ZTW added as CA row b in 29, 29 (companion 2), Kumar 2024 rows, 29 (companion 3)); T3 CTMTR-ZTW excluded (puddled per Mishra 2021 Table 1). Consistent with 72 (companion) DSWP-RI-ZTW = CA, DSWP-RR-ZTW = ZT.
A105: Yield components & phenology sheets (author 2026-10-04) | B105: New sheets PANICLE-SPIKE DENSITY, GRAINS PER PANICLE, 1000-GRAIN WEIGHT, HARVEST INDEX, DAYS TO FLOWERING, DAYS TO MATURITY, GRAIN FILLING DAYS (W = wheat, R = rice columns, as the root sheets). Straw yield = biomass - grain when only biomass is printed. Uptake at anthesis and post-anthesis accumulation go on the uptake sheets as SEPARATE rows (stage in 'Crop/season of sampling'). | C105: First used for studies 120 (rice) and 121 (wheat).
A106: Derived yield / economic / carbon parameters (author 2026-10-04) | B106: Straw yield = biomass - grain (live formula) when only biomass is printed; HI = grain / (grain + straw) DERIVED for every YIELD row with both and no printed HI; NET RETURN sheet (printed currency, gross-margin and model rows flagged); CL/LI/CPI/CMI with CT as reference wherever POXC and SOC share a depth; GHGI = GWP / grain yield wherever both exist. All formulas on the FORMULAS sheet. | C106: Printed values always take precedence over derived ones (no derived row where the paper prints the parameter).
A107: New sheet 15N RESIDUAL (author 2026-10-04) | B107: Residual 15N-labelled fertiliser or straw N (kg N/ha) per soil layer after each harvest; source and season in 'Crop/season of sampling'. First used for study 132. | C107: Rice-season samplings in red.
A108: Soil-water sheets restructured (author 2026-10-04) | B108: GWC = gravimetric water content at any instant (former VWC sheet, v/v values divided by BD); AWC (weight basis) and AWC (volume basis) hold every AWC row in both bases; WHC = Keen-Raczkowski box only; FC (weight basis) and PWP (weight basis) new. Conversions use the BD of the same study / depth / treatment (live link to the BD sheet) or the default BD 1.35 Mg/m3 where none is reported. | C108: Weight basis = volume basis / BD; volume basis = weight basis x BD.
A109: Soil-water classification check (author 2026-10-05) | B109: Every soil-water row carries a 'WATER-QUANTITY CHECK' note stating, from the paper's Methods, whether the number is available water (FC - PWP) -> both AWC sheets, water content at the time of sampling -> GWC (weight basis), field capacity -> FC, wilting point -> PWP, Keen-box maximum WHC -> WHC, or saturated water content -> SAT WC. Rice-season duplicates of studies with wheat-season rows stay in notes. | C109: GWC = VWC / BD (BD sheet, else the paper's own layer BD, else 1.35); AWC = FC - PWP.
A110: Author decisions 2026-10-05 (ext\221-225) | B110: Rice-season-only paper from a genuine rice-wheat CA trial -> red rice rows (Rana 2023); shallow 3-5 cm rotary stubble-breaking + surface straw -> MTR; artificial night warming -> ambient rows only; re-submitted included paper -> companion re-entry; device soil with simulated tillage stays out. | C110: Serials 133-136 (133, 135 excluded); 102 (companion 3); 129 (companion); 28 (companion).
A111: Author decisions 2026-10-05 (ext\226-230) | B111: MODEL OUTPUT entered on request (study 28 DSSAT Table 6; 117 (companion) APSIM pooled yields, in SYS columns because not crop-specific). Rice-only DSR trial Bazaya 2009 included as red rows (ZT into standing wheat stubble -> CA; stubble incorporated -> CTR). | C111: Serials 137-141 (137, 138, 141 excluded); 117 (companion); 105 (companion 2); 31 (companion) excluded.
A112: Author decisions 2026-10-05 (ext\231-235) | B112: Kahlon & Dhingra 2019 full mapping: per rice method x deep variant, CT = CTRW-CT, CA = CTRW-NTR, DT = deep-CT, DTR = deep-NTR (CT/CA repeated). Re-submissions 232 / 233 / 235 = studies 121 / 64 / 111 -> companion clones. | C112: Serials 142 (Kahlon & Dhingra), 143 (Cheng, excluded); 121 (companion), 121 (companion 2), 64 (companion), 111 (companion).
A113: ROTARY / ROTAVATOR TILLAGE RULE (author 2026-10-05) | B113: Applies equally to ROTAVATOR and rotary-tiller operations (rotavator = rotary tillage). Full-width rotary / rotavator tillage to >=10 cm depth, or >=2 full-width passes = CT (CTR with residue), whatever the paper calls it. Rotary <=8 cm, a single-pass rotary till-drill, Super Seeder / Roto Seeder, or strip / zone rotary (only the seed rows tilled) = MT (MTR with residue). | C113: Conflicting older rows were RECODED in updated 47 (2026-10-05) on author instruction: 25 T6/T7 -> CT/CTR (row b); 41 Rot+R100 (Roto Seeder) -> MTR (row b); 64 and 64 (companion) RT -> CTR (row b); 69 AR -> CT, study EXCLUDED (no contrast); 74 RT -> CTR; 82 rotavator -> CT/CTR (row a, depth not stated - FLAG). Every recoded row starts 'RECODED 2026-10-05' in Notes. Grey zone (8-10 cm, or depth unstated and not clearly full-width primary tillage) -> ask the author.
A114: New columns on every data sheet (2026-10-05) | B114: 'Treatment details (from paper)' = Study_Info 'Treatments in paper' + every Treatment_Mapping line of the study (label -> code, full description, rice / wheat tillage, residue, rate) so treatments can be re-classified. 'Method used (from paper)' = analytical / measurement method AUTO-DETECTED from the paper's methods section with a quoted context (verify). | C114: Crop sheets: grain moisture basis and harvest area; calculated sheets (WUE, NUE, BC ratio, NET RETURN, C input/output, CSI, CER): see UNIT / FORMULAS.
... A119: Author decisions 2026-10-05 (ext\100-110 batch) | B119: Permanent beds + residue in the BISA Pusa trial companions -> CA (flagged) although study 71 coded PBDSR-PBDDW as ZT; main effects pooled over a mismatched factor level (Sarkar & Kar 2011) -> notes only; new sheets EARTHWORM (EW_) and DOC (DOC_); Gora 2024 supplement downloaded. Defaults: tilled unpuddled rice + ZT wheat (+ residue) -> ZT (CA) flagged (rule 24) incl. Gora Sc2; extra CT controls (rotary x2, farmers' practice) as CT rows b/c. | C119: Serials 156-163; companions 15 (companion), 59 (companion 2), 71 (companion), 71 (companion 2), 23 (companion 2), 24 (companion); 5 papers excluded (EXCLUDED_rows).

Sheet FORMULAS
A1: Parameter | B1: Formula (definition) | C1: Excel implementation in this workbook | D1: Unit | E1: Where applied | F1: Reference / note
A2: SD | B2: SD = SQRT(2 x Obs / Rep) | C2: Excel: =IF(AND(N(Obs)>0,N(Rep)>0),SQRT(2*Obs/Rep),"") | D2: - | E2: every data sheet (SD column) | F2: Original workbook rule; replaced by real SD only when a paper prints SD/SE
A3: Obs | B3: Obs = Y + T + D (years + paper treatments under one code + original depths collapsed into the row) | C3: entered value | D3: count | E3: every data sheet | F3: Codes / README rule
A4: STRAW YIELD | B4: Straw yield = biological (above-ground) yield - grain yield | C4: Excel: =ROUND(biomass - grain_cell, 2) in W STRAW_ / RSTRAW_ columns | D4: t/ha | E4: YIELD: studies 47 (row 50), 53 (row 62), 104, 106, 120 (all rows where only biomass is printed) | F4: Author instruction 2026-10-04
A5: HARVEST INDEX | B5: HI = grain / biological yield = grain / (grain + straw) | C5: Excel: =ROUND('YIELD'!grain/('YIELD'!grain+'YIELD'!straw),3) or =ROUND(grain/biomass,3); printed % -> /100 | D5: ratio 0-1 | E5: HARVEST INDEX sheet (printed values where the paper gives HI; DERIVED rows reference the YIELD cells) | F5: Added 2026-10-04
A6: BIOLOGICAL YIELD | B6: Biological yield = grain + straw | C6: (inverse of the straw rule; used only in notes) | D6: t/ha | E6: notes
A7: UNIT CONVERSIONS | B7: kg/ha / 1000 = t/ha; q/ha / 10 = t/ha; 10^4 spikes/ha = spikes/m2; grains per 5 spikes / 5 = grains per spike; printed x1000 Rs -> x 1000 | C7: Excel: =value/1000 , =value/10 , =ROUND(x/5,2) , =ROUND(x*1000,0) | D7: - | E7: YIELD, GRAINS PER PANICLE, NET RETURN
A8: TOTAL POROSITY | B8: Porosity (%) = (1 - BD / PD) x 100; PD = treatment PD, else initial PD of the paper, else 2.65 Mg/m3 | C8: Excel: =ROUND((1-BD!cell/PD)*100,2) (live link to the BD sheet; PD cell or value named in Notes) | D8: % | E8: POROSITY sheet (all treatment columns incl. pCA / pZT / pMT / pMTR) | F8: Author rule 2026-10-05
A9: SOC FROM SOM / OM | B9: SOC = SOM (or OM) / 1.724 | C9: Excel: =ROUND(SOM/1.724,3) | D9: g/kg | E9: SOC, soc (initial) where only OM is printed | F9: Van Bemmelen factor
A10: SOC STOCK | B10: SOC stock (Mg/ha) = SOC (g/kg) x BD (Mg/m3) x depth (cm) x 0.1 | C10: live formula from SOC and BD cells | D10: Mg C/ha | E10: stock-SOC
A11: C LIABILITY (CL) | B11: CL = labile C / non-labile C = POXC / (SOC x 1000 - POXC) | C11: Excel: =ROUND(POXC/(SOC*1000-POXC),3) | D11: ratio | E11: C liability (75 companion, 92, 102) | F11: Blair et al. 1995
A12: LABILITY INDEX (LI) | B12: LI = CL_treatment / CL_reference (reference = CT) | C12: LI_CT = 1; LI_x = CL_x / CL_CT | D12: - | E12: LI sheet | F12: Blair et al. 1995
A13: C POOL INDEX (CPI) | B13: CPI = SOC_treatment / SOC_reference (reference = CT) | C13: CPI_CT = 1; CPI_x = SOC_x / SOC_CT | D13: - | E13: CPI sheet | F13: Blair et al. 1995
A14: C MANAGEMENT INDEX (CMI) | B14: CMI = CPI x LI x 100 | C14: CMI_CT = 100; =ROUND(CPI*LI*100,2) | D14: - | E14: CMI sheet | F14: Blair et al. 1995
A15: GWP | B15: GWP = CH4 x 28 + N2O x 265 (kg CO2-eq/ha); CH4 = CH4-C x 16/12; N2O = N2O-N x 44/28 | C15: Excel: =ROUND(CH4*28+N2O*265,0) | D15: kg CO2-eq/ha | E15: GWP sheet | F15: IPCC AR5 100-yr factors
A16: GHG INTENSITY (GHGI) | B16: GHGI = GWP / grain yield | C16: Excel: =ROUND('GWP'!x/('YIELD'!y*1000),3) | D16: kg CO2-eq/kg grain | E16: GHG intensity (printed rows 76, 103; DERIVED rows 17, 26, 29, 45, 46, 89, 90c) | F16: Added 2026-10-04
A17: NET RETURN | B17: Net return = gross return - total cost of cultivation | C17: entered as printed (or =x*1000 / =rice+wheat sums) | D17: currency/ha as printed | E17: NET RETURN sheet | F17: Sheet added 2026-10-04; gross-margin rows flagged
A18: B:C RATIO | B18: B:C (sheet definition) = net return / cost; when a paper prints gross/cost: B:C - 1 | C18: Excel: =ROUND(net/cost,3) or =ROUND(printed-1,2) | D18: ratio | E18: BC ratio sheet | F18: Workbook definition
A19: SYSTEM YIELD / REY | B19: System yield = rice + wheat grain; REY = sum(yield_i x price_i / price_rice) | C19: Excel: =rice+wheat | D19: t/ha | E19: YIELD SYS columns, SYS STRAW
A20: POXC DERIVATIONS | B20: POXC (mg/kg) = ASOM / 1.724 x 1000 (study 92); = LOC/SOC ratio x SOC x 1000 (study 102) | C20: Excel: =ROUND(x/1.724*1000,1) ; =ROUND(ratio*SOC*1000,0) | D20: mg/kg | E20: POXC(KMnO4-C)
A21: WATER CONTENT BASIS | B21: theta_w (% w/w) = theta_v (% v/v) / BD; theta_v = theta_w x BD | C21: Excel: =ROUND(value/BD!cell,2) or =ROUND(value/1.35,2) (default BD) | D21: % w/w / % v/v | E21: GWC, AWC (weight / volume basis), FC, PWP | F21: Author rule 2026-10-04: default BD 1.35 Mg/m3
A22: AWC FROM FC AND PWP | B22: AWC = FC - PWP (same basis) | C22: derived in notes / rows | D22: % | E22: AWC sheets (study 28)
A23: AWC AS WATER DEPTH | B23: AWC (% v/v) = water depth (cm) / layer thickness (cm) x 100 | C23: Excel: =ROUND(cm/15*100,2) | D23: % v/v | E23: AWC (study 3)
A24: AWC FROM FC AND PWP (live) | B24: AWC (w/w) = FC (w/w) - PWP (w/w); AWC (v/v) = AWC (w/w) x BD | C24: Excel: =ROUND('FC (weight basis)'!cell-'PWP (weight basis)'!cell,2) ; =ROUND('AWC (weight basis)'!cell*BD!cell,2) | D24: % w/w / % v/v | E24: AWC sheets (study 9) | F24: Added 2026-10-05
A25: GWC FROM PLOTTED VWC | B25: GWC (% w/w) = VWC (m3/m3) x 100 / BD of the same layer (paper's own BD when the study has no BD-sheet rows) | C25: Excel: =ROUND(vwc*100/bd,2) | D25: % w/w | E25: GWC (study 12) | F25: Added 2026-10-05
A26: PMN FROM NET N MINERALISATION RATE | B26: PMN (mg/kg) = net N mineralisation rate (mg/kg/d) x incubation days (14) | C26: Excel: =ROUND(rate*14,2) | D26: mg/kg | E26: no3,nh4,PMN (study 136) | F26: Added 2026-10-05
A27: ENZYME UNIT umol/g/d -> nmol/h/g | B27: nmol/h/g = umol/g/d x 1000 / 24 | C27: Excel: =ROUND(x*1000/24,1) | D27: nmol/h/g | E27: NAG, LAP (study 136) | F27: Added 2026-10-05

Sheet Study_Info
A1: No. | B1: SERIAL NO | C1: Authors | D1: Year | E1: Journal | F1: Full reference | G1: DOI / link | H1: Country | I1: Site/Location | J1: latitude | K1: longitude | L1: latitude (as reported) | M1: longitude (as reported) | N1: Coordinates source | O1: CLIMATE | P1: Experiment established (year) | Q1: year of data collection/experiment | R1: Years of data reported | S1: DURATION | T1: SOIL | U1: Texture as reported | V1: sand | W1: silt | X1: CLAY | Y1: ph (initial) | Z1: soc (initial) | AA1: Bdi | AB1: MIN TEMP | AC1: MAX TEMP | AD1: AVG T | AE1: April max temp | AF1: RAIN FALL | AG1: Crop rotation | AH1: Wheat variety | AI1: Rice variety | AJ1: N dose (kg/ha) | AK1: P dose (kg/ha) | AL1: K dose (kg/ha) | AM1: Residue type & rate (t/ha) | AN1: Irrigation / water management | AO1: Treatments in paper | AP1: Parameters extracted | AQ1: Supplementary data? | AR1: Notes/Doubts
A2: 164 | B2: 164 | C2: Yadav R.L., Dwivedi B.S., Prasad K., Tomar O.K., Shurpali N.J. & Pandey P.S. | D2: 2000 | E2: Field Crops Research | F2: Yadav RL et al. (2000) Yield trends, and changes in soil organic-C and available NPK in a long-term rice-wheat system under integrated use of manures and fertilisers. Field Crops Res 68:219-246 | G2: https://doi.org/10.1016/S0378-4290(00)00126-X | H2: India (7 sites) | I2: Ludhiana, Pantnagar, Kanpur, Faizabad, Sabour, Kalyani, Jabalpur (one row per site in data sheets) | N2: Paper (each site); see LAT_LONG | O2: ST (Ludhiana TEMP) | P2: 1983-1986 (by site) | Q2: 1983-84 to 1998-99 | R2: 12-15 seasons per site (year-wise yields); soil after final wheat | S2: >10 Y | AG2: Rice-wheat (transplanted rice) | AJ2: 120 (100F); 60 + CR (50F+CR rice) | AK2: 26 | AL2: 33 | AM2: Wheat straw to rice: 8.8-15.8 t/ha/yr (by site) in 50F+CR | AN2: Irrigated; rice 5 cm flooding; wheat 5 irrigations | AO2: TREATMENTS IN PAPER (network long-term experiment, RBD 4 reps, plots 6 x 5 m, since 1983): Control (no fertiliser/manure); 50F (50% NPK rice, 100% wheat); 100F (100% NPK both crops) ; 50F+FYM, 50F+CR, 50F+GM = 50% NPK + 50% of recommended N through FYM, wheat crop residue (CR) or Sesbania green manure TO RICE ONLY, wheat 100% NPK. Recommended 120-26-33 kg N-P-K/ha each crop. Rice transplanted (puddled) 20 x 10 cm, wheat sown in 23 cm rows; above-ground biomass of both crops removed (sickle at ground level) except the CR returned in 50F+CR. 100F -> CT ; 50F+CR -> CTR (FLAG fertiliser offset, rule 62); Control, 50F, 50F+FYM, 50F+GM EXCLUDED. | AP2: YIELD (year-wise rice & wheat, 7 sites); SOC; available N (4 sites), P, K (final year) | AQ2: None found - web search 2026-10-05 (publisher pages not reachable from this environment) | AR2: INCLUDED FLAGGED (rule 62): 100F (CT) vs 50F+CR (CTR) - fertiliser cut offset by straw. Yields digitised year-wise from Fig. 2 and validated against Table 3 means. FLAG - FERTILISER OFFSET (rule 62): 50F+CR gets only 50% NPK to rice (wheat straw supplies the other 50% of N; P cut, K over-supplied) and 100% NPK to wheat; wheat straw is incorporated 1 month before rice transplanting (residue enters before the RICE phase only). Wheat tillage not described -> conventional (puddled transplanted rice + tilled wheat). Supplementary: none found (web search 2026-10-05; publisher site not reachable). Source file 112.pdf.
A3: 165 | B3: 165 | C3: Davari M.R., Sharma S.N. & Mirzakhani M. | D3: 2012 | E3: Biological Agriculture & Horticulture | F3: Davari MR, Sharma SN, Mirzakhani M (2012) Effect of cropping systems and crop residue incorporation on production and properties of soil in an organic agroecosystem. Biol Agric Hortic 28(3):206-222 | G3: https://doi.org/10.1080/01448765.2012.735005 | H3: India (Delhi) | I3: IARI research farm, New Delhi (organic rice-based cropping systems trial) | J3: 28.633 | K3: 77.183 | L3: 28 deg 38'N | M3: 77 deg 11'E | N3: Paper | O3: ST | P3: 2006 | Q3: 2006-07, 2007-08 | R3: 2 | S3: 0-3 Y | T3: LOAMY | U3: Sandy clay loam | V3: 52.06 | W3: 22.54 | X3: 25.4 | Y3: 8.16 | Z3: 5.2 | AA3: 1.5 | AG3: Rice-wheat and rice-wheat-mungbean (organic) | AH3: HD 2643 | AI3: Pusa Basmati 1 | AJ3: 60 (FYM-N, organic) | AM3: All residues incorporated in RI: 14.2-19.7 Mg DM/ha/yr | AN3: Rice flooded/puddled; mungbean 2 irrigations | AO3: TREATMENTS IN PAPER: strip-plot, 3 reps, 2006-07 and 2007-08, ORGANIC management. Rows = cropping system: RW (rice-wheat, summer fallow) and RWM (rice-wheat-mungbean, summer mungbean with Rhizobium + PSB); columns = residue: RR (entire above-ground biomass removed) and RI (all residue of each crop incorporated before the next crop: rice residue for wheat, wheat residue for rice in RW / for mungbean in RWM, mungbean residue for rice). Rice: field flooded and PUDDLED with tractor-drawn offset disc harrow, Pusa Basmati 1 transplanted 20 x 10 cm. Wheat: after rice harvest, residue (RI) + FYM incorporated with tractor-drawn heavy disc, then disked and planked twice; HD 2643 sown 3rd week Nov. RR -> CT, RI -> CTR (in both systems). | AP3: Rice, wheat, rice-equivalent yield (year-wise); SOC, Kjeldahl N, Olsen P, NH4OAc K (year-wise); BD, porosity, HC; bacteria, fungi, actinomycetes, MBC, DHA, CO2 evolution | AQ3: None found - web search 2026-10-05 (publisher pages not reachable from this environment) | AR3: INCLUDED: RR (CT) vs RI (CTR) in RW and in RWM (mungbean in both treatments of the RWM row, flagged). Protein yield and energy output (Figs 1-2) have no sheet. Rotation-matched: puddled transplanted rice + disc-tilled wheat = conventional in both phases; residue incorporated by disc -> CTR. FLAG: RI plots also received a cellulolytic culture spray (confounded with residue). Supplementary: none found (web search 2026-10-05; publisher site not reachable). Source file 113_rqal.pdf.
A4: 166 | B4: 166 | C4: Das B., Chakraborty D., Singh V.K., Aggarwal P., Singh R., Dwivedi B.S. & Mishra R.P. | D4: 2014 | E4: Soil & Tillage Research | F4: Das B et al. (2014) Effect of integrated nutrient management practice on soil aggregate properties, its stability and aggregate-associated carbon content in an intensive rice-wheat system. Soil Tillage Res 136:9-18 | G4: https://doi.org/10.1016/j.still.2013.09.009 | H4: India (Uttar Pradesh) | I4: PDFSR (now ICAR-IIFSR) long-term INM experiment, Modipuram, Meerut | J4: 29.067 | K4: 77.767 | L4: 29 deg 4'N | M4: 77 deg 46'E | N4: Paper | O4: ST | P4: 1993 | Q4: 2011 | R4: Soil 2011; yields as 3-yr means 1993-96 and 2008-11 | S4: >10 Y | T4: LOAMY | U4: Sandy loam | V4: 55 | W4: 18 | X4: 27 | Y4: 7.98 | Z4: 4.1 | AA4: 1.55 | AB4: 5 | AC4: 45.5 | AF4: 863 | AG4: Rice-wheat | AH4: HD 2338 | AI4: Saket 4 | AJ4: 120 (T2); 90 + CR (T8) | AK4: 26 | AL4: 33 | AM4: T8: rice and wheat straw supplying 25% of N (61.5 + 47.7 Mg C/ha over 18 yr) | AN4: Rice continuous 5 cm submergence; wheat 5 irrigations | AO4: TREATMENTS IN PAPER (Table 1, RBD 3 reps, since 1993, PDFSR Modipuram): T1 unfertilised; T2 recommended NPK (+Zn to rice) through fertilisers; T3 NPK + Zn + S (rice); T4 75% NPK + 25% N via FYM (rice); T5 75% NPK + 25% N via sulphitation press mud (rice); T6 75% NPK + green gram residue incorporated before rice; T7 = T6 (rice) + 75% NPK + 25% N via FYM (wheat); T8 75% NPK + 25% N via WHEAT STRAW to rice and 75% NPK + 25% N via RICE STRAW to wheat (CR). Rice puddled and transplanted (Saket 4, 20 x 10 cm, continuous 5 cm submergence); wheat HD 2338 drilled after dry tillage ('wet tillage followed by dry tillage'); recommended 120-26-33 kg N-P-K/ha to each crop. T2 -> CT ; T8 -> CTR (FLAG fertiliser offset, rule 62); T1, T3-T7 EXCLUDED (unfertilised / amendments / third crop in some treatments only). | AP4: TOC; macro/micro aggregates, WSA (derived), MWD (slaked + capillary), macro-C, micro-C, cPOM-C; aggregate FC/PWP/AWC; yields (3-yr means) | AQ4: None found - web search 2026-10-05 (publisher pages not reachable from this environment) | AR4: INCLUDED FLAGGED (rule 62): T2 (CT) vs T8 (CTR). FLAG - FERTILISER OFFSET (rule 62): in T8 crop residue replaces 25% of fertiliser N and 25% of P and K are also cut; drop for a fertiliser-matched sensitivity check. Wheat tillage not described in detail ('wet tillage followed by dry tillage', residue incorporated) -> conventional. Supplementary: none found (web search 2026-10-05; publisher site not reachable). Source file 113.pdf.
A5: 167 | B5: 167 | C5: Naz A., Rebi A., Naz R., Akbar M.U., Aslam A., Kalsom A., Niaz A., Ahmad M.I., Nawaz S., Kausar R., Ali B., Saleem M.H. & Zhou J. | D5: 2023 | E5: Land | F5: Naz A et al. (2023) Impact of green manuring on health of low fertility calcareous soils. Land 12:546 | G5: https://doi.org/10.3390/land12030546 | H5: Pakistan (Punjab) | I5: Khushab / Faisalabad, Punjab (calcareous soil field trial) | P5: 2015 | Q5: 2015-2018 | AG5: Rice-berseem (green manure) | AO5: Control; NPK (100% RDF); GM100, GM75, GM50 = berseem green manure (last cutting rotavated in) + 100/75/50% RDF; rice puddled-transplanted in all | AP5: NONE (excluded) | AQ5: None found - web search 2026-10-05 (publisher pages not reachable from this environment) | AR5: EXCLUDED: rice-berseem green-manure x fertiliser-dose trial - no wheat phase in the treatments, identical (puddled/rotavator) tillage and no crop-residue contrast; green manure is an amendment here, not part of a CA treatment (rule 34; rule 71 lets GM support CA, but there is no CA). Source file 111_real.pdf.
A6: 168 | B6: 168 | C6: Dhaliwal J.K., Singh M.J., Sharma S., Gupta N. & Kukal S.S. | D6: 2020 | E6: Soil Research | F6: Dhaliwal JK, Singh MJ, Sharma S, Gupta N, Kukal SS (2020) Medium-term impact of tillage and residue retention on soil physical and biological properties in dry-seeded rice-wheat system in north-west India. Soil Research 58:468-477 | G6: https://doi.org/10.1071/SR19238 | H6: India (Punjab) | I6: PAU research farm, Ludhiana (DSR-wheat tillage x mulch trial of Gupta et al. 2016) | J6: 30.933 | K6: 75.867 | L6: 30 deg 56'N | M6: 75 deg 52'E | N6: Paper | O6: TEMP | P6: 2011 | Q6: 2016 | R6: 1 | S6: 4-10 Y | T6: LOAMY | U6: Sandy loam (Typic Ustochrept) | Y6: 7.4 | AF6: 734 | AG6: Dry-seeded rice-wheat | AH6: PBW 621 | AI6: PR 115 | AM6: Rice residue 7 t/ha surface mulch in wheat (+M) | AN6: Irrigated (PAU recommendations) | AO6: TREATMENTS IN PAPER (Table 1; three-factor trial est. 2011 - only the 'absolute' CT and ZT rice and wheat combinations were studied): 1 CTW-CTDSR (-M) = conventionally tilled wheat (1 discing + 1 tyne harrowing + planking) and conventionally tilled dry-seeded rice, all rice residue removed -> CT ; 2 CTW+M-CTDSR = as 1 with ALL rice residue (7 t/ha) retained as surface mulch in wheat -> CTR ; 3 ZTW-ZTDSR = zero-till wheat (Turbo Happy Seeder) and zero-till DSR (inverted-T tyne ZT drill), residue removed -> ZT ; 4 ZTW+M-ZTDSR = as 3 with rice residue mulch -> CA. Wheat straw removed in every treatment (cut 3-5 cm above ground). RBD 3 reps; plots 9.3 x 6.5 m. | AP6: SOC, SOC stock, macro/micro WSA, WSA (derived), MWD, BD, porosity (derived), IR (initial + steady), FC/PWP/AWC, MBC, BSR, DHA, urease, ALP, ACP | AQ6: None found - web search 2026-10-05 (publisher pages not reachable from this environment) | AR6: INCLUDED: CT, CTR, ZT, CA. ALL ROWS RED (rice-season fallback - sampling after 2016 rice harvest only). Enzymes = tillage main effects (flagged). RICE-SEASON DATA (RED ROW): the paper samples ONLY after the 2016 rice harvest, so values are entered under the rice-season fallback rule (rule 36). Rotation-matched: CT rice + CT wheat = CT; ZT rice + ZT wheat = ZT/CA (rice residue is the mulch factor). Supplementary: none found (web search 2026-10-05; publisher site not reachable from this environment). Source file 112_real.pdf.

Sheet PARAMETERS_BY_STUDY
A1: PARAMETERS OF EACH STUDY - auto-generated from the data sheets (2026-10-05); regenerated at every build
A3: No. | B3: Serial | C3: Authors | D3: Year | E3: Journal | F3: Status | G3: Data rows | H3: No. of parameters (sheets) | I3: Parameters in this workbook (sheet: rows) | J3: Parameters extracted (Study_Info, paper-level description)
A4: 1 | B4: 164 | C4: Yadav R.L., Dwivedi B.S., Prasad K., Tomar O.K., Shurpali N.J. & Pandey P.S. | D4: 2000 | E4: Field Crops Research | F4: INCLUDED | G4: 120 | H4: 5 | I4: SOC(active C pool): 7; N: 4; P: 7; K: 7; YIELD: 95 | J4: YIELD (year-wise rice & wheat, 7 sites); SOC; available N (4 sites), P, K (final year)
A5: 2 | B5: 165 | C5: Davari M.R., Sharma S.N. & Mirzakhani M. | D5: 2012 | E5: Biological Agriculture & Horticulture | F5: INCLUDED | G5: 38 | H5: 14 | I5: BD: 2; POROSITY: 2; HC: 2; SOC(active C pool): 4; RESP: 2; P: 4; K: 4; total N: 4; MBC: 2; DHA: 2; Actinomycetes: 2; Soil microbial count: 2; Fungal count: 2; YIELD: 4 | J5: Rice, wheat, rice-equivalent yield (year-wise); SOC, Kjeldahl N, Olsen P, NH4OAc K (year-wise); BD, porosity, HC; bacteria, fungi, actinomycetes, MBC, DHA, CO2 evolution
A6: 3 | B6: 166 | C6: Das B., Chakraborty D., Singh V.K., Aggarwal P., Singh R., Dwivedi B.S. & Mishra R.P. | D6: 2014 | E6: Soil & Tillage Research | F6: INCLUDED | G6: 53 | H6: 13 | I6: MWD 1: 6; WSA: 3; MACRO: 3; MICRO: 3; macro c: 3; micro c: 3; AWC (weight basis): 6; AWC (volume basis): 6; FC (weight basis): 6; PWP (weight basis): 6; TOC: 3; cPOM-C: 3; YIELD: 2 | J6: TOC; macro/micro aggregates, WSA (derived), MWD (slaked + capillary), macro-C, micro-C, cPOM-C; aggregate FC/PWP/AWC; yields (3-yr means)
A7: 4 | B7: 167 | C7: Naz A., Rebi A., Naz R., Akbar M.U., Aslam A., Kalsom A., Niaz A., Ahmad M.I., Nawaz S., Kausar R., Ali B., Saleem M.H. & Zhou J. | D7: 2023 | E7: Land | F7: EXCLUDED | G7: 0 | H7: 0 | I7: - | J7: NONE (excluded)
A8: 5 | B8: 168 | C8: Dhaliwal J.K., Singh M.J., Sharma S., Gupta N. & Kukal S.S. | D8: 2020 | E8: Soil Research | F8: INCLUDED | G8: 27 | H8: 19 | I8: BD: 2; POROSITY: 2; MWD 1: 2; WSA: 2; MACRO: 2; MICRO: 2; IR: 1; AWC (weight basis): 1; AWC (volume basis): 1; FC (weight basis): 1; PWP (weight basis): 1; SOC(active C pool): 2; stock-SOC: 2; RESP: 1; MBC: 1; DHA: 1; ACP: 1; ALKP: 1; UREASE: 1 | J8: SOC, SOC stock, macro/micro WSA, WSA (derived), MWD, BD, porosity (derived), IR (initial + steady), FC/PWP/AWC, MBC, BSR, DHA, urease, ALP, ACP

Sheet STUDIES_BY_PARAMETER
A1: STUDIES OF EACH PARAMETER SHEET - auto-generated (2026-10-05); 'NO DATA' = none of the entered studies reports this parameter
A3: No. | B3: Parameter sheet | C3: Unit | D3: Data rows | E3: No. of studies | F3: Studies (serial: rows)
A4: 1 | B4: BD | C4: Mg/m3 | D4: 4 | E4: 2 | F4: 168: 2; 165: 2
A5: 2 | B5: PD | C5: Mg/m3 | D5: 0 | E5: 0 | F5: NO DATA
A6: 3 | B6: POROSITY | C6: % v/v | D6: 4 | E6: 2 | F6: 168: 2; 165: 2
A7: 4 | B7: macro pore | C7: % v/v | D7: 0 | E7: 0 | F7: NO DATA
A8: 5 | B8: meso pore | C8: % v/v | D8: 0 | E8: 0 | F8: NO DATA
A9: 6 | B9: micro pore | C9: % v/v | D9: 0 | E9: 0 | F9: NO DATA
A10: 7 | B10: MWD 1 | C10: mm (wet sieving) | D10: 8 | E10: 2 | F10: 168: 2; 166: 6
A11: 8 | B11: MWDA | C11: mm (dry sieving) | D11: 0 | E11: 0 | F11: NO DATA
A12: 9 | B12: GMD 1 | C12: mm | D12: 0 | E12: 0 | F12: NO DATA
A13: 10 | B13: WSA | C13: g/g soil (water-stable aggregates = sum of ALL water-stable fractions > 0.053 mm; % / 100) | D13: 5 | E13: 2 | F13: 168: 2; 166: 3
A14: 11 | B14: MACRO | C14: % (>0.25 mm aggregates) | D14: 5 | E14: 2 | F14: 168: 2; 166: 3
A15: 12 | B15: MICRO | C15: % (<0.25 mm aggregates) | D15: 5 | E15: 2 | F15: 168: 2; 166: 3
... A140: 137 | B140: GHG intensity | C140: kg CO2-eq/kg grain (yield-scaled GWP) | D140: 0 | E140: 0 | F140: NO DATA
A141: 138 | B141: AGG-TP | D141: 0 | E141: 0 | F141: NO DATA
A142: 139 | B142: AGG-AvP | D142: 0 | E142: 0 | F142: NO DATA
A143: 140 | B143: AGG-ALKP | D143: 0 | E143: 0 | F143: NO DATA
A144: 141 | B144: AGG-PhytinP | D144: 0 | E144: 0 | F144: NO DATA

Sheet Treatment_Mapping
A1: No. | B1: SERIAL NO | C1: Authors | D1: Year | E1: Paper's treatment label (verbatim) | F1: Full description from paper | G1: Rice-phase tillage | H1: Wheat-phase tillage | I1: Residue retained? | J1: Residue rate (t/ha) | K1: ASSIGNED CODE | L1: Rationale | M1: Confidence | N1: Status
A2: 164 | B2: 164 | C2: Yadav R.L. et al. | D2: 2000 | E2: Control | F2: No fertiliser or manure to either crop | G2: Puddled TPR | H2: Conventional (not described) | I2: No | K2: EXCLUDED | L2: Unfertilised control (rule 34) | M2: High | N2: EXCLUDED
A3: 164 | B3: 164 | C3: Yadav R.L. et al. | D3: 2000 | E3: 50F | F3: 50% NPK to rice, 100% to wheat | G3: Puddled TPR | H3: Conventional | I3: No | K3: EXCLUDED | L3: Sub-optimal fertiliser tier, no residue/tillage contrast | M3: High | N3: EXCLUDED
A4: 164 | B4: 164 | C4: Yadav R.L. et al. | D4: 2000 | E4: 100F | F4: 100% recommended NPK (120-26-33) to rice and wheat; all biomass removed | G4: Puddled TPR | H4: Conventional | I4: No | K4: CT | L4: Conventional rice + wheat, residue removed | M4: Medium (wheat tillage not described) | N4: INCLUDED
A5: 164 | B5: 164 | C5: Yadav R.L. et al. | D5: 2000 | E5: 50F + FYM | F5: 50% NPK + 50% N through FYM to rice; 100% NPK wheat | G5: Puddled TPR | H5: Conventional | I5: No | K5: EXCLUDED | L5: Amendment (FYM), rule 34 | M5: High | N5: EXCLUDED
A6: 164 | B6: 164 | C6: Yadav R.L. et al. | D6: 2000 | E6: 50F + CR | F6: 50% NPK + 50% N through wheat crop residue incorporated 1 month before rice; 100% NPK wheat | G6: Puddled TPR | H6: Conventional | I6: Yes (wheat straw to rice) | J6: 8.8-15.8 by site | K6: CTR | L6: Straw return with fertiliser cut to offset -> CTR FLAGGED (rule 62) | M6: Medium | N6: INCLUDED - FLAGGED
A7: 164 | B7: 164 | C7: Yadav R.L. et al. | D7: 2000 | E7: 50F + GM | F7: 50% NPK + 50% N through Sesbania green manure to rice; 100% NPK wheat | G7: Puddled TPR | H7: Conventional | I7: No (GM) | K7: EXCLUDED | L7: Green manure in a conventional system - amendment; GM only supports CA (rule 71) | M7: High | N7: EXCLUDED
A8: 165 | B8: 165 | C8: Davari M.R. et al. | D8: 2012 | E8: RW-RR | F8: Rice-wheat, residue removed (organic, FYM 60 kg N) | G8: Puddled (offset disc) | H8: Heavy disc + disk & plank x2 | I8: No | K8: CT | L8: Conventional in both phases | M8: High | N8: INCLUDED
A9: 165 | B9: 165 | C9: Davari M.R. et al. | D9: 2012 | E9: RW-RI | F9: Rice-wheat, all residue incorporated | G9: Puddled (offset disc) | H9: Heavy disc + disk & plank x2 | I9: Yes (incorporated) | J9: 14.2-16.0 Mg DM/yr | K9: CTR | L9: Conventional + residue incorporation | M9: High | N9: INCLUDED
A10: 165 | B10: 165 | C10: Davari M.R. et al. | D10: 2012 | E10: RWM-RR | F10: Rice-wheat-mungbean, residue removed | G10: Puddled (offset disc) | H10: Heavy disc + disk & plank x2 | I10: No | K10: CT | L10: Conventional; summer mungbean in both RWM treatments (flag) | M10: High | N10: INCLUDED
A11: 165 | B11: 165 | C11: Davari M.R. et al. | D11: 2012 | E11: RWM-RI | F11: Rice-wheat-mungbean, all residue incorporated | G11: Puddled (offset disc) | H11: Heavy disc + disk & plank x2 | I11: Yes (incorporated) | J11: 17.8-19.7 Mg DM/yr | K11: CTR | L11: Conventional + residue; mungbean in both (flag) | M11: High | N11: INCLUDED
A12: 166 | B12: 166 | C12: Das B. et al. | D12: 2014 | E12: T1 | F12: Unfertilised | G12: Puddled TPR | H12: Dry tillage | I12: No | K12: EXCLUDED | L12: Unfertilised control | M12: High | N12: EXCLUDED
A13: 166 | B13: 166 | C13: Das B. et al. | D13: 2014 | E13: T2 | F13: Recommended NPK (+Zn rice) through fertilisers | G13: Puddled TPR | H13: Dry tillage (conventional) | I13: No | K13: CT | L13: Conventional, residue removed | M13: High | N13: INCLUDED
A14: 166 | B14: 166 | C14: Das B. et al. | D14: 2014 | E14: T3 | F14: NPK + Zn + S | G14: Puddled TPR | H14: Dry tillage | I14: No | K14: EXCLUDED | L14: Nutrient tier (S), no residue contrast | M14: High | N14: EXCLUDED
A15: 166 | B15: 166 | C15: Das B. et al. | D15: 2014 | E15: T4 | F15: 75% NPK + 25% N via FYM (rice) | G15: Puddled TPR | H15: Dry tillage | I15: No | K15: EXCLUDED | L15: Amendment (FYM) | M15: High | N15: EXCLUDED
A16: 166 | B16: 166 | C16: Das B. et al. | D16: 2014 | E16: T5 | F16: 75% NPK + 25% N via sulphitation press mud (rice) | G16: Puddled TPR | H16: Dry tillage | I16: No | K16: EXCLUDED | L16: Amendment (press mud) | M16: High | N16: EXCLUDED
A17: 166 | B17: 166 | C17: Das B. et al. | D17: 2014 | E17: T6 | F17: 75% NPK + green gram residue before rice | G17: Puddled TPR | H17: Dry tillage | I17: Green gram residue | K17: EXCLUDED | L17: Third crop (green gram) in some treatments only (rule 30); GM only supports CA | M17: High | N17: EXCLUDED
A18: 166 | B18: 166 | C18: Das B. et al. | D18: 2014 | E18: T7 | F18: T6 + 75% NPK + 25% N via FYM (wheat) | G18: Puddled TPR | H18: Dry tillage | I18: Green gram residue | K18: EXCLUDED | L18: Third crop + FYM | M18: High | N18: EXCLUDED
A19: 166 | B19: 166 | C19: Das B. et al. | D19: 2014 | E19: T8 | F19: 75% NPK + 25% N via wheat straw (rice) and rice straw (wheat) | G19: Puddled TPR | H19: Dry tillage (straw incorporated) | I19: Yes (both crops) | J19: N-equivalent (61.5 + 47.7 Mg C over 18 yr) | K19: CTR | L19: Straw return with fertiliser cut -> CTR FLAGGED (rule 62) | M19: Medium | N19: INCLUDED - FLAGGED
A20: 167 | B20: 167 | C20: Naz A. et al. | D20: 2023 | E20: Control / NPK / GM100 / GM75 / GM50 | F20: Rice-berseem; berseem GM with 100/75/50% RDF vs NPK and control | G20: Puddled TPR | H20: No wheat (berseem) | I20: No | K20: EXCLUDED | L20: Not a rice-wheat tillage/residue study | M20: High | N20: EXCLUDED
A21: 168 | B21: 168 | C21: Dhaliwal J.K. et al. | D21: 2020 | E21: CTW-CTDSR (-M) | F21: CT wheat (disc + tyne harrow + plank) after CT dry-seeded rice, residue removed | G21: CT DSR | H21: CT | I21: No | K21: CT | L21: Conventional both phases | M21: High | N21: INCLUDED
A22: 168 | B22: 168 | C22: Dhaliwal J.K. et al. | D22: 2020 | E22: CTW+M-CTDSR | F22: As above + 7 t/ha rice residue mulch in wheat | G22: CT DSR | H22: CT | I22: Yes (surface mulch) | J22: 7 | K22: CTR | L22: Conventional + residue | M22: High | N22: INCLUDED
A23: 168 | B23: 168 | C23: Dhaliwal J.K. et al. | D23: 2020 | E23: ZTW-ZTDSR | F23: ZT wheat (Turbo Happy Seeder) after ZT DSR, residue removed | G23: ZT DSR | H23: ZT | I23: No | K23: ZT | L23: Zero till both phases, no residue | M23: High | N23: INCLUDED
A24: 168 | B24: 168 | C24: Dhaliwal J.K. et al. | D24: 2020 | E24: ZTW+M-ZTDSR | F24: ZT wheat + rice residue mulch after ZT DSR | G24: ZT DSR | H24: ZT | I24: Yes (surface mulch) | J24: 7 | K24: CA | L24: Zero till both phases + residue | M24: High | N24: INCLUDED

Sheet LAT_LONG
A1: No. | B1: SERIAL NO | C1: Authors | D1: Year | E1: Country | F1: Site/Location | G1: latitude (as reported) | H1: longitude (as reported) | I1: latitude | J1: longitude | K1: Coordinates source | L1: CLIMATE | M1: Notes
A2: 164 | B2: 164 | C2: Yadav R.L. et al. | D2: 2000 | E2: India (Punjab) | F2: Ludhiana | G2: 30 deg 56'N | H2: 75 deg 52'E | I2: 30.933 | J2: 75.867 | K2: Paper | L2: TEMP
A3: 164 | B3: 164 | C3: Yadav R.L. et al. | D3: 2000 | E3: India (Uttarakhand (then Uttar Pradesh)) | F3: Pantnagar | G3: 29 deg N | H3: 79 deg 5'E | I3: 29 | J3: 79.083 | K3: Paper | L3: ST | M3: GBPUAT Pantnagar ~29.02 N, 79.48 E; printed 79 deg 5'E
A4: 164 | B4: 164 | C4: Yadav R.L. et al. | D4: 2000 | E4: India (Uttar Pradesh) | F4: Kanpur | G4: 26 deg 58'N | H4: 80 deg 34'E | I4: 26.967 | J4: 80.567 | K4: Paper | L4: ST
A5: 164 | B5: 164 | C5: Yadav R.L. et al. | D5: 2000 | E5: India (Uttar Pradesh) | F5: Faizabad | G5: 26 deg 4'N | H5: 82 deg 8'E | I5: 26.067 | J5: 82.133 | K5: Paper | L5: ST | M5: Printed coords ~50 km from NDUAT Kumarganj (26.54 N, 81.84 E) - kept as printed
A6: 164 | B6: 164 | C6: Yadav R.L. et al. | D6: 2000 | E6: India (Bihar) | F6: Sabour | G6: 25 deg 14'N | H6: 87 deg 4'E | I6: 25.233 | J6: 87.067 | K6: Paper | L6: ST
A7: 164 | B7: 164 | C7: Yadav R.L. et al. | D7: 2000 | E7: India (West Bengal) | F7: Kalyani | G7: 23 deg N | H7: 89 deg E | I7: 23 | J7: 89 | K7: Paper | L7: ST | M7: Printed to whole degrees; BCKV Kalyani ~22.98 N, 88.43 E
A8: 164 | B8: 164 | C8: Yadav R.L. et al. | D8: 2000 | E8: India (Madhya Pradesh) | F8: Jabalpur | G8: 23 deg 10'N | H8: 79 deg 57'E | I8: 23.167 | J8: 79.95 | K8: Paper | L8: ST
A9: 165 | B9: 165 | C9: Davari M.R. et al. | D9: 2012 | E9: India (Delhi) | F9: IARI, New Delhi | G9: 28 deg 38'N | H9: 77 deg 11'E | I9: 28.633 | J9: 77.183 | K9: Paper | L9: ST
A10: 166 | B10: 166 | C10: Das B. et al. | D10: 2014 | E10: India (Uttar Pradesh) | F10: PDFSR Modipuram, Meerut | G10: 29 deg 4'N | H10: 77 deg 46'E | I10: 29.067 | J10: 77.767 | K10: Paper | L10: ST
A11: 167 | B11: 167 | C11: Naz A. et al. | D11: 2023 | E11: Pakistan (Punjab) | F11: Khushab / Faisalabad | K11: Not given (study excluded) | M11: EXCLUDED study
A12: 168 | B12: 168 | C12: Dhaliwal J.K. et al. | D12: 2020 | E12: India (Punjab) | F12: PAU, Ludhiana | G12: 30 deg 56'N | H12: 75 deg 52'E | I12: 30.933 | J12: 75.867 | K12: Paper | L12: TEMP

Sheet BD
A1: No. | B1: SERIAL NO | C1: Authors | D1: Year | E1: Journal | F1: Country | G1: Site/Location | H1: latitude | I1: longitude | J1: CLIMATE | K1: year of data collection/experiment | L1: DURATION | M1: SOIL | N1: DEPTH | O1: DEPTH (as reported in paper) | P1: BD_CA | Q1: BD_CT | R1: BD_ZT | S1: BD_DT | T1: BD_MTR | U1: BD_MT | V1: BD_CTR | W1: BD_DTR | X1: BD_pCA | Y1: BD_pZT | Z1: BD_pMT | AA1: BD_pMTR | AB1: Obs | AC1: Rep | AD1: SD | AE1: CLAY | AF1: MIN TEMP | AG1: MAX TEMP | AH1: RAIN FALL | AI1: LATT | AJ1: YEAR OF DATA (duration) | AK1: AVG T | AL1: April max temp | AM1: ph (initial) | AN1: soc (initial) | AO1: Bdi | AP1: sand | AQ1: silt | AR1: UNIT | AS1: Treatment mapping (paper's name -> code) | AT1: Crop/season of sampling | AU1: Fertilizer dose & other management | AV1: Data source | AW1: Notes/Doubts | AX1: Treatment details (from paper) | AY1: Method used (from paper) | BA1: UNIT FOR THIS SHEET:
A2: 168 | B2: 168 | C2: Dhaliwal J.K., Singh M.J., Sharma S., Gupta N. & Kukal S.S. | D2: 2020 | E2: Soil Research | F2: India (Punjab) | G2: PAU research farm, Ludhiana (DSR-wheat tillage x mulch trial of Gupta et al. 2016) | H2: 30.933 | I2: 75.867 | J2: TEMP | K2: 2016 | L2: 4-10 Y | M2: LOAMY | N2: 0-15 CM | O2: 0-15 cm | P2: 1.6 | Q2: 1.56 | R2: 1.6 | V2: 1.5 | AB2: 1 | AC2: 3 | AD2: =IF(AND(N(AB2)>0,N(AC2)>0),SQRT(2*AB2/AC2),"") -> 0.81649658 | AH2: 734 | AI2: 30.933 | AJ2: 5 | AM2: 7.4 | AR2: Mg/m3 | AS2: CTW-CTDSR (-M) -> CT ; CTW+M-CTDSR -> CTR ; ZTW-ZTDSR -> ZT ; ZTW+M-ZTDSR -> CA | AT2: RICE SEASON - soil sampled in 2016 after rice harvest (no wheat-season sampling in the paper) | AU2: Fertiliser, water and pest management as PAU recommendations (doses not printed; see Gupta et al. 2016 FCR 196:219). Wheat PBW 621, 113 kg/ha, Turbo Happy Seeder, 20 cm rows; rice PR 115 DSR 40 kg/ha, 20 cm rows. +M: 7 t/ha rice residue spread between rows after wheat sowing (2.5 t/ha left at wheat harvest). Wheat straw removed in all plots. Surface soil pH 7.4 (1:2), EC 0.31 dS/m (1:2); Typic Ustochrept, sandy loam to 120 cm. | AV2: Table 5 | AW2: RICE-SEASON DATA (RED ROW): the paper samples ONLY after the 2016 rice harvest, so values are entered under the rice-season fallback rule (rule 36). Rotation-matched: CT rice + CT wheat = CT; ZT rice + ZT wheat = ZT/CA (rice residue is the mulch factor). Supplementary: none found (web search 2026-10-05; publisher site not reachable from this environment). Source file 112_real.pdf. LSD (0-15) T 0.02, M 0.02, TxM 0.03; (15-30) T 0.03. | AX2: TREATMENTS IN PAPER (Table 1; three-factor trial est. 2011 - only the 'absolute' CT and ZT rice and wheat combinations were studied): 1 CTW-CTDSR (-M) = conventionally tilled wheat (1 discing + 1 tyne harrowing + planking) and conventionally tilled dry-seeded rice, all rice residue removed -> CT ; 2 CTW+M-CTDSR = as 1 with ALL rice residue (7 t/ha) retained as surface mulch in wheat -> CTR ; 3 ZTW-ZTDSR = zero-till wheat (Turbo Happy Seeder) and zero-till DSR (inverted-T tyne ZT drill), residue removed -> ZT ; 4 ZTW+M-ZTDSR = as 3 with rice residue mulch -> CA. Wheat straw removed in every treatment (cut 3-5 cm above ground). RBD 3 reps; plots 9.3 x 6.5 m. | AY2: Core method (Blake & Hartge 1986), steel core 5 cm high x 5 cm i.d., 3 cores/plot | BA2: Mg/m3
A3: 168 | B3: 168 | C3: Dhaliwal J.K., Singh M.J., Sharma S., Gupta N. & Kukal S.S. | D3: 2020 | E3: Soil Research | F3: India (Punjab) | G3: PAU research farm, Ludhiana (DSR-wheat tillage x mulch trial of Gupta et al. 2016) | H3: 30.933 | I3: 75.867 | J3: TEMP | K3: 2016 | L3: 4-10 Y | M3: LOAMY | N3: 15-30 CM | O3: 15-30 cm | P3: 1.65 | Q3: 1.77 | R3: 1.67 | V3: 1.75 | AB3: 1 | AC3: 3 | AD3: =IF(AND(N(AB3)>0,N(AC3)>0),SQRT(2*AB3/AC3),"") -> 0.81649658 | AH3: 734 | AI3: 30.933 | AJ3: 5 | AM3: 7.4 | AR3: Mg/m3 | AS3: CTW-CTDSR (-M) -> CT ; CTW+M-CTDSR -> CTR ; ZTW-ZTDSR -> ZT ; ZTW+M-ZTDSR -> CA | AT3: RICE SEASON - soil sampled in 2016 after rice harvest (no wheat-season sampling in the paper) | AU3: Fertiliser, water and pest management as PAU recommendations (doses not printed; see Gupta et al. 2016 FCR 196:219). Wheat PBW 621, 113 kg/ha, Turbo Happy Seeder, 20 cm rows; rice PR 115 DSR 40 kg/ha, 20 cm rows. +M: 7 t/ha rice residue spread between rows after wheat sowing (2.5 t/ha left at wheat harvest). Wheat straw removed in all plots. Surface soil pH 7.4 (1:2), EC 0.31 dS/m (1:2); Typic Ustochrept, sandy loam to 120 cm. | AV3: Table 5 | AW3: RICE-SEASON DATA (RED ROW): the paper samples ONLY after the 2016 rice harvest, so values are entered under the rice-season fallback rule (rule 36). Rotation-matched: CT rice + CT wheat = CT; ZT rice + ZT wheat = ZT/CA (rice residue is the mulch factor). Supplementary: none found (web search 2026-10-05; publisher site not reachable from this environment). Source file 112_real.pdf. LSD (0-15) T 0.02, M 0.02, TxM 0.03; (15-30) T 0.03. | AX3: TREATMENTS IN PAPER (Table 1; three-factor trial est. 2011 - only the 'absolute' CT and ZT rice and wheat combinations were studied): 1 CTW-CTDSR (-M) = conventionally tilled wheat (1 discing + 1 tyne harrowing + planking) and conventionally tilled dry-seeded rice, all rice residue removed -> CT ; 2 CTW+M-CTDSR = as 1 with ALL rice residue (7 t/ha) retained as surface mulch in wheat -> CTR ; 3 ZTW-ZTDSR = zero-till wheat (Turbo Happy Seeder) and zero-till DSR (inverted-T tyne ZT drill), residue removed -> ZT ; 4 ZTW+M-ZTDSR = as 3 with rice residue mulch -> CA. Wheat straw removed in every treatment (cut 3-5 cm above ground). RBD 3 reps; plots 9.3 x 6.5 m. | AY3: Core method (Blake & Hartge 1986), steel core 5 cm high x 5 cm i.d., 3 cores/plot
A4: 165 | B4: 165 | C4: Davari M.R., Sharma S.N. & Mirzakhani M. | D4: 2012 | E4: Biological Agriculture & Horticulture | F4: India (Delhi) | G4: IARI research farm, New Delhi (organic rice-based cropping systems trial) | H4: 28.633 | I4: 77.183 | J4: ST | K4: 2007-08 | L4: 0-3 Y | M4: LOAMY | N4: 0-15 CM | O4: 0-15 cm | Q4: 1.46 | V4: 1.4 | AB4: 1 | AC4: 3 | AD4: =IF(AND(N(AB4)>0,N(AC4)>0),SQRT(2*AB4/AC4),"") -> 0.81649658 | AE4: 25.4 | AI4: 28.633 | AJ4: 2 | AM4: 8.16 | AN4: 5.2 | AO4: 1.5 | AP4: 52.06 | AQ4: 22.54 | AR4: Mg/m3 | AS4: RW-RR -> CT ; RW-RI -> CTR | AT4: After completion of two cycles (June 2008, after wheat / fallow) | AU4: ORGANIC: FYM equivalent to 60 kg N/ha to rice and to wheat (FYM ~0.61% N, 22-23 C:N), no mineral fertiliser; BGA 1.5 kg/ha in rice 20 DAT; Azotobacter + PSB seed inoculation of wheat; cellulolytic fungal culture 600 g/t sprayed on residue in RI plots only. RI residue added (Mg DM/ha): RW 14.2 (2006-07), 16.0 (2007-08); RWM 17.8, 19.7. Initial soil: SCL, EC 0.79 dS/m, CEC 14.73 cmol/kg, OC 5.2 g/kg, Kjeldahl N 580 mg/kg, Olsen P 8.42, NH4OAc K 187 mg/kg, BD 1.50, FC 24.57%. | AV4: Table 9 | AW4: LSD residue 0.04. 15-30 cm values not printed (not significantly different). Rotation-matched: puddled transplanted rice + disc-tilled wheat = conventional in both phases; residue incorporated by disc -> CTR. FLAG: RI plots also received a cellulolytic culture spray (confounded with residue). Supplementary: none found (web search 2026-10-05; publisher site not reachable). Source file 113_rqal.pdf. | AX4: TREATMENTS IN PAPER: strip-plot, 3 reps, 2006-07 and 2007-08, ORGANIC management. Rows = cropping system: RW (rice-wheat, summer fallow) and RWM (rice-wheat-mungbean, summer mungbean with Rhizobium + PSB); columns = residue: RR (entire above-ground biomass removed) and RI (all residue of each crop incorporated before the next crop: rice residue for wheat, wheat residue for rice in RW / for mungbean in RWM, mungbean residue for rice). Rice: field flooded and PUDDLED with tractor-drawn offset disc harrow, Pusa Basmati 1 transplanted 20 x 10 cm. Wheat: after rice harvest, residue (RI) + FYM incorporated with tractor-drawn heavy disc, then disked and planked twice; HD 2643 sown 3rd week Nov. RR -> CT, RI -> CTR (in both systems). | AY4: Core method (Veihmeyer & Hendrickson 1948), oven-dry 105 C 48 h
A5: 165 | B5: 165 | C5: Davari M.R., Sharma S.N. & Mirzakhani M. | D5: 2012 | E5: Biological Agriculture & Horticulture | F5: India (Delhi) | G5: IARI research farm, New Delhi (organic rice-based cropping systems trial) | H5: 28.633 | I5: 77.183 | J5: ST | K5: 2007-08 | L5: 0-3 Y | M5: LOAMY | N5: 0-15 CM | O5: 0-15 cm | Q5: 1.44 | V5: 1.38 | AB5: 1 | AC5: 3 | AD5: =IF(AND(N(AB5)>0,N(AC5)>0),SQRT(2*AB5/AC5),"") -> 0.81649658 | AE5: 25.4 | AI5: 28.633 | AJ5: 2 | AM5: 8.16 | AN5: 5.2 | AO5: 1.5 | AP5: 52.06 | AQ5: 22.54 | AR5: Mg/m3 | AS5: RWM-RR -> CT ; RWM-RI -> CTR | AT5: After completion of two cycles (June 2008, after wheat and mungbean) | AU5: ORGANIC: FYM equivalent to 60 kg N/ha to rice and to wheat (FYM ~0.61% N, 22-23 C:N), no mineral fertiliser; BGA 1.5 kg/ha in rice 20 DAT; Azotobacter + PSB seed inoculation of wheat; cellulolytic fungal culture 600 g/t sprayed on residue in RI plots only. RI residue added (Mg DM/ha): RW 14.2 (2006-07), 16.0 (2007-08); RWM 17.8, 19.7. Initial soil: SCL, EC 0.79 dS/m, CEC 14.73 cmol/kg, OC 5.2 g/kg, Kjeldahl N 580 mg/kg, Olsen P 8.42, NH4OAc K 187 mg/kg, BD 1.50, FC 24.57%. | AV5: Table 9 | AW5: LSD residue 0.04. GREEN MANURE / 3rd CROP: summer mungbean in BOTH treatments of this row (pods picked, residue incorporated in RI only). 15-30 cm values not printed (not significantly different). Rotation-matched: puddled transplanted rice + disc-tilled wheat = conventional in both phases; residue incorporated by disc -> CTR. FLAG: RI plots also received a cellulolytic culture spray (confounded with residue). Supplementary: none found (web search 2026-10-05; publisher site not reachable). Source file 113_rqal.pdf. | AX5: TREATMENTS IN PAPER: strip-plot, 3 reps, 2006-07 and 2007-08, ORGANIC management. Rows = cropping system: RW (rice-wheat, summer fallow) and RWM (rice-wheat-mungbean, summer mungbean with Rhizobium + PSB); columns = residue: RR (entire above-ground biomass removed) and RI (all residue of each crop incorporated before the next crop: rice residue for wheat, wheat residue for rice in RW / for mungbean in RWM, mungbean residue for rice). Rice: field flooded and PUDDLED with tractor-drawn offset disc harrow, Pusa Basmati 1 transplanted 20 x 10 cm. Wheat: after rice harvest, residue (RI) + FYM incorporated with tractor-drawn heavy disc, then disked and planked twice; HD 2643 sown 3rd week Nov. RR -> CT, RI -> CTR (in both systems). | AY5: Core method (Veihmeyer & Hendrickson 1948), oven-dry 105 C 48 h

Sheet PD
A1: No. | B1: SERIAL NO | C1: Authors | D1: Year | E1: Journal | F1: Country | G1: Site/Location | H1: latitude | I1: longitude | J1: CLIMATE | K1: year of data collection/experiment | L1: DURATION | M1: SOIL | N1: DEPTH | O1: DEPTH (as reported in paper) | P1: PD_CA | Q1: PD_CT | R1: PD_ZT | S1: PD_DT | T1: PD_MTR | U1: PD_MT | V1: PD_CTR | W1: PD_DTR | X1: PD_pCA | Y1: PD_pZT | Z1: PD_pMT | AA1: PD_pMTR | AB1: Pdi | AC1: Obs | AD1: Rep | AE1: SD | AF1: CLAY | AG1: MIN TEMP | AH1: MAX TEMP | AI1: RAIN FALL | AJ1: LATT | AK1: YEAR OF DATA (duration) | AL1: AVG T | AM1: April max temp | AN1: ph (initial) | AO1: soc (initial) | AP1: Bdi | AQ1: sand | AR1: silt | AS1: UNIT | AT1: Treatment mapping (paper's name -> code) | AU1: Crop/season of sampling | AV1: Fertilizer dose & other management | AW1: Data source | AX1: Notes/Doubts | AY1: Treatment details (from paper) | AZ1: Method used (from paper) | BB1: UNIT FOR THIS SHEET:
BB2: Mg/m3

Sheet POROSITY
A1: No. | B1: SERIAL NO | C1: Authors | D1: Year | E1: Journal | F1: Country | G1: Site/Location | H1: latitude | I1: longitude | J1: CLIMATE | K1: year of data collection/experiment | L1: DURATION | M1: SOIL | N1: DEPTH | O1: DEPTH (as reported in paper) | P1: POROSITY_CA | Q1: POROSITY_CT | R1: POROSITY_ZT | S1: POROSITY_DT | T1: POROSITY_MTR | U1: POROSITY_MT | V1: POROSITY_CTR | W1: POROSITY_DTR | X1: POROSITY_pCA | Y1: POROSITY_pZT | Z1: POROSITY_pMT | AA1: POROSITY_pMTR | AB1: Obs | AC1: Rep | AD1: SD | AE1: CLAY | AF1: MIN TEMP | AG1: MAX TEMP | AH1: RAIN FALL | AI1: LATT | AJ1: YEAR OF DATA (duration) | AK1: AVG T | AL1: April max temp | AM1: ph (initial) | AN1: soc (initial) | AO1: Bdi | AP1: sand | AQ1: silt | AR1: UNIT | AS1: Treatment mapping (paper's name -> code) | AT1: Crop/season of sampling | AU1: Fertilizer dose & other management | AV1: Data source | AW1: Notes/Doubts | AX1: Treatment details (from paper) | AY1: Method used (from paper) | BA1: UNIT FOR THIS SHEET:
A2: 168 | B2: 168 | C2: Dhaliwal J.K., Singh M.J., Sharma S., Gupta N. & Kukal S.S. | D2: 2020 | E2: Soil Research | F2: India (Punjab) | G2: PAU research farm, Ludhiana (DSR-wheat tillage x mulch trial of Gupta et al. 2016) | H2: 30.933 | I2: 75.867 | J2: TEMP | K2: 2016 | L2: 4-10 Y | M2: LOAMY | N2: 0-15 CM | O2: 0-15 cm | P2: =ROUND((1-BD!P2/2.65)*100,2) -> 39.62 | Q2: =ROUND((1-BD!Q2/2.65)*100,2) -> 41.13 | R2: =ROUND((1-BD!R2/2.65)*100,2) -> 39.62 | V2: =ROUND((1-BD!V2/2.65)*100,2) -> 43.4 | AB2: 1 | AC2: 3 | AD2: =IF(AND(N(AB2)>0,N(AC2)>0),SQRT(2*AB2/AC2),"") -> 0.81649658 | AH2: 734 | AI2: 30.933 | AJ2: 5 | AM2: 7.4 | AR2: % v/v | AS2: CTW-CTDSR (-M) -> CT ; CTW+M-CTDSR -> CTR ; ZTW-ZTDSR -> ZT ; ZTW+M-ZTDSR -> CA | AT2: RICE SEASON - soil sampled in 2016 after rice harvest (no wheat-season sampling in the paper) | AU2: Fertiliser, water and pest management as PAU recommendations (doses not printed; see Gupta et al. 2016 FCR 196:219). Wheat PBW 621, 113 kg/ha, Turbo Happy Seeder, 20 cm rows; rice PR 115 DSR 40 kg/ha, 20 cm rows. +M: 7 t/ha rice residue spread between rows after wheat sowing (2.5 t/ha left at wheat harvest). Wheat straw removed in all plots. Surface soil pH 7.4 (1:2), EC 0.31 dS/m (1:2); Typic Ustochrept, sandy loam to 120 cm. | AV2: DERIVED from Table 5 BD | AW2: DERIVED (rule 73): porosity = (1 - treatment BD / PD) x 100, live link to the BD row; no treatment or initial PD in the paper -> PD = 2.65 Mg/m3 (default, flag). RICE-SEASON DATA (RED ROW): the paper samples ONLY after the 2016 rice harvest, so values are entered under the rice-season fallback rule (rule 36). Rotation-matched: CT rice + CT wheat = CT; ZT rice + ZT wheat = ZT/CA (rice residue is the mulch factor). Supplementary: none found (web search 2026-10-05; publisher site not reachable from this environment). Source file 112_real.pdf. | AX2: TREATMENTS IN PAPER (Table 1; three-factor trial est. 2011 - only the 'absolute' CT and ZT rice and wheat combinations were studied): 1 CTW-CTDSR (-M) = conventionally tilled wheat (1 discing + 1 tyne harrowing + planking) and conventionally tilled dry-seeded rice, all rice residue removed -> CT ; 2 CTW+M-CTDSR = as 1 with ALL rice residue (7 t/ha) retained as surface mulch in wheat -> CTR ; 3 ZTW-ZTDSR = zero-till wheat (Turbo Happy Seeder) and zero-till DSR (inverted-T tyne ZT drill), residue removed -> ZT ; 4 ZTW+M-ZTDSR = as 3 with rice residue mulch -> CA. Wheat straw removed in every treatment (cut 3-5 cm above ground). RBD 3 reps; plots 9.3 x 6.5 m. | AY2: Porosity = (1 - BD/PD) x 100 | BA2: % v/v
A3: 168 | B3: 168 | C3: Dhaliwal J.K., Singh M.J., Sharma S., Gupta N. & Kukal S.S. | D3: 2020 | E3: Soil Research | F3: India (Punjab) | G3: PAU research farm, Ludhiana (DSR-wheat tillage x mulch trial of Gupta et al. 2016) | H3: 30.933 | I3: 75.867 | J3: TEMP | K3: 2016 | L3: 4-10 Y | M3: LOAMY | N3: 15-30 CM | O3: 15-30 cm | P3: =ROUND((1-BD!P3/2.65)*100,2) -> 37.74 | Q3: =ROUND((1-BD!Q3/2.65)*100,2) -> 33.21 | R3: =ROUND((1-BD!R3/2.65)*100,2) -> 36.98 | V3: =ROUND((1-BD!V3/2.65)*100,2) -> 33.96 | AB3: 1 | AC3: 3 | AD3: =IF(AND(N(AB3)>0,N(AC3)>0),SQRT(2*AB3/AC3),"") -> 0.81649658 | AH3: 734 | AI3: 30.933 | AJ3: 5 | AM3: 7.4 | AR3: % v/v | AS3: CTW-CTDSR (-M) -> CT ; CTW+M-CTDSR -> CTR ; ZTW-ZTDSR -> ZT ; ZTW+M-ZTDSR -> CA | AT3: RICE SEASON - soil sampled in 2016 after rice harvest (no wheat-season sampling in the paper) | AU3: Fertiliser, water and pest management as PAU recommendations (doses not printed; see Gupta et al. 2016 FCR 196:219). Wheat PBW 621, 113 kg/ha, Turbo Happy Seeder, 20 cm rows; rice PR 115 DSR 40 kg/ha, 20 cm rows. +M: 7 t/ha rice residue spread between rows after wheat sowing (2.5 t/ha left at wheat harvest). Wheat straw removed in all plots. Surface soil pH 7.4 (1:2), EC 0.31 dS/m (1:2); Typic Ustochrept, sandy loam to 120 cm. | AV3: DERIVED from Table 5 BD | AW3: DERIVED (rule 73): porosity = (1 - treatment BD / PD) x 100, live link to the BD row; no treatment or initial PD in the paper -> PD = 2.65 Mg/m3 (default, flag). RICE-SEASON DATA (RED ROW): the paper samples ONLY after the 2016 rice harvest, so values are entered under the rice-season fallback rule (rule 36). Rotation-matched: CT rice + CT wheat = CT; ZT rice + ZT wheat = ZT/CA (rice residue is the mulch factor). Supplementary: none found (web search 2026-10-05; publisher site not reachable from this environment). Source file 112_real.pdf. | AX3: TREATMENTS IN PAPER (Table 1; three-factor trial est. 2011 - only the 'absolute' CT and ZT rice and wheat combinations were studied): 1 CTW-CTDSR (-M) = conventionally tilled wheat (1 discing + 1 tyne harrowing + planking) and conventionally tilled dry-seeded rice, all rice residue removed -> CT ; 2 CTW+M-CTDSR = as 1 with ALL rice residue (7 t/ha) retained as surface mulch in wheat -> CTR ; 3 ZTW-ZTDSR = zero-till wheat (Turbo Happy Seeder) and zero-till DSR (inverted-T tyne ZT drill), residue removed -> ZT ; 4 ZTW+M-ZTDSR = as 3 with rice residue mulch -> CA. Wheat straw removed in every treatment (cut 3-5 cm above ground). RBD 3 reps; plots 9.3 x 6.5 m. | AY3: Porosity = (1 - BD/PD) x 100
A4: 165 | B4: 165 | C4: Davari M.R., Sharma S.N. & Mirzakhani M. | D4: 2012 | E4: Biological Agriculture & Horticulture | F4: India (Delhi) | G4: IARI research farm, New Delhi (organic rice-based cropping systems trial) | H4: 28.633 | I4: 77.183 | J4: ST | K4: 2007-08 | L4: 0-3 Y | M4: LOAMY | N4: 0-15 CM | O4: 0-15 cm | Q4: 44.9 | V4: 47.2 | AB4: 1 | AC4: 3 | AD4: =IF(AND(N(AB4)>0,N(AC4)>0),SQRT(2*AB4/AC4),"") -> 0.81649658 | AE4: 25.4 | AI4: 28.633 | AJ4: 2 | AM4: 8.16 | AN4: 5.2 | AO4: 1.5 | AP4: 52.06 | AQ4: 22.54 | AR4: % v/v (printed) | AS4: RW-RR -> CT ; RW-RI -> CTR | AT4: After completion of two cycles (June 2008, after wheat / fallow) | AU4: ORGANIC: FYM equivalent to 60 kg N/ha to rice and to wheat (FYM ~0.61% N, 22-23 C:N), no mineral fertiliser; BGA 1.5 kg/ha in rice 20 DAT; Azotobacter + PSB seed inoculation of wheat; cellulolytic fungal culture 600 g/t sprayed on residue in RI plots only. RI residue added (Mg DM/ha): RW 14.2 (2006-07), 16.0 (2007-08); RWM 17.8, 19.7. Initial soil: SCL, EC 0.79 dS/m, CEC 14.73 cmol/kg, OC 5.2 g/kg, Kjeldahl N 580 mg/kg, Olsen P 8.42, NH4OAc K 187 mg/kg, BD 1.50, FC 24.57%. | AV4: Table 9 | AW4: PRINTED porosity (paper derived it from BD and PD; values reproduce PD = 2.65). LSD residue 1.46. 15-30 cm values not printed (not significantly different). Rotation-matched: puddled transplanted rice + disc-tilled wheat = conventional in both phases; residue incorporated by disc -> CTR. FLAG: RI plots also received a cellulolytic culture spray (confounded with residue). Supplementary: none found (web search 2026-10-05; publisher site not reachable). Source file 113_rqal.pdf. | AX4: TREATMENTS IN PAPER: strip-plot, 3 reps, 2006-07 and 2007-08, ORGANIC management. Rows = cropping system: RW (rice-wheat, summer fallow) and RWM (rice-wheat-mungbean, summer mungbean with Rhizobium + PSB); columns = residue: RR (entire above-ground biomass removed) and RI (all residue of each crop incorporated before the next crop: rice residue for wheat, wheat residue for rice in RW / for mungbean in RWM, mungbean residue for rice). Rice: field flooded and PUDDLED with tractor-drawn offset disc harrow, Pusa Basmati 1 transplanted 20 x 10 cm. Wheat: after rice harvest, residue (RI) + FYM incorporated with tractor-drawn heavy disc, then disked and planked twice; HD 2643 sown 3rd week Nov. RR -> CT, RI -> CTR (in both systems). | AY4: Porosity = (1 - BD/PD) x 100 (authors' calculation)
A5: 165 | B5: 165 | C5: Davari M.R., Sharma S.N. & Mirzakhani M. | D5: 2012 | E5: Biological Agriculture & Horticulture | F5: India (Delhi) | G5: IARI research farm, New Delhi (organic rice-based cropping systems trial) | H5: 28.633 | I5: 77.183 | J5: ST | K5: 2007-08 | L5: 0-3 Y | M5: LOAMY | N5: 0-15 CM | O5: 0-15 cm | Q5: 45.7 | V5: 48 | AB5: 1 | AC5: 3 | AD5: =IF(AND(N(AB5)>0,N(AC5)>0),SQRT(2*AB5/AC5),"") -> 0.81649658 | AE5: 25.4 | AI5: 28.633 | AJ5: 2 | AM5: 8.16 | AN5: 5.2 | AO5: 1.5 | AP5: 52.06 | AQ5: 22.54 | AR5: % v/v (printed) | AS5: RWM-RR -> CT ; RWM-RI -> CTR | AT5: After completion of two cycles (June 2008, after wheat and mungbean) | AU5: ORGANIC: FYM equivalent to 60 kg N/ha to rice and to wheat (FYM ~0.61% N, 22-23 C:N), no mineral fertiliser; BGA 1.5 kg/ha in rice 20 DAT; Azotobacter + PSB seed inoculation of wheat; cellulolytic fungal culture 600 g/t sprayed on residue in RI plots only. RI residue added (Mg DM/ha): RW 14.2 (2006-07), 16.0 (2007-08); RWM 17.8, 19.7. Initial soil: SCL, EC 0.79 dS/m, CEC 14.73 cmol/kg, OC 5.2 g/kg, Kjeldahl N 580 mg/kg, Olsen P 8.42, NH4OAc K 187 mg/kg, BD 1.50, FC 24.57%. | AV5: Table 9 | AW5: PRINTED porosity (paper derived it from BD and PD; values reproduce PD = 2.65). LSD residue 1.46. GREEN MANURE / 3rd CROP: summer mungbean in BOTH treatments of this row (pods picked, residue incorporated in RI only). 15-30 cm values not printed (not significantly different). Rotation-matched: puddled transplanted rice + disc-tilled wheat = conventional in both phases; residue incorporated by disc -> CTR. FLAG: RI plots also received a cellulolytic culture spray (confounded with residue). Supplementary: none found (web search 2026-10-05; publisher site not reachable). Source file 113_rqal.pdf. | AX5: TREATMENTS IN PAPER: strip-plot, 3 reps, 2006-07 and 2007-08, ORGANIC management. Rows = cropping system: RW (rice-wheat, summer fallow) and RWM (rice-wheat-mungbean, summer mungbean with Rhizobium + PSB); columns = residue: RR (entire above-ground biomass removed) and RI (all residue of each crop incorporated before the next crop: rice residue for wheat, wheat residue for rice in RW / for mungbean in RWM, mungbean residue for rice). Rice: field flooded and PUDDLED with tractor-drawn offset disc harrow, Pusa Basmati 1 transplanted 20 x 10 cm. Wheat: after rice harvest, residue (RI) + FYM incorporated with tractor-drawn heavy disc, then disked and planked twice; HD 2643 sown 3rd week Nov. RR -> CT, RI -> CTR (in both systems). | AY5: Porosity = (1 - BD/PD) x 100 (authors' calculation) | BA5: Mg/m3

Sheet macro pore
A1: No. | B1: SERIAL NO | C1: Authors | D1: Year | E1: Journal | F1: Country | G1: Site/Location | H1: latitude | I1: longitude | J1: CLIMATE | K1: year of data collection/experiment | L1: DURATION | M1: SOIL | N1: DEPTH | O1: DEPTH (as reported in paper) | P1: MACROPORE_CA | Q1: MACROPORE_CT | R1: MACROPORE_ZT | S1: MACROPORE_DT | T1: MACROPORE_MTR | U1: MACROPORE_MT | V1: MACROPORE_CTR | W1: MACROPORE_DTR | X1: MACROPORE_pCA | Y1: MACROPORE_pZT | Z1: MACROPORE_pMT | AA1: MACROPORE_pMTR | AB1: Obs | AC1: Rep | AD1: SD | AE1: CLAY | AF1: MIN TEMP | AG1: MAX TEMP | AH1: RAIN FALL | AI1: LATT | AJ1: YEAR OF DATA (duration) | AK1: AVG T | AL1: April max temp | AM1: ph (initial) | AN1: soc (initial) | AO1: Bdi | AP1: sand | AQ1: silt | AR1: UNIT | AS1: Treatment mapping (paper's name -> code) | AT1: Crop/season of sampling | AU1: Fertilizer dose & other management | AV1: Data source | AW1: Notes/Doubts | AX1: Treatment details (from paper) | AY1: Method used (from paper) | BA1: UNIT FOR THIS SHEET:
BA2: % v/v

Sheet meso pore
A1: No. | B1: SERIAL NO | C1: Authors | D1: Year | E1: Journal | F1: Country | G1: Site/Location | H1: latitude | I1: longitude | J1: CLIMATE | K1: year of data collection/experiment | L1: DURATION | M1: SOIL | N1: DEPTH | O1: DEPTH (as reported in paper) | P1: MESOPORE_CA | Q1: MESOPORE_CT | R1: MESOPORE_ZT | S1: MESOPORE_DT | T1: MESOPORE_MTR | U1: MESOPORE_MT | V1: MESOPORE_CTR | W1: MESOPORE_DTR | X1: MESOPORE_pCA | Y1: MESOPORE_pZT | Z1: MESOPORE_pMT | AA1: MESOPORE_pMTR | AB1: Obs | AC1: Rep | AD1: SD | AE1: CLAY | AF1: MIN TEMP | AG1: MAX TEMP | AH1: RAIN FALL | AI1: LATT | AJ1: YEAR OF DATA (duration) | AK1: AVG T | AL1: April max temp | AM1: ph (initial) | AN1: soc (initial) | AO1: Bdi | AP1: sand | AQ1: silt | AR1: UNIT | AS1: Treatment mapping (paper's name -> code) | AT1: Crop/season of sampling | AU1: Fertilizer dose & other management | AV1: Data source | AW1: Notes/Doubts | AX1: Treatment details (from paper) | AY1: Method used (from paper) | BA1: UNIT FOR THIS SHEET:
BA2: % v/v

Sheet micro pore
A1: No. | B1: SERIAL NO | C1: Authors | D1: Year | E1: Journal | F1: Country | G1: Site/Location | H1: latitude | I1: longitude | J1: CLIMATE | K1: year of data collection/experiment | L1: DURATION | M1: SOIL | N1: DEPTH | O1: DEPTH (as reported in paper) | P1: MICROPORE_CA | Q1: MICROPORE_CT | R1: MICROPORE_ZT | S1: MICROPORE_DT | T1: MICROPORE_MTR | U1: MICROPORE_MT | V1: MICROPORE_CTR | W1: MICROPORE_DTR | X1: MICROPORE_pCA | Y1: MICROPORE_pZT | Z1: MICROPORE_pMT | AA1: MICROPORE_pMTR | AB1: Obs | AC1: Rep | AD1: SD | AE1: CLAY | AF1: MIN TEMP | AG1: MAX TEMP | AH1: RAIN FALL | AI1: LATT | AJ1: YEAR OF DATA (duration) | AK1: AVG T | AL1: April max temp | AM1: ph (initial) | AN1: soc (initial) | AO1: Bdi | AP1: sand | AQ1: silt | AR1: UNIT | AS1: Treatment mapping (paper's name -> code) | AT1: Crop/season of sampling | AU1: Fertilizer dose & other management | AV1: Data source | AW1: Notes/Doubts | AX1: Treatment details (from paper) | AY1: Method used (from paper) | BA1: UNIT FOR THIS SHEET:
BA2: % v/v

Sheet MWD 1
A1: No. | B1: SERIAL NO | C1: Authors | D1: Year | E1: Journal | F1: Country | G1: Site/Location | H1: latitude | I1: longitude | J1: CLIMATE | K1: year of data collection/experiment | L1: DURATION | M1: SOIL | N1: DEPTH | O1: DEPTH (as reported in paper) | P1: MWD_CA | Q1: MWD_CT | R1: MWD_ZT | S1: MWD_DT | T1: MWD_MTR | U1: MWD_MT | V1: MWD_CTR | W1: MWD_DTR | X1: MWD_pCA | Y1: MWD_pZT | Z1: MWD_pMT | AA1: MWD_pMTR | AB1: Obs | AC1: Rep | AD1: SD | AE1: CLAY | AF1: MIN TEMP | AG1: MAX TEMP | AH1: RAIN FALL | AI1: LATT | AJ1: YEAR OF DATA (duration) | AK1: AVG T | AL1: April max temp | AM1: ph (initial) | AN1: soc (initial) | AO1: Bdi | AP1: sand | AQ1: silt | AR1: UNIT | AS1: Treatment mapping (paper's name -> code) | AT1: Crop/season of sampling | AU1: Fertilizer dose & other management | AV1: Data source | AW1: Notes/Doubts | AX1: Treatment details (from paper) | AY1: Method used (from paper) | BA1: UNIT FOR THIS SHEET:
A2: 168 | B2: 168 | C2: Dhaliwal J.K., Singh M.J., Sharma S., Gupta N. & Kukal S.S. | D2: 2020 | E2: Soil Research | F2: India (Punjab) | G2: PAU research farm, Ludhiana (DSR-wheat tillage x mulch trial of Gupta et al. 2016) | H2: 30.933 | I2: 75.867 | J2: TEMP | K2: 2016 | L2: 4-10 Y | M2: LOAMY | N2: 0-15 CM | O2: 0-15 cm | P2: 1.33 | Q2: 0.46 | R2: 0.99 | V2: 1.21 | AB2: 1 | AC2: 3 | AD2: =IF(AND(N(AB2)>0,N(AC2)>0),SQRT(2*AB2/AC2),"") -> 0.81649658 | AH2: 734 | AI2: 30.933 | AJ2: 5 | AM2: 7.4 | AR2: mm (wet sieving) | AS2: CTW-CTDSR (-M) -> CT ; CTW+M-CTDSR -> CTR ; ZTW-ZTDSR -> ZT ; ZTW+M-ZTDSR -> CA | AT2: RICE SEASON - soil sampled in 2016 after rice harvest (no wheat-season sampling in the paper) | AU2: Fertiliser, water and pest management as PAU recommendations (doses not printed; see Gupta et al. 2016 FCR 196:219). Wheat PBW 621, 113 kg/ha, Turbo Happy Seeder, 20 cm rows; rice PR 115 DSR 40 kg/ha, 20 cm rows. +M: 7 t/ha rice residue spread between rows after wheat sowing (2.5 t/ha left at wheat harvest). Wheat straw removed in all plots. Surface soil pH 7.4 (1:2), EC 0.31 dS/m (1:2); Typic Ustochrept, sandy loam to 120 cm. | AV2: Table 4 | AW2: RICE-SEASON DATA (RED ROW): the paper samples ONLY after the 2016 rice harvest, so values are entered under the rice-season fallback rule (rule 36). Rotation-matched: CT rice + CT wheat = CT; ZT rice + ZT wheat = ZT/CA (rice residue is the mulch factor). Supplementary: none found (web search 2026-10-05; publisher site not reachable from this environment). Source file 112_real.pdf. LSD (0-15) T 0.23, M 0.23, TxM 0.30; (15-30) T 0.09. | AX2: TREATMENTS IN PAPER (Table 1; three-factor trial est. 2011 - only the 'absolute' CT and ZT rice and wheat combinations were studied): 1 CTW-CTDSR (-M) = conventionally tilled wheat (1 discing + 1 tyne harrowing + planking) and conventionally tilled dry-seeded rice, all rice residue removed -> CT ; 2 CTW+M-CTDSR = as 1 with ALL rice residue (7 t/ha) retained as surface mulch in wheat -> CTR ; 3 ZTW-ZTDSR = zero-till wheat (Turbo Happy Seeder) and zero-till DSR (inverted-T tyne ZT drill), residue removed -> ZT ; 4 ZTW+M-ZTDSR = as 3 with rice residue mulch -> CA. Wheat straw removed in every treatment (cut 3-5 cm above ground). RBD 3 reps; plots 9.3 x 6.5 m. | AY2: Wet sieving, Yoder apparatus (Kemper & Rosenau 1986): 50 g air-dry 5-8 mm aggregates, capillary pre-wetting 10 min, sieves 2, 1, 0.5, 0.25, 0.1 mm, 30 min at 30 osc/min; sand-corrected (Na-hexametaphosphate); MWD = sum(di*wi)/sum(wi) (Youker & McGuinness 1957) | BA2: mm (wet sieving)
A3: 168 | B3: 168 | C3: Dhaliwal J.K., Singh M.J., Sharma S., Gupta N. & Kukal S.S. | D3: 2020 | E3: Soil Research | F3: India (Punjab) | G3: PAU research farm, Ludhiana (DSR-wheat tillage x mulch trial of Gupta et al. 2016) | H3: 30.933 | I3: 75.867 | J3: TEMP | K3: 2016 | L3: 4-10 Y | M3: LOAMY | N3: 15-30 CM | O3: 15-30 cm | P3: 0.5 | Q3: 0.35 | R3: 0.42 | V3: 0.27 | AB3: 1 | AC3: 3 | AD3: =IF(AND(N(AB3)>0,N(AC3)>0),SQRT(2*AB3/AC3),"") -> 0.81649658 | AH3: 734 | AI3: 30.933 | AJ3: 5 | AM3: 7.4 | AR3: mm (wet sieving) | AS3: CTW-CTDSR (-M) -> CT ; CTW+M-CTDSR -> CTR ; ZTW-ZTDSR -> ZT ; ZTW+M-ZTDSR -> CA | AT3: RICE SEASON - soil sampled in 2016 after rice harvest (no wheat-season sampling in the paper) | AU3: Fertiliser, water and pest management as PAU recommendations (doses not printed; see Gupta et al. 2016 FCR 196:219). Wheat PBW 621, 113 kg/ha, Turbo Happy Seeder, 20 cm rows; rice PR 115 DSR 40 kg/ha, 20 cm rows. +M: 7 t/ha rice residue spread between rows after wheat sowing (2.5 t/ha left at wheat harvest). Wheat straw removed in all plots. Surface soil pH 7.4 (1:2), EC 0.31 dS/m (1:2); Typic Ustochrept, sandy loam to 120 cm. | AV3: Table 4 | AW3: RICE-SEASON DATA (RED ROW): the paper samples ONLY after the 2016 rice harvest, so values are entered under the rice-season fallback rule (rule 36). Rotation-matched: CT rice + CT wheat = CT; ZT rice + ZT wheat = ZT/CA (rice residue is the mulch factor). Supplementary: none found (web search 2026-10-05; publisher site not reachable from this environment). Source file 112_real.pdf. LSD (0-15) T 0.23, M 0.23, TxM 0.30; (15-30) T 0.09. | AX3: TREATMENTS IN PAPER (Table 1; three-factor trial est. 2011 - only the 'absolute' CT and ZT rice and wheat combinations were studied): 1 CTW-CTDSR (-M) = conventionally tilled wheat (1 discing + 1 tyne harrowing + planking) and conventionally tilled dry-seeded rice, all rice residue removed -> CT ; 2 CTW+M-CTDSR = as 1 with ALL rice residue (7 t/ha) retained as surface mulch in wheat -> CTR ; 3 ZTW-ZTDSR = zero-till wheat (Turbo Happy Seeder) and zero-till DSR (inverted-T tyne ZT drill), residue removed -> ZT ; 4 ZTW+M-ZTDSR = as 3 with rice residue mulch -> CA. Wheat straw removed in every treatment (cut 3-5 cm above ground). RBD 3 reps; plots 9.3 x 6.5 m. | AY3: Wet sieving, Yoder apparatus (Kemper & Rosenau 1986): 50 g air-dry 5-8 mm aggregates, capillary pre-wetting 10 min, sieves 2, 1, 0.5, 0.25, 0.1 mm, 30 min at 30 osc/min; sand-corrected (Na-hexametaphosphate); MWD = sum(di*wi)/sum(wi) (Youker & McGuinness 1957)
A4: 166 | B4: 166 | C4: Das B., Chakraborty D., Singh V.K., Aggarwal P., Singh R., Dwivedi B.S. & Mishra R.P. | D4: 2014 | E4: Soil & Tillage Research | F4: India (Uttar Pradesh) | G4: PDFSR (now ICAR-IIFSR) long-term INM experiment, Modipuram, Meerut | H4: 29.067 | I4: 77.767 | J4: ST | K4: 2011 | L4: >10 Y | M4: LOAMY | N4: 0-15 CM | O4: 0-7.5 cm | Q4: 1.41 | V4: 2.36 | AB4: 2 | AC4: 3 | AD4: =IF(AND(N(AB4)>0,N(AC4)>0),SQRT(2*AB4/AC4),"") -> 1.1547005 | AE4: 27 | AF4: 5 | AG4: 45.5 | AH4: 863 | AI4: 29.067 | AJ4: 18 | AM4: 7.98 | AN4: 4.1 | AO4: 1.55 | AP4: 55 | AQ4: 18 | AR4: mm (wet sieving, SLAKED pre-treatment) | AS4: T2 (100% NPK, residues removed) -> CT ; T8 (75% NPK + 25% N via crop residue, both crops) -> CTR [FLAG: fertiliser offset] | AT4: Wheat season - sampled 14 May 2011 after wheat harvest (18th year) | AU4: T2: 120-26-33 kg N-P-K/ha to rice and wheat + Zn 5 kg/ha to rice. T8: 75% of NPK + 25% of N through wheat straw (rice) and rice straw (wheat); 1993-2011 organic C added by CR 61.54 (rice) + 47.72 (wheat) Mg C/ha; total C input T2 40.54, T8 154.36 Mg C/ha. Rice continuous submergence; wheat 5 irrigations. Initial soil: SL, EC 0.4 dS/m, Olsen P 16.4, avail. K 96, S 14.5 kg/ha, WHC 42%. | AV4: Fig. 2a (digitised) | AW4: SLAKED aggregates (fast wetting). DIGITISED from the raster Fig. 2a (approx.). Obs = 2 (D=2: 0-7.5 and 7.5-15 cm both in the 0-15 CM class, separate rows). FLAG - FERTILISER OFFSET (rule 62): in T8 crop residue replaces 25% of fertiliser N and 25% of P and K are also cut; drop for a fertiliser-matched sensitivity check. Wheat tillage not described in detail ('wet tillage followed by dry tillage', residue incorporated) -> conventional. Supplementary: none found (web search 2026-10-05; publisher site not reachable). Source file 113.pdf. | AX4: TREATMENTS IN PAPER (Table 1, RBD 3 reps, since 1993, PDFSR Modipuram): T1 unfertilised; T2 recommended NPK (+Zn to rice) through fertilisers; T3 NPK + Zn + S (rice); T4 75% NPK + 25% N via FYM (rice); T5 75% NPK + 25% N via sulphitation press mud (rice); T6 75% NPK + green gram residue incorporated before rice; T7 = T6 (rice) + 75% NPK + 25% N via FYM (wheat); T8 75% NPK + 25% N via WHEAT STRAW to rice and 75% NPK + 25% N via RICE STRAW to wheat (CR). Rice puddled and transplanted (Saket 4, 20 x 10 cm, continuous 5 cm submergence); wheat HD 2338 drilled after dry tillage ('wet tillage followed by dry tillage'); recommended 120-26-33 kg N-P-K/ha to each crop. T2 -> CT ; T8 -> CTR (FLAG fertiliser offset, rule 62); T1, T3-T7 EXCLUDED (unfertilised / amendments / third crop in some treatments only). | AY4: Wet sieving after slaking (rapid immersion), Kemper & Rosenau (1986) MWD
A5: 166 | B5: 166 | C5: Das B., Chakraborty D., Singh V.K., Aggarwal P., Singh R., Dwivedi B.S. & Mishra R.P. | D5: 2014 | E5: Soil & Tillage Research | F5: India (Uttar Pradesh) | G5: PDFSR (now ICAR-IIFSR) long-term INM experiment, Modipuram, Meerut | H5: 29.067 | I5: 77.767 | J5: ST | K5: 2011 | L5: >10 Y | M5: LOAMY | N5: 0-15 CM | O5: 0-7.5 cm | Q5: 3.86 | V5: 4.32 | AB5: 2 | AC5: 3 | AD5: =IF(AND(N(AB5)>0,N(AC5)>0),SQRT(2*AB5/AC5),"") -> 1.1547005 | AE5: 27 | AF5: 5 | AG5: 45.5 | AH5: 863 | AI5: 29.067 | AJ5: 18 | AM5: 7.98 | AN5: 4.1 | AO5: 1.55 | AP5: 55 | AQ5: 18 | AR5: mm (wet sieving, CAPILLARY-REWETTED pre-treatment) | AS5: T2 (100% NPK, residues removed) -> CT ; T8 (75% NPK + 25% N via crop residue, both crops) -> CTR [FLAG: fertiliser offset] | AT5: Wheat season - sampled 14 May 2011 after wheat harvest (18th year) | AU5: T2: 120-26-33 kg N-P-K/ha to rice and wheat + Zn 5 kg/ha to rice. T8: 75% of NPK + 25% of N through wheat straw (rice) and rice straw (wheat); 1993-2011 organic C added by CR 61.54 (rice) + 47.72 (wheat) Mg C/ha; total C input T2 40.54, T8 154.36 Mg C/ha. Rice continuous submergence; wheat 5 irrigations. Initial soil: SL, EC 0.4 dS/m, Olsen P 16.4, avail. K 96, S 14.5 kg/ha, WHC 42%. | AV5: Fig. 2b (digitised) | AW5: CAPILLARY-REWETTED (slow-wetting) pre-treatment - second MWD of the same soil; filter on this flag to keep one MWD per study. DIGITISED from Fig. 2b (approx.). Obs = 2 (D=2: 0-7.5 and 7.5-15 cm both in the 0-15 CM class, separate rows). FLAG - FERTILISER OFFSET (rule 62): in T8 crop residue replaces 25% of fertiliser N and 25% of P and K are also cut; drop for a fertiliser-matched sensitivity check. Wheat tillage not described in detail ('wet tillage followed by dry tillage', residue incorporated) -> conventional. Supplementary: none found (web search 2026-10-05; publisher site not reachable). Source file 113.pdf. | AX5: TREATMENTS IN PAPER (Table 1, RBD 3 reps, since 1993, PDFSR Modipuram): T1 unfertilised; T2 recommended NPK (+Zn to rice) through fertilisers; T3 NPK + Zn + S (rice); T4 75% NPK + 25% N via FYM (rice); T5 75% NPK + 25% N via sulphitation press mud (rice); T6 75% NPK + green gram residue incorporated before rice; T7 = T6 (rice) + 75% NPK + 25% N via FYM (wheat); T8 75% NPK + 25% N via WHEAT STRAW to rice and 75% NPK + 25% N via RICE STRAW to wheat (CR). Rice puddled and transplanted (Saket 4, 20 x 10 cm, continuous 5 cm submergence); wheat HD 2338 drilled after dry tillage ('wet tillage followed by dry tillage'); recommended 120-26-33 kg N-P-K/ha to each crop. T2 -> CT ; T8 -> CTR (FLAG fertiliser offset, rule 62); T1, T3-T7 EXCLUDED (unfertilised / amendments / third crop in some treatments only). | AY5: Wet sieving after capillary re-wetting to field capacity (slow wetting)
A6: 166 | B6: 166 | C6: Das B., Chakraborty D., Singh V.K., Aggarwal P., Singh R., Dwivedi B.S. & Mishra R.P. | D6: 2014 | E6: Soil & Tillage Research | F6: India (Uttar Pradesh) | G6: PDFSR (now ICAR-IIFSR) long-term INM experiment, Modipuram, Meerut | H6: 29.067 | I6: 77.767 | J6: ST | K6: 2011 | L6: >10 Y | M6: LOAMY | N6: 0-15 CM | O6: 7.5-15 cm | Q6: 1.17 | V6: 1.64 | AB6: 2 | AC6: 3 | AD6: =IF(AND(N(AB6)>0,N(AC6)>0),SQRT(2*AB6/AC6),"") -> 1.1547005 | AE6: 27 | AF6: 5 | AG6: 45.5 | AH6: 863 | AI6: 29.067 | AJ6: 18 | AM6: 7.98 | AN6: 4.1 | AO6: 1.55 | AP6: 55 | AQ6: 18 | AR6: mm (wet sieving, SLAKED pre-treatment) | AS6: T2 (100% NPK, residues removed) -> CT ; T8 (75% NPK + 25% N via crop residue, both crops) -> CTR [FLAG: fertiliser offset] | AT6: Wheat season - sampled 14 May 2011 after wheat harvest (18th year) | AU6: T2: 120-26-33 kg N-P-K/ha to rice and wheat + Zn 5 kg/ha to rice. T8: 75% of NPK + 25% of N through wheat straw (rice) and rice straw (wheat); 1993-2011 organic C added by CR 61.54 (rice) + 47.72 (wheat) Mg C/ha; total C input T2 40.54, T8 154.36 Mg C/ha. Rice continuous submergence; wheat 5 irrigations. Initial soil: SL, EC 0.4 dS/m, Olsen P 16.4, avail. K 96, S 14.5 kg/ha, WHC 42%. | AV6: Fig. 2a (digitised) | AW6: SLAKED aggregates (fast wetting). DIGITISED from the raster Fig. 2a (approx.). Obs = 2 (D=2: 0-7.5 and 7.5-15 cm both in the 0-15 CM class, separate rows). FLAG - FERTILISER OFFSET (rule 62): in T8 crop residue replaces 25% of fertiliser N and 25% of P and K are also cut; drop for a fertiliser-matched sensitivity check. Wheat tillage not described in detail ('wet tillage followed by dry tillage', residue incorporated) -> conventional. Supplementary: none found (web search 2026-10-05; publisher site not reachable). Source file 113.pdf. | AX6: TREATMENTS IN PAPER (Table 1, RBD 3 reps, since 1993, PDFSR Modipuram): T1 unfertilised; T2 recommended NPK (+Zn to rice) through fertilisers; T3 NPK + Zn + S (rice); T4 75% NPK + 25% N via FYM (rice); T5 75% NPK + 25% N via sulphitation press mud (rice); T6 75% NPK + green gram residue incorporated before rice; T7 = T6 (rice) + 75% NPK + 25% N via FYM (wheat); T8 75% NPK + 25% N via WHEAT STRAW to rice and 75% NPK + 25% N via RICE STRAW to wheat (CR). Rice puddled and transplanted (Saket 4, 20 x 10 cm, continuous 5 cm submergence); wheat HD 2338 drilled after dry tillage ('wet tillage followed by dry tillage'); recommended 120-26-33 kg N-P-K/ha to each crop. T2 -> CT ; T8 -> CTR (FLAG fertiliser offset, rule 62); T1, T3-T7 EXCLUDED (unfertilised / amendments / third crop in some treatments only). | AY6: Wet sieving after slaking (rapid immersion), Kemper & Rosenau (1986) MWD
A7: 166 | B7: 166 | C7: Das B., Chakraborty D., Singh V.K., Aggarwal P., Singh R., Dwivedi B.S. & Mishra R.P. | D7: 2014 | E7: Soil & Tillage Research | F7: India (Uttar Pradesh) | G7: PDFSR (now ICAR-IIFSR) long-term INM experiment, Modipuram, Meerut | H7: 29.067 | I7: 77.767 | J7: ST | K7: 2011 | L7: >10 Y | M7: LOAMY | N7: 0-15 CM | O7: 7.5-15 cm | Q7: 3.65 | V7: 3.93 | AB7: 2 | AC7: 3 | AD7: =IF(AND(N(AB7)>0,N(AC7)>0),SQRT(2*AB7/AC7),"") -> 1.1547005 | AE7: 27 | AF7: 5 | AG7: 45.5 | AH7: 863 | AI7: 29.067 | AJ7: 18 | AM7: 7.98 | AN7: 4.1 | AO7: 1.55 | AP7: 55 | AQ7: 18 | AR7: mm (wet sieving, CAPILLARY-REWETTED pre-treatment) | AS7: T2 (100% NPK, residues removed) -> CT ; T8 (75% NPK + 25% N via crop residue, both crops) -> CTR [FLAG: fertiliser offset] | AT7: Wheat season - sampled 14 May 2011 after wheat harvest (18th year) | AU7: T2: 120-26-33 kg N-P-K/ha to rice and wheat + Zn 5 kg/ha to rice. T8: 75% of NPK + 25% of N through wheat straw (rice) and rice straw (wheat); 1993-2011 organic C added by CR 61.54 (rice) + 47.72 (wheat) Mg C/ha; total C input T2 40.54, T8 154.36 Mg C/ha. Rice continuous submergence; wheat 5 irrigations. Initial soil: SL, EC 0.4 dS/m, Olsen P 16.4, avail. K 96, S 14.5 kg/ha, WHC 42%. | AV7: Fig. 2b (digitised) | AW7: CAPILLARY-REWETTED (slow-wetting) pre-treatment - second MWD of the same soil; filter on this flag to keep one MWD per study. DIGITISED from Fig. 2b (approx.). Obs = 2 (D=2: 0-7.5 and 7.5-15 cm both in the 0-15 CM class, separate rows). FLAG - FERTILISER OFFSET (rule 62): in T8 crop residue replaces 25% of fertiliser N and 25% of P and K are also cut; drop for a fertiliser-matched sensitivity check. Wheat tillage not described in detail ('wet tillage followed by dry tillage', residue incorporated) -> conventional. Supplementary: none found (web search 2026-10-05; publisher site not reachable). Source file 113.pdf. | AX7: TREATMENTS IN PAPER (Table 1, RBD 3 reps, since 1993, PDFSR Modipuram): T1 unfertilised; T2 recommended NPK (+Zn to rice) through fertilisers; T3 NPK + Zn + S (rice); T4 75% NPK + 25% N via FYM (rice); T5 75% NPK + 25% N via sulphitation press mud (rice); T6 75% NPK + green gram residue incorporated before rice; T7 = T6 (rice) + 75% NPK + 25% N via FYM (wheat); T8 75% NPK + 25% N via WHEAT STRAW to rice and 75% NPK + 25% N via RICE STRAW to wheat (CR). Rice puddled and transplanted (Saket 4, 20 x 10 cm, continuous 5 cm submergence); wheat HD 2338 drilled after dry tillage ('wet tillage followed by dry tillage'); recommended 120-26-33 kg N-P-K/ha to each crop. T2 -> CT ; T8 -> CTR (FLAG fertiliser offset, rule 62); T1, T3-T7 EXCLUDED (unfertilised / amendments / third crop in some treatments only). | AY7: Wet sieving after capillary re-wetting to field capacity (slow wetting)
A8: 166 | B8: 166 | C8: Das B., Chakraborty D., Singh V.K., Aggarwal P., Singh R., Dwivedi B.S. & Mishra R.P. | D8: 2014 | E8: Soil & Tillage Research | F8: India (Uttar Pradesh) | G8: PDFSR (now ICAR-IIFSR) long-term INM experiment, Modipuram, Meerut | H8: 29.067 | I8: 77.767 | J8: ST | K8: 2011 | L8: >10 Y | M8: LOAMY | N8: 15-30 CM | O8: 15-30 cm | Q8: 0.93 | V8: 1.62 | AB8: 1 | AC8: 3 | AD8: =IF(AND(N(AB8)>0,N(AC8)>0),SQRT(2*AB8/AC8),"") -> 0.81649658 | AE8: 27 | AF8: 5 | AG8: 45.5 | AH8: 863 | AI8: 29.067 | AJ8: 18 | AM8: 7.98 | AN8: 4.1 | AO8: 1.55 | AP8: 55 | AQ8: 18 | AR8: mm (wet sieving, SLAKED pre-treatment) | AS8: T2 (100% NPK, residues removed) -> CT ; T8 (75% NPK + 25% N via crop residue, both crops) -> CTR [FLAG: fertiliser offset] | AT8: Wheat season - sampled 14 May 2011 after wheat harvest (18th year) | AU8: T2: 120-26-33 kg N-P-K/ha to rice and wheat + Zn 5 kg/ha to rice. T8: 75% of NPK + 25% of N through wheat straw (rice) and rice straw (wheat); 1993-2011 organic C added by CR 61.54 (rice) + 47.72 (wheat) Mg C/ha; total C input T2 40.54, T8 154.36 Mg C/ha. Rice continuous submergence; wheat 5 irrigations. Initial soil: SL, EC 0.4 dS/m, Olsen P 16.4, avail. K 96, S 14.5 kg/ha, WHC 42%. | AV8: Fig. 2a (digitised) | AW8: SLAKED aggregates (fast wetting). DIGITISED from the raster Fig. 2a (approx.). Obs = 1 (D=1: one layer). FLAG - FERTILISER OFFSET (rule 62): in T8 crop residue replaces 25% of fertiliser N and 25% of P and K are also cut; drop for a fertiliser-matched sensitivity check. Wheat tillage not described in detail ('wet tillage followed by dry tillage', residue incorporated) -> conventional. Supplementary: none found (web search 2026-10-05; publisher site not reachable). Source file 113.pdf. | AX8: TREATMENTS IN PAPER (Table 1, RBD 3 reps, since 1993, PDFSR Modipuram): T1 unfertilised; T2 recommended NPK (+Zn to rice) through fertilisers; T3 NPK + Zn + S (rice); T4 75% NPK + 25% N via FYM (rice); T5 75% NPK + 25% N via sulphitation press mud (rice); T6 75% NPK + green gram residue incorporated before rice; T7 = T6 (rice) + 75% NPK + 25% N via FYM (wheat); T8 75% NPK + 25% N via WHEAT STRAW to rice and 75% NPK + 25% N via RICE STRAW to wheat (CR). Rice puddled and transplanted (Saket 4, 20 x 10 cm, continuous 5 cm submergence); wheat HD 2338 drilled after dry tillage ('wet tillage followed by dry tillage'); recommended 120-26-33 kg N-P-K/ha to each crop. T2 -> CT ; T8 -> CTR (FLAG fertiliser offset, rule 62); T1, T3-T7 EXCLUDED (unfertilised / amendments / third crop in some treatments only). | AY8: Wet sieving after slaking (rapid immersion), Kemper & Rosenau (1986) MWD
A9: 166 | B9: 166 | C9: Das B., Chakraborty D., Singh V.K., Aggarwal P., Singh R., Dwivedi B.S. & Mishra R.P. | D9: 2014 | E9: Soil & Tillage Research | F9: India (Uttar Pradesh) | G9: PDFSR (now ICAR-IIFSR) long-term INM experiment, Modipuram, Meerut | H9: 29.067 | I9: 77.767 | J9: ST | K9: 2011 | L9: >10 Y | M9: LOAMY | N9: 15-30 CM | O9: 15-30 cm | Q9: 3.38 | V9: 3.85 | AB9: 1 | AC9: 3 | AD9: =IF(AND(N(AB9)>0,N(AC9)>0),SQRT(2*AB9/AC9),"") -> 0.81649658 | AE9: 27 | AF9: 5 | AG9: 45.5 | AH9: 863 | AI9: 29.067 | AJ9: 18 | AM9: 7.98 | AN9: 4.1 | AO9: 1.55 | AP9: 55 | AQ9: 18 | AR9: mm (wet sieving, CAPILLARY-REWETTED pre-treatment) | AS9: T2 (100% NPK, residues removed) -> CT ; T8 (75% NPK + 25% N via crop residue, both crops) -> CTR [FLAG: fertiliser offset] | AT9: Wheat season - sampled 14 May 2011 after wheat harvest (18th year) | AU9: T2: 120-26-33 kg N-P-K/ha to rice and wheat + Zn 5 kg/ha to rice. T8: 75% of NPK + 25% of N through wheat straw (rice) and rice straw (wheat); 1993-2011 organic C added by CR 61.54 (rice) + 47.72 (wheat) Mg C/ha; total C input T2 40.54, T8 154.36 Mg C/ha. Rice continuous submergence; wheat 5 irrigations. Initial soil: SL, EC 0.4 dS/m, Olsen P 16.4, avail. K 96, S 14.5 kg/ha, WHC 42%. | AV9: Fig. 2b (digitised) | AW9: CAPILLARY-REWETTED (slow-wetting) pre-treatment - second MWD of the same soil; filter on this flag to keep one MWD per study. DIGITISED from Fig. 2b (approx.). Obs = 1 (D=1: one layer). FLAG - FERTILISER OFFSET (rule 62): in T8 crop residue replaces 25% of fertiliser N and 25% of P and K are also cut; drop for a fertiliser-matched sensitivity check. Wheat tillage not described in detail ('wet tillage followed by dry tillage', residue incorporated) -> conventional. Supplementary: none found (web search 2026-10-05; publisher site not reachable). Source file 113.pdf. | AX9: TREATMENTS IN PAPER (Table 1, RBD 3 reps, since 1993, PDFSR Modipuram): T1 unfertilised; T2 recommended NPK (+Zn to rice) through fertilisers; T3 NPK + Zn + S (rice); T4 75% NPK + 25% N via FYM (rice); T5 75% NPK + 25% N via sulphitation press mud (rice); T6 75% NPK + green gram residue incorporated before rice; T7 = T6 (rice) + 75% NPK + 25% N via FYM (wheat); T8 75% NPK + 25% N via WHEAT STRAW to rice and 75% NPK + 25% N via RICE STRAW to wheat (CR). Rice puddled and transplanted (Saket 4, 20 x 10 cm, continuous 5 cm submergence); wheat HD 2338 drilled after dry tillage ('wet tillage followed by dry tillage'); recommended 120-26-33 kg N-P-K/ha to each crop. T2 -> CT ; T8 -> CTR (FLAG fertiliser offset, rule 62); T1, T3-T7 EXCLUDED (unfertilised / amendments / third crop in some treatments only). | AY9: Wet sieving after capillary re-wetting to field capacity (slow wetting)

Sheet MWDA
A1: No. | B1: SERIAL NO | C1: Authors | D1: Year | E1: Journal | F1: Country | G1: Site/Location | H1: latitude | I1: longitude | J1: CLIMATE | K1: year of data collection/experiment | L1: DURATION | M1: SOIL | N1: DEPTH | O1: DEPTH (as reported in paper) | P1: MWDA_CA | Q1: MWDA_CT | R1: MWDA_ZT | S1: MWDA_DT | T1: MWDA_MTR | U1: MWDA_MT | V1: MWDA_CTR | W1: MWDA_DTR | X1: MWDA_pCA | Y1: MWDA_pZT | Z1: MWDA_pMT | AA1: MWDA_pMTR | AB1: Obs | AC1: Rep | AD1: SD | AE1: CLAY | AF1: MIN TEMP | AG1: MAX TEMP | AH1: RAIN FALL | AI1: LATT | AJ1: YEAR OF DATA (duration) | AK1: AVG T | AL1: April max temp | AM1: ph (initial) | AN1: soc (initial) | AO1: Bdi | AP1: sand | AQ1: silt | AR1: UNIT | AS1: Treatment mapping (paper's name -> code) | AT1: Crop/season of sampling | AU1: Fertilizer dose & other management | AV1: Data source | AW1: Notes/Doubts | AX1: Treatment details (from paper) | AY1: Method used (from paper) | BA1: UNIT FOR THIS SHEET:
BA2: mm (dry sieving)

Sheet GMD 1
A1: No. | B1: SERIAL NO | C1: Authors | D1: Year | E1: Journal | F1: Country | G1: Site/Location | H1: latitude | I1: longitude | J1: CLIMATE | K1: year of data collection/experiment | L1: DURATION | M1: SOIL | N1: DEPTH | O1: DEPTH (as reported in paper) | P1: GMD_CA | Q1: GMD_CT | R1: GMD_ZT | S1: GMD_DT | T1: GMD_MTR | U1: GMD_MT | V1: GMD_CTR | W1: GMD_DTR | X1: GMD_pCA | Y1: GMD_pZT | Z1: GMD_pMT | AA1: GMD_pMTR | AB1: Obs | AC1: Rep | AD1: SD | AE1: CLAY | AF1: MIN TEMP | AG1: MAX TEMP | AH1: RAIN FALL | AI1: LATT | AJ1: YEAR OF DATA (duration) | AK1: AVG T | AL1: April max temp | AM1: ph (initial) | AN1: soc (initial) | AO1: Bdi | AP1: sand | AQ1: silt | AR1: UNIT | AS1: Treatment mapping (paper's name -> code) | AT1: Crop/season of sampling | AU1: Fertilizer dose & other management | AV1: Data source | AW1: Notes/Doubts | AX1: Treatment details (from paper) | AY1: Method used (from paper) | BA1: UNIT FOR THIS SHEET:
BA2: mm

Sheet WSA
A1: No. | B1: SERIAL NO | C1: Authors | D1: Year | E1: Journal | F1: Country | G1: Site/Location | H1: latitude | I1: longitude | J1: CLIMATE | K1: year of data collection/experiment | L1: DURATION | M1: SOIL | N1: DEPTH | O1: DEPTH (as reported in paper) | P1: WSA_CA | Q1: WSA_CT | R1: WSA_ZT | S1: WSA_DT | T1: WSA_MTR | U1: WSA_MT | V1: WSA_CTR | W1: WSA_DTR | X1: WSA_pCA | Y1: WSA_pZT | Z1: WSA_pMT | AA1: WSA_pMTR | AB1: Obs | AC1: Rep | AD1: SD | AE1: CLAY | AF1: MIN TEMP | AG1: MAX TEMP | AH1: RAIN FALL | AI1: LATT | AJ1: YEAR OF DATA (duration) | AK1: AVG T | AL1: April max temp | AM1: ph (initial) | AN1: soc (initial) | AO1: Bdi | AP1: sand | AQ1: silt | AR1: UNIT | AS1: Treatment mapping (paper's name -> code) | AT1: Crop/season of sampling | AU1: Fertilizer dose & other management | AV1: Data source | AW1: Notes/Doubts | AX1: Treatment details (from paper) | AY1: Method used (from paper) | BA1: UNIT FOR THIS SHEET:
A2: 168 | B2: 168 | C2: Dhaliwal J.K., Singh M.J., Sharma S., Gupta N. & Kukal S.S. | D2: 2020 | E2: Soil Research | F2: India (Punjab) | G2: PAU research farm, Ludhiana (DSR-wheat tillage x mulch trial of Gupta et al. 2016) | H2: 30.933 | I2: 75.867 | J2: TEMP | K2: 2016 | L2: 4-10 Y | M2: LOAMY | N2: 0-15 CM | O2: 0-15 cm | P2: =ROUND((MACRO!P2+MICRO!P2)/100,3) -> 0.674 | Q2: =ROUND((MACRO!Q2+MICRO!Q2)/100,3) -> 0.585 | R2: =ROUND((MACRO!R2+MICRO!R2)/100,3) -> 0.655 | V2: =ROUND((MACRO!V2+MICRO!V2)/100,3) -> 0.702 | AB2: 1 | AC2: 3 | AD2: =IF(AND(N(AB2)>0,N(AC2)>0),SQRT(2*AB2/AC2),"") -> 0.81649658 | AH2: 734 | AI2: 30.933 | AJ2: 5 | AM2: 7.4 | AR2: g/g soil (sum of water-stable fractions >0.1 mm) | AS2: CTW-CTDSR (-M) -> CT ; CTW+M-CTDSR -> CTR ; ZTW-ZTDSR -> ZT ; ZTW+M-ZTDSR -> CA | AT2: RICE SEASON - soil sampled in 2016 after rice harvest (no wheat-season sampling in the paper) | AU2: Fertiliser, water and pest management as PAU recommendations (doses not printed; see Gupta et al. 2016 FCR 196:219). Wheat PBW 621, 113 kg/ha, Turbo Happy Seeder, 20 cm rows; rice PR 115 DSR 40 kg/ha, 20 cm rows. +M: 7 t/ha rice residue spread between rows after wheat sowing (2.5 t/ha left at wheat harvest). Wheat straw removed in all plots. Surface soil pH 7.4 (1:2), EC 0.31 dS/m (1:2); Typic Ustochrept, sandy loam to 120 cm. | AV2: Table 3 - DERIVED (WSA = macro + micro) | AW2: DERIVED (rule 74): WSA = (WSA-mac + WSA-mic)/100, live links to the MACRO and MICRO rows. FLAG: lowest sieve 0.1 mm, so the sum covers >0.1 mm, not >0.053 mm. RICE-SEASON DATA (RED ROW): the paper samples ONLY after the 2016 rice harvest, so values are entered under the rice-season fallback rule (rule 36). Rotation-matched: CT rice + CT wheat = CT; ZT rice + ZT wheat = ZT/CA (rice residue is the mulch factor). Supplementary: none found (web search 2026-10-05; publisher site not reachable from this environment). Source file 112_real.pdf. | AX2: TREATMENTS IN PAPER (Table 1; three-factor trial est. 2011 - only the 'absolute' CT and ZT rice and wheat combinations were studied): 1 CTW-CTDSR (-M) = conventionally tilled wheat (1 discing + 1 tyne harrowing + planking) and conventionally tilled dry-seeded rice, all rice residue removed -> CT ; 2 CTW+M-CTDSR = as 1 with ALL rice residue (7 t/ha) retained as surface mulch in wheat -> CTR ; 3 ZTW-ZTDSR = zero-till wheat (Turbo Happy Seeder) and zero-till DSR (inverted-T tyne ZT drill), residue removed -> ZT ; 4 ZTW+M-ZTDSR = as 3 with rice residue mulch -> CA. Wheat straw removed in every treatment (cut 3-5 cm above ground). RBD 3 reps; plots 9.3 x 6.5 m. | AY2: Wet sieving, Yoder apparatus (Kemper & Rosenau 1986): 50 g air-dry 5-8 mm aggregates, capillary pre-wetting 10 min, sieves 2, 1, 0.5, 0.25, 0.1 mm, 30 min at 30 osc/min; sand-corrected (Na-hexametaphosphate) | BA2: g/g soil (water-stable aggregates = sum of ALL water-stable fractions > 0.053 mm; % / 100)
A3: 168 | B3: 168 | C3: Dhaliwal J.K., Singh M.J., Sharma S., Gupta N. & Kukal S.S. | D3: 2020 | E3: Soil Research | F3: India (Punjab) | G3: PAU research farm, Ludhiana (DSR-wheat tillage x mulch trial of Gupta et al. 2016) | H3: 30.933 | I3: 75.867 | J3: TEMP | K3: 2016 | L3: 4-10 Y | M3: LOAMY | N3: 15-30 CM | O3: 15-30 cm | P3: =ROUND((MACRO!P3+MICRO!P3)/100,3) -> 0.598 | Q3: =ROUND((MACRO!Q3+MICRO!Q3)/100,3) -> 0.565 | R3: =ROUND((MACRO!R3+MICRO!R3)/100,3) -> 0.609 | V3: =ROUND((MACRO!V3+MICRO!V3)/100,3) -> 0.611 | AB3: 1 | AC3: 3 | AD3: =IF(AND(N(AB3)>0,N(AC3)>0),SQRT(2*AB3/AC3),"") -> 0.81649658 | AH3: 734 | AI3: 30.933 | AJ3: 5 | AM3: 7.4 | AR3: g/g soil (sum of water-stable fractions >0.1 mm) | AS3: CTW-CTDSR (-M) -> CT ; CTW+M-CTDSR -> CTR ; ZTW-ZTDSR -> ZT ; ZTW+M-ZTDSR -> CA | AT3: RICE SEASON - soil sampled in 2016 after rice harvest (no wheat-season sampling in the paper) | AU3: Fertiliser, water and pest management as PAU recommendations (doses not printed; see Gupta et al. 2016 FCR 196:219). Wheat PBW 621, 113 kg/ha, Turbo Happy Seeder, 20 cm rows; rice PR 115 DSR 40 kg/ha, 20 cm rows. +M: 7 t/ha rice residue spread between rows after wheat sowing (2.5 t/ha left at wheat harvest). Wheat straw removed in all plots. Surface soil pH 7.4 (1:2), EC 0.31 dS/m (1:2); Typic Ustochrept, sandy loam to 120 cm. | AV3: Table 3 - DERIVED (WSA = macro + micro) | AW3: DERIVED (rule 74): WSA = (WSA-mac + WSA-mic)/100, live links to the MACRO and MICRO rows. FLAG: lowest sieve 0.1 mm, so the sum covers >0.1 mm, not >0.053 mm. RICE-SEASON DATA (RED ROW): the paper samples ONLY after the 2016 rice harvest, so values are entered under the rice-season fallback rule (rule 36). Rotation-matched: CT rice + CT wheat = CT; ZT rice + ZT wheat = ZT/CA (rice residue is the mulch factor). Supplementary: none found (web search 2026-10-05; publisher site not reachable from this environment). Source file 112_real.pdf. | AX3: TREATMENTS IN PAPER (Table 1; three-factor trial est. 2011 - only the 'absolute' CT and ZT rice and wheat combinations were studied): 1 CTW-CTDSR (-M) = conventionally tilled wheat (1 discing + 1 tyne harrowing + planking) and conventionally tilled dry-seeded rice, all rice residue removed -> CT ; 2 CTW+M-CTDSR = as 1 with ALL rice residue (7 t/ha) retained as surface mulch in wheat -> CTR ; 3 ZTW-ZTDSR = zero-till wheat (Turbo Happy Seeder) and zero-till DSR (inverted-T tyne ZT drill), residue removed -> ZT ; 4 ZTW+M-ZTDSR = as 3 with rice residue mulch -> CA. Wheat straw removed in every treatment (cut 3-5 cm above ground). RBD 3 reps; plots 9.3 x 6.5 m. | AY3: Wet sieving, Yoder apparatus (Kemper & Rosenau 1986): 50 g air-dry 5-8 mm aggregates, capillary pre-wetting 10 min, sieves 2, 1, 0.5, 0.25, 0.1 mm, 30 min at 30 osc/min; sand-corrected (Na-hexametaphosphate)
A4: 166 | B4: 166 | C4: Das B., Chakraborty D., Singh V.K., Aggarwal P., Singh R., Dwivedi B.S. & Mishra R.P. | D4: 2014 | E4: Soil & Tillage Research | F4: India (Uttar Pradesh) | G4: PDFSR (now ICAR-IIFSR) long-term INM experiment, Modipuram, Meerut | H4: 29.067 | I4: 77.767 | J4: ST | K4: 2011 | L4: >10 Y | M4: LOAMY | N4: 0-15 CM | O4: 0-7.5 cm | Q4: =ROUND((MACRO!Q4+MICRO!Q4)/100,4) -> 0.756 | V4: =ROUND((MACRO!V4+MICRO!V4)/100,4) -> 0.9787 | AB4: 2 | AC4: 3 | AD4: =IF(AND(N(AB4)>0,N(AC4)>0),SQRT(2*AB4/AC4),"") -> 1.1547005 | AE4: 27 | AF4: 5 | AG4: 45.5 | AH4: 863 | AI4: 29.067 | AJ4: 18 | AM4: 7.98 | AN4: 4.1 | AO4: 1.55 | AP4: 55 | AQ4: 18 | AR4: g/g soil (LM + SM + mi, all fractions >0.053 mm) | AS4: T2 (100% NPK, residues removed) -> CT ; T8 (75% NPK + 25% N via crop residue, both crops) -> CTR [FLAG: fertiliser offset] | AT4: Wheat season - sampled 14 May 2011 after wheat harvest (18th year) | AU4: T2: 120-26-33 kg N-P-K/ha to rice and wheat + Zn 5 kg/ha to rice. T8: 75% of NPK + 25% of N through wheat straw (rice) and rice straw (wheat); 1993-2011 organic C added by CR 61.54 (rice) + 47.72 (wheat) Mg C/ha; total C input T2 40.54, T8 154.36 Mg C/ha. Rice continuous submergence; wheat 5 irrigations. Initial soil: SL, EC 0.4 dS/m, Olsen P 16.4, avail. K 96, S 14.5 kg/ha, WHC 42%. | AV4: Table 4 - DERIVED | AW4: DERIVED (rule 74): WSA = (macro + micro)/100, live links. Obs = 2 (D=2: 0-7.5 and 7.5-15 cm both in the 0-15 CM class, separate rows). FLAG - FERTILISER OFFSET (rule 62): in T8 crop residue replaces 25% of fertiliser N and 25% of P and K are also cut; drop for a fertiliser-matched sensitivity check. Wheat tillage not described in detail ('wet tillage followed by dry tillage', residue incorporated) -> conventional. Supplementary: none found (web search 2026-10-05; publisher site not reachable). Source file 113.pdf. | AX4: TREATMENTS IN PAPER (Table 1, RBD 3 reps, since 1993, PDFSR Modipuram): T1 unfertilised; T2 recommended NPK (+Zn to rice) through fertilisers; T3 NPK + Zn + S (rice); T4 75% NPK + 25% N via FYM (rice); T5 75% NPK + 25% N via sulphitation press mud (rice); T6 75% NPK + green gram residue incorporated before rice; T7 = T6 (rice) + 75% NPK + 25% N via FYM (wheat); T8 75% NPK + 25% N via WHEAT STRAW to rice and 75% NPK + 25% N via RICE STRAW to wheat (CR). Rice puddled and transplanted (Saket 4, 20 x 10 cm, continuous 5 cm submergence); wheat HD 2338 drilled after dry tillage ('wet tillage followed by dry tillage'); recommended 120-26-33 kg N-P-K/ha to each crop. T2 -> CT ; T8 -> CTR (FLAG fertiliser offset, rule 62); T1, T3-T7 EXCLUDED (unfertilised / amendments / third crop in some treatments only). | AY4: Wet sieving 2, 0.25, 0.053 mm after slaking (Six et al. 2000); macro = LM (>2 mm) + SM (0.25-2 mm); micro = mi (0.053-0.25 mm)
A5: 166 | B5: 166 | C5: Das B., Chakraborty D., Singh V.K., Aggarwal P., Singh R., Dwivedi B.S. & Mishra R.P. | D5: 2014 | E5: Soil & Tillage Research | F5: India (Uttar Pradesh) | G5: PDFSR (now ICAR-IIFSR) long-term INM experiment, Modipuram, Meerut | H5: 29.067 | I5: 77.767 | J5: ST | K5: 2011 | L5: >10 Y | M5: LOAMY | N5: 0-15 CM | O5: 7.5-15 cm | Q5: =ROUND((MACRO!Q5+MICRO!Q5)/100,4) -> 0.8023 | V5: =ROUND((MACRO!V5+MICRO!V5)/100,4) -> 0.9499 | AB5: 2 | AC5: 3 | AD5: =IF(AND(N(AB5)>0,N(AC5)>0),SQRT(2*AB5/AC5),"") -> 1.1547005 | AE5: 27 | AF5: 5 | AG5: 45.5 | AH5: 863 | AI5: 29.067 | AJ5: 18 | AM5: 7.98 | AN5: 4.1 | AO5: 1.55 | AP5: 55 | AQ5: 18 | AR5: g/g soil (LM + SM + mi, all fractions >0.053 mm) | AS5: T2 (100% NPK, residues removed) -> CT ; T8 (75% NPK + 25% N via crop residue, both crops) -> CTR [FLAG: fertiliser offset] | AT5: Wheat season - sampled 14 May 2011 after wheat harvest (18th year) | AU5: T2: 120-26-33 kg N-P-K/ha to rice and wheat + Zn 5 kg/ha to rice. T8: 75% of NPK + 25% of N through wheat straw (rice) and rice straw (wheat); 1993-2011 organic C added by CR 61.54 (rice) + 47.72 (wheat) Mg C/ha; total C input T2 40.54, T8 154.36 Mg C/ha. Rice continuous submergence; wheat 5 irrigations. Initial soil: SL, EC 0.4 dS/m, Olsen P 16.4, avail. K 96, S 14.5 kg/ha, WHC 42%. | AV5: Table 4 - DERIVED | AW5: DERIVED (rule 74): WSA = (macro + micro)/100, live links. Obs = 2 (D=2: 0-7.5 and 7.5-15 cm both in the 0-15 CM class, separate rows). FLAG - FERTILISER OFFSET (rule 62): in T8 crop residue replaces 25% of fertiliser N and 25% of P and K are also cut; drop for a fertiliser-matched sensitivity check. Wheat tillage not described in detail ('wet tillage followed by dry tillage', residue incorporated) -> conventional. Supplementary: none found (web search 2026-10-05; publisher site not reachable). Source file 113.pdf. | AX5: TREATMENTS IN PAPER (Table 1, RBD 3 reps, since 1993, PDFSR Modipuram): T1 unfertilised; T2 recommended NPK (+Zn to rice) through fertilisers; T3 NPK + Zn + S (rice); T4 75% NPK + 25% N via FYM (rice); T5 75% NPK + 25% N via sulphitation press mud (rice); T6 75% NPK + green gram residue incorporated before rice; T7 = T6 (rice) + 75% NPK + 25% N via FYM (wheat); T8 75% NPK + 25% N via WHEAT STRAW to rice and 75% NPK + 25% N via RICE STRAW to wheat (CR). Rice puddled and transplanted (Saket 4, 20 x 10 cm, continuous 5 cm submergence); wheat HD 2338 drilled after dry tillage ('wet tillage followed by dry tillage'); recommended 120-26-33 kg N-P-K/ha to each crop. T2 -> CT ; T8 -> CTR (FLAG fertiliser offset, rule 62); T1, T3-T7 EXCLUDED (unfertilised / amendments / third crop in some treatments only). | AY5: Wet sieving 2, 0.25, 0.053 mm after slaking (Six et al. 2000); macro = LM (>2 mm) + SM (0.25-2 mm); micro = mi (0.053-0.25 mm)
A6: 166 | B6: 166 | C6: Das B., Chakraborty D., Singh V.K., Aggarwal P., Singh R., Dwivedi B.S. & Mishra R.P. | D6: 2014 | E6: Soil & Tillage Research | F6: India (Uttar Pradesh) | G6: PDFSR (now ICAR-IIFSR) long-term INM experiment, Modipuram, Meerut | H6: 29.067 | I6: 77.767 | J6: ST | K6: 2011 | L6: >10 Y | M6: LOAMY | N6: 15-30 CM | O6: 15-30 cm | Q6: =ROUND((MACRO!Q6+MICRO!Q6)/100,4) -> 0.9878 | V6: =ROUND((MACRO!V6+MICRO!V6)/100,4) -> 0.934 | AB6: 1 | AC6: 3 | AD6: =IF(AND(N(AB6)>0,N(AC6)>0),SQRT(2*AB6/AC6),"") -> 0.81649658 | AE6: 27 | AF6: 5 | AG6: 45.5 | AH6: 863 | AI6: 29.067 | AJ6: 18 | AM6: 7.98 | AN6: 4.1 | AO6: 1.55 | AP6: 55 | AQ6: 18 | AR6: g/g soil (LM + SM + mi, all fractions >0.053 mm) | AS6: T2 (100% NPK, residues removed) -> CT ; T8 (75% NPK + 25% N via crop residue, both crops) -> CTR [FLAG: fertiliser offset] | AT6: Wheat season - sampled 14 May 2011 after wheat harvest (18th year) | AU6: T2: 120-26-33 kg N-P-K/ha to rice and wheat + Zn 5 kg/ha to rice. T8: 75% of NPK + 25% of N through wheat straw (rice) and rice straw (wheat); 1993-2011 organic C added by CR 61.54 (rice) + 47.72 (wheat) Mg C/ha; total C input T2 40.54, T8 154.36 Mg C/ha. Rice continuous submergence; wheat 5 irrigations. Initial soil: SL, EC 0.4 dS/m, Olsen P 16.4, avail. K 96, S 14.5 kg/ha, WHC 42%. | AV6: Table 4 - DERIVED | AW6: DERIVED (rule 74): WSA = (macro + micro)/100, live links. Obs = 1 (D=1: one layer). FLAG - FERTILISER OFFSET (rule 62): in T8 crop residue replaces 25% of fertiliser N and 25% of P and K are also cut; drop for a fertiliser-matched sensitivity check. Wheat tillage not described in detail ('wet tillage followed by dry tillage', residue incorporated) -> conventional. Supplementary: none found (web search 2026-10-05; publisher site not reachable). Source file 113.pdf. | AX6: TREATMENTS IN PAPER (Table 1, RBD 3 reps, since 1993, PDFSR Modipuram): T1 unfertilised; T2 recommended NPK (+Zn to rice) through fertilisers; T3 NPK + Zn + S (rice); T4 75% NPK + 25% N via FYM (rice); T5 75% NPK + 25% N via sulphitation press mud (rice); T6 75% NPK + green gram residue incorporated before rice; T7 = T6 (rice) + 75% NPK + 25% N via FYM (wheat); T8 75% NPK + 25% N via WHEAT STRAW to rice and 75% NPK + 25% N via RICE STRAW to wheat (CR). Rice puddled and transplanted (Saket 4, 20 x 10 cm, continuous 5 cm submergence); wheat HD 2338 drilled after dry tillage ('wet tillage followed by dry tillage'); recommended 120-26-33 kg N-P-K/ha to each crop. T2 -> CT ; T8 -> CTR (FLAG fertiliser offset, rule 62); T1, T3-T7 EXCLUDED (unfertilised / amendments / third crop in some treatments only). | AY6: Wet sieving 2, 0.25, 0.053 mm after slaking (Six et al. 2000); macro = LM (>2 mm) + SM (0.25-2 mm); micro = mi (0.053-0.25 mm)

Sheet MACRO
A1: No. | B1: SERIAL NO | C1: Authors | D1: Year | E1: Journal | F1: Country | G1: Site/Location | H1: latitude | I1: longitude | J1: CLIMATE | K1: year of data collection/experiment | L1: DURATION | M1: SOIL | N1: DEPTH | O1: DEPTH (as reported in paper) | P1: MACRO_CA | Q1: MACRO_CT | R1: MACRO_ZT | S1: MACRO_DT | T1: MACRO_MTR | U1: MACRO_MT | V1: MACRO_CTR | W1: MACRO_DTR | X1: MACRO_pCA | Y1: MACRO_pZT | Z1: MACRO_pMT | AA1: MACRO_pMTR | AB1: Obs | AC1: Rep | AD1: SD | AE1: CLAY | AF1: MIN TEMP | AG1: MAX TEMP | AH1: RAIN FALL | AI1: LATT | AJ1: YEAR OF DATA (duration) | AK1: AVG T | AL1: April max temp | AM1: ph (initial) | AN1: soc (initial) | AO1: Bdi | AP1: sand | AQ1: silt | AR1: UNIT | AS1: Treatment mapping (paper's name -> code) | AT1: Crop/season of sampling | AU1: Fertilizer dose & other management | AV1: Data source | AW1: Notes/Doubts | AX1: Treatment details (from paper) | AY1: Method used (from paper) | BA1: UNIT FOR THIS SHEET:
A2: 168 | B2: 168 | C2: Dhaliwal J.K., Singh M.J., Sharma S., Gupta N. & Kukal S.S. | D2: 2020 | E2: Soil Research | F2: India (Punjab) | G2: PAU research farm, Ludhiana (DSR-wheat tillage x mulch trial of Gupta et al. 2016) | H2: 30.933 | I2: 75.867 | J2: TEMP | K2: 2016 | L2: 4-10 Y | M2: LOAMY | N2: 0-15 CM | O2: 0-15 cm | P2: 55.5 | Q2: 43.7 | R2: 52.4 | V2: 56.1 | AB2: 1 | AC2: 3 | AD2: =IF(AND(N(AB2)>0,N(AC2)>0),SQRT(2*AB2/AC2),"") -> 0.81649658 | AH2: 734 | AI2: 30.933 | AJ2: 5 | AM2: 7.4 | AR2: % (water-stable macro-aggregates >0.25 mm, sand-corrected) | AS2: CTW-CTDSR (-M) -> CT ; CTW+M-CTDSR -> CTR ; ZTW-ZTDSR -> ZT ; ZTW+M-ZTDSR -> CA | AT2: RICE SEASON - soil sampled in 2016 after rice harvest (no wheat-season sampling in the paper) | AU2: Fertiliser, water and pest management as PAU recommendations (doses not printed; see Gupta et al. 2016 FCR 196:219). Wheat PBW 621, 113 kg/ha, Turbo Happy Seeder, 20 cm rows; rice PR 115 DSR 40 kg/ha, 20 cm rows. +M: 7 t/ha rice residue spread between rows after wheat sowing (2.5 t/ha left at wheat harvest). Wheat straw removed in all plots. Surface soil pH 7.4 (1:2), EC 0.31 dS/m (1:2); Typic Ustochrept, sandy loam to 120 cm. | AV2: Table 3 | AW2: RICE-SEASON DATA (RED ROW): the paper samples ONLY after the 2016 rice harvest, so values are entered under the rice-season fallback rule (rule 36). Rotation-matched: CT rice + CT wheat = CT; ZT rice + ZT wheat = ZT/CA (rice residue is the mulch factor). Supplementary: none found (web search 2026-10-05; publisher site not reachable from this environment). Source file 112_real.pdf. LSD (0-15) T 2.17, M 2.17, TxM 3.07; (15-30) T 2.40, M 2.40, TxM 3.38. | AX2: TREATMENTS IN PAPER (Table 1; three-factor trial est. 2011 - only the 'absolute' CT and ZT rice and wheat combinations were studied): 1 CTW-CTDSR (-M) = conventionally tilled wheat (1 discing + 1 tyne harrowing + planking) and conventionally tilled dry-seeded rice, all rice residue removed -> CT ; 2 CTW+M-CTDSR = as 1 with ALL rice residue (7 t/ha) retained as surface mulch in wheat -> CTR ; 3 ZTW-ZTDSR = zero-till wheat (Turbo Happy Seeder) and zero-till DSR (inverted-T tyne ZT drill), residue removed -> ZT ; 4 ZTW+M-ZTDSR = as 3 with rice residue mulch -> CA. Wheat straw removed in every treatment (cut 3-5 cm above ground). RBD 3 reps; plots 9.3 x 6.5 m. | AY2: Wet sieving, Yoder apparatus (Kemper & Rosenau 1986): 50 g air-dry 5-8 mm aggregates, capillary pre-wetting 10 min, sieves 2, 1, 0.5, 0.25, 0.1 mm, 30 min at 30 osc/min; sand-corrected (Na-hexametaphosphate) | BA2: % (>0.25 mm aggregates)
A3: 168 | B3: 168 | C3: Dhaliwal J.K., Singh M.J., Sharma S., Gupta N. & Kukal S.S. | D3: 2020 | E3: Soil Research | F3: India (Punjab) | G3: PAU research farm, Ludhiana (DSR-wheat tillage x mulch trial of Gupta et al. 2016) | H3: 30.933 | I3: 75.867 | J3: TEMP | K3: 2016 | L3: 4-10 Y | M3: LOAMY | N3: 15-30 CM | O3: 15-30 cm | P3: 47.8 | Q3: 41.5 | R3: 48.8 | V3: 47.5 | AB3: 1 | AC3: 3 | AD3: =IF(AND(N(AB3)>0,N(AC3)>0),SQRT(2*AB3/AC3),"") -> 0.81649658 | AH3: 734 | AI3: 30.933 | AJ3: 5 | AM3: 7.4 | AR3: % (water-stable macro-aggregates >0.25 mm, sand-corrected) | AS3: CTW-CTDSR (-M) -> CT ; CTW+M-CTDSR -> CTR ; ZTW-ZTDSR -> ZT ; ZTW+M-ZTDSR -> CA | AT3: RICE SEASON - soil sampled in 2016 after rice harvest (no wheat-season sampling in the paper) | AU3: Fertiliser, water and pest management as PAU recommendations (doses not printed; see Gupta et al. 2016 FCR 196:219). Wheat PBW 621, 113 kg/ha, Turbo Happy Seeder, 20 cm rows; rice PR 115 DSR 40 kg/ha, 20 cm rows. +M: 7 t/ha rice residue spread between rows after wheat sowing (2.5 t/ha left at wheat harvest). Wheat straw removed in all plots. Surface soil pH 7.4 (1:2), EC 0.31 dS/m (1:2); Typic Ustochrept, sandy loam to 120 cm. | AV3: Table 3 | AW3: RICE-SEASON DATA (RED ROW): the paper samples ONLY after the 2016 rice harvest, so values are entered under the rice-season fallback rule (rule 36). Rotation-matched: CT rice + CT wheat = CT; ZT rice + ZT wheat = ZT/CA (rice residue is the mulch factor). Supplementary: none found (web search 2026-10-05; publisher site not reachable from this environment). Source file 112_real.pdf. LSD (0-15) T 2.17, M 2.17, TxM 3.07; (15-30) T 2.40, M 2.40, TxM 3.38. | AX3: TREATMENTS IN PAPER (Table 1; three-factor trial est. 2011 - only the 'absolute' CT and ZT rice and wheat combinations were studied): 1 CTW-CTDSR (-M) = conventionally tilled wheat (1 discing + 1 tyne harrowing + planking) and conventionally tilled dry-seeded rice, all rice residue removed -> CT ; 2 CTW+M-CTDSR = as 1 with ALL rice residue (7 t/ha) retained as surface mulch in wheat -> CTR ; 3 ZTW-ZTDSR = zero-till wheat (Turbo Happy Seeder) and zero-till DSR (inverted-T tyne ZT drill), residue removed -> ZT ; 4 ZTW+M-ZTDSR = as 3 with rice residue mulch -> CA. Wheat straw removed in every treatment (cut 3-5 cm above ground). RBD 3 reps; plots 9.3 x 6.5 m. | AY3: Wet sieving, Yoder apparatus (Kemper & Rosenau 1986): 50 g air-dry 5-8 mm aggregates, capillary pre-wetting 10 min, sieves 2, 1, 0.5, 0.25, 0.1 mm, 30 min at 30 osc/min; sand-corrected (Na-hexametaphosphate)
A4: 166 | B4: 166 | C4: Das B., Chakraborty D., Singh V.K., Aggarwal P., Singh R., Dwivedi B.S. & Mishra R.P. | D4: 2014 | E4: Soil & Tillage Research | F4: India (Uttar Pradesh) | G4: PDFSR (now ICAR-IIFSR) long-term INM experiment, Modipuram, Meerut | H4: 29.067 | I4: 77.767 | J4: ST | K4: 2011 | L4: >10 Y | M4: LOAMY | N4: 0-15 CM | O4: 0-7.5 cm | Q4: =ROUND(15.33+55.58,2) -> 70.91 | V4: =ROUND(34.15+57.72,2) -> 91.87 | AB4: 2 | AC4: 3 | AD4: =IF(AND(N(AB4)>0,N(AC4)>0),SQRT(2*AB4/AC4),"") -> 1.1547005 | AE4: 27 | AF4: 5 | AG4: 45.5 | AH4: 863 | AI4: 29.067 | AJ4: 18 | AM4: 7.98 | AN4: 4.1 | AO4: 1.55 | AP4: 55 | AQ4: 18 | AR4: % (g/100 g soil, LM >2 mm + SM 0.25-2 mm) | AS4: T2 (100% NPK, residues removed) -> CT ; T8 (75% NPK + 25% N via crop residue, both crops) -> CTR [FLAG: fertiliser offset] | AT4: Wheat season - sampled 14 May 2011 after wheat harvest (18th year) | AU4: T2: 120-26-33 kg N-P-K/ha to rice and wheat + Zn 5 kg/ha to rice. T8: 75% of NPK + 25% of N through wheat straw (rice) and rice straw (wheat); 1993-2011 organic C added by CR 61.54 (rice) + 47.72 (wheat) Mg C/ha; total C input T2 40.54, T8 154.36 Mg C/ha. Rice continuous submergence; wheat 5 irrigations. Initial soil: SL, EC 0.4 dS/m, Olsen P 16.4, avail. K 96, S 14.5 kg/ha, WHC 42%. | AV4: Table 4 - summed | AW4: Obs = 2 (D=2: 0-7.5 and 7.5-15 cm both in the 0-15 CM class, separate rows). Macro = LM + SM (printed LM 15.33/34.15, SM 55.58/57.72 for T2/T8). Silt+clay (<0.053) T2/T8: 24.39/2.13. FLAG - FERTILISER OFFSET (rule 62): in T8 crop residue replaces 25% of fertiliser N and 25% of P and K are also cut; drop for a fertiliser-matched sensitivity check. Wheat tillage not described in detail ('wet tillage followed by dry tillage', residue incorporated) -> conventional. Supplementary: none found (web search 2026-10-05; publisher site not reachable). Source file 113.pdf. | AX4: TREATMENTS IN PAPER (Table 1, RBD 3 reps, since 1993, PDFSR Modipuram): T1 unfertilised; T2 recommended NPK (+Zn to rice) through fertilisers; T3 NPK + Zn + S (rice); T4 75% NPK + 25% N via FYM (rice); T5 75% NPK + 25% N via sulphitation press mud (rice); T6 75% NPK + green gram residue incorporated before rice; T7 = T6 (rice) + 75% NPK + 25% N via FYM (wheat); T8 75% NPK + 25% N via WHEAT STRAW to rice and 75% NPK + 25% N via RICE STRAW to wheat (CR). Rice puddled and transplanted (Saket 4, 20 x 10 cm, continuous 5 cm submergence); wheat HD 2338 drilled after dry tillage ('wet tillage followed by dry tillage'); recommended 120-26-33 kg N-P-K/ha to each crop. T2 -> CT ; T8 -> CTR (FLAG fertiliser offset, rule 62); T1, T3-T7 EXCLUDED (unfertilised / amendments / third crop in some treatments only). | AY4: Wet sieving 2, 0.25, 0.053 mm after slaking (Six et al. 2000); macro = LM (>2 mm) + SM (0.25-2 mm); micro = mi (0.053-0.25 mm)
A5: 166 | B5: 166 | C5: Das B., Chakraborty D., Singh V.K., Aggarwal P., Singh R., Dwivedi B.S. & Mishra R.P. | D5: 2014 | E5: Soil & Tillage Research | F5: India (Uttar Pradesh) | G5: PDFSR (now ICAR-IIFSR) long-term INM experiment, Modipuram, Meerut | H5: 29.067 | I5: 77.767 | J5: ST | K5: 2011 | L5: >10 Y | M5: LOAMY | N5: 0-15 CM | O5: 7.5-15 cm | Q5: =ROUND(8.2+66.6,2) -> 74.8 | V5: =ROUND(18.5+64.84,2) -> 83.34 | AB5: 2 | AC5: 3 | AD5: =IF(AND(N(AB5)>0,N(AC5)>0),SQRT(2*AB5/AC5),"") -> 1.1547005 | AE5: 27 | AF5: 5 | AG5: 45.5 | AH5: 863 | AI5: 29.067 | AJ5: 18 | AM5: 7.98 | AN5: 4.1 | AO5: 1.55 | AP5: 55 | AQ5: 18 | AR5: % (g/100 g soil, LM >2 mm + SM 0.25-2 mm) | AS5: T2 (100% NPK, residues removed) -> CT ; T8 (75% NPK + 25% N via crop residue, both crops) -> CTR [FLAG: fertiliser offset] | AT5: Wheat season - sampled 14 May 2011 after wheat harvest (18th year) | AU5: T2: 120-26-33 kg N-P-K/ha to rice and wheat + Zn 5 kg/ha to rice. T8: 75% of NPK + 25% of N through wheat straw (rice) and rice straw (wheat); 1993-2011 organic C added by CR 61.54 (rice) + 47.72 (wheat) Mg C/ha; total C input T2 40.54, T8 154.36 Mg C/ha. Rice continuous submergence; wheat 5 irrigations. Initial soil: SL, EC 0.4 dS/m, Olsen P 16.4, avail. K 96, S 14.5 kg/ha, WHC 42%. | AV5: Table 4 - summed | AW5: Obs = 2 (D=2: 0-7.5 and 7.5-15 cm both in the 0-15 CM class, separate rows). Macro = LM + SM (printed LM 8.2/18.5, SM 66.6/64.84 for T2/T8). Silt+clay (<0.053) T2/T8: 19.77/5.01. FLAG - FERTILISER OFFSET (rule 62): in T8 crop residue replaces 25% of fertiliser N and 25% of P and K are also cut; drop for a fertiliser-matched sensitivity check. Wheat tillage not described in detail ('wet tillage followed by dry tillage', residue incorporated) -> conventional. Supplementary: none found (web search 2026-10-05; publisher site not reachable). Source file 113.pdf. | AX5: TREATMENTS IN PAPER (Table 1, RBD 3 reps, since 1993, PDFSR Modipuram): T1 unfertilised; T2 recommended NPK (+Zn to rice) through fertilisers; T3 NPK + Zn + S (rice); T4 75% NPK + 25% N via FYM (rice); T5 75% NPK + 25% N via sulphitation press mud (rice); T6 75% NPK + green gram residue incorporated before rice; T7 = T6 (rice) + 75% NPK + 25% N via FYM (wheat); T8 75% NPK + 25% N via WHEAT STRAW to rice and 75% NPK + 25% N via RICE STRAW to wheat (CR). Rice puddled and transplanted (Saket 4, 20 x 10 cm, continuous 5 cm submergence); wheat HD 2338 drilled after dry tillage ('wet tillage followed by dry tillage'); recommended 120-26-33 kg N-P-K/ha to each crop. T2 -> CT ; T8 -> CTR (FLAG fertiliser offset, rule 62); T1, T3-T7 EXCLUDED (unfertilised / amendments / third crop in some treatments only). | AY5: Wet sieving 2, 0.25, 0.053 mm after slaking (Six et al. 2000); macro = LM (>2 mm) + SM (0.25-2 mm); micro = mi (0.053-0.25 mm)
A6: 166 | B6: 166 | C6: Das B., Chakraborty D., Singh V.K., Aggarwal P., Singh R., Dwivedi B.S. & Mishra R.P. | D6: 2014 | E6: Soil & Tillage Research | F6: India (Uttar Pradesh) | G6: PDFSR (now ICAR-IIFSR) long-term INM experiment, Modipuram, Meerut | H6: 29.067 | I6: 77.767 | J6: ST | K6: 2011 | L6: >10 Y | M6: LOAMY | N6: 15-30 CM | O6: 15-30 cm | Q6: =ROUND(5.3+54.01,2) -> 59.31 | V6: =ROUND(17.4+65.43,2) -> 82.83 | AB6: 1 | AC6: 3 | AD6: =IF(AND(N(AB6)>0,N(AC6)>0),SQRT(2*AB6/AC6),"") -> 0.81649658 | AE6: 27 | AF6: 5 | AG6: 45.5 | AH6: 863 | AI6: 29.067 | AJ6: 18 | AM6: 7.98 | AN6: 4.1 | AO6: 1.55 | AP6: 55 | AQ6: 18 | AR6: % (g/100 g soil, LM >2 mm + SM 0.25-2 mm) | AS6: T2 (100% NPK, residues removed) -> CT ; T8 (75% NPK + 25% N via crop residue, both crops) -> CTR [FLAG: fertiliser offset] | AT6: Wheat season - sampled 14 May 2011 after wheat harvest (18th year) | AU6: T2: 120-26-33 kg N-P-K/ha to rice and wheat + Zn 5 kg/ha to rice. T8: 75% of NPK + 25% of N through wheat straw (rice) and rice straw (wheat); 1993-2011 organic C added by CR 61.54 (rice) + 47.72 (wheat) Mg C/ha; total C input T2 40.54, T8 154.36 Mg C/ha. Rice continuous submergence; wheat 5 irrigations. Initial soil: SL, EC 0.4 dS/m, Olsen P 16.4, avail. K 96, S 14.5 kg/ha, WHC 42%. | AV6: Table 4 - summed | AW6: Obs = 1 (D=1: one layer). Macro = LM + SM (printed LM 5.3/17.4, SM 54.01/65.43 for T2/T8). Silt+clay (<0.053) T2/T8: 1.22/6.59. FLAG - FERTILISER OFFSET (rule 62): in T8 crop residue replaces 25% of fertiliser N and 25% of P and K are also cut; drop for a fertiliser-matched sensitivity check. Wheat tillage not described in detail ('wet tillage followed by dry tillage', residue incorporated) -> conventional. Supplementary: none found (web search 2026-10-05; publisher site not reachable). Source file 113.pdf. | AX6: TREATMENTS IN PAPER (Table 1, RBD 3 reps, since 1993, PDFSR Modipuram): T1 unfertilised; T2 recommended NPK (+Zn to rice) through fertilisers; T3 NPK + Zn + S (rice); T4 75% NPK + 25% N via FYM (rice); T5 75% NPK + 25% N via sulphitation press mud (rice); T6 75% NPK + green gram residue incorporated before rice; T7 = T6 (rice) + 75% NPK + 25% N via FYM (wheat); T8 75% NPK + 25% N via WHEAT STRAW to rice and 75% NPK + 25% N via RICE STRAW to wheat (CR). Rice puddled and transplanted (Saket 4, 20 x 10 cm, continuous 5 cm submergence); wheat HD 2338 drilled after dry tillage ('wet tillage followed by dry tillage'); recommended 120-26-33 kg N-P-K/ha to each crop. T2 -> CT ; T8 -> CTR (FLAG fertiliser offset, rule 62); T1, T3-T7 EXCLUDED (unfertilised / amendments / third crop in some treatments only). | AY6: Wet sieving 2, 0.25, 0.053 mm after slaking (Six et al. 2000); macro = LM (>2 mm) + SM (0.25-2 mm); micro = mi (0.053-0.25 mm)

Sheet MICRO
A1: No. | B1: SERIAL NO | C1: Authors | D1: Year | E1: Journal | F1: Country | G1: Site/Location | H1: latitude | I1: longitude | J1: CLIMATE | K1: year of data collection/experiment | L1: DURATION | M1: SOIL | N1: DEPTH | O1: DEPTH (as reported in paper) | P1: MICRO_CA | Q1: MICRO_CT | R1: MICRO_ZT | S1: MICRO_DT | T1: MICRO_MTR | U1: MICRO_MT | V1: MICRO_CTR | W1: MICRO_DTR | X1: MICRO_pCA | Y1: MICRO_pZT | Z1: MICRO_pMT | AA1: MICRO_pMTR | AB1: Obs | AC1: Rep | AD1: SD | AE1: CLAY | AF1: MIN TEMP | AG1: MAX TEMP | AH1: RAIN FALL | AI1: LATT | AJ1: YEAR OF DATA (duration) | AK1: AVG T | AL1: April max temp | AM1: ph (initial) | AN1: soc (initial) | AO1: Bdi | AP1: sand | AQ1: silt | AR1: UNIT | AS1: Treatment mapping (paper's name -> code) | AT1: Crop/season of sampling | AU1: Fertilizer dose & other management | AV1: Data source | AW1: Notes/Doubts | AX1: Treatment details (from paper) | AY1: Method used (from paper) | BA1: UNIT FOR THIS SHEET:
A2: 168 | B2: 168 | C2: Dhaliwal J.K., Singh M.J., Sharma S., Gupta N. & Kukal S.S. | D2: 2020 | E2: Soil Research | F2: India (Punjab) | G2: PAU research farm, Ludhiana (DSR-wheat tillage x mulch trial of Gupta et al. 2016) | H2: 30.933 | I2: 75.867 | J2: TEMP | K2: 2016 | L2: 4-10 Y | M2: LOAMY | N2: 0-15 CM | O2: 0-15 cm | P2: 11.9 | Q2: 14.8 | R2: 13.1 | V2: 14.1 | AB2: 1 | AC2: 3 | AD2: =IF(AND(N(AB2)>0,N(AC2)>0),SQRT(2*AB2/AC2),"") -> 0.81649658 | AH2: 734 | AI2: 30.933 | AJ2: 5 | AM2: 7.4 | AR2: % (water-stable micro-aggregates 0.1-0.25 mm, sand-corrected) | AS2: CTW-CTDSR (-M) -> CT ; CTW+M-CTDSR -> CTR ; ZTW-ZTDSR -> ZT ; ZTW+M-ZTDSR -> CA | AT2: RICE SEASON - soil sampled in 2016 after rice harvest (no wheat-season sampling in the paper) | AU2: Fertiliser, water and pest management as PAU recommendations (doses not printed; see Gupta et al. 2016 FCR 196:219). Wheat PBW 621, 113 kg/ha, Turbo Happy Seeder, 20 cm rows; rice PR 115 DSR 40 kg/ha, 20 cm rows. +M: 7 t/ha rice residue spread between rows after wheat sowing (2.5 t/ha left at wheat harvest). Wheat straw removed in all plots. Surface soil pH 7.4 (1:2), EC 0.31 dS/m (1:2); Typic Ustochrept, sandy loam to 120 cm. | AV2: Table 3 | AW2: RICE-SEASON DATA (RED ROW): the paper samples ONLY after the 2016 rice harvest, so values are entered under the rice-season fallback rule (rule 36). Rotation-matched: CT rice + CT wheat = CT; ZT rice + ZT wheat = ZT/CA (rice residue is the mulch factor). Supplementary: none found (web search 2026-10-05; publisher site not reachable from this environment). Source file 112_real.pdf. Smallest sieve 0.1 mm, so this fraction is 0.1-0.25 mm (not 0.053-0.25). | AX2: TREATMENTS IN PAPER (Table 1; three-factor trial est. 2011 - only the 'absolute' CT and ZT rice and wheat combinations were studied): 1 CTW-CTDSR (-M) = conventionally tilled wheat (1 discing + 1 tyne harrowing + planking) and conventionally tilled dry-seeded rice, all rice residue removed -> CT ; 2 CTW+M-CTDSR = as 1 with ALL rice residue (7 t/ha) retained as surface mulch in wheat -> CTR ; 3 ZTW-ZTDSR = zero-till wheat (Turbo Happy Seeder) and zero-till DSR (inverted-T tyne ZT drill), residue removed -> ZT ; 4 ZTW+M-ZTDSR = as 3 with rice residue mulch -> CA. Wheat straw removed in every treatment (cut 3-5 cm above ground). RBD 3 reps; plots 9.3 x 6.5 m. | AY2: Wet sieving, Yoder apparatus (Kemper & Rosenau 1986): 50 g air-dry 5-8 mm aggregates, capillary pre-wetting 10 min, sieves 2, 1, 0.5, 0.25, 0.1 mm, 30 min at 30 osc/min; sand-corrected (Na-hexametaphosphate) | BA2: % (<0.25 mm aggregates)
A3: 168 | B3: 168 | C3: Dhaliwal J.K., Singh M.J., Sharma S., Gupta N. & Kukal S.S. | D3: 2020 | E3: Soil Research | F3: India (Punjab) | G3: PAU research farm, Ludhiana (DSR-wheat tillage x mulch trial of Gupta et al. 2016) | H3: 30.933 | I3: 75.867 | J3: TEMP | K3: 2016 | L3: 4-10 Y | M3: LOAMY | N3: 15-30 CM | O3: 15-30 cm | P3: 12 | Q3: 15 | R3: 12.1 | V3: 13.6 | AB3: 1 | AC3: 3 | AD3: =IF(AND(N(AB3)>0,N(AC3)>0),SQRT(2*AB3/AC3),"") -> 0.81649658 | AH3: 734 | AI3: 30.933 | AJ3: 5 | AM3: 7.4 | AR3: % (water-stable micro-aggregates 0.1-0.25 mm, sand-corrected) | AS3: CTW-CTDSR (-M) -> CT ; CTW+M-CTDSR -> CTR ; ZTW-ZTDSR -> ZT ; ZTW+M-ZTDSR -> CA | AT3: RICE SEASON - soil sampled in 2016 after rice harvest (no wheat-season sampling in the paper) | AU3: Fertiliser, water and pest management as PAU recommendations (doses not printed; see Gupta et al. 2016 FCR 196:219). Wheat PBW 621, 113 kg/ha, Turbo Happy Seeder, 20 cm rows; rice PR 115 DSR 40 kg/ha, 20 cm rows. +M: 7 t/ha rice residue spread between rows after wheat sowing (2.5 t/ha left at wheat harvest). Wheat straw removed in all plots. Surface soil pH 7.4 (1:2), EC 0.31 dS/m (1:2); Typic Ustochrept, sandy loam to 120 cm. | AV3: Table 3 | AW3: RICE-SEASON DATA (RED ROW): the paper samples ONLY after the 2016 rice harvest, so values are entered under the rice-season fallback rule (rule 36). Rotation-matched: CT rice + CT wheat = CT; ZT rice + ZT wheat = ZT/CA (rice residue is the mulch factor). Supplementary: none found (web search 2026-10-05; publisher site not reachable from this environment). Source file 112_real.pdf. Smallest sieve 0.1 mm, so this fraction is 0.1-0.25 mm (not 0.053-0.25). | AX3: TREATMENTS IN PAPER (Table 1; three-factor trial est. 2011 - only the 'absolute' CT and ZT rice and wheat combinations were studied): 1 CTW-CTDSR (-M) = conventionally tilled wheat (1 discing + 1 tyne harrowing + planking) and conventionally tilled dry-seeded rice, all rice residue removed -> CT ; 2 CTW+M-CTDSR = as 1 with ALL rice residue (7 t/ha) retained as surface mulch in wheat -> CTR ; 3 ZTW-ZTDSR = zero-till wheat (Turbo Happy Seeder) and zero-till DSR (inverted-T tyne ZT drill), residue removed -> ZT ; 4 ZTW+M-ZTDSR = as 3 with rice residue mulch -> CA. Wheat straw removed in every treatment (cut 3-5 cm above ground). RBD 3 reps; plots 9.3 x 6.5 m. | AY3: Wet sieving, Yoder apparatus (Kemper & Rosenau 1986): 50 g air-dry 5-8 mm aggregates, capillary pre-wetting 10 min, sieves 2, 1, 0.5, 0.25, 0.1 mm, 30 min at 30 osc/min; sand-corrected (Na-hexametaphosphate)
A4: 166 | B4: 166 | C4: Das B., Chakraborty D., Singh V.K., Aggarwal P., Singh R., Dwivedi B.S. & Mishra R.P. | D4: 2014 | E4: Soil & Tillage Research | F4: India (Uttar Pradesh) | G4: PDFSR (now ICAR-IIFSR) long-term INM experiment, Modipuram, Meerut | H4: 29.067 | I4: 77.767 | J4: ST | K4: 2011 | L4: >10 Y | M4: LOAMY | N4: 0-15 CM | O4: 0-7.5 cm | Q4: 4.69 | V4: 6 | AB4: 2 | AC4: 3 | AD4: =IF(AND(N(AB4)>0,N(AC4)>0),SQRT(2*AB4/AC4),"") -> 1.1547005 | AE4: 27 | AF4: 5 | AG4: 45.5 | AH4: 863 | AI4: 29.067 | AJ4: 18 | AM4: 7.98 | AN4: 4.1 | AO4: 1.55 | AP4: 55 | AQ4: 18 | AR4: % (g/100 g soil, mi 0.053-0.25 mm) | AS4: T2 (100% NPK, residues removed) -> CT ; T8 (75% NPK + 25% N via crop residue, both crops) -> CTR [FLAG: fertiliser offset] | AT4: Wheat season - sampled 14 May 2011 after wheat harvest (18th year) | AU4: T2: 120-26-33 kg N-P-K/ha to rice and wheat + Zn 5 kg/ha to rice. T8: 75% of NPK + 25% of N through wheat straw (rice) and rice straw (wheat); 1993-2011 organic C added by CR 61.54 (rice) + 47.72 (wheat) Mg C/ha; total C input T2 40.54, T8 154.36 Mg C/ha. Rice continuous submergence; wheat 5 irrigations. Initial soil: SL, EC 0.4 dS/m, Olsen P 16.4, avail. K 96, S 14.5 kg/ha, WHC 42%. | AV4: Table 4 | AW4: Obs = 2 (D=2: 0-7.5 and 7.5-15 cm both in the 0-15 CM class, separate rows). FLAG - FERTILISER OFFSET (rule 62): in T8 crop residue replaces 25% of fertiliser N and 25% of P and K are also cut; drop for a fertiliser-matched sensitivity check. Wheat tillage not described in detail ('wet tillage followed by dry tillage', residue incorporated) -> conventional. Supplementary: none found (web search 2026-10-05; publisher site not reachable). Source file 113.pdf. | AX4: TREATMENTS IN PAPER (Table 1, RBD 3 reps, since 1993, PDFSR Modipuram): T1 unfertilised; T2 recommended NPK (+Zn to rice) through fertilisers; T3 NPK + Zn + S (rice); T4 75% NPK + 25% N via FYM (rice); T5 75% NPK + 25% N via sulphitation press mud (rice); T6 75% NPK + green gram residue incorporated before rice; T7 = T6 (rice) + 75% NPK + 25% N via FYM (wheat); T8 75% NPK + 25% N via WHEAT STRAW to rice and 75% NPK + 25% N via RICE STRAW to wheat (CR). Rice puddled and transplanted (Saket 4, 20 x 10 cm, continuous 5 cm submergence); wheat HD 2338 drilled after dry tillage ('wet tillage followed by dry tillage'); recommended 120-26-33 kg N-P-K/ha to each crop. T2 -> CT ; T8 -> CTR (FLAG fertiliser offset, rule 62); T1, T3-T7 EXCLUDED (unfertilised / amendments / third crop in some treatments only). | AY4: Wet sieving 2, 0.25, 0.053 mm after slaking (Six et al. 2000); macro = LM (>2 mm) + SM (0.25-2 mm); micro = mi (0.053-0.25 mm)
A5: 166 | B5: 166 | C5: Das B., Chakraborty D., Singh V.K., Aggarwal P., Singh R., Dwivedi B.S. & Mishra R.P. | D5: 2014 | E5: Soil & Tillage Research | F5: India (Uttar Pradesh) | G5: PDFSR (now ICAR-IIFSR) long-term INM experiment, Modipuram, Meerut | H5: 29.067 | I5: 77.767 | J5: ST | K5: 2011 | L5: >10 Y | M5: LOAMY | N5: 0-15 CM | O5: 7.5-15 cm | Q5: 5.43 | V5: 11.65 | AB5: 2 | AC5: 3 | AD5: =IF(AND(N(AB5)>0,N(AC5)>0),SQRT(2*AB5/AC5),"") -> 1.1547005 | AE5: 27 | AF5: 5 | AG5: 45.5 | AH5: 863 | AI5: 29.067 | AJ5: 18 | AM5: 7.98 | AN5: 4.1 | AO5: 1.55 | AP5: 55 | AQ5: 18 | AR5: % (g/100 g soil, mi 0.053-0.25 mm) | AS5: T2 (100% NPK, residues removed) -> CT ; T8 (75% NPK + 25% N via crop residue, both crops) -> CTR [FLAG: fertiliser offset] | AT5: Wheat season - sampled 14 May 2011 after wheat harvest (18th year) | AU5: T2: 120-26-33 kg N-P-K/ha to rice and wheat + Zn 5 kg/ha to rice. T8: 75% of NPK + 25% of N through wheat straw (rice) and rice straw (wheat); 1993-2011 organic C added by CR 61.54 (rice) + 47.72 (wheat) Mg C/ha; total C input T2 40.54, T8 154.36 Mg C/ha. Rice continuous submergence; wheat 5 irrigations. Initial soil: SL, EC 0.4 dS/m, Olsen P 16.4, avail. K 96, S 14.5 kg/ha, WHC 42%. | AV5: Table 4 | AW5: Obs = 2 (D=2: 0-7.5 and 7.5-15 cm both in the 0-15 CM class, separate rows). FLAG - FERTILISER OFFSET (rule 62): in T8 crop residue replaces 25% of fertiliser N and 25% of P and K are also cut; drop for a fertiliser-matched sensitivity check. Wheat tillage not described in detail ('wet tillage followed by dry tillage', residue incorporated) -> conventional. Supplementary: none found (web search 2026-10-05; publisher site not reachable). Source file 113.pdf. | AX5: TREATMENTS IN PAPER (Table 1, RBD 3 reps, since 1993, PDFSR Modipuram): T1 unfertilised; T2 recommended NPK (+Zn to rice) through fertilisers; T3 NPK + Zn + S (rice); T4 75% NPK + 25% N via FYM (rice); T5 75% NPK + 25% N via sulphitation press mud (rice); T6 75% NPK + green gram residue incorporated before rice; T7 = T6 (rice) + 75% NPK + 25% N via FYM (wheat); T8 75% NPK + 25% N via WHEAT STRAW to rice and 75% NPK + 25% N via RICE STRAW to wheat (CR). Rice puddled and transplanted (Saket 4, 20 x 10 cm, continuous 5 cm submergence); wheat HD 2338 drilled after dry tillage ('wet tillage followed by dry tillage'); recommended 120-26-33 kg N-P-K/ha to each crop. T2 -> CT ; T8 -> CTR (FLAG fertiliser offset, rule 62); T1, T3-T7 EXCLUDED (unfertilised / amendments / third crop in some treatments only). | AY5: Wet sieving 2, 0.25, 0.053 mm after slaking (Six et al. 2000); macro = LM (>2 mm) + SM (0.25-2 mm); micro = mi (0.053-0.25 mm)
A6: 166 | B6: 166 | C6: Das B., Chakraborty D., Singh V.K., Aggarwal P., Singh R., Dwivedi B.S. & Mishra R.P. | D6: 2014 | E6: Soil & Tillage Research | F6: India (Uttar Pradesh) | G6: PDFSR (now ICAR-IIFSR) long-term INM experiment, Modipuram, Meerut | H6: 29.067 | I6: 77.767 | J6: ST | K6: 2011 | L6: >10 Y | M6: LOAMY | N6: 15-30 CM | O6: 15-30 cm | Q6: 39.47 | V6: 10.57 | AB6: 1 | AC6: 3 | AD6: =IF(AND(N(AB6)>0,N(AC6)>0),SQRT(2*AB6/AC6),"") -> 0.81649658 | AE6: 27 | AF6: 5 | AG6: 45.5 | AH6: 863 | AI6: 29.067 | AJ6: 18 | AM6: 7.98 | AN6: 4.1 | AO6: 1.55 | AP6: 55 | AQ6: 18 | AR6: % (g/100 g soil, mi 0.053-0.25 mm) | AS6: T2 (100% NPK, residues removed) -> CT ; T8 (75% NPK + 25% N via crop residue, both crops) -> CTR [FLAG: fertiliser offset] | AT6: Wheat season - sampled 14 May 2011 after wheat harvest (18th year) | AU6: T2: 120-26-33 kg N-P-K/ha to rice and wheat + Zn 5 kg/ha to rice. T8: 75% of NPK + 25% of N through wheat straw (rice) and rice straw (wheat); 1993-2011 organic C added by CR 61.54 (rice) + 47.72 (wheat) Mg C/ha; total C input T2 40.54, T8 154.36 Mg C/ha. Rice continuous submergence; wheat 5 irrigations. Initial soil: SL, EC 0.4 dS/m, Olsen P 16.4, avail. K 96, S 14.5 kg/ha, WHC 42%. | AV6: Table 4 | AW6: Obs = 1 (D=1: one layer). FLAG - FERTILISER OFFSET (rule 62): in T8 crop residue replaces 25% of fertiliser N and 25% of P and K are also cut; drop for a fertiliser-matched sensitivity check. Wheat tillage not described in detail ('wet tillage followed by dry tillage', residue incorporated) -> conventional. Supplementary: none found (web search 2026-10-05; publisher site not reachable). Source file 113.pdf. | AX6: TREATMENTS IN PAPER (Table 1, RBD 3 reps, since 1993, PDFSR Modipuram): T1 unfertilised; T2 recommended NPK (+Zn to rice) through fertilisers; T3 NPK + Zn + S (rice); T4 75% NPK + 25% N via FYM (rice); T5 75% NPK + 25% N via sulphitation press mud (rice); T6 75% NPK + green gram residue incorporated before rice; T7 = T6 (rice) + 75% NPK + 25% N via FYM (wheat); T8 75% NPK + 25% N via WHEAT STRAW to rice and 75% NPK + 25% N via RICE STRAW to wheat (CR). Rice puddled and transplanted (Saket 4, 20 x 10 cm, continuous 5 cm submergence); wheat HD 2338 drilled after dry tillage ('wet tillage followed by dry tillage'); recommended 120-26-33 kg N-P-K/ha to each crop. T2 -> CT ; T8 -> CTR (FLAG fertiliser offset, rule 62); T1, T3-T7 EXCLUDED (unfertilised / amendments / third crop in some treatments only). | AY6: Wet sieving 2, 0.25, 0.053 mm after slaking (Six et al. 2000); macro = LM (>2 mm) + SM (0.25-2 mm); micro = mi (0.053-0.25 mm)

Sheet macro c
A1: No. | B1: SERIAL NO | C1: Authors | D1: Year | E1: Journal | F1: Country | G1: Site/Location | H1: latitude | I1: longitude | J1: CLIMATE | K1: year of data collection/experiment | L1: DURATION | M1: SOIL | N1: DEPTH | O1: DEPTH (as reported in paper) | P1: MACRO c_CA | Q1: MACRO c_CT | R1: MACRO c_ZT | S1: MACRO c_DT | T1: MACRO c_MTR | U1: MACRO c_MT | V1: MACRO c_CTR | W1: MACRO c_DTR | X1: MACRO c_pCA | Y1: MACRO c_pZT | Z1: MACRO c_pMT | AA1: MACRO c_pMTR | AB1: Obs | AC1: Rep | AD1: SD | AE1: CLAY | AF1: MIN TEMP | AG1: MAX TEMP | AH1: RAIN FALL | AI1: LATT | AJ1: YEAR OF DATA (duration) | AK1: AVG T | AL1: April max temp | AM1: ph (initial) | AN1: soc (initial) | AO1: Bdi | AP1: sand | AQ1: silt | AR1: UNIT | AS1: Treatment mapping (paper's name -> code) | AT1: Crop/season of sampling | AU1: Fertilizer dose & other management | AV1: Data source | AW1: Notes/Doubts | AX1: Treatment details (from paper) | AY1: Method used (from paper) | BA1: UNIT FOR THIS SHEET:
A2: 166 | B2: 166 | C2: Das B., Chakraborty D., Singh V.K., Aggarwal P., Singh R., Dwivedi B.S. & Mishra R.P. | D2: 2014 | E2: Soil & Tillage Research | F2: India (Uttar Pradesh) | G2: PDFSR (now ICAR-IIFSR) long-term INM experiment, Modipuram, Meerut | H2: 29.067 | I2: 77.767 | J2: ST | K2: 2011 | L2: >10 Y | M2: LOAMY | N2: 0-15 CM | O2: 0-7.5 cm | Q2: =ROUND((15.33*10.56+55.58*8.02)/(15.33+55.58),2) -> 8.57 | V2: =ROUND((34.15*14.58+57.72*12.99)/(34.15+57.72),2) -> 13.58 | AB2: 2 | AC2: 3 | AD2: =IF(AND(N(AB2)>0,N(AC2)>0),SQRT(2*AB2/AC2),"") -> 1.1547005 | AE2: 27 | AF2: 5 | AG2: 45.5 | AH2: 863 | AI2: 29.067 | AJ2: 18 | AM2: 7.98 | AN2: 4.1 | AO2: 1.55 | AP2: 55 | AQ2: 18 | AR2: g/kg (C in >0.25 mm aggregates, mass-weighted LM + SM) | AS2: T2 (100% NPK, residues removed) -> CT ; T8 (75% NPK + 25% N via crop residue, both crops) -> CTR [FLAG: fertiliser offset] | AT2: Wheat season - sampled 14 May 2011 after wheat harvest (18th year) | AU2: T2: 120-26-33 kg N-P-K/ha to rice and wheat + Zn 5 kg/ha to rice. T8: 75% of NPK + 25% of N through wheat straw (rice) and rice straw (wheat); 1993-2011 organic C added by CR 61.54 (rice) + 47.72 (wheat) Mg C/ha; total C input T2 40.54, T8 154.36 Mg C/ha. Rice continuous submergence; wheat 5 irrigations. Initial soil: SL, EC 0.4 dS/m, Olsen P 16.4, avail. K 96, S 14.5 kg/ha, WHC 42%. | AV2: Tables 4-5 - DERIVED | AW2: DERIVED: macro C = (LM x LM-C + SM x SM-C)/(LM + SM); printed LM-C 10.56/14.58, SM-C 8.02/12.99 g/kg (T2/T8). Obs = 2 (D=2: 0-7.5 and 7.5-15 cm both in the 0-15 CM class, separate rows). FLAG - FERTILISER OFFSET (rule 62): in T8 crop residue replaces 25% of fertiliser N and 25% of P and K are also cut; drop for a fertiliser-matched sensitivity check. Wheat tillage not described in detail ('wet tillage followed by dry tillage', residue incorporated) -> conventional. Supplementary: none found (web search 2026-10-05; publisher site not reachable). Source file 113.pdf. | AX2: TREATMENTS IN PAPER (Table 1, RBD 3 reps, since 1993, PDFSR Modipuram): T1 unfertilised; T2 recommended NPK (+Zn to rice) through fertilisers; T3 NPK + Zn + S (rice); T4 75% NPK + 25% N via FYM (rice); T5 75% NPK + 25% N via sulphitation press mud (rice); T6 75% NPK + green gram residue incorporated before rice; T7 = T6 (rice) + 75% NPK + 25% N via FYM (wheat); T8 75% NPK + 25% N via WHEAT STRAW to rice and 75% NPK + 25% N via RICE STRAW to wheat (CR). Rice puddled and transplanted (Saket 4, 20 x 10 cm, continuous 5 cm submergence); wheat HD 2338 drilled after dry tillage ('wet tillage followed by dry tillage'); recommended 120-26-33 kg N-P-K/ha to each crop. T2 -> CT ; T8 -> CTR (FLAG fertiliser offset, rule 62); T1, T3-T7 EXCLUDED (unfertilised / amendments / third crop in some treatments only). | AY2: C of aggregate fractions by elemental analyser (Vario EL) | BA2: g/kg (C in >0.25 mm aggregates)
A3: 166 | B3: 166 | C3: Das B., Chakraborty D., Singh V.K., Aggarwal P., Singh R., Dwivedi B.S. & Mishra R.P. | D3: 2014 | E3: Soil & Tillage Research | F3: India (Uttar Pradesh) | G3: PDFSR (now ICAR-IIFSR) long-term INM experiment, Modipuram, Meerut | H3: 29.067 | I3: 77.767 | J3: ST | K3: 2011 | L3: >10 Y | M3: LOAMY | N3: 0-15 CM | O3: 7.5-15 cm | Q3: =ROUND((8.2*9.02+66.6*7.95)/(8.2+66.6),2) -> 8.07 | V3: =ROUND((18.5*13.65+64.84*9.04)/(18.5+64.84),2) -> 10.06 | AB3: 2 | AC3: 3 | AD3: =IF(AND(N(AB3)>0,N(AC3)>0),SQRT(2*AB3/AC3),"") -> 1.1547005 | AE3: 27 | AF3: 5 | AG3: 45.5 | AH3: 863 | AI3: 29.067 | AJ3: 18 | AM3: 7.98 | AN3: 4.1 | AO3: 1.55 | AP3: 55 | AQ3: 18 | AR3: g/kg (C in >0.25 mm aggregates, mass-weighted LM + SM) | AS3: T2 (100% NPK, residues removed) -> CT ; T8 (75% NPK + 25% N via crop residue, both crops) -> CTR [FLAG: fertiliser offset] | AT3: Wheat season - sampled 14 May 2011 after wheat harvest (18th year) | AU3: T2: 120-26-33 kg N-P-K/ha to rice and wheat + Zn 5 kg/ha to rice. T8: 75% of NPK + 25% of N through wheat straw (rice) and rice straw (wheat); 1993-2011 organic C added by CR 61.54 (rice) + 47.72 (wheat) Mg C/ha; total C input T2 40.54, T8 154.36 Mg C/ha. Rice continuous submergence; wheat 5 irrigations. Initial soil: SL, EC 0.4 dS/m, Olsen P 16.4, avail. K 96, S 14.5 kg/ha, WHC 42%. | AV3: Tables 4-5 - DERIVED | AW3: DERIVED: macro C = (LM x LM-C + SM x SM-C)/(LM + SM); printed LM-C 9.02/13.65, SM-C 7.95/9.04 g/kg (T2/T8). Obs = 2 (D=2: 0-7.5 and 7.5-15 cm both in the 0-15 CM class, separate rows). FLAG - FERTILISER OFFSET (rule 62): in T8 crop residue replaces 25% of fertiliser N and 25% of P and K are also cut; drop for a fertiliser-matched sensitivity check. Wheat tillage not described in detail ('wet tillage followed by dry tillage', residue incorporated) -> conventional. Supplementary: none found (web search 2026-10-05; publisher site not reachable). Source file 113.pdf. | AX3: TREATMENTS IN PAPER (Table 1, RBD 3 reps, since 1993, PDFSR Modipuram): T1 unfertilised; T2 recommended NPK (+Zn to rice) through fertilisers; T3 NPK + Zn + S (rice); T4 75% NPK + 25% N via FYM (rice); T5 75% NPK + 25% N via sulphitation press mud (rice); T6 75% NPK + green gram residue incorporated before rice; T7 = T6 (rice) + 75% NPK + 25% N via FYM (wheat); T8 75% NPK + 25% N via WHEAT STRAW to rice and 75% NPK + 25% N via RICE STRAW to wheat (CR). Rice puddled and transplanted (Saket 4, 20 x 10 cm, continuous 5 cm submergence); wheat HD 2338 drilled after dry tillage ('wet tillage followed by dry tillage'); recommended 120-26-33 kg N-P-K/ha to each crop. T2 -> CT ; T8 -> CTR (FLAG fertiliser offset, rule 62); T1, T3-T7 EXCLUDED (unfertilised / amendments / third crop in some treatments only). | AY3: C of aggregate fractions by elemental analyser (Vario EL)
A4: 166 | B4: 166 | C4: Das B., Chakraborty D., Singh V.K., Aggarwal P., Singh R., Dwivedi B.S. & Mishra R.P. | D4: 2014 | E4: Soil & Tillage Research | F4: India (Uttar Pradesh) | G4: PDFSR (now ICAR-IIFSR) long-term INM experiment, Modipuram, Meerut | H4: 29.067 | I4: 77.767 | J4: ST | K4: 2011 | L4: >10 Y | M4: LOAMY | N4: 15-30 CM | O4: 15-30 cm | Q4: =ROUND((5.3*5.24+54.01*3.63)/(5.3+54.01),2) -> 3.77 | V4: =ROUND((17.4*13.24+65.43*8.66)/(17.4+65.43),2) -> 9.62 | AB4: 1 | AC4: 3 | AD4: =IF(AND(N(AB4)>0,N(AC4)>0),SQRT(2*AB4/AC4),"") -> 0.81649658 | AE4: 27 | AF4: 5 | AG4: 45.5 | AH4: 863 | AI4: 29.067 | AJ4: 18 | AM4: 7.98 | AN4: 4.1 | AO4: 1.55 | AP4: 55 | AQ4: 18 | AR4: g/kg (C in >0.25 mm aggregates, mass-weighted LM + SM) | AS4: T2 (100% NPK, residues removed) -> CT ; T8 (75% NPK + 25% N via crop residue, both crops) -> CTR [FLAG: fertiliser offset] | AT4: Wheat season - sampled 14 May 2011 after wheat harvest (18th year) | AU4: T2: 120-26-33 kg N-P-K/ha to rice and wheat + Zn 5 kg/ha to rice. T8: 75% of NPK + 25% of N through wheat straw (rice) and rice straw (wheat); 1993-2011 organic C added by CR 61.54 (rice) + 47.72 (wheat) Mg C/ha; total C input T2 40.54, T8 154.36 Mg C/ha. Rice continuous submergence; wheat 5 irrigations. Initial soil: SL, EC 0.4 dS/m, Olsen P 16.4, avail. K 96, S 14.5 kg/ha, WHC 42%. | AV4: Tables 4-5 - DERIVED | AW4: DERIVED: macro C = (LM x LM-C + SM x SM-C)/(LM + SM); printed LM-C 5.24/13.24, SM-C 3.63/8.66 g/kg (T2/T8). Obs = 1 (D=1: one layer). FLAG - FERTILISER OFFSET (rule 62): in T8 crop residue replaces 25% of fertiliser N and 25% of P and K are also cut; drop for a fertiliser-matched sensitivity check. Wheat tillage not described in detail ('wet tillage followed by dry tillage', residue incorporated) -> conventional. Supplementary: none found (web search 2026-10-05; publisher site not reachable). Source file 113.pdf. | AX4: TREATMENTS IN PAPER (Table 1, RBD 3 reps, since 1993, PDFSR Modipuram): T1 unfertilised; T2 recommended NPK (+Zn to rice) through fertilisers; T3 NPK + Zn + S (rice); T4 75% NPK + 25% N via FYM (rice); T5 75% NPK + 25% N via sulphitation press mud (rice); T6 75% NPK + green gram residue incorporated before rice; T7 = T6 (rice) + 75% NPK + 25% N via FYM (wheat); T8 75% NPK + 25% N via WHEAT STRAW to rice and 75% NPK + 25% N via RICE STRAW to wheat (CR). Rice puddled and transplanted (Saket 4, 20 x 10 cm, continuous 5 cm submergence); wheat HD 2338 drilled after dry tillage ('wet tillage followed by dry tillage'); recommended 120-26-33 kg N-P-K/ha to each crop. T2 -> CT ; T8 -> CTR (FLAG fertiliser offset, rule 62); T1, T3-T7 EXCLUDED (unfertilised / amendments / third crop in some treatments only). | AY4: C of aggregate fractions by elemental analyser (Vario EL)

Sheet micro c
A1: No. | B1: SERIAL NO | C1: Authors | D1: Year | E1: Journal | F1: Country | G1: Site/Location | H1: latitude | I1: longitude | J1: CLIMATE | K1: year of data collection/experiment | L1: DURATION | M1: SOIL | N1: DEPTH | O1: DEPTH (as reported in paper) | P1: MICRO c_CA | Q1: MICRO c_CT | R1: MICRO c_ZT | S1: MICRO c_DT | T1: MICRO c_MTR | U1: MICRO c_MT | V1: MICRO c_CTR | W1: MICRO c_DTR | X1: MICRO c_pCA | Y1: MICRO c_pZT | Z1: MICRO c_pMT | AA1: MICRO c_pMTR | AB1: Obs | AC1: Rep | AD1: SD | AE1: CLAY | AF1: MIN TEMP | AG1: MAX TEMP | AH1: RAIN FALL | AI1: LATT | AJ1: YEAR OF DATA (duration) | AK1: AVG T | AL1: April max temp | AM1: ph (initial) | AN1: soc (initial) | AO1: Bdi | AP1: sand | AQ1: silt | AR1: UNIT | AS1: Treatment mapping (paper's name -> code) | AT1: Crop/season of sampling | AU1: Fertilizer dose & other management | AV1: Data source | AW1: Notes/Doubts | AX1: Treatment details (from paper) | AY1: Method used (from paper) | BA1: UNIT FOR THIS SHEET:
A2: 166 | B2: 166 | C2: Das B., Chakraborty D., Singh V.K., Aggarwal P., Singh R., Dwivedi B.S. & Mishra R.P. | D2: 2014 | E2: Soil & Tillage Research | F2: India (Uttar Pradesh) | G2: PDFSR (now ICAR-IIFSR) long-term INM experiment, Modipuram, Meerut | H2: 29.067 | I2: 77.767 | J2: ST | K2: 2011 | L2: >10 Y | M2: LOAMY | N2: 0-15 CM | O2: 0-7.5 cm | Q2: 5.68 | V2: 8.91 | AB2: 2 | AC2: 3 | AD2: =IF(AND(N(AB2)>0,N(AC2)>0),SQRT(2*AB2/AC2),"") -> 1.1547005 | AE2: 27 | AF2: 5 | AG2: 45.5 | AH2: 863 | AI2: 29.067 | AJ2: 18 | AM2: 7.98 | AN2: 4.1 | AO2: 1.55 | AP2: 55 | AQ2: 18 | AR2: g/kg (C in 0.053-0.25 mm aggregates) | AS2: T2 (100% NPK, residues removed) -> CT ; T8 (75% NPK + 25% N via crop residue, both crops) -> CTR [FLAG: fertiliser offset] | AT2: Wheat season - sampled 14 May 2011 after wheat harvest (18th year) | AU2: T2: 120-26-33 kg N-P-K/ha to rice and wheat + Zn 5 kg/ha to rice. T8: 75% of NPK + 25% of N through wheat straw (rice) and rice straw (wheat); 1993-2011 organic C added by CR 61.54 (rice) + 47.72 (wheat) Mg C/ha; total C input T2 40.54, T8 154.36 Mg C/ha. Rice continuous submergence; wheat 5 irrigations. Initial soil: SL, EC 0.4 dS/m, Olsen P 16.4, avail. K 96, S 14.5 kg/ha, WHC 42%. | AV2: Table 5 | AW2: Obs = 2 (D=2: 0-7.5 and 7.5-15 cm both in the 0-15 CM class, separate rows). FLAG - FERTILISER OFFSET (rule 62): in T8 crop residue replaces 25% of fertiliser N and 25% of P and K are also cut; drop for a fertiliser-matched sensitivity check. Wheat tillage not described in detail ('wet tillage followed by dry tillage', residue incorporated) -> conventional. Supplementary: none found (web search 2026-10-05; publisher site not reachable). Source file 113.pdf. | AX2: TREATMENTS IN PAPER (Table 1, RBD 3 reps, since 1993, PDFSR Modipuram): T1 unfertilised; T2 recommended NPK (+Zn to rice) through fertilisers; T3 NPK + Zn + S (rice); T4 75% NPK + 25% N via FYM (rice); T5 75% NPK + 25% N via sulphitation press mud (rice); T6 75% NPK + green gram residue incorporated before rice; T7 = T6 (rice) + 75% NPK + 25% N via FYM (wheat); T8 75% NPK + 25% N via WHEAT STRAW to rice and 75% NPK + 25% N via RICE STRAW to wheat (CR). Rice puddled and transplanted (Saket 4, 20 x 10 cm, continuous 5 cm submergence); wheat HD 2338 drilled after dry tillage ('wet tillage followed by dry tillage'); recommended 120-26-33 kg N-P-K/ha to each crop. T2 -> CT ; T8 -> CTR (FLAG fertiliser offset, rule 62); T1, T3-T7 EXCLUDED (unfertilised / amendments / third crop in some treatments only). | AY2: Elemental analyser (Vario EL) | BA2: g/kg (C in <0.25 mm aggregates)
