Workbook

Sheet README
A1: TITLE | B1: Conservation agriculture meta-analysis - NEW data extraction workbook (structure of META_ANALYSIS_MASTER updated 53, no previous data)
A2: NEW SERIES | B2: Started 2026-10-05. All data rows of the old master were removed at the author's request; serials continue from the old master, starting at 164, so the two files can be merged. The history entries further down describe the OLD master (updated 53) and are kept only as the rulebook.
A3: PARTIAL CA COLUMNS | B3: Every parameter sheet has <prefix>pCA, pZT, pMT, pMTR (olive-green headers) after <prefix>DTR: puddled / conventional rice + ZT wheat with residue (pCA) / without residue (pZT), + MT wheat without (pMT) / with residue (pMTR). See Codes and RULES.
A4: LAT_LONG | B4: One row per study x site: coordinates as reported and in decimal degrees, source (paper / Google Maps), climate class.
A6: HOW TO USE | B6: Upload ONE research paper at a time. Data are extracted and appended to the relevant parameter sheets only. Sheets for parameters absent from a paper are left untouched.
A8: SHEET TYPES
A9: Study_Info | B9: One row per study x site. Master record of coordinates, climate, initial soil properties, management. Fill this FIRST for every new paper.
A10: Treatment_Mapping | B10: Log of every treatment in every paper and the code it was assigned. Any treatment that is unclear is logged here with status NEEDS CONFIRMATION and left out of the data sheets.
A11: Codes | B11: Treatment codes + all reclassification rules (climate, texture, duration, depth).
A12: Parameter sheets | B12: One sheet per measured parameter (BD, SOC, MWD, PR, YIELD, ...). Unit for each sheet is written in the orange note to the right of the header row AND in the UNIT column.
A14: COLUMN COLOUR KEY
A15: Dark blue | B15: Study identification
A16: Teal | B16: Soil depth (reclassified + as reported)
A17: Green | B17: Treatment mean values
A18: Amber | B18: Obs / Rep / SD
A19: Grey | B19: Site covariates (climate, initial soil)
A20: Purple | B20: Unit, treatment mapping, management, data source, notes
A22: RULES APPLIED
A23: Rep | B23: Always 3 unless the paper clearly states otherwise.
A24: Obs | B24: Number of paper-level data points collapsed into that row for that depth class: years x sub-treatments x original depths falling in the class. e.g. 3 years x 1 depth = 3; 3 years x 2 original depths in the same class x 2 qualifying treatments = 12.
A25: SD | B25: SD = SQRT(2*Obs/Rep) - the formula used in the original workbook. Written as a live formula so it updates if Obs changes. Overwritten with the real value when the paper reports SD (or SE, converted as SD = SE*sqrt(Rep)).
A26: Season | B26: Soil parameters are taken from the WHEAT season, not the rice season.
A27: Coordinates | B27: Decimal degrees. Taken from the paper; if absent, looked up from the stated location and flagged in Notes.
A28: Figures | B28: Values read off figures are digitised (WebPlotDigitizer style) and marked 'Figure' in Data source.
A29: Supplementary | B29: Supplementary files are searched for online and extracted; marked 'Supplementary' in Data source.
A30: Multi-year / multi-site | B30: Every year and every site is entered - separate rows, Site/Location and YEAR OF DATA distinguish them.
A31: Doubtful treatments | B31: Left blank in the data sheets and raised with you; logged in Treatment_Mapping.
A32: Porosity | B32: Where a paper reports total porosity it is entered as printed (studies 5 and 11). Everywhere else it is DERIVED as porosity (%) = (1 - BD / PD) x 100, using the TREATMENT bulk density from the BD sheet - as a live cross-sheet formula, so correcting a bulk density corrects the porosity - and PD = 2.65 Mg/m3, since no study with bulk-density data reports its own particle density. That default reproduces both measured porosities in this workbook to within 0.1 percentage points. Derived rows say DERIVED in Data source; replace 2.65 in the formulas to change the assumption.
A33: EXAMPLE ROW (BD sheet) | B33: Do not keep this in the data sheets - shown here only as a format guide.
A35: No. | B35: SERIAL NO | C35: Authors | D35: Year | E35: Journal | F35: Country | G35: Site/Location | H35: latitude | I35: longitude | J35: CLIMATE | K35: year of data collection/experiment | L35: DURATION | M35: SOIL | N35: DEPTH | O35: DEPTH (as reported in paper) | P35: BD_CA | Q35: BD_CT | R35: BD_ZT | S35: Obs | T35: Rep | U35: SD | V35: CLAY | W35: RAIN FALL | X35: ph (initial) | Y35: UNIT | Z35: Treatment mapping (paper's name -> code) | AA35: Data source
A36: 1 | B36: 1 | C36: Roy D. et al. | D36: 2021 | E36: Geoderma | F36: India | G36: Karnal, Haryana | H36: 29.42 | I36: 76.57 | J36: ST | K36: 10 | L36: 4-10 Y | M36: LOAMY | N36: 0-15 CM | O36: 0-5 + 5-15 cm pooled | P36: 1.39 | Q36: 1.5 | R36: 1.44 | S36: 2 | T36: 3 | U36: SD = SQRT(2*Obs/Rep) (live formula in the data sheets) | V36: 19.89 | W36: 670 | X36: 8 | Y36: Mg/m3 | Z36: ZT+R (ZTW with full residue) -> CA; CTW no residue -> CT; ZTW no residue -> ZT | AA36: Table 3
A38: SHEET SET | B38: Sheets are added only when you ask for them. Six were added on 2026-10-01 at your request: WSC, LFC-LFOC, LFON, PON, cPOM-C and fPOM-C - each carries its full form in the purple note to the right of its header row. For any OTHER parameter this workbook does not carry, values are kept in the Notes/Doubts column of the closest existing sheet. Those still parked in notes are listed below.
A39: SOC(active C pool) | B39: Soil organic carbon as the papers report it - in most papers simply "SOC" or "organic carbon", measured by Walkley-Black wet oxidation, i.e. the oxidisable / labile fraction rather than total carbon. ALL studies that report treatment-level SOC go on this sheet. Total carbon by dry combustion goes on TC(total c); inorganic carbon on SIC.
A40: ACTIVE C-MACRO / MICRO | B40: Active carbon pool associated with macroaggregates (>0.25 mm) and microaggregates (<0.25 mm), g/kg - these live on the macro c and micro c sheets, no separate sheets.
A41: Still parked in Notes | B41: DOC (dissolved organic carbon), KMnO4-oxidisable carbon, the Chan et al. very-labile / labile / less-labile / non-labile pools P1-P4, cumulative CO2-C, sorptivity, cumulative infiltration, stratification ratios, energy-budget terms, and the 0-90 cm carbon stocks of study 25. Say the word and any of these becomes a sheet.
A45: Derived-value rule | B45: Anything computed rather than printed carries its formula and inputs in the Notes column and names its Data source as DERIVED.
A46: ROOT sheets (added 2026-10-03) | B46: On author instruction, root parameters of rice and wheat are entered as DENSITIES plus diameter: RLD(CM-CM3), RVD(cm3-cm3), RMD(mg-cm3) and two new sheets RSD(cm2-cm3) (root surface area density) and ROOT DIA(mm) (average root diameter). Per-sample root values are converted with the sampled soil volume (formula and assumption in Notes). _W = wheat, _R = rice columns.
A47: New sheets (updated 8, 2026-10-03) | B47: Carbon/soil sheets added for Gupta et al. 2022 (study 75 companion) and Kahlon 2014 (study 74): POXC(KMnO4-C) mg/kg; the Chan et al. (2001) oxidisable C fractions VLC(Cfrac1), LC(Cfrac2), LLC(Cfrac3), NLC(Cfrac4) g/kg (VLC + LC + LLC + NLC = TOC); Fungal count and Cellulolytic count (CFU/g, multiplier in UNIT); Moisture storage (mm, soil-profile water storage). Same column layout as every parameter sheet.
A48: IR sheet (2026-10-03) | B48: IR_ columns = STEADY-STATE infiltration rate; IIR_ columns = INITIAL infiltration rate (both cm/hr). Final, basic and quasi-steady rates go in IR_; the first-reading rate goes in IIR_.
A49: FORMULAS sheet + NET RETURN sheet (2026-10-04) | B49: Every derivation used in the workbook is listed on the FORMULAS sheet (straw = biomass - grain, HI = grain / biomass, CL/LI/CPI/CMI, GHGI = GWP / grain, porosity, SD, unit conversions). NET RETURN sheet = net return per ha in the printed currency (W / R / SYS groups, as BC ratio). DERIVED rows reference their source cells with live formulas and say so in Data source.
A50: Soil-water sheets (2026-10-04) | B50: GWC (gravimetric water content), AWC (weight basis), AWC (volume basis), WHC (Keen box only), FC (weight basis), PWP (weight basis). See Codes and FORMULAS.
A51: Soil-water re-check (2026-10-05) | B51: All previous studies re-checked against Methods; WATER-QUANTITY CHECK notes added; new rows: GWC studies 11 (Table 3), 12 (Fig. 4), 18 (Fig. 6), 62 (Fig. 2); FC / PWP / AWC study 9 (Figs 3-6).
A52: Batch ext\221-225 (2026-10-05) | B52: 102 (companion 3) Yu 2026; 129 (companion) Guo 2026 yields; 134 Rana 2023 (rice, red); 136 Hou 2026 (W0); 28 (companion) re-submission; 133 Yan 2018 and 135 Li 2026 excluded.
... A66: Batch 12 (updated 12, 2026-10-05) | B66: updated 12 = updated 11 + files 123_real, 123, 122_real, 124_real, 124: 115 (companion) Pokharel 2018 (SRFSI Sunsari, Nepal: CT, pCA, CA rows a/b; residue per old-master 115, flag; rice-maize excluded); 174 Gathala 2017 J Ecosys Ecograph (Modipuram 2005-07: T1 pZT, T2 pCA, T3/T5 ZT, T4/T6 CA rows a/b; EC, SOC, K, MACRO, MICRO, WSA, MWD, BD 4 layers + porosity, SPR 9 depths, steady IR - all figures read exactly from vector objects); 175 Hossain 2022 (Mymensingh on-farm: TA CT vs CA strip tillage + residue MTR; yields, B:C, yield components, REY, growth duration); 176 Devkota 2015 Eur J Agron (Khorezm, Uzbekistan: ZT R0 vs CA R50/R100 on beds and flats, rows a-d; gross margin, B:C, wheat-season ECe) and 176 (companion) Devkota 2015 Agric For Meteorol (measured yields digitised from the vector scatter; DSSAT MODEL OUTPUT yields, N uptake, N leached). WSRF (conventional water-seeded rice + surface-seeded wheat) NOT entered pending the author. New default rules 103-106. Obs = Y + T + D on every new row (rule 101).

Sheet RULES
A1: RULES - consolidated extraction, coding and analysis rules of this workbook (author-confirmed unless marked). Updated 2026-10-05
A3: No. | B3: Category | C3: Rule | D3: Details / worked examples | E3: Source / date | F3: Status
A4: WORKFLOW & DATA MANAGEMENT
A5: 1 | B5: Workflow & data management | C5: Existing entries are correct and are not recalculated or 'fixed'. | D5: New rules apply to new papers. Earlier rows are changed only when the author asks (e.g. an entry shown to be wrong against its source: study 59 in updated 17; rotary-rule recoding in updated 47). | E5: Author 2026-10-03 | F5: IN FORCE
A6: 2 | B6: Workflow & data management | C6: Every batch is saved as a new numbered version (META_ANALYSIS_MASTER updated NN.xlsx); the previous file is never overwritten. | D6: Each build is checked cell-by-cell against the previous version (only intended cells may change, 0 formula errors). | E6: Workbook convention | F6: IN FORCE
A7: 3 | B7: Workflow & data management | C7: Ask the author whenever in doubt. | D7: Unclear treatments are left out of the data sheets and raised with the author; doubts are written in Notes/Doubts. | E7: Author | F7: IN FORCE
A8: 4 | B8: Workflow & data management | C8: Fill Study_Info first; log EVERY treatment of every paper in Treatment_Mapping with its code (or EXCLUDED) and rationale; excluded data go to EXCLUDED_rows. | D8: Check Study_Info for duplicates (DOI, title, authors, year) before adding a paper. | E8: Workbook convention | F8: IN FORCE
A9: 5 | B9: Workflow & data management | C9: Same experiment reported in two papers = ONE serial; same site but a different experiment = separate serials. | D9: Different papers of one trial are filed as 'NN (companion)', 'NN (companion 2)' ... | E9: Codes - SAME-EXPERIMENT RULE | F9: IN FORCE
A10: 6 | B10: Workflow & data management | C10: A re-submitted paper that is already in the workbook is entered AGAIN as 'NN (companion)' (duplicate-flagged); the original study is not changed. | D10: Two identical files in the SAME batch: enter once, record the duplicate in EXCLUDED_rows. Same-trial papers reporting the same seasons: keep both, flag duplicate seasons. | E10: Author 2026-10-03 / 2026-10-05 | F10: IN FORCE
A11: 7 | B11: Workflow & data management | C11: Look for supplementary material online for every paper and report what was found (or 'none found' and where searched); extract its data (Data source = 'Supplementary ...'). | D11: Downloading a supplement needs the author's permission. CAPTCHA pages are never bypassed - the file is fetched from the publisher's direct link only after permission, or the author supplies it (Desktop\SUPP DATA). | E11: Author 2026-10-03 | F11: IN FORCE
A12: 8 | B12: Workflow & data management | C12: Extract everything: tables, text AND figures (digitised; approximate values flagged). | D12: End each batch with a list of anything not extracted. Figures: vector paths read exactly where possible, raster figures by calibrated colour digitising. | E12: Author 2026-10-03 | F12: IN FORCE
A13: 9 | B13: Workflow & data management | C13: The author wants MORE data: enter every parameter that has a sheet, even when it must be derived or has a non-standard definition/unit (flagged). | D13: When unsure whether something goes in notes or on a sheet, lean to a sheet. Parameters with NO sheet are not entered unless the author asks for a new sheet (e.g. PLFA not entered). | E13: Author 2026-10-03 / 2026-10-04 | F13: IN FORCE
A14: 10 | B14: Workflow & data management | C14: Every data sheet carries 'Treatment details (from paper)' and 'Method used (from paper)' right after Notes/Doubts. | D14: Treatment details = Study_Info treatments + every Treatment_Mapping line of the study (so treatments can be re-classified). Method = analytical method auto-detected from the paper's Methods with a quoted context (verify). Filled for every new row of every build. | E14: Author 2026-10-05 | F14: IN FORCE
A15: 11 | B15: Workflow & data management | C15: Data source tags: Text / Table n / Figure n (digitised) / Supplementary / Calculated / DERIVED / MODEL OUTPUT / Author-reported. | E15: Codes | F15: IN FORCE
A16: TREATMENT CODES
A17: 12 | B17: Treatment codes | C17: CA = zero tillage + residue; ZT = zero tillage, no residue; CT = conventional tillage, no residue; CTR = conventional + residue; MT = minimum/reduced tillage, no residue; MTR = minimum/reduced + residue; DT = deep tillage, no residue; DTR = deep tillage + residue. | D17: Typical descriptions of each code are on the Codes sheet. | E17: Codes | F17: IN FORCE
A18: 13 | B18: Treatment codes | C18: ROTARY / ROTAVATOR RULE: full-width rotary or rotavator tillage to >=10 cm, OR >=2 full-width passes = CT (CTR with residue), whatever the paper calls it. Rotary <=8 cm, a single-pass rotary till-drill, Super Seeder / Roto Seeder, or strip / zone rotary (only the seed rows tilled) = MT (MTR with residue). | D18: Rotavator = rotary tillage (same rule). 8-10 cm, or depth unstated and not clearly full-width primary tillage -> ask. Applied to old studies in updated 47: 25 T6/T7 -> CT/CTR (row b), 41 Rot+R100 -> MTR (row b), 64 + 64 (companion) RT -> CTR (row b), 69 AR -> CT (study excluded, no contrast), 74 RT -> CTR, 82 rotavator -> CT/CTR (row a, depth not stated - flag). | E18: Author 2026-10-05 | F18: IN FORCE
A19: 14 | B19: Treatment codes | C19: Deep tillage: ploughing / chiselling / sub-soiling >= 25 cm, or straw buried to 30 cm -> DT (no straw) / DTR (straw). | D19: Studies 9, 65, 108. | E19: Author 2026-10-03 | F19: IN FORCE
A20: 15 | B20: Treatment codes | C20: Bed systems: permanent beds + residue -> CA; permanent beds without residue -> ZT; freshly made beds each season -> MT; VMP beds re-formed + non-puddled transplanting -> MTR. | E20: Codes; author 2026-10-04 | F20: IN FORCE
A21: 16 | B21: Treatment codes | C21: Strip tillage, zone-disc tiller or strip drill + residue -> MTR, even when the paper calls it CA. | D21: Studies 124, 125, 127. | E21: Author 2026-10-03 / 2026-10-04 | F21: IN FORCE
A22: 17 | B22: Treatment codes | C22: Shallow rotary 3-5 cm stubble breaking + surface straw -> MTR; shallow rotary 6-7 cm + straw mulch -> MTR. | D22: Guo 2026 'NT' (129 companion); Kong 121 STS. | E22: Author 2026-10-04 / 2026-10-05 | F22: IN FORCE
A23: 18 | B23: Treatment codes | C23: Low residue (about 20 % stubble, farmer practice) counts as residue -> CTR / MTR. | D23: Rows pair like residue levels (as study 40). | E23: Author 2026-10-04 | F23: IN FORCE
A24: 19 | B24: Treatment codes | C24: Tillage ~25 cm with a 'conventional tiller' + straw -> CT / CTR; PTOS (power-tiller-operated seeder, full tillage) -> CTR. | E24: Author 2026-10-04 / 2026-10-05 | F24: IN FORCE
A25: 20 | B25: Treatment codes | C25: Several of the paper's treatments under ONE code -> one row per treatment (rows a, b, c ...), the other codes repeated in each row. | D25: Obs adds T = number of treatments under that code (see Statistics). | E25: Author 2026-10-03 | F25: IN FORCE
A26: 21 | B26: Treatment codes | C26: Inclusion threshold: a study is included if it yields ANY TWO usable codes; a CT reference is not required. | D26: A study left with one code after the rotation rule contributes nothing (e.g. study 69 after the rotary rule). | E26: Codes - INCLUSION THRESHOLD | F26: IN FORCE
A27: ROTATION MATCHING (RICE + WHEAT PHASES)
A28: 22 | B28: Rotation matching (rice + wheat phases) | C28: Rice tillage stated: the rice and wheat phases of a treatment must be the SAME type of tillage; a mismatched treatment is EXCLUDED, in either direction. | D28: Excluded: no-till rice + conventional wheat (RNT-WCT); puddled rice + ZT / bed wheat; alternate tillage. Logged in Treatment_Mapping as EXCLUDED. | E28: Codes - STANDING RULE 1 | F28: IN FORCE
A29: 23 | B29: Rotation matching (rice + wheat phases) | C29: Rice tillage NOT stated: classify on the wheat-phase tillage alone (do not assume a puddled rice phase). | D29: Studies 9, 11, 12, 41. | E29: Codes - STANDING RULE 2 | F29: IN FORCE
A30: 24 | B30: Rotation matching (rice + wheat phases) | C30: Author exceptions: puddled rice + conservation wheat INCLUDED and flagged 'PUDDLED RICE PHASE'. | D30: Kahlon 2014 (74), 34 (companion), Yangzhou group 126-128, 130, 132 - filter on the flag for sensitivity analysis. | E30: Author 2026-10-03 / 2026-10-04 | F30: IN FORCE
A31: 25 | B31: Rotation matching (rice + wheat phases) | C31: Tilled UNPUDDLED rice (dry tillage, transplanted or direct-seeded) + ZT wheat: without residue -> ZT, with residue -> CA (flagged). | D31: UPTR-ZTW, MTR/DSR-ZTW, CT-DDSR fb ZT -> ZT; study 29 family T6 -> CA. Puddled / wet-tilled rice + ZTW stays a mismatch. | E31: Author 2026-10-03 / 2026-10-04 | F31: IN FORCE
A32: 26 | B32: Rotation matching (rice + wheat phases) | C32: Zero-till DSR + one-pass rotary till-drill wheat -> MT; tilled DSR + reduced-till wheat -> MT (+ residue -> MTR). | D32: Studies 76, 79, 113. | E32: Author 2026-10-03 / 2026-10-04 | F32: IN FORCE
A33: 27 | B33: Rotation matching (rice + wheat phases) | C33: Unpuddled (aerobic) rice = reduced tillage -> MT. | D33: Study 69 AR. Superseded on 2026-10-05: AR land preparation was disc plough + rotavator = CT under the rotary rule, so study 69 is excluded (rows in EXCLUDED_rows). | E33: Author 2026-10-03 | F33: SUPERSEDED (rotary rule)
A34: 28 | B34: Rotation matching (rice + wheat phases) | C34: Puddled drum-seeded rice + CT wheat -> CT; SRI fb SWI -> CT; SRI-SWI with a different nutrient regime is excluded when a proper CT exists; CT dry-seeded unpuddled rice + CT wheat -> CT / CTR (flagged). | E34: Author 2026-10-03 / 2026-10-04 | F34: IN FORCE
A35: 29 | B35: Rotation matching (rice + wheat phases) | C35: When papers of one trial disagree on puddling, follow the main paper. | D35: Mishra Table 1 used over Saurabh for study 29 T3. | E35: Author 2026-10-04 | F35: IN FORCE
A36: CROPPING SYSTEM & DESIGN
A37: 30 | B37: Cropping system & design | C37: Third crop grown in EVERY treatment -> included; added in some treatments only -> those treatments excluded; with a mixed rotation history -> include flagged. | D37: When a third crop is present only in some treatments, use the treatment with the same rotation as the CT reference (Chaki CS1 vs CS2/CS3). | E37: Codes; author 2026-10-04 | F37: IN FORCE
A38: 31 | B38: Cropping system & design | C38: Excluded systems: rice-maize, wheat-maize, soybean-wheat, double rice, rice-only or rice-rice TRIALS. | D38: Exception: a rice-season-only paper from a genuine rice-wheat CA trial -> red rice rows (Rana 2023, Bazaya 2009). | E38: Author 2026-10-03 / 2026-10-05 | F38: IN FORCE
A39: 32 | B39: Cropping system & design | C39: Factorial / split-plot papers: use the interaction (cell) means; papers with only marginal / mixed-rotation means -> excluded, values in notes. | D39: Tripathi 2007 (72). | E39: Codes | F39: IN FORCE
A40: 33 | B40: Cropping system & design | C40: Non-tillage factors (N dose, irrigation, nutrient source, variety, density, rotation ...) crossed with tillage -> one row per factor level (cell means), level named in Notes and 'Fertilizer dose & other management'. | D40: Only if no cell means are printed, the main-effect mean is used and flagged. From serial 76 onward (not retroactive). Main-effect means pooled over residue -> entered flagged. | E40: Author 2026-10-03 / 2026-10-04 | F40: IN FORCE
A41: 34 | B41: Cropping system & design | C41: Amendments and confounded treatments are excluded: biochar, compost added, INM / nutrient-management trials with identical tillage, unfertilised control or undefined farmer practice when a fertilised tier exists, rotation treatments. | D41: Artificial warming: ambient (W0) rows only, warmed rows in notes. Rhizosphere devices / simulated tillage soil excluded. | E41: Author 2026-10-03 / 2026-10-05 | F41: IN FORCE
A42: SEASONS, YEARS & ROWS
A43: 35 | B43: Seasons, years & rows | C43: Wheat season is the default for soil parameters. | D43: Rice-season soil values that duplicate a wheat-season parameter -> Notes only. | E43: Codes | F43: IN FORCE
A44: 36 | B44: Seasons, years & rows | C44: Rice-season fallback: a parameter reported ONLY for the rice season is entered with the WHOLE ROW in RED and 'RICE SEASON' at the start of 'Crop/season of sampling'. | D44: Filter on font colour or that column to include / exclude. | E44: Codes - RICE-SEASON FALLBACK | F44: IN FORCE
A45: 37 | B45: Seasons, years & rows | C45: Year-wise data always: every year a paper gives (table or figure) is a separate row; the multi-year mean goes to Notes. | D45: From study 101 onward. | E45: Author 2026-10-03 | F45: IN FORCE
A46: 38 | B46: Seasons, years & rows | C46: Soil sampled at several crop stages in one season -> one row per stage (stage in 'Crop/season of sampling'). | E46: Author 2026-10-03 | F46: IN FORCE - extended by rule 90 (all parameters, soil and plant)
A47: 39 | B47: Seasons, years & rows | C47: Box plots: not entered by default; box-plot means entered when the author asks or when they are the only data for a parameter (flagged). | D47: Studies 101, 388. | E47: Author 2026-10-03 | F47: IN FORCE
A48: SITE CLASSIFICATION
A49: 40 | B49: Site classification | C49: Climate: latitude > 30 deg -> TEMP; <= 30 deg -> ST. | D49: Pittelkow et al. 2015; Mondal et al. 2018. | E49: Codes | F49: IN FORCE
A50: 41 | B50: Site classification | C50: Texture: SCL, SiCL, CL, Si, SiL, L, SL -> LOAMY; LS, S -> SANDY; SC, SiC, C -> CLAYEY; class not stated -> USDA triangle from sand/silt/clay. | D50: Shirazi et al. 2001. | E50: Codes | F50: IN FORCE
A51: 42 | B51: Site classification | C51: Duration: 0-3 Y / 4-10 Y / >10 Y = years since the trial was established at sampling. | E51: Codes | F51: IN FORCE
A52: 43 | B52: Site classification | C52: Depth classes 0-15 / 15-30 / 30-45 / 45-60 / >60 CM by maximum overlap: 0-10 -> 0-15; 10-20 and 20-30 -> 15-30 (separate rows, D=2); 20-40 -> 30-45; 0-30 -> 0-15; 30-60 -> 30-45; 60-90 -> >60. | D52: Penetration resistance: 0-10 ... 50-60 CM classes. C stock / sequestration: cumulative 0-10, 0-20 ... 0-60 CM (0-15 -> 0-20, 0-45 -> 0-50). | E52: Codes; author 2026-10-03 | F52: IN FORCE
A53: STATISTICS (OBS, REP, SD)
A54: 44 | B54: Statistics (Obs, Rep, SD) | C54: Rep = 3 unless the paper states a different number of replications. | E54: Codes | F54: IN FORCE
A55: 45 | B55: Statistics (Obs, Rep, SD) | C55: Obs (new papers) = additive per row: Y (years in that row's mean) + T (paper treatments under one code) + D (depths inside the depth class); a factor equal to 1 adds nothing; minimum 1. | D55: 3 years -> 3; 2 treatments -> 2; 3 depths -> 3; all three -> 8. No-depth parameters (yield, WUE, uptake, GHG): D = 0. Row-b recoding adds T=2 to rows a and b. | E55: Author 2026-10-03 | F55: IN FORCE - restated by rule 101 (recomputed for all studies in updated 11)
A56: 46 | B56: Statistics (Obs, Rep, SD) | C56: SD = workbook formula SQRT(2*Obs/Rep) when the paper gives no SD/SE; a reported SD (or SE x SQRT(Rep)) replaces it. | D56: Paper-reported SD kept in Notes when the single SD column keeps the formula. | E56: Codes; author 2026-10-03 | F56: IN FORCE
A57: PARAMETER-SPECIFIC
A58: 47 | B58: Parameter-specific | C58: Carbon: oxidisable / labile organic C as most papers report it (SOC, Walkley-Black, OM/1.724) -> 'SOC (active C pool)' in g/kg; TOC = labile + non-labile or C by dry combustion. | D58: Every paper's SOC must appear on one concentration sheet (derive from content/stock with BD, flagged). | E58: Author 2026-10-03 | F58: IN FORCE
A59: 48 | B59: Parameter-specific | C59: SOC stock = SOC (g/kg) x BD x thickness (cm) x 0.1, cumulative from the surface, live cross-sheet formulas; sequestration rate = (treatment stock - initial stock) / years from the same initial SOC x initial BD. | D59: Only where SOC and treatment BD share a layer; do not duplicate printed stocks; skipped when the baseline is implausible. | E59: Author 2026-10-03 | F59: IN FORCE
A60: 49 | B60: Parameter-specific | C60: Soil water: GWC = gravimetric water content at any instant (v/v / BD); AWC (FC - PWP) on BOTH 'AWC (weight basis)' and 'AWC (volume basis)'; field capacity -> 'FC (weight basis)'; wilting point -> 'PWP (weight basis)'; WHC only for Keen-Raczkowski box; saturated WC -> 'SAT WC'; profile storage (mm) -> 'Moisture storage'. | D60: Each soil-water row carries a 'WATER-QUANTITY CHECK' note from the paper's Methods. BD for conversions: same study/depth/treatment from the BD sheet, else the paper's own layer BD, else 1.35 Mg/m3. Basis not stated -> GWC, flagged. | E60: Author 2026-10-04 / 2026-10-05 | F60: IN FORCE
A61: 50 | B61: Parameter-specific | C61: Infiltration: IR_ = steady-state (final / basic) rate, IIR_ = initial rate, both cm/hr on the IR sheet; cumulative infiltration in Notes. | E61: Author 2026-10-03 | F61: IN FORCE
A62: 51 | B62: Parameter-specific | C62: Roots as densities: RLD (cm/cm3), RVD (cm3/cm3), RMD (mg/cm3), RSD (cm2/cm3); ROOT DIA (mm); per-sample values converted with the sampled soil volume (live formula, assumption in Notes). | E62: Author 2026-10-03 | F62: IN FORCE
A63: 52 | B63: Parameter-specific | C63: Derived values (live formulas, flagged DERIVED): straw = biomass - grain; HI = grain / (grain + straw); GHGI = GWP / (grain t/ha x 1000); CL / LI / CPI / CMI with CT as reference; porosity = (1 - BD/PD) x 100 with PD 2.65 default. | D63: A printed value always wins over a derived one. Every derivation is documented on the FORMULAS sheet. | E63: Author 2026-10-04 | F63: IN FORCE
A64: 53 | B64: Parameter-specific | C64: %-variation tables: treatment value = reference x (1 + VR/100) as a live formula; ratio-only papers: concentration = ratio x SOC (flagged). | D64: Studies 64, 90, 102. | E64: Author default 2026-10-03 | F64: IN FORCE
A65: 54 | B65: Parameter-specific | C65: System values (system / rice-equivalent yield, system B:C, WP, GWP, uptake) go in the SYS columns; flagged if they include a third crop. | D65: The paper's own system value replaces a derived rice + wheat sum. | E65: Author 2026-10-03 | F65: IN FORCE
A66: 55 | B66: Parameter-specific | C66: Model / simulation output (APSIM, DSSAT) IS entered when available or asked for, every row flagged 'MODEL OUTPUT' in Notes and Data source. | D66: Studies 28 (DSSAT Table 6), 78 and 117 (companion) (APSIM). Input-based LCA GWP entered flagged. | E66: Author 2026-10-03 / 2026-10-05 | F66: IN FORCE
A67: 56 | B67: Parameter-specific | C67: Simulated output is not entered. | D67: Original Codes rule. | E67: Codes (old) | F67: SUPERSEDED (model output now entered)
A68: 57 | B68: Parameter-specific | C68: Economics: paper B:C defined as gross/cost is converted to net/cost (B:C - 1); NET RETURN sheet in the printed currency (gross margin and model rows flagged). | E68: Author 2026-10-03 / 2026-10-04 | F68: IN FORCE
A69: 58 | B69: Parameter-specific | C69: Unit conversions: GHG kg CH4 -> kg C (x 12/16), kg N2O -> kg N (x 28/44); P mg/kg x 2.25 -> kg/ha; available N/P/K and NO3 in mg/kg kept as printed when no layer BD; enzyme rates converted to the sheet unit (e.g. per day / 24). | D69: Penetration resistance in non-convertible units (N/cm) entered as printed, flagged. | E69: Workbook practice | F69: IN FORCE
A70: 59 | B70: Parameter-specific | C70: Kept in Notes only (no sheet): soil temperature, crop growth, energy, water footprint, relative water content (% of FC), site-level FC/PWP profiles. | E70: Author 2026-10-03 / 2026-10-05 | F70: IN FORCE
A71: FORMATTING & BUILD
A72: 60 | B72: Formatting & build | C72: Arial 10; Notes/Doubts fill FFF2CC; rice-season rows whole row red; the orange 'UNIT FOR THIS SHEET' note column is never restyled; formulas stay live and their values are cached after every save. | D72: fullCalcOnLoad is set so Excel recalculates on opening. | E72: Workbook convention | F72: IN FORCE
A73: 61 | B73: Formatting & build | C73: Every recoded or added row states what was done at the start of Notes ('RECODED <date> ...', 'ROW b (added <date>) ...', 'DUPLICATE RE-SUBMISSION ...', 'MODEL OUTPUT ...'). | D73: Lets any decision be filtered and reversed. | E73: Workbook convention | F73: IN FORCE
A74: 62 | B74: Cropping system & design | C74: A straw-return treatment whose mineral fertiliser was cut to offset straw nutrients is coded CTR (or MTR / CA by tillage) and FLAGGED. | D74: He et al. 2021 (145) OF+S: rice N 182 vs 225, wheat 189 vs 210 kg/ha. Drop the flagged rows for a fertiliser-matched sensitivity check. | E74: Author 2026-10-05 | F74: IN FORCE
A75: 63 | B75: Parameter-specific | C75: Plant height, glycine aminopeptidase, mycorrhizal spore counts, net GWP (NGWP) and net economic benefit get their own sheets; root length per plant is converted to root length density (assumptions in the formula, flagged). | D75: Sheets PLANT HEIGHT, GAP, MYCORRHIZAL SPORES, NGWP, NET ECONOMIC BENEFIT (first filled from ext\241-250). | E75: Author 2026-10-05 | F75: IN FORCE
A76: 64 | B76: Coding | C76: Permanent raised beds WITH residue retention = CA (flagged) in companion papers even when the main study coded the bed treatment ZT. | D76: 71 (companion), 71 (companion 2) | E76: Author 2026-10-05 | F76: IN FORCE
A77: 65 | B77: Pooled means | C77: Main effects pooled over a factor level that would itself be excluded (e.g. shallow wheat tillage after puddled rice) go to Notes only; enter only rotation-matched cells. | D77: 163 Sarkar & Kar 2011 | E77: Author 2026-10-05 | F77: IN FORCE
A78: 66 | B78: Parameter-specific | C78: Earthworm density and dissolved organic C get their own sheets (EARTHWORM, DOC); DOC printed per litre of extract is entered as printed and flagged. | D78: 156, 161 | E78: Author 2026-10-05 | F78: IN FORCE
A79: NEW WORKBOOK SERIES (2026-10-05)
A80: 67 | B80: Workflow & data management | C80: NEW workbook: built on the updated 53 structure with NO previous data carried over. Serial numbers CONTINUE from the old master: the first new study is 164 (old master ends at 163), so the two files can be merged. Each upload is saved as a new numbered version (META_ANALYSIS_NEW_updated_NN.xlsx). | D80: README, RULES, Codes and FORMULAS are kept as the rulebook; worked examples there cite the OLD master's serials (updated 53), not studies of this workbook. | E80: Author 2026-10-05 | F80: IN FORCE
A81: 68 | B81: Treatment codes | C81: PARTIAL CA CODES: pCA = puddled / conventional rice + ZT wheat WITH residue; pZT = puddled / conventional rice + ZT wheat, residue removed; pMT = puddled / conventional rice + MT wheat, no residue; pMTR = puddled / conventional rice + MT wheat WITH residue. | D81: Every parameter sheet carries <prefix>pCA, pZT, pMT, pMTR right after <prefix>DTR (olive-green headers). These treatments are NO LONGER excluded under the rotation-matching rule (rule 22) and are NOT entered in the CA / ZT / MT / MTR columns; they go to the p-columns. The reverse mismatch (ZT / no-till rice + conventional wheat, RNT-WCT) stays EXCLUDED (author re-confirmed). MT vs MTR for the wheat phase follows the rotary rule (rule 13). | E81: Author 2026-10-05 | F81: IN FORCE
A82: 69 | B82: Treatment codes | C82: Rotary rule restated: full-width rotary to >= 10 cm, or >= 2 full-width passes = CT / CTR whatever the paper calls it; rotary <= 8 cm, single-pass till-drill, Super / Roto Seeder, strip or zone rotary = MT / MTR. | D82: 8-10 cm or depth unstated -> ask the author. | E82: Author 2026-10-05 | F82: IN FORCE
A83: 70 | B83: Treatment codes | C83: Same treatment type in rice and wheat = include (e.g. puddled transplanted rice + CT wheat = CT). Rice tillage not stated -> classify on the wheat tillage alone. | D83: Rules 22-23 unchanged except for the partial-CA codes above. | E83: Author 2026-10-05 | F83: IN FORCE
A84: 71 | B84: Cropping system & design | C84: Green manuring / a third crop (mungbean, Sesbania, etc.) in a rice-wheat system: study included. Green manuring is a SUPPLEMENTARY condition for CA, NOT a necessary one: ZT + residue = CA with or without green manure. | D84: A green manure / third crop grown only in the CA treatment does not exclude that treatment and does not change its code; the crop is named in Notes and 'Fertilizer dose & other management' ('GREEN MANURE'). Green manure never turns a non-CA treatment into CA (e.g. ZT without residue + green manure stays ZT). | E84: Author 2026-10-05 | F84: IN FORCE
A85: 72 | B85: Cropping system & design | C85: Inclusion: any study with ANY TWO of CT, ZT, CA, DT, MT, MTR, CTR, DTR, pCA, pZT, pMT, pMTR is included. Not restricted to South Asia. | D85: Rule 21 extended to the partial-CA codes. | E85: Author 2026-10-05 | F85: IN FORCE
A86: 73 | B86: Parameter-specific | C86: Porosity (%) = (1 - BD / PD) x 100 from the TREATMENT BD (changed BD). PD = the treatment's PD if reported, else the paper's initial PD, else 2.65 Mg/m3 (flagged). | D86: Live formula linking the BD sheet (and PD sheet where used). A printed total porosity is entered as printed. | E86: Author 2026-10-05 | F86: IN FORCE
A87: 74 | B87: Parameter-specific | C87: WSA = sum of ALL water-stable aggregate fractions > 0.053 mm, in g/g of soil (0-1). A printed WSA in % is divided by 100; when the paper gives only the fractions, WSA is their sum (DERIVED, flagged). | D87: The silt + clay fraction (< 0.053 mm) is never included. The old master (updated 53) holds WSA in % - divide by 100 when merging. | E87: Author 2026-10-05 | F87: IN FORCE
A88: 75 | B88: Parameter-specific | C88: Penetration resistance: 10 cm classes 0-10, 10-20, 20-30, 30-40, 40-50, 50-60 CM (and >60 CM) - do NOT stop at 30 cm. C stock and sequestration: cumulative 0-10 ... 0-60 CM. | D88: Rule 43 restated. | E88: Author 2026-10-05 | F88: IN FORCE
A89: 76 | B89: Parameter-specific | C89: SOC (Walkley-Black / 'SOC' / OM/1.724) of every paper goes to SOC(active C pool); every other carbon pool reported (TOC, TC, POXC, PSOC, MOC, WSC, DOC, LFOC, HFOC, Chan fractions, macro/micro-aggregate C, stocks) goes to its own sheet. | D89: Rule 47 restated. | E89: Author 2026-10-05 | F89: IN FORCE
A90: 77 | B90: Parameter-specific | C90: Soil water: AWC (FC - PWP) on BOTH AWC sheets (converted with BD); water content at sampling -> GWC (weight basis; v/v / BD); FC (-33 kPa) -> FC (weight basis); PWP (-1500 kPa) -> PWP (weight basis); Keen box -> WHC; saturated WC -> SAT WC. | D90: Rule 49 restated. | E90: Author 2026-10-05 | F90: IN FORCE
A91: 78 | B91: Treatment codes | C91: INM papers with a crop-residue treatment: 100% NPK (CT) vs reduced NPK + straw substituting the cut N (CTR), FLAGGED under rule 62. | D91: Applied to Yadav 2000 (164: 100F vs 50F+CR, 50% NPK + wheat straw to rice only) and Das 2014 (166: T2 vs T8, 25% N via straw to both crops). FYM / press mud / green manure / unfertilised tiers excluded. | E91: Default 2026-10-05 | F91: IN FORCE (author confirmed 2026-10-05)
... A119: 106 | B119: Parameter-specific | C119: Crop-model papers: MEASURED values printed only as points of a measured-vs-simulated plot are entered as measured data (read from the measured axis and checked against the printed measured means); the paper's simulated long-term means are entered as separate MODEL OUTPUT rows (rule 55); simulation-only scenarios never tested in the field are not entered. | D119: 176 (companion) Devkota 2015 AFM: Figs 3A / 4 measured yields 2008-2009 (means reproduce Tables 4-5 within 3 kg/ha); Tables 6-7 DSSAT 1971-2010 yields, N uptake, N leached; scenarios 9-11 excluded. | E119: Default 2026-10-05 | F119: IN FORCE - awaiting author confirmation

Sheet Codes
A1: TREATMENT CODES
A2: Code | B2: Meaning | C2: Typical descriptions in papers
A3: CA | B3: Zero tillage + residue retention | C3: ZT+R, ZTW with residue, permanent beds with residue, NT + mulch, CA-based scenario
A4: CT | B4: Conventional tillage, NO residue | C4: CT, farmers practice, puddled transplanted rice - conventional till wheat, residue removed/burnt
A5: ZT | B5: Zero tillage only, no residue | C5: ZT, NT, direct drilled without residue
A6: DT | B6: Deep tillage only, no residue | C6: deep ploughing, sub-soiling, chiselling without residue
A7: MTR | B7: Minimum / reduced tillage WITH residue | C7: RT+R, reduced till (power tiller 2 passes, 0.08-0.10 m) + residue, rotary till drill + residue, reduced puddling + residue, unpuddled harrowing+rotavator + residue
A8: MT | B8: Minimum / reduced tillage only, no residue | C8: RT, reduced till, rotary till drill, reduced puddling, 2 passes power tiller, unpuddled rice without residue
A9: CTR | B9: Conventional tillage WITH residue | C9: CT+R, conventional till with residue incorporated
A10: DTR | B10: Deep tillage WITH residue | C10: deep tillage + residue incorporation
A11: pCA | B11: PARTIAL CA: puddled / conventional-till rice + ZERO-TILL wheat WITH residue retained | C11: PTR-ZTW+R, TPR fb ZTW (Happy Seeder / Turbo Happy Seeder into rice residue), puddled rice + ZT wheat with mulch
A12: pZT | B12: PARTIAL ZT: puddled / conventional-till rice + ZERO-TILL wheat, residue REMOVED / burnt | C12: PTR-ZTW, TPR fb ZTW (no residue), puddled rice + ZT drill wheat
A13: pMT | B13: PARTIAL MT: puddled / conventional-till rice + MINIMUM / REDUCED-till wheat, NO residue | C13: PTR + rotary till-drill / Super Seeder / strip-till wheat (rotary <= 8 cm or single pass), no residue
... A18: NOTE | B18: Unclear treatments | C18: Left out of the data sheets and raised with you.
A20: RECLASSIFICATION
A21: Climate | B21: latitude > 30 deg -> TEMP (temperate) | C21: Pittelkow et al. 2015; Mondal et al. 2018
A22: Climate | B22: latitude <= 30 deg -> ST (sub-tropical)
A23: Texture | B23: Sandy clay loam, silty clay loam, clay loam, silt, silt loam, loam, sandy loam -> LOAMY | C23: Shirazi et al. 2001
A24: Texture | B24: Loamy sand, sand -> SANDY
A25: Texture | B25: Sandy clay, silty clay, clay -> CLAYEY
A26: Texture | B26: Class not stated -> derive from sand/silt/clay using the USDA texture triangle, then reclassify
A27: Duration | B27: 0-3 Y / 4-10 Y / >10 Y | C27: Years since the trial was established at the time of sampling
A28: Depth (general) | B28: 0-15, 15-30, 30-45, 45-60, >60 CM | C28: Reported depth reassigned by MAXIMUM OVERLAP, applied SEQUENTIALLY so consecutive reported layers fall in consecutive classes. Worked rules agreed with author: (a) paper reports 0-20 / 20-40 cm -> 0-20 = 0-15 CM, 20-40 = 15-30 CM. (b) paper reports 0-10 / 10-20 / 20-40 cm -> 0-10 = 0-15 CM, 10-20 = 15-30 CM, 20-40 = 30-45 CM. Original depth always kept in 'DEPTH (as reported in paper)'. If a paper genuinely reports >1 layer inside one class, all are entered and Obs increases.
A29: Depth (PR) | B29: 0-10, 10-20, 20-30, 30-40, 40-50, 50-60 CM | C29: Penetration resistance only
A30: Depth (C stock / sequestration) | B30: 0-10, 0-20, 0-30, 0-40, 0-50, 0-60 CM | C30: Cumulative depths
A32: DATA SOURCE TAGS | B32: Text / Table n / Figure n (digitised) / Supplementary / Calculated / Author-reported
A34: DECISIONS (author-confirmed)
A35: EXCLUDED | B35: No-till rice + conventional-till wheat (RNT-WCT, AT1 type) | C35: Excluded from the meta-analysis entirely. Log in Treatment_Mapping with ASSIGNED CODE = EXCLUDED, Status = EXCLUDED.
A36: SD | B36: SD = SQRT(2*Obs/Rep) | C36: Formula carried over from the original workbook; replaced by the real SD when a paper reports SD or SE (SD = SE*SQRT(Rep)).
A37: Rep | B37: Always 3 | C37: Unless the paper explicitly states a different number of replications.
A38: Season | B38: Wheat season only | C38: Soil parameters measured in the rice season are not entered.
A40: ROTATION-MATCHING RULE
A41: Rule | B41: Within a SINGLE treatment, the rice phase and the wheat phase must be the SAME type of tillage. If one phase is conventional and the other is conservation (or vice versa), that treatment is EXCLUDED. | C41: INCLUDE: puddled transplanted rice + conventional tillage wheat = CT. ZT/unpuddled/DSR rice + ZT wheat, residue in both = CA. ZT rice + ZT wheat, no residue = ZT. EXCLUDE: no-till rice + conventional-till wheat (RNT-WCT). EXCLUDE: conventionally puddled transplanted rice + zero-till wheat. EXCLUDE: conventional-till DSR + reduced-till wheat (CTDSR-RTW).
A42: Consequence | B42: Any treatment with contrasting tillage between the two phases is dropped, in either direction. | C42: Log it in Treatment_Mapping with ASSIGNED CODE = EXCLUDED. If this leaves a study with no CA-vs-CT (or other-vs-CT) pair, the whole study contributes nothing and its rows are moved to EXCLUDED_rows.
A43: Factorial / split-plot papers | B43: Use the INTERACTION (cell) means so the rice and wheat phase are matched, not the marginal means of one factor. | C43: A marginal mean for a wheat treatment is averaged across every rice treatment, so its rice phase is a mixture. If the paper reports only marginal means and no cell means, note it in Notes/Doubts and flag the row.
A45: RULE AMENDMENT - WITHDRAWN
A46: WITHDRAWN | B46: A short-lived amendment exempted wheat-phase-only experiments from the rotation-matching rule. It has been WITHDRAWN at the author's instruction. | C46: The rule applies in full again: the previous crop's tillage counts, and only treatments with the SAME type of treatment in the rice and the wheat phase are included (e.g. puddled transplanted rice + conventional tillage wheat = CT). Reversed for Singh & Singh 2021 (ZT removed again) and Kumar et al. 2012 (all rows moved to EXCLUDED_rows).
A47: IN FORCE | B47: Any treatment whose rice and wheat phases differ in tillage type is excluded, whether or not the contrast was part of the experimental design. | C47: Excludes: no-till rice + conventional-till wheat (RNT-WCT); conventionally puddled rice + zero-till or bed-planted wheat; conventional-till DSR + reduced-till wheat.
A48: CONSISTENT | B48: Sharma et al. 2022 (study 1) stays excluded - its ZTWR0 and ZTWR100 follow a conventionally puddled rice phase. | C48: Its 22 rows remain in EXCLUDED_rows. Consistent with Singh & Singh 2021 ZT, Kumar et al. 2012, Bachchan et al. 2018 and Paliwal et al. TPR-ZTW-ZTS.
A50: RULE REFINEMENT (author instruction)
A51: When the rice phase is NOT described | B51: Classify on the WHEAT-phase tillage alone. Do not assume the preceding rice was conventionally puddled. | C51: Applied to Balwinder-Singh et al. 2011 (study 12): mulch -> CA, non-mulch -> ZT. The rule in full still applies wherever the paper DOES state the rice establishment.
A52: Still excluded | B52: Papers that state a conventional/puddled rice phase alongside conservation wheat. | C52: Sharma et al. 2022 (PTR stated); Paliwal et al. TPR-ZTW-ZTS (transplanted rice stated); Choudhury & Singh 2013 (TPR stated).
A53: OPEN - needs your decision | B53: Two studies already excluded also do NOT describe the rice phase. | C53: Singh & Singh 2021 (study 9) ZT - would return as CA; Kumar et al. 2012 (study 11) ZT and CT - would return the whole study with BD, porosity, Ksat, infiltration, PAWC and penetration resistance. Say the word and I will restore them from EXCLUDED_rows.
A55: STANDING RULE (current)
A56: 1. Rice tillage IS stated | B56: The rice and wheat phases must be the SAME type of tillage within a treatment. | C56: e.g. puddled transplanted rice + conventional tillage wheat = CT. Puddled rice + zero-till wheat = EXCLUDED.
A57: 2. Rice tillage NOT stated | B57: Classify on the WHEAT-phase tillage alone; do not assume a conventional rice phase. | C57: Applied to Balwinder-Singh et al. 2011 (study 12), Singh & Singh 2021 ZT -> CA (study 9) and Kumar et al. 2012 (study 11), all restored.
A58: 3. Still excluded | B58: Studies that explicitly state a conventional/puddled rice phase alongside conservation wheat. | C58: Sharma et al. 2022 (study 1, PTR stated); Paliwal et al. TPR-ZTW-ZTS (study 7); Choudhury & Singh 2013 bed/ZT variants (study 6); Gathala et al. T2 (study 15); Aryal et al. 2015 (study 17).
A60: INCLUSION THRESHOLD (author instruction)
A61: Any TWO codes is enough | B61: A study is included if it yields ANY TWO of CT, ZT, CA, DT, MT, MTR, DTR (and CTR). A conventional-tillage reference is NOT required. | C61: e.g. CA vs ZT (Balwinder-Singh et al. 2011, study 12); CT vs CTR (Bandyopadhyay et al. 2011, study 3; Akwakwa & Wang 2023, study 18); ZT vs CT (Aryal et al. 2015, study 17, brought back in on this rule).
A62: Still excluded on one code | B62: A study left with only ONE usable code after the rotation rule contributes no contrast. | C62: Sharma et al. 2022 (study 1): CTWR0 is rotation-matched CT, but ZTWR0 and ZTWR100 follow an explicitly puddled rice phase and are excluded, leaving one code.
A63: Still excluded for no data | B63: Treatment codes are irrelevant if the paper publishes no values. | C63: Nandipamu et al. 2025 (study 13, energy indices only, though CT/CTR/CA are all matched); Biswas et al. 2024 (study 14, raw values not released); Bachchan et al. 2018 (study 10, data duplicate Kumar et al. 2012); Lou et al. 2024 (study 16, no tillage treatment).
A65: SAME-EXPERIMENT RULE
A66: Two papers, one experiment -> ONE serial | B66: When two papers report the SAME trial, they share a serial number so the experiment is counted once and no pseudo-replication is introduced. Parameters are split between them, never duplicated. | C66: Applied to: Jat H.S. et al. 2022 (Front. Microbiol.) + Jat H.S. et al. 2021 (Eur. J. Soil Biol.) = study 23, CSSRI Karnal scenarios; Choudhury & Singh 2013 + Choudhury, Bouman & Singh 2007 = study 6, IARI New Delhi.
A67: Same site, different experiment -> SEPARATE serials | B67: Trials at the same location and start year but with different designs are separate studies. | C67: Author-confirmed for study 19 (Choudhary K.M. et al. 2018, 8 treatments) and study 24 (Choudhary M. et al. 2018, 14 treatments), both at Taraori, Karnal, both established 2012.
A69: THIRD CROP IN THE ROTATION
A70: Common to every treatment -> IN | B70: A rice-wheat system carrying a third crop is included when that crop is grown in EVERY treatment, because it then does not confound the tillage contrast. The study is flagged in Study_Info and in every row's Notes, and only the rice and wheat figures are entered - system-level figures that bundle the third crop are left out. | C70: Mishra et al. 2021 (study 29): rice-wheat-greengram, zero-till greengram in all seven treatments. Rice and wheat yields, water productivity, BCR and GWP entered; rice-equivalent system yield, system water productivity, system BCR and system GWP left out.
A71: Varies between treatments -> OUT | B71: When the third crop is added to some treatments and not others, rotation is confounded with tillage and those treatments are excluded. | C71: Raj et al. 2023 (study 22): CA4 and CA5 insert zero-till mungbean while CA1-CA3 and CT do not, so both are excluded while the rest of the study is kept.
A73: MODELLED AND LCA-ESTIMATED VALUES
A74: Simulated output -> not entered | B74: Crop-model output is not a measurement and does not go on the data sheets. | C74: Vashisht et al. 2025 (study 28) Table 6: DSSAT CERES-rice and CERES-wheat yields, water balance and water productivity - left out, recorded in the BC ratio notes.
A75: Input-based LCA -> entered, flagged | B75: GWP built from activity data and emission factors includes embedded upstream emissions (fertiliser manufacture, diesel, electricity) that a chamber measurement does not. Entered, but flagged on the row so it is not pooled blind with measured flux. | C75: Mishra et al. 2021 (study 29) Table 8 - fertiliser manufacture alone is 670 of its ~900 kg CO2-eq/ha, against chamber-measured GWP in Hu et al. 2016 (study 26).
A77: RICE-SEASON FALLBACK (author instruction)
A78: Rule | B78: Wheat season stays the default. If a study reports a parameter ONLY for the preceding rice season (no wheat-season value of that parameter in that study), the rice-season value is entered. | C78: Applied only where the wheat-season value is absent - rice-season duplicates of parameters that already have a wheat-season value are still left out.
A79: Formatting | B79: The WHOLE ROW is written in RED text, and Crop/season of sampling starts with "RICE SEASON". | C79: Filter on font colour or on that column to include/exclude these rows in the analysis.
A80: Applied to | B80: Choudhury & Singh 2013 (study 6): rice root weight density at flowering, Fig. 3 -> RMD(mg-cm3), rice columns, 6 rows. | C80: Checked and NOT needed: Suryawanshi 2018 (study 2, kharif BD/N/total N - rabi values present); Choudhury & Singh 2013 BD and Ks (wheat values present); Paliwal 2017 (study 7, after-rice BD and moisture - after-wheat values present); Sanketh 2026 (study 38, rice MBC/FDA - wheat values present).
A82: AUTHOR EXCEPTIONS (updated 8, 2026-10-03)
A83: Kahlon 2014 (study 74) | B83: INCLUDED although rice is puddled transplanted in every treatment (NT -> ZT, RT -> MTR, HS -> CA). | C83: Author instruction 2026-10-03; every row flagged 'FLAG - PUDDLED RICE PHASE' in Notes - filter SERIAL NO 74 for sensitivity analysis.
A84: Unpuddled transplanted rice + ZT wheat | B84: Coded ZT (Jat et al. 2011, study 71, UPTR-ZTW). | C84: Dry tillage without puddling treated as compatible with ZT wheat (author approved).
A85: Marginal means | B85: Tripathi et al. 2007 (study 72) has only marginal / mixed-rotation means -> EXCLUDED, values kept in notes. | C85: Codes rule 'Factorial / split-plot papers'.
A86: Model output exception (2026-10-03) | B86: Bana et al. 2023 (study 78) APSIM simulated values ENTERED on author instruction. | C86: Every row starts 'MODEL OUTPUT (APSIM)' in Notes and Data source; filter on it for sensitivity analysis.
A87: New sheets (updated 10) | B87: SYS STRAW, C input, C output, CSI, CER, GHG intensity | C87: Added for Chaudhary et al. 2025 (study 76) on author instruction; system-level values, same column layout as the uptake sheets.
A88: Multi-experiment papers (2026-10-03) | B88: Tomar 2008 lecture split into serials 80-84, one per experiment; serial 84 is secondary data (Aslam et al. 1993). | C88: Included in full on author instruction ('involve all'); flags in Notes.
A89: Zero-till rice + reduced-till wheat | B89: Applied to study 79 (P1T1 rotavator, P1T3 strip till) as MT, following the author decision for study 76 ZTDSR-RTW.
A90: Dry-tilled non-puddled rice + ZT wheat (2026-10-03) | B90: Coded ZT (studies 86 MTR/DSR-ZTW, 87 CT-DDSR fb ZT), consistent with study 71 UPTR-ZTW; flagged because the rice phase is tilled, not zero-till. | C90: Author decision; supersedes the older 'conventional-till DSR + reduced-till wheat -> exclude' note for ZT wheat. SRI fb SWI -> CT.
A91: Depth class of a 20-30 cm layer (2026-10-03) | B91: A reported 20-30 cm layer -> 15-30 CM (NOT 30-45 CM). With 10-20 cm also in 15-30 CM, the two layers are separate rows and D=2 is added to Obs. | C91: Author correction; applied to studies 80, 91, 92 in updated 15.
A92: Infiltration (IR sheet, 2026-10-03) | B92: IR_ = steady-state infiltration rate (final, basic or quasi-steady rate); IIR_ = initial infiltration rate (first reading). Both in cm/hr on the IR sheet. | C92: Author definition. Steady-state and initial rates stay as two column groups on the one IR sheet; cumulative infiltration is kept in Notes.
A93: Depth class of a 20-40 cm layer (2026-10-03) | B93: A reported 20-40 cm layer -> 30-45 CM (author decision, study 97). | C93: Contrast: a 20-30 cm layer -> 15-30 CM.
A94: Puddled rice + ZT Happy-Seeder wheat - 34 (companion) (2026-10-03) | B94: Included flagged on author instruction (Kahlon-type exception): M1-M3 -> CA, M4 -> CTR. | C94: Study 34 itself stays excluded.
A95: Depth classes 0-30 / 30-60 / 60-90 cm (2026-10-03) | B95: 0-30 -> 0-15 CM, 30-60 -> 30-45 CM, 60-90 -> >60 CM (existing precedent applied to study 101).
A96: New K-pool sheets (updated 21) | B96: WS-K (water-soluble K), EX-K (exchangeable K), NEX-K (non-exchangeable K) - added for Rattan et al. 2025 (study 101). | C96: Lean-to-sheet rule.
A97: Year-wise data (author instruction 2026-10-03) | B97: When a paper gives year-wise values (tables or figures), enter every year as a separate row - not only the multi-year mean. | C97: Applies from study 101 onward; means then go in notes to avoid double counting.
A98: Box plots on request | B98: Box-plot mean markers entered for study 101 on author request (pooled over N); default remains: box plots not entered unless the author asks.
A99: Several sampling stages in one season (author 2026-10-03) | B99: When a paper samples soil at several crop stages (e.g. heading, grain filling, maturity), each stage is entered as its own row with the stage named in 'Crop/season of sampling'. | C99: Applied to 102 (companion) = Chen et al. 2022.
A100: Parameters without a sheet (author 2026-10-03) | B100: Extract only parameters that already have a sheet unless the author asks for a new one (PLFA of study 105 not entered).
A101: Deep burying of straw to 30 cm (author 2026-10-03) | B101: Plough + rake burying straw to 30 cm counts as deep tillage: no-straw control -> DT, straw treatments -> DTR (study 108). | C101: Consistent with the >= 25 cm deep-tillage threshold (study 9).
A102: Duplicate files within one batch (author 2026-10-03) | B102: When two files in the same batch are the same paper, enter it once and record the duplicate in EXCLUDED_rows (390 = 388).
A103: System values in SYS columns (author 2026-10-03) | B103: Paper-reported SYSTEM values (rice-equivalent / system yield, system B:C, system WP, system GWP, system nutrient uptake) are entered in the SYS columns, flagged when they include a third crop. Supersedes the study-29 rule that kept them in the notes. | C103: Applied retroactively to studies 29, 29 (companion 2), 45, 48, 56 (uptake sheets got new SYS columns). Studies 22 (CA4/CA5) and 50 have system values that are not recorded in the notes - need the papers.
A104: Tilled unpuddled rice + ZT wheat, by residue (author 2026-10-04) | B104: Dry-tilled (cultivator / harrow / rotavator) UNPUDDLED rice - transplanted or direct-seeded - followed by zero-till wheat: WITHOUT residue -> ZT (flagged); WITH residue retained -> CA (flagged, tilled rice phase). If the rice is wet-tilled/puddled it remains a rotation mismatch (excluded). Where two papers of one trial disagree on puddling, follow the main paper. | C104: Applied to study 29 family (T6 CTDSR-ZTW added as CA row b in 29, 29 (companion 2), Kumar 2024 rows, 29 (companion 3)); T3 CTMTR-ZTW excluded (puddled per Mishra 2021 Table 1). Consistent with 72 (companion) DSWP-RI-ZTW = CA, DSWP-RR-ZTW = ZT.
A105: Yield components & phenology sheets (author 2026-10-04) | B105: New sheets PANICLE-SPIKE DENSITY, GRAINS PER PANICLE, 1000-GRAIN WEIGHT, HARVEST INDEX, DAYS TO FLOWERING, DAYS TO MATURITY, GRAIN FILLING DAYS (W = wheat, R = rice columns, as the root sheets). Straw yield = biomass - grain when only biomass is printed. Uptake at anthesis and post-anthesis accumulation go on the uptake sheets as SEPARATE rows (stage in 'Crop/season of sampling'). | C105: First used for studies 120 (rice) and 121 (wheat).
A106: Derived yield / economic / carbon parameters (author 2026-10-04) | B106: Straw yield = biomass - grain (live formula) when only biomass is printed; HI = grain / (grain + straw) DERIVED for every YIELD row with both and no printed HI; NET RETURN sheet (printed currency, gross-margin and model rows flagged); CL/LI/CPI/CMI with CT as reference wherever POXC and SOC share a depth; GHGI = GWP / grain yield wherever both exist. All formulas on the FORMULAS sheet. | C106: Printed values always take precedence over derived ones (no derived row where the paper prints the parameter).
A107: New sheet 15N RESIDUAL (author 2026-10-04) | B107: Residual 15N-labelled fertiliser or straw N (kg N/ha) per soil layer after each harvest; source and season in 'Crop/season of sampling'. First used for study 132. | C107: Rice-season samplings in red.
A108: Soil-water sheets restructured (author 2026-10-04) | B108: GWC = gravimetric water content at any instant (former VWC sheet, v/v values divided by BD); AWC (weight basis) and AWC (volume basis) hold every AWC row in both bases; WHC = Keen-Raczkowski box only; FC (weight basis) and PWP (weight basis) new. Conversions use the BD of the same study / depth / treatment (live link to the BD sheet) or the default BD 1.35 Mg/m3 where none is reported. | C108: Weight basis = volume basis / BD; volume basis = weight basis x BD.
A109: Soil-water classification check (author 2026-10-05) | B109: Every soil-water row carries a 'WATER-QUANTITY CHECK' note stating, from the paper's Methods, whether the number is available water (FC - PWP) -> both AWC sheets, water content at the time of sampling -> GWC (weight basis), field capacity -> FC, wilting point -> PWP, Keen-box maximum WHC -> WHC, or saturated water content -> SAT WC. Rice-season duplicates of studies with wheat-season rows stay in notes. | C109: GWC = VWC / BD (BD sheet, else the paper's own layer BD, else 1.35); AWC = FC - PWP.
A110: Author decisions 2026-10-05 (ext\221-225) | B110: Rice-season-only paper from a genuine rice-wheat CA trial -> red rice rows (Rana 2023); shallow 3-5 cm rotary stubble-breaking + surface straw -> MTR; artificial night warming -> ambient rows only; re-submitted included paper -> companion re-entry; device soil with simulated tillage stays out. | C110: Serials 133-136 (133, 135 excluded); 102 (companion 3); 129 (companion); 28 (companion).
A111: Author decisions 2026-10-05 (ext\226-230) | B111: MODEL OUTPUT entered on request (study 28 DSSAT Table 6; 117 (companion) APSIM pooled yields, in SYS columns because not crop-specific). Rice-only DSR trial Bazaya 2009 included as red rows (ZT into standing wheat stubble -> CA; stubble incorporated -> CTR). | C111: Serials 137-141 (137, 138, 141 excluded); 117 (companion); 105 (companion 2); 31 (companion) excluded.
A112: Author decisions 2026-10-05 (ext\231-235) | B112: Kahlon & Dhingra 2019 full mapping: per rice method x deep variant, CT = CTRW-CT, CA = CTRW-NTR, DT = deep-CT, DTR = deep-NTR (CT/CA repeated). Re-submissions 232 / 233 / 235 = studies 121 / 64 / 111 -> companion clones. | C112: Serials 142 (Kahlon & Dhingra), 143 (Cheng, excluded); 121 (companion), 121 (companion 2), 64 (companion), 111 (companion).
A113: ROTARY / ROTAVATOR TILLAGE RULE (author 2026-10-05) | B113: Applies equally to ROTAVATOR and rotary-tiller operations (rotavator = rotary tillage). Full-width rotary / rotavator tillage to >=10 cm depth, or >=2 full-width passes = CT (CTR with residue), whatever the paper calls it. Rotary <=8 cm, a single-pass rotary till-drill, Super Seeder / Roto Seeder, or strip / zone rotary (only the seed rows tilled) = MT (MTR with residue). | C113: Conflicting older rows were RECODED in updated 47 (2026-10-05) on author instruction: 25 T6/T7 -> CT/CTR (row b); 41 Rot+R100 (Roto Seeder) -> MTR (row b); 64 and 64 (companion) RT -> CTR (row b); 69 AR -> CT, study EXCLUDED (no contrast); 74 RT -> CTR; 82 rotavator -> CT/CTR (row a, depth not stated - FLAG). Every recoded row starts 'RECODED 2026-10-05' in Notes. Grey zone (8-10 cm, or depth unstated and not clearly full-width primary tillage) -> ask the author.
A114: New columns on every data sheet (2026-10-05) | B114: 'Treatment details (from paper)' = Study_Info 'Treatments in paper' + every Treatment_Mapping line of the study (label -> code, full description, rice / wheat tillage, residue, rate) so treatments can be re-classified. 'Method used (from paper)' = analytical / measurement method AUTO-DETECTED from the paper's methods section with a quoted context (verify). | C114: Crop sheets: grain moisture basis and harvest area; calculated sheets (WUE, NUE, BC ratio, NET RETURN, C input/output, CSI, CER): see UNIT / FORMULAS.
... A119: Author decisions 2026-10-05 (ext\100-110 batch) | B119: Permanent beds + residue in the BISA Pusa trial companions -> CA (flagged) although study 71 coded PBDSR-PBDDW as ZT; main effects pooled over a mismatched factor level (Sarkar & Kar 2011) -> notes only; new sheets EARTHWORM (EW_) and DOC (DOC_); Gora 2024 supplement downloaded. Defaults: tilled unpuddled rice + ZT wheat (+ residue) -> ZT (CA) flagged (rule 24) incl. Gora Sc2; extra CT controls (rotary x2, farmers' practice) as CT rows b/c. | C119: Serials 156-163; companions 15 (companion), 59 (companion 2), 71 (companion), 71 (companion 2), 23 (companion 2), 24 (companion); 5 papers excluded (EXCLUDED_rows).

Sheet FORMULAS
A1: Parameter | B1: Formula (definition) | C1: Excel implementation in this workbook | D1: Unit | E1: Where applied | F1: Reference / note
A2: SD | B2: SD = SQRT(2 x Obs / Rep) | C2: Excel: =IF(AND(N(Obs)>0,N(Rep)>0),SQRT(2*Obs/Rep),"") | D2: - | E2: every data sheet (SD column) | F2: Original workbook rule; replaced by real SD only when a paper prints SD/SE
A3: Obs | B3: Obs = Y + T + D (years + paper treatments under one code + original depths collapsed into the row) | C3: entered value | D3: count | E3: every data sheet | F3: Codes / README rule
A4: STRAW YIELD | B4: Straw yield = biological (above-ground) yield - grain yield | C4: Excel: =ROUND(biomass - grain_cell, 2) in W STRAW_ / RSTRAW_ columns | D4: t/ha | E4: YIELD: studies 47 (row 50), 53 (row 62), 104, 106, 120 (all rows where only biomass is printed) | F4: Author instruction 2026-10-04
A5: HARVEST INDEX | B5: HI = grain / biological yield = grain / (grain + straw) | C5: Excel: =ROUND('YIELD'!grain/('YIELD'!grain+'YIELD'!straw),3) or =ROUND(grain/biomass,3); printed % -> /100 | D5: ratio 0-1 | E5: HARVEST INDEX sheet (printed values where the paper gives HI; DERIVED rows reference the YIELD cells) | F5: Added 2026-10-04
A6: BIOLOGICAL YIELD | B6: Biological yield = grain + straw | C6: (inverse of the straw rule; used only in notes) | D6: t/ha | E6: notes
A7: UNIT CONVERSIONS | B7: kg/ha / 1000 = t/ha; q/ha / 10 = t/ha; 10^4 spikes/ha = spikes/m2; grains per 5 spikes / 5 = grains per spike; printed x1000 Rs -> x 1000 | C7: Excel: =value/1000 , =value/10 , =ROUND(x/5,2) , =ROUND(x*1000,0) | D7: - | E7: YIELD, GRAINS PER PANICLE, NET RETURN
A8: TOTAL POROSITY | B8: Porosity (%) = (1 - BD / PD) x 100; PD = treatment PD, else initial PD of the paper, else 2.65 Mg/m3 | C8: Excel: =ROUND((1-BD!cell/PD)*100,2) (live link to the BD sheet; PD cell or value named in Notes) | D8: % | E8: POROSITY sheet (all treatment columns incl. pCA / pZT / pMT / pMTR) | F8: Author rule 2026-10-05
A9: SOC FROM SOM / OM | B9: SOC = SOM (or OM) / 1.724 | C9: Excel: =ROUND(SOM/1.724,3) | D9: g/kg | E9: SOC, soc (initial) where only OM is printed | F9: Van Bemmelen factor
A10: SOC STOCK | B10: SOC stock (Mg/ha) = SOC (g/kg) x BD (Mg/m3) x depth (cm) x 0.1 | C10: live formula from SOC and BD cells | D10: Mg C/ha | E10: stock-SOC
A11: C LIABILITY (CL) | B11: CL = labile C / non-labile C = POXC / (SOC x 1000 - POXC) | C11: Excel: =ROUND(POXC/(SOC*1000-POXC),3) | D11: ratio | E11: C liability (75 companion, 92, 102) | F11: Blair et al. 1995
A12: LABILITY INDEX (LI) | B12: LI = CL_treatment / CL_reference (reference = CT) | C12: LI_CT = 1; LI_x = CL_x / CL_CT | D12: - | E12: LI sheet | F12: Blair et al. 1995
A13: C POOL INDEX (CPI) | B13: CPI = SOC_treatment / SOC_reference (reference = CT) | C13: CPI_CT = 1; CPI_x = SOC_x / SOC_CT | D13: - | E13: CPI sheet | F13: Blair et al. 1995
A14: C MANAGEMENT INDEX (CMI) | B14: CMI = CPI x LI x 100 | C14: CMI_CT = 100; =ROUND(CPI*LI*100,2) | D14: - | E14: CMI sheet | F14: Blair et al. 1995
A15: GWP | B15: GWP = CH4 x 28 + N2O x 265 (kg CO2-eq/ha); CH4 = CH4-C x 16/12; N2O = N2O-N x 44/28 | C15: Excel: =ROUND(CH4*28+N2O*265,0) | D15: kg CO2-eq/ha | E15: GWP sheet | F15: IPCC AR5 100-yr factors
A16: GHG INTENSITY (GHGI) | B16: GHGI = GWP / grain yield | C16: Excel: =ROUND('GWP'!x/('YIELD'!y*1000),3) | D16: kg CO2-eq/kg grain | E16: GHG intensity (printed rows 76, 103; DERIVED rows 17, 26, 29, 45, 46, 89, 90c) | F16: Added 2026-10-04
A17: NET RETURN | B17: Net return = gross return - total cost of cultivation | C17: entered as printed (or =x*1000 / =rice+wheat sums) | D17: currency/ha as printed | E17: NET RETURN sheet | F17: Sheet added 2026-10-04; gross-margin rows flagged
A18: B:C RATIO | B18: B:C (sheet definition) = net return / cost; when a paper prints gross/cost: B:C - 1 | C18: Excel: =ROUND(net/cost,3) or =ROUND(printed-1,2) | D18: ratio | E18: BC ratio sheet | F18: Workbook definition
A19: SYSTEM YIELD / REY | B19: System yield = rice + wheat grain; REY = sum(yield_i x price_i / price_rice) | C19: Excel: =rice+wheat | D19: t/ha | E19: YIELD SYS columns, SYS STRAW
A20: POXC DERIVATIONS | B20: POXC (mg/kg) = ASOM / 1.724 x 1000 (study 92); = LOC/SOC ratio x SOC x 1000 (study 102) | C20: Excel: =ROUND(x/1.724*1000,1) ; =ROUND(ratio*SOC*1000,0) | D20: mg/kg | E20: POXC(KMnO4-C)
A21: WATER CONTENT BASIS | B21: theta_w (% w/w) = theta_v (% v/v) / BD; theta_v = theta_w x BD | C21: Excel: =ROUND(value/BD!cell,2) or =ROUND(value/1.35,2) (default BD) | D21: % w/w / % v/v | E21: GWC, AWC (weight / volume basis), FC, PWP | F21: Author rule 2026-10-04: default BD 1.35 Mg/m3
A22: AWC FROM FC AND PWP | B22: AWC = FC - PWP (same basis) | C22: derived in notes / rows | D22: % | E22: AWC sheets (study 28)
A23: AWC AS WATER DEPTH | B23: AWC (% v/v) = water depth (cm) / layer thickness (cm) x 100 | C23: Excel: =ROUND(cm/15*100,2) | D23: % v/v | E23: AWC (study 3)
A24: AWC FROM FC AND PWP (live) | B24: AWC (w/w) = FC (w/w) - PWP (w/w); AWC (v/v) = AWC (w/w) x BD | C24: Excel: =ROUND('FC (weight basis)'!cell-'PWP (weight basis)'!cell,2) ; =ROUND('AWC (weight basis)'!cell*BD!cell,2) | D24: % w/w / % v/v | E24: AWC sheets (study 9) | F24: Added 2026-10-05
A25: GWC FROM PLOTTED VWC | B25: GWC (% w/w) = VWC (m3/m3) x 100 / BD of the same layer (paper's own BD when the study has no BD-sheet rows) | C25: Excel: =ROUND(vwc*100/bd,2) | D25: % w/w | E25: GWC (study 12) | F25: Added 2026-10-05
A26: PMN FROM NET N MINERALISATION RATE | B26: PMN (mg/kg) = net N mineralisation rate (mg/kg/d) x incubation days (14) | C26: Excel: =ROUND(rate*14,2) | D26: mg/kg | E26: no3,nh4,PMN (study 136) | F26: Added 2026-10-05
A27: ENZYME UNIT umol/g/d -> nmol/h/g | B27: nmol/h/g = umol/g/d x 1000 / 24 | C27: Excel: =ROUND(x*1000/24,1) | D27: nmol/h/g | E27: NAG, LAP (study 136) | F27: Added 2026-10-05

Sheet Study_Info
A1: No. | B1: SERIAL NO | C1: Authors | D1: Year | E1: Journal | F1: Full reference | G1: DOI / link | H1: Country | I1: Site/Location | J1: latitude | K1: longitude | L1: latitude (as reported) | M1: longitude (as reported) | N1: Coordinates source | O1: CLIMATE | P1: Experiment established (year) | Q1: year of data collection/experiment | R1: Years of data reported | S1: DURATION | T1: SOIL | U1: Texture as reported | V1: sand | W1: silt | X1: CLAY | Y1: ph (initial) | Z1: soc (initial) | AA1: Bdi | AB1: MIN TEMP | AC1: MAX TEMP | AD1: AVG T | AE1: April max temp | AF1: RAIN FALL | AG1: Crop rotation | AH1: Wheat variety | AI1: Rice variety | AJ1: N dose (kg/ha) | AK1: P dose (kg/ha) | AL1: K dose (kg/ha) | AM1: Residue type & rate (t/ha) | AN1: Irrigation / water management | AO1: Treatments in paper | AP1: Parameters extracted | AQ1: Supplementary data? | AR1: Notes/Doubts
A2: 164 | B2: 164 | C2: Yadav R.L., Dwivedi B.S., Prasad K., Tomar O.K., Shurpali N.J. & Pandey P.S. | D2: 2000 | E2: Field Crops Research | F2: Yadav RL et al. (2000) Yield trends, and changes in soil organic-C and available NPK in a long-term rice-wheat system under integrated use of manures and fertilisers. Field Crops Res 68:219-246 | G2: https://doi.org/10.1016/S0378-4290(00)00126-X | H2: India (7 sites) | I2: Ludhiana, Pantnagar, Kanpur, Faizabad, Sabour, Kalyani, Jabalpur (one row per site in data sheets) | N2: Paper (each site); see LAT_LONG | O2: ST (Ludhiana TEMP) | P2: 1983-1986 (by site) | Q2: 1983-84 to 1998-99 | R2: 12-15 seasons per site (year-wise yields); soil after final wheat | S2: >10 Y | AG2: Rice-wheat (transplanted rice) | AJ2: 120 (100F); 60 + CR (50F+CR rice) | AK2: 26 | AL2: 33 | AM2: Wheat straw to rice: 8.8-15.8 t/ha/yr (by site) in 50F+CR | AN2: Irrigated; rice 5 cm flooding; wheat 5 irrigations | AO2: TREATMENTS IN PAPER (network long-term experiment, RBD 4 reps, plots 6 x 5 m, since 1983): Control (no fertiliser/manure); 50F (50% NPK rice, 100% wheat); 100F (100% NPK both crops) ; 50F+FYM, 50F+CR, 50F+GM = 50% NPK + 50% of recommended N through FYM, wheat crop residue (CR) or Sesbania green manure TO RICE ONLY, wheat 100% NPK. Recommended 120-26-33 kg N-P-K/ha each crop. Rice transplanted (puddled) 20 x 10 cm, wheat sown in 23 cm rows; above-ground biomass of both crops removed (sickle at ground level) except the CR returned in 50F+CR. 100F -> CT ; 50F+CR -> CTR (FLAG fertiliser offset, rule 62); Control, 50F, 50F+FYM, 50F+GM EXCLUDED. | AP2: YIELD (year-wise rice & wheat, 7 sites); SOC; available N (4 sites), P, K (final year) | AQ2: None found - web search 2026-10-05 (publisher pages not reachable from this environment) | AR2: INCLUDED FLAGGED (rule 62): 100F (CT) vs 50F+CR (CTR) - fertiliser cut offset by straw. Yields digitised year-wise from Fig. 2 and validated against Table 3 means. FLAG - FERTILISER OFFSET (rule 62): 50F+CR gets only 50% NPK to rice (wheat straw supplies the other 50% of N; P cut, K over-supplied) and 100% NPK to wheat; wheat straw is incorporated 1 month before rice transplanting (residue enters before the RICE phase only). Wheat tillage not described -> conventional (puddled transplanted rice + tilled wheat). Supplementary: none found (web search 2026-10-05; publisher site not reachable). Source file 112.pdf.
A3: 165 | B3: 165 | C3: Davari M.R., Sharma S.N. & Mirzakhani M. | D3: 2012 | E3: Biological Agriculture & Horticulture | F3: Davari MR, Sharma SN, Mirzakhani M (2012) Effect of cropping systems and crop residue incorporation on production and properties of soil in an organic agroecosystem. Biol Agric Hortic 28(3):206-222 | G3: https://doi.org/10.1080/01448765.2012.735005 | H3: India (Delhi) | I3: IARI research farm, New Delhi (organic rice-based cropping systems trial) | J3: 28.633 | K3: 77.183 | L3: 28 deg 38'N | M3: 77 deg 11'E | N3: Paper | O3: ST | P3: 2006 | Q3: 2006-07, 2007-08 | R3: 2 | S3: 0-3 Y | T3: LOAMY | U3: Sandy clay loam | V3: 52.06 | W3: 22.54 | X3: 25.4 | Y3: 8.16 | Z3: 5.2 | AA3: 1.5 | AG3: Rice-wheat and rice-wheat-mungbean (organic) | AH3: HD 2643 | AI3: Pusa Basmati 1 | AJ3: 60 (FYM-N, organic) | AM3: All residues incorporated in RI: 14.2-19.7 Mg DM/ha/yr | AN3: Rice flooded/puddled; mungbean 2 irrigations | AO3: TREATMENTS IN PAPER: strip-plot, 3 reps, 2006-07 and 2007-08, ORGANIC management. Rows = cropping system: RW (rice-wheat, summer fallow) and RWM (rice-wheat-mungbean, summer mungbean with Rhizobium + PSB); columns = residue: RR (entire above-ground biomass removed) and RI (all residue of each crop incorporated before the next crop: rice residue for wheat, wheat residue for rice in RW / for mungbean in RWM, mungbean residue for rice). Rice: field flooded and PUDDLED with tractor-drawn offset disc harrow, Pusa Basmati 1 transplanted 20 x 10 cm. Wheat: after rice harvest, residue (RI) + FYM incorporated with tractor-drawn heavy disc, then disked and planked twice; HD 2643 sown 3rd week Nov. RR -> CT, RI -> CTR (in both systems). | AP3: Rice, wheat, rice-equivalent yield (year-wise); SOC, Kjeldahl N, Olsen P, NH4OAc K (year-wise); BD, porosity, HC; bacteria, fungi, actinomycetes, MBC, DHA, CO2 evolution | AQ3: None found - web search 2026-10-05 (publisher pages not reachable from this environment) | AR3: INCLUDED: RR (CT) vs RI (CTR) in RW and in RWM (mungbean in both treatments of the RWM row, flagged). Protein yield and energy output (Figs 1-2) have no sheet. Rotation-matched: puddled transplanted rice + disc-tilled wheat = conventional in both phases; residue incorporated by disc -> CTR. FLAG: RI plots also received a cellulolytic culture spray (confounded with residue). Supplementary: none found (web search 2026-10-05; publisher site not reachable). Source file 113_rqal.pdf.
A4: 166 | B4: 166 | C4: Das B., Chakraborty D., Singh V.K., Aggarwal P., Singh R., Dwivedi B.S. & Mishra R.P. | D4: 2014 | E4: Soil & Tillage Research | F4: Das B et al. (2014) Effect of integrated nutrient management practice on soil aggregate properties, its stability and aggregate-associated carbon content in an intensive rice-wheat system. Soil Tillage Res 136:9-18 | G4: https://doi.org/10.1016/j.still.2013.09.009 | H4: India (Uttar Pradesh) | I4: PDFSR (now ICAR-IIFSR) long-term INM experiment, Modipuram, Meerut | J4: 29.067 | K4: 77.767 | L4: 29 deg 4'N | M4: 77 deg 46'E | N4: Paper | O4: ST | P4: 1993 | Q4: 2011 | R4: Soil 2011; yields as 3-yr means 1993-96 and 2008-11 | S4: >10 Y | T4: LOAMY | U4: Sandy loam | V4: 55 | W4: 18 | X4: 27 | Y4: 7.98 | Z4: 4.1 | AA4: 1.55 | AB4: 5 | AC4: 45.5 | AF4: 863 | AG4: Rice-wheat | AH4: HD 2338 | AI4: Saket 4 | AJ4: 120 (T2); 90 + CR (T8) | AK4: 26 | AL4: 33 | AM4: T8: rice and wheat straw supplying 25% of N (61.5 + 47.7 Mg C/ha over 18 yr) | AN4: Rice continuous 5 cm submergence; wheat 5 irrigations | AO4: TREATMENTS IN PAPER (Table 1, RBD 3 reps, since 1993, PDFSR Modipuram): T1 unfertilised; T2 recommended NPK (+Zn to rice) through fertilisers; T3 NPK + Zn + S (rice); T4 75% NPK + 25% N via FYM (rice); T5 75% NPK + 25% N via sulphitation press mud (rice); T6 75% NPK + green gram residue incorporated before rice; T7 = T6 (rice) + 75% NPK + 25% N via FYM (wheat); T8 75% NPK + 25% N via WHEAT STRAW to rice and 75% NPK + 25% N via RICE STRAW to wheat (CR). Rice puddled and transplanted (Saket 4, 20 x 10 cm, continuous 5 cm submergence); wheat HD 2338 drilled after dry tillage ('wet tillage followed by dry tillage'); recommended 120-26-33 kg N-P-K/ha to each crop. T2 -> CT ; T8 -> CTR (FLAG fertiliser offset, rule 62); T1, T3-T7 EXCLUDED (unfertilised / amendments / third crop in some treatments only). | AP4: TOC; macro/micro aggregates, WSA (derived), MWD (slaked + capillary), macro-C, micro-C, cPOM-C; aggregate FC/PWP/AWC; yields (3-yr means) | AQ4: None found - web search 2026-10-05 (publisher pages not reachable from this environment) | AR4: INCLUDED FLAGGED (rule 62): T2 (CT) vs T8 (CTR). FLAG - FERTILISER OFFSET (rule 62): in T8 crop residue replaces 25% of fertiliser N and 25% of P and K are also cut; drop for a fertiliser-matched sensitivity check. Wheat tillage not described in detail ('wet tillage followed by dry tillage', residue incorporated) -> conventional. Supplementary: none found (web search 2026-10-05; publisher site not reachable). Source file 113.pdf.
A5: 167 | B5: 167 | C5: Naz A., Rebi A., Naz R., Akbar M.U., Aslam A., Kalsom A., Niaz A., Ahmad M.I., Nawaz S., Kausar R., Ali B., Saleem M.H. & Zhou J. | D5: 2023 | E5: Land | F5: Naz A et al. (2023) Impact of green manuring on health of low fertility calcareous soils. Land 12:546 | G5: https://doi.org/10.3390/land12030546 | H5: Pakistan (Punjab) | I5: Khushab / Faisalabad, Punjab (calcareous soil field trial) | P5: 2015 | Q5: 2015-2018 | AG5: Rice-berseem (green manure) | AO5: Control; NPK (100% RDF); GM100, GM75, GM50 = berseem green manure (last cutting rotavated in) + 100/75/50% RDF; rice puddled-transplanted in all | AP5: NONE (excluded) | AQ5: None found - web search 2026-10-05 (publisher pages not reachable from this environment) | AR5: EXCLUDED: rice-berseem green-manure x fertiliser-dose trial - no wheat phase in the treatments, identical (puddled/rotavator) tillage and no crop-residue contrast; green manure is an amendment here, not part of a CA treatment (rule 34; rule 71 lets GM support CA, but there is no CA). Source file 111_real.pdf.
A6: 168 | B6: 168 | C6: Dhaliwal J.K., Singh M.J., Sharma S., Gupta N. & Kukal S.S. | D6: 2020 | E6: Soil Research | F6: Dhaliwal JK, Singh MJ, Sharma S, Gupta N, Kukal SS (2020) Medium-term impact of tillage and residue retention on soil physical and biological properties in dry-seeded rice-wheat system in north-west India. Soil Research 58:468-477 | G6: https://doi.org/10.1071/SR19238 | H6: India (Punjab) | I6: PAU research farm, Ludhiana (DSR-wheat tillage x mulch trial of Gupta et al. 2016) | J6: 30.933 | K6: 75.867 | L6: 30 deg 56'N | M6: 75 deg 52'E | N6: Paper | O6: TEMP | P6: 2011 | Q6: 2016 | R6: 1 | S6: 4-10 Y | T6: LOAMY | U6: Sandy loam (Typic Ustochrept) | Y6: 7.4 | AF6: 734 | AG6: Dry-seeded rice-wheat | AH6: PBW 621 | AI6: PR 115 | AM6: Rice residue 7 t/ha surface mulch in wheat (+M) | AN6: Irrigated (PAU recommendations) | AO6: TREATMENTS IN PAPER (Table 1; three-factor trial est. 2011 - only the 'absolute' CT and ZT rice and wheat combinations were studied): 1 CTW-CTDSR (-M) = conventionally tilled wheat (1 discing + 1 tyne harrowing + planking) and conventionally tilled dry-seeded rice, all rice residue removed -> CT ; 2 CTW+M-CTDSR = as 1 with ALL rice residue (7 t/ha) retained as surface mulch in wheat -> CTR ; 3 ZTW-ZTDSR = zero-till wheat (Turbo Happy Seeder) and zero-till DSR (inverted-T tyne ZT drill), residue removed -> ZT ; 4 ZTW+M-ZTDSR = as 3 with rice residue mulch -> CA. Wheat straw removed in every treatment (cut 3-5 cm above ground). RBD 3 reps; plots 9.3 x 6.5 m. | AP6: SOC, SOC stock, macro/micro WSA, WSA (derived), MWD, BD, porosity (derived), IR (initial + steady), FC/PWP/AWC, MBC, BSR, DHA, urease, ALP, ACP | AQ6: None found - web search 2026-10-05 (publisher pages not reachable from this environment) | AR6: INCLUDED: CT, CTR, ZT, CA. ALL ROWS RED (rice-season fallback - sampling after 2016 rice harvest only). Enzymes = tillage main effects (flagged). RICE-SEASON DATA (RED ROW): the paper samples ONLY after the 2016 rice harvest, so values are entered under the rice-season fallback rule (rule 36). Rotation-matched: CT rice + CT wheat = CT; ZT rice + ZT wheat = ZT/CA (rice residue is the mulch factor). Supplementary: none found (web search 2026-10-05; publisher site not reachable from this environment). Source file 112_real.pdf.
A7: 169 | B7: 169 | C7: Singh V.K., Dwivedi B.S., Shukla A.K., Chauhan Y.S. & Yadav R.L. | D7: 2005 | E7: Field Crops Research | F7: Singh VK et al. (2005) Diversification of rice with pigeonpea in a rice-wheat cropping system on a Typic Ustochrept: effect on soil fertility, yield and nutrient use efficiency. Field Crops Res 92:85-105 | G7: https://doi.org/10.1016/j.fcr.2004.09.002 | H7: India (Uttar Pradesh) | I7: PDCSR Modipuram, Meerut + farmers' survey (Upper Gangetic Plain) | AG7: Rice-wheat vs pigeonpea-wheat | AO7: Cropping system (rice-wheat vs pigeonpea-wheat) x N (0/120) x P (0/26) to wheat | AP7: NONE (excluded) | AQ7: None found - web search 2026-10-05 (publisher pages not reachable from this environment) | AR7: EXCLUDED: crop-diversification x fertiliser trial (rice replaced by pigeonpea); no tillage or crop-residue contrast within rice-wheat (rule 34). Source file 114.pdf.
A8: 23 (companion 3) | B8: 23 (companion 3) | C8: Jat H.S., Datta A., Choudhary M., Yadav A.K., Choudhary V., Sharma P.C., Gathala M.K., Jat M.L. & McDonald A. | D8: 2019 | E8: Soil & Tillage Research | F8: Jat HS et al. (2019) Effects of tillage, crop establishment and diversification on soil organic carbon, aggregation, aggregate associated carbon and productivity in cereal systems of semi-arid Northwest India. Soil Tillage Res 190:128-138 | G8: https://doi.org/10.1016/j.still.2019.03.005 | H8: India (Haryana) | I8: ICAR-CSSRI research farm, Karnal (CSISA scenario trial, est. 2009) | J8: 29.7 | K8: 76.96 | L8: 29 deg 70'N (as printed) | M8: 76 deg 96'E (as printed) | N8: Paper (non-standard minutes, read as decimals) | O8: ST | P8: 2009 | Q8: 2013, 2015 (soil); 2009-10 to 2014-15 (yield) | R8: 2 soil samplings; 6 yield years | S8: 4-10 Y | T8: LOAMY | U8: Loam, reclaimed alkali (Typic Natrustalf) | AB8: 2 | AC8: 42.5 | AF8: 700 | AG8: Rice-wheat (Sc1); rice-wheat-mungbean (Sc2, Sc3) | AM8: Sc2 78.5, Sc3 74.5 t/ha over 6 yr | AO8: TREATMENTS IN PAPER (CSISA scenario trial, ICAR-CSSRI Karnal, est. 2009, RBD 3 reps, 100 x 20 m plots): Sc1 conventional rice-wheat (puddled manually transplanted rice, broadcast CT wheat, residues removed; farmers' practice) -> CT ; Sc2 partial CA rice-wheat-mungbean (puddled transplanted rice; ZT drill-seeded wheat and mungbean; anchored rice stubble 4.1-12.7 t/ha retained at wheat sowing, mungbean residue incorporated during puddling) -> pCA ; Sc3 full CA rice-wheat-mungbean (ZT DSR, ZT wheat, ZT mungbean, residues retained on the surface) -> CA ; Sc4 full CA maize-wheat-mungbean -> EXCLUDED (maize). Residue added 2009-15: Sc2 78.5, Sc3 74.5 t/ha. | AP8: WB-C, TOC, macro/micro WSA, WSA, MWD, GMD, macro-C, micro-C, POC (2013, 2015, 2 depths); REY 6 years | AQ8: None found - web search 2026-10-05 (publisher pages not reachable from this environment) | AR8: INCLUDED: Sc1 CT, Sc2 pCA, Sc3 CA. Soil rows RED (after rice harvest). GREEN MANURE / 3rd CROP: ZT mungbean in Sc2 and Sc3, not in Sc1 (rule 71). pCA (Sc2) was EXCLUDED in old-master study 23 (rotation mismatch) and is now coded pCA (rule 68). COMPANION of old-master study 23 (same CSSRI trial). Supplementary: none found. Source file 115_rep.pdf.
A9: 23 (companion 4) | B9: 23 (companion 4) | C9: Jat H.S., Datta A., Choudhary M., Sharma P.C., Yadav A.K., Choudhary V., Gathala M.K., Jat M.L. & McDonald A. | D9: 2019 | E9: Catena (accepted manuscript; version of record S0341816219301936) | F9: Jat HS et al. (2019) Climate Smart Agriculture practices improve soil organic carbon pools, biological properties and crop productivity in cereal-based systems of North-West India. Catena | G9: https://www.sciencedirect.com/science/article/pii/S0341816219301936 | H9: India (Haryana) | I9: ICAR-CSSRI research farm, Karnal (CSISA scenario trial, est. 2009) | J9: 29.7 | K9: 76.95 | N9: Paper | O9: ST | P9: 2009 | Q9: 2013 | R9: 1 | S9: 4-10 Y | T9: LOAMY | U9: Loam (Typic Natrustalf), OC 0.45% | Z9: 4.5 | AB9: 11.62 | AC9: 31.68 | AF9: 670 | AG9: Rice-wheat (Sc1); rice-wheat-mungbean (Sc2, Sc3) | AM9: Sc2 47.9, Sc3 56.1 t/ha over 4 yr | AO9: TREATMENTS IN PAPER (CSISA scenario trial, ICAR-CSSRI Karnal, est. 2009, RBD 3 reps, 100 x 20 m plots): Sc1 conventional rice-wheat (puddled manually transplanted rice, broadcast CT wheat, residues removed; farmers' practice) -> CT ; Sc2 partial CA rice-wheat-mungbean (puddled transplanted rice; ZT drill-seeded wheat and mungbean; anchored rice stubble 4.1-12.7 t/ha retained at wheat sowing, mungbean residue incorporated during puddling) -> pCA ; Sc3 full CA rice-wheat-mungbean (ZT DSR, ZT wheat, ZT mungbean, residues retained on the surface) -> CA ; Sc4 full CA maize-wheat-mungbean -> EXCLUDED (maize). Residue added 2009-13: Sc2 47.9, Sc3 56.1 t/ha. | AP9: SOC stock; VL/L/LL/NL C (derived g/kg); DHA, ALP, MBC, MBN, BSR, fungi, bacteria, actinomycetes (2 depths) | AQ9: None found - web search 2026-10-05 (publisher pages not reachable from this environment) | AR9: INCLUDED: Sc1 CT, Sc2 pCA, Sc3 CA. All rows RED. RICE-SEASON DATA (RED ROW). SAME SAMPLING (Oct 2013) as 23 (companion 3); parameters split between the two papers (no duplicates): concentrations of WB-C/TOC from companion 3, stocks, C pools and biology from this paper. GREEN MANURE / 3rd CROP: mungbean in Sc2 and Sc3 (rule 71). Supplementary: none found. Source file 116_rep.pdf.
A10: 165 (companion) | B10: 165 (companion) | C10: Meena A.L., Pandey R.N., Kumar D., Dotaniya M.L., Sharma V.K., Singh G., Meena B.P., Kumar A. & Bhanu C. | D10: 2020 | E10: Communications in Soil Science and Plant Analysis | F10: Meena AL et al. (2020) Impact of 12-year-long rice based organic farming on soil quality in terms of soil physical properties, available micronutrients and rice yield in a typic Ustochrept soil of India. Commun Soil Sci Plant Anal | G10: https://doi.org/10.1080/00103624.2020.1822386 | H10: India (Delhi) | I10: IARI research farm, New Delhi (long-term organic rice-based project, since 2003) | J10: 28.4 | K10: 77.1 | L10: 28.4 N | M10: 77.1 E | N10: Paper | O10: ST | P10: 2003 | Q10: 2015-16 (soil); 2009-2015 (rice yield mean) | S10: >10 Y | T10: LOAMY | U10: Sandy clay loam | V10: 52.1 | W10: 22.5 | X10: 25.4 | Y10: 8.45 | Z10: 5.1 | AA10: 1.5 | AB10: 18 | AC10: 35.2 | AF10: 750 | AG10: Organic basmati rice-wheat and rice-wheat-mungbean | AH10: HD 2967 | AI10: Pusa Basmati 1121 | AJ10: 60 (FYM or VC N) | AM10: 3 t/ha preceding-crop residue to each crop (CR treatments) | AO10: TREATMENTS IN PAPER (IARI long-term organic project 'Nutrient management in rice-wheat cropping system under organic conditions', since kharif 2003, organic from 2006; strip plot, 3 reps): main strips RWCS (basmati rice-wheat) and RWMCS (rice-wheat-mungbean); rows: Control (no organics), FYM, VC (each = 60 kg N/ha), FYM + CR, VC + CR (crop residue of the preceding crop 3 t/ha to each crop), FYM + CR + BF, VC + CR + BF (BF = BGA + PSB + cellulolytic culture in rice; Azotobacter + PSB + cellulolytic in wheat; Rhizobium + PSB in mungbean). FYM -> CT, FYM + CR -> CTR (row a), FYM + CR + BF -> CTR (row b, BF flag); VC -> CT, VC + CR -> CTR (row a), VC + CR + BF -> CTR (row b); Control EXCLUDED (no organics). | AP10: BD, porosity (derived), WHC, MWD, GMD, Ks, pH, EC, SOC, C stock, available N, P, DTPA Cu/Zn/Mn/Fe, rice grain and straw yield | AQ10: None found - web search 2026-10-05 (publisher pages not reachable from this environment) | AR10: INCLUDED: FYM/VC (CT) vs +CR (CTR), rows a/b (+BF). Soil rows RED (after rice harvest). SAME IARI ORGANIC PROJECT as serial 165 (Davari et al. 2012: identical initial soil, rotations and strip-plot layout) -> filed as 165 (companion); the CR rate (3 t/ha) and treatment set differ from Davari's 2006-08 RR/RI comparison - check. Tillage not described in this paper; from the same project (Davari 2012): puddled transplanted rice, disc-ploughed wheat -> conventional (flag). Supplementary: none found. Source file 116_real.pdf.
A11: 131 (companion) | B11: 131 (companion) | C11: Zhang Y.-P., Li X., He H.-J., Zhou H., Geng D.-Y. & Zhang Y.-Z. | D11: 2023 | E11: Sustainability | F11: Zhang Y-P et al. (2023) Effects of rotational tillage on soil physicochemical properties and crop yield in a rice-wheat double cropping area. Sustainability 15:474 | G11: https://doi.org/10.3390/su15010474 | H11: China (Shandong) | I11: Taoluo Town, Donggang District, Rizhao, Shandong | J11: 35.27 | K11: 119.38 | N11: Approximate - Taoluo town centre (paper gives none; Donggang district 35.425 N, 119.462 E) | O11: TEMP | P11: 2017 | Q11: 2018-2020 | R11: BD 2018-2020; other soil after 3 yr | S11: 0-3 Y | U11: Paddy soil (texture not stated) | Y11: 6.8 | Z11: 5.75 | AA11: 1.423 | AD11: 12.6 | AF11: 916 | AG11: Rice-wheat (double cropping) | AH11: Yannong 21 | AI11: Linhan 1 | AJ11: Wheat 225; rice slow-release 25-10-10 600 kg + compound | AM11: Full straw return (crushed) in all | AO11: TREATMENTS IN PAPER (one 960 m2 strip per pattern, 2017-2019 rice seasons, Taoluo, Rizhao): RT = rotational tillage before rice (no-till 2017 and 2018, plough 2019; no-till dry direct-seeded rice) -> EXCLUDED (alternate tillage); CN = continuous no-till dry direct-seeded rice (wide-belt stubble seeder) 2017-2019 -> CA ; PR = plough + rotary tillage, irrigation, puddling and transplanting (30 x 12 cm) every year -> pCA. In ALL treatments wheat (Yannong 21, 187.5 kg/ha, 14 Oct) is sown WITHOUT tillage with the same seeder, and the crushed straw (<=10 cm) of the previous crop is fully returned. Before the trial: ploughing + rotary 15-18 cm, transplanting, straw removed. | AP11: BD (2018-20, 3 layers), porosity (derived), water-stable macro-aggregates, MWD (wet, dry), SOC, total N, alkali-N, P, K, SOC stock and sequestration (derived), rice/wheat yield and components | AQ11: None found - web search 2026-10-05 (publisher pages not reachable from this environment) | AR11: INCLUDED: CN = CA, PR = pCA (RT excluded). RE-ENTRY of old-master study 131 (excluded there 2026-10-04 as a rotation mismatch); re-evaluated under the PARTIAL-CA rule (rule 68): PR = puddled transplanted rice + no-till wheat with straw -> pCA, CN -> CA. FLAG: UNREPLICATED (one strip per pattern, multi-point sampling) - Rep kept 3 by rule. Coordinates approximate (Taoluo town centre; paper gives none). Texture not stated (paddy soil). Supplementary: none found. Source file 114_reqal.pdf.
A12: 170 | B12: 170 | C12: Kukal S.S. & Aggarwal G.C. | D12: 2003 | E12: Soil & Tillage Research | F12: Kukal SS & Aggarwal GC (2003) Puddling depth and intensity effects in rice-wheat system on a sandy loam soil. I. Development of subsurface compaction. Soil Tillage Res 72:1-8 | G12: https://doi.org/10.1016/S0167-1987(03)00093-X | H12: India (Punjab) | I12: Punjab Agricultural University, Ludhiana | J12: 30.933 | K12: 75.867 | L12: 30 deg 56' N | M12: 75 deg 52' E | N12: Paper | O12: TEMP | P12: 1994 | Q12: 1994-1996 (rice), 1994-95 to 1996-97 (wheat) | R12: 3 | S12: 0-3 Y | T12: SANDY | U12: Fatehpur sandy loam (71 % sand, 17 % silt, 12 % clay), Typic Ustochrept | V12: 71 | W12: 17 | X12: 12 | Z12: 3.3 | AG12: Rice-wheat | AH12: CPAN 3004 | AI12: PR 110 | AJ12: Wheat 120; rice urea 105 kg (1/3 basal) | AK12: Wheat 26 | AO12: TREATMENTS IN PAPER (PAU Ludhiana, 1994-1996, RBD, 22 x 1.8 m plots; rice puddled with a 35-HP tractor cultivator in 5-6 cm standing water, then planked): medium (2 passes) or intensive (4 passes) puddling x shallow (5-6 cm; tines set 4-5 cm) or normal (10-12 cm; full tine length, farmers' practice) depth; achieved depth medium 5.1 / 10.3 cm, intensive 6.8 / 11.8 cm. Unpuddled plots kept in the same field outside the randomised layout. Wheat after every treatment: pre-sowing irrigation, 1 disc + 2 cultivator passes + planking (conventional), drilled 22.5 cm rows. | AP12: BD per layer 0-5 ... 22-24 cm at rice harvest (red) and after wheat seedbed preparation 1996 (Fig. 1, digitised; ZT from Table 3), porosity (derived), SPR per 5-cm layer to 30 cm at both stages (Fig. 2, digitised), BD 14-20 cm 1994-95 and SPR 15-20 cm 1994-96 at rice harvest (Tables 4-5, red) | AQ12: None (2003 article) | AR12: INCLUDED (author 2026-10-05): normal puddling CT, shallow puddling MT, unpuddled ZT. NOT ON A SHEET: puddling depth achieved (Table 2) and penetrometer calibration (Table 1); Table 3 BD of normal-depth plots by intensity (in the BD rows' Notes). AUTHOR CODING 2026-10-05: unpuddled -> ZT, shallow puddling -> MT, normal puddling -> CT. FLAG: the WHEAT phase is conventionally tilled after every treatment (contrast is the rice-phase puddling only); unpuddled plots were outside the randomised layout (flag). Shallow (MT) and normal (CT) values in the figures are pooled over medium and intensive puddling (T = 2 in Obs). Supplementary: none (2003). Source file 117_real.pdf.
A13: 15 (companion 2) | B13: 15 (companion 2) | C13: Gathala M.K., Ladha J.K., Saharawat Y.S., Kumar V., Kumar V. & Sharma P.K. | D13: 2011 | E13: Soil Science Society of America Journal | F13: Gathala MK, Ladha JK, Saharawat YS, Kumar V, Kumar V & Sharma PK (2011) Effect of tillage and crop establishment methods on physical properties of a medium-textured soil under a seven-year rice-wheat rotation. Soil Sci Soc Am J 75:1851-1862 | G13: https://doi.org/10.2136/sssaj2010.0362 | H13: India (Uttar Pradesh) | I13: SVBPUAT research farm, Modipuram, Meerut (IRRI-India trial of old-master 15) | J13: 29.017 | K13: 77.75 | L13: 29 deg 01' N (old-master 15) | M13: 77 deg 45' E | N13: Paper / old-master 15 | O13: ST | P13: 2002 | Q13: 2002-03 to 2008-09 | R13: WSA 6 yr, IR 6 yr (year-wise); BD and SPR 4-yr mean; SOC after 7 yr | S13: 0-3 Y to 4-10 Y (per row) | T13: LOAMY | U13: Sandy loam (0-45 cm); 0-15 cm clay 19, silt 26, sand 55 % | V13: 55 | W13: 26 | X13: 19 | Y13: 8.1 | AB13: 2 | AC13: 43 | AF13: 800 | AG13: Rice-wheat | AH13: PBW 343 | AI13: NDR 359 | AJ13: 150 (rice, +22.5 in DSR) / 150 (wheat) | AK13: 26 / 26 | AL13: 50 / 50 | AM13: ~1 Mg/ha anchored stubble after every crop in all plots (not a treatment) | AN13: TPR flooded 2 wk then at hairline cracks; T2 AWD 20-70 DAT; DSR every 3-4 d for 4 wk | AO13: TREATMENTS IN PAPER (Modipuram, est. kharif 2002, RCBD 3 reps, 15.0 x 6.7 m plots; ~1 Mg/ha anchored stubble after every crop in ALL plots, incorporated in CT/puddled plots, standing in ZT plots): T1 CT-TPR/CT-DSW (puddled TPR; wheat after conventional tillage, drill-seeded) -> CT ; T2 CTAWD-TPR/ZT-DSW (puddled TPR with mid-season AWD; ZT drill-seeded wheat) -> pZT ; T3 Bed-DSR/Bed-DSW (permanent raised beds, DSR; beds reshaped in one tractor pass at wheat sowing) -> MT row a ; T4 Bed-TPR/Bed-DSW (permanent beds, transplanted rice, reshaped for wheat) -> MT row b ; T5 ZT-DSR/ZT-DSW -> ZT row a ; T6 ZT-TPR/ZT-DSW (zero-till plots flooded 1 d before transplanting, not puddled) -> ZT row b. | AP13: BD (4 layers), porosity (derived), SPR (every 5 cm to 45 cm, digitised), WSA >0.25 mm (6 yr), water-stable aggregate size classes (7 classes, digitised) and MWD (derived), steady infiltration (6 yr), SOC 0-15 cm, SOC stock (derived), LLWR 0-5 / 6-10 cm (Fig. 5), weekly soil temperature at 5 cm (Fig. 3, 20 weeks x 0700 / 1500 h), 7-yr mean yields (duplicate flag) | AQ13: None found - web search 2026-10-05 (publisher pages not reachable from this environment) | AR13: INCLUDED: T1 CT, T2 pZT, MT T3 (row a) / T4 (row b), ZT T5 (row a) / T6 (row b). NOT ON A SHEET: initial water retention -30 / -1500 kPa 25.5 / 9.9 % v/v, AWC 15.6 % v/v (initial only); Fig. 4 (LLWR vs wheat yield regression). COMPANION of old-master 15 (Gathala et al. 2011 Agron. J., same trial; old-master 15 used T1 CT vs T5 ZT only). AUTHOR CODING 2026-10-05: T1 CT, T2 pZT (puddled AWD rice + ZT wheat; FLAG AWD), T3 and T4 (permanent beds reshaped at every wheat sowing) MT, T5 and T6 ZT. Rows a/b pair the rice establishment (a: T5 ZT-DSR + T3 bed-DSR; b: T6 ZT-TPR + T4 bed-TPR); CT and pZT repeated in both rows (rule 20, T = 2 in Obs). Residue is not a treatment factor (~1 Mg/ha stubble in all) -> no R codes. Supplementary: None found - web search 2026-10-05 (publisher pages not reachable from this environment). Source file 118.pdf (scanned).
A14: 40 (companion) | B14: 40 (companion) | C14: Kader M.A., Jahangir M.M.R., Islam M.R., Begum R., Nasreen S.S., Islam Md.R., Mahmud A.Al., Haque M.E., Bell R.W. & Jahiruddin M. | D14: 2022 | E14: Field Crops Research | F14: Kader MA et al. (2022) Long-term conservation agriculture increases nitrogen use efficiency by crops, land equivalent ratio and soil carbon stock in a subtropical rice-based cropping system. Field Crops Res 287:108636 | G14: https://doi.org/10.1016/j.fcr.2022.108636 | H14: Bangladesh | I14: Bangladesh Agricultural University farm, Mymensingh (Old Brahmaputra Floodplain) | J14: 24.724 | K14: 90.437 | L14: 24 deg 43.407' N | M14: 90 deg 26.22' E | N14: Paper | O14: ST | P14: 2012 | Q14: 2012-13 to 2020-21; soil after 23rd crop (wheat 2019-20) | R14: Economics 9 yr; yields/NUE 2018-2021; soil 1 sampling | S14: 0-3 Y to 4-10 Y (per row) | T14: LOAMY | U14: Silt loam (110 sand : 760 silt : 130 clay g/kg), Aeric Haplaquept | V14: 11 | W14: 76 | X14: 13 | Y14: 6.92 | Z14: 13.2 | AA14: 1.58 | AF14: 2400 | AG14: Rice (aman) - wheat - mungbean | AH14: BARI Gom 25 | AI14: BRRI dhan49 | AJ14: RFD rice 75, wheat 100, mungbean 20 (60-140 % tiers) | AK14: rice 10, wheat 20, mungbean 20 | AL14: rice 30, wheat 60, mungbean 30 | AM14: Anchored stubble 15 % (LR) or 30 % (HR) of plant height; mungbean 0 / 100 % | AN14: Rice rainfed; wheat 2 irrigations | AO14: TREATMENTS IN PAPER (BAU farm, Mymensingh, est. monsoon rice 2012, split-split plot, 3 reps, 7 x 7 m sub-sub plots; rice-wheat-mungbean every year): main plot tillage - CT = conventional (rice: soil flooded 5-6 cm and puddled with 4 rotary passes of a 2-wheel-tractor rotary tiller; wheat and mungbean: 4 full cross rotary passes) -> CTR ; ST = strip tillage (Versatile Multi-crop Planter, 4-6 cm wide x 5-6 cm deep strips, 75-80 % of soil untilled; rice transplanted unpuddled into strips softened overnight) -> MTR. Sub-plot residue - LR = 15 % of crop height retained (farmers' practice) / HR = 30 % of rice and wheat + 100 % mungbean residue -> both residue-retained (rows a = LR, b = HR). Sub-sub plot N - 60, 80, 100, 120, 140 % of RFD (RFD 75 / 100 / 20 kg N/ha rice / wheat / mungbean). | AP14: BD, porosity (derived), total N, SOC, MBC, SOC stock, C sequestration (derived) - 0-15 cm rows a/b; rice & wheat yields 2018-21 x 5 N rates (digitised); NUE (PFP, AE) x N; gross margin 9 yr | AQ14: Supplementary Tables S1-S4 (year-wise main-effect yields, interactions) exist but could not be reached - None found - web search 2026-10-05 (publisher pages not reachable from this environment) | AR14: INCLUDED: CT -> CTR, ST -> MTR (both residue levels retained; rows a LR / b HR). Optimum N (Table 5) and LER (Table 1) not on a sheet. COMPANION of old-master 40 (Mumu et al. 2024 SSRN; same BAU trial est. 2012, same coordinates; coded CT-LR/HR -> CTR, ST-LR/HR -> MTR there). THIRD CROP: mungbean every year in both tillage systems (rule 71). CT here is 4-pass rotary (CT under the rotary rule) with puddling for rice. Supplementary Tables S1-S4 (year-wise main-effect yields) not reachable - None found - web search 2026-10-05 (publisher pages not reachable from this environment). Source file 119_real.pdf.
A15: 23 (companion 5) | B15: 23 (companion 5) | C15: Roy D., Datta A., Jat H.S., Choudhary M., Sharma P.C., Singh P.K. & Jat M.L. | D15: 2022 | E15: Geoderma | F15: Roy D, Datta A, Jat HS, Choudhary M, Sharma PC, Singh PK & Jat ML (2022) Impact of long term conservation agriculture on soil quality under cereal based systems of North West India. Geoderma 405:115391 | G15: https://doi.org/10.1016/j.geoderma.2021.115391 | H15: India (Haryana) | I15: ICAR-CSSRI research farm, Karnal (CSISA scenario trial, est. 2009) | J15: 29.706 | K15: 76.956 | L15: 29 deg 42' 20.7" N | M15: 76 deg 57' 19.79" E | N15: Paper | O15: ST | P15: 2009 | Q15: 2019 | R15: 1 sampling (after wheat 2019) | S15: 4-10 Y | T15: LOAMY | U15: Loam, Haplic Solonetz (siltic) | AF15: 670 | AG15: Rice-wheat (Sc1); rice-wheat-mungbean (Sc2, Sc3) | AJ15: 150 (rice and wheat, CA scenarios) | AK15: 60 P2O5 | AL15: 60 K2O | AM15: 100 % rice + mungbean, 30 % wheat (Sc2, Sc3) | AO15: TREATMENTS IN PAPER (CIMMYT-ICAR-CSSRI platform, Karnal, est. kharif 2009, RCBD 3 reps): Sc1 TPR-CTW (puddled transplanted rice; wheat broadcast after 2 harrowings + 2 cultivator passes; no residue) -> CT ; Sc2 TPR-ZTWMb (puddled TPR; ZT wheat and mungbean by Happy Seeder; 100 % rice + mungbean and 30 % wheat residue retained) -> pCA ; Sc3 ZTDSR-ZTWMb (ZT DSR, ZT wheat, ZT mungbean, same residue) -> CA ; Sc4 ZT maize-wheat-mungbean -> EXCLUDED (maize) ; Sc5 = Sc3 + sub-surface drip irrigation (from 2016, 25 % less N) -> NOT ENTERED (irrigation/fertigation contrast, as old-master 23) ; Sc6 = Sc4 + SDI -> EXCLUDED. | AP15: 0-5, 5-15, 15-30 cm: BD, porosity (derived), GWC (derived), pH, EC, SOC, SOC stock, available N/P/K, DTPA Fe/Zn/Cu/Mn, MBC, DHA, ACP, ALKP, B-GLU, SQI; SPR x 9 layers (digitised); steady infiltration | AQ15: None found - web search 2026-10-05 (publisher pages not reachable from this environment) | AR15: INCLUDED: Sc1 CT, Sc2 pCA, Sc3 CA; wheat-season sampling (not red). COMPANION of old-master 23 (same CSSRI scenario trial; Sc2 was excluded there and is now pCA, rule 68 - see 23 (companion 3/4)). THIRD CROP: ZT mungbean in Sc2/Sc3 only (rule 71). Sc5 (Sc3 + SDI) not entered (same tillage/residue as Sc3; values in Notes, as old-master 23). Supplementary: None found - web search 2026-10-05 (publisher pages not reachable from this environment). Source file 117.pdf.
A16: 171 | B16: 171 | C16: Ghimire R., Adhikari K.R., Chen Z.-S., Shah S.C. & Dahal K.R. | D16: 2012 | E16: Paddy and Water Environment | F16: Ghimire R, Adhikari KR, Chen Z-S, Shah SC & Dahal KR (2012) Soil organic carbon sequestration as affected by tillage, crop residue, and nitrogen application in rice-wheat rotation system. Paddy Water Environ 10:95-102 | G16: https://doi.org/10.1007/s10333-011-0268-0 | H16: Nepal | I16: IAAS Rampur campus farm, Chitwan Valley (inner Terai) | J16: 27.647 | K16: 84.346 | L16: 27 deg 38' 49" N | M16: 84 deg 20' 45" E | N16: Paper | O16: ST | P16: 1999 (NT); CT/NT split 2001-02; factorial Nov 2002 | Q16: March 2006 | R16: 1 | S16: 4-10 Y | T16: LOAMY | U16: Sandy clay loam to 30 cm, sandy loam 30-50 cm (Typic Haplustoll) | V16: 57 | W16: 19 | X16: 24 | Y16: 5.4 | AF16: 2000 | AG16: Rice-wheat-mungbean (cover crop) | AH16: BL 1473 | AI16: Sabitri | AJ16: 100 / 100 (N1 recommended vs N2 LCC timing) | AK16: 60 / 40 P2O5 | AL16: 40 / 40 K2O | AM16: 4 Mg/ha per crop (12 Mg/ha/yr) in M1 | AO16: TREATMENTS IN PAPER (IAAS Rampur, Chitwan; factorial RCBD, 3 reps, 3 x 5 m plots; Nov 2002 - Mar 2006 phase of a trial under no-till since 1999, split into CT / NT for wheat 2001-02): T0 no-tillage (surface seeding of all crops; rice, wheat and mungbean) vs T1 conventional tillage (mould-board / disc 15-20 cm + cultivation; rice puddled) x M0 no residue (roots only) vs M1 residue 4 Mg/ha per crop (rice straw to wheat and mungbean, wheat straw to rice; 12 Mg/ha/yr) x N1 recommended N timing vs N2 leaf-colour-chart N in rice. Mungbean cover crop between wheat and rice in ALL plots. | AP16: SOC stock 0-5, 5-10, 10-15, 15-30, 30-50 cm (Table 4) -> SOC concentration (derived, BD 1.07) and cumulative stocks 0-10 / 0-15 / 0-30 / 0-50 cm | AQ16: None found - web search 2026-10-05 (publisher pages not reachable from this environment) | AR16: INCLUDED: CT, CTR, ZT, CA (N timing pooled). TILLAGE x RESIDUE cell means POOLED OVER the two N-timing treatments (Table 4; flag). THIRD CROP: mungbean cover crop in every plot (rule 71). BD not different among treatments - the paper used one mean BD 1.07 Mg/m3 (SD 0.11) for all stocks. Main effects (Table 3, not entered): T0 / T1 0-5 11.8 / 9.20, 5-10 11.2 / 9.94, 10-15 11.8 / 10.5, 15-30 21.6 / 23.7, 30-50 23.6 / 23.2, 0-50 82.2 / 74.8 Mg C/ha; M0 / M1 0-50 77.1 / 79.9; N1 / N2 0-50 76.5 / 80.5. Sequestration rates printed by the paper are RELATIVE TO CT (not vs initial): NT 0.59 (0-5 cm), NT+R vs CT-R 0.73 / 0.37 / 0.48 Mg C/ha/yr (0-5 / 5-10 / 10-15 cm). Supplementary: None found - web search 2026-10-05 (publisher pages not reachable from this environment). Source file 120_real.pdf.
A17: 172 | B17: 172 | C17: Tirol-Padre A., Tsuchiya K., Inubushi K. & Ladha J.K. | D17: 2005 | E17: Soil Science and Plant Nutrition | F17: Tirol-Padre A, Tsuchiya K, Inubushi K & Ladha JK (2005) Enhancing soil quality through residue management in a rice-wheat system in Fukuoka, Japan. Soil Sci Plant Nutr 51:849-860 | G17: https://doi.org/10.1111/j.1747-0765.2005.tb00120.x | H17: Japan | I17: Kyushu National Agricultural Experiment Station (NARC/KOR), Chikugo, Fukuoka - long-term rice-wheat experiment | J17: 33.2 | K17: 130.5 | N17: Approximate (Chikugo city; paper gives none) | O17: TEMP | P17: 1963 | Q17: Soil Oct 2003; rice yields 1989-2003 | R17: 1 soil sampling; 12 yield years | S17: >10 Y | T17: LOAMY | U17: Gray Lowland soil, 29 % clay, 56 % silt, 16 % sand | V17: 16 | W17: 56 | X17: 29 | AG17: Rice-wheat | AJ17: 0 or 70 (urea) | AM17: Rice straw 10; compost 20; ryegrass 8 then wheat straw 10 / 6 (incorporated at puddling) | AO17: TREATMENTS IN PAPER (Kyushu National Agricultural Experiment Station LTE, Chikugo, Fukuoka; rice-wheat since 1963; residues incorporated at puddling in mid-June): 1 unfertilised control, 2 70 kg N/ha urea, 3 rice straw 10 Mg/ha, 4 rice straw + N, 5 rice-straw compost 20 Mg/ha, 6 compost + N, 7 Italian ryegrass 8 Mg/ha (1963-84) then wheat straw 10 Mg/ha (1985-93) and 6 Mg/ha (1994-2003), 8 = 7 + N. ENTERED (+N tier): row a CT = urea N only vs CTR = rice straw + N; row b CT = urea N vs CTR = wheat straw + N; row c CT = urea N vs CTR = rice-straw compost + N (author 2026-10-05). NOT ENTERED: -N tier (unfertilised control as CT, rule 78). | AP17: RED soil rows (+N tier): pH, Olsen P (kg/ha, assumed depth), Ex-K, CEC, total C, organic C, total N, MBC and basal respiration (aerobic / flooded incubations), hot-water C, POXC, PMN; rice yield 12 years (Fig. 1, digitised); rice N uptake | AQ17: None found - web search 2026-10-05 (publisher pages not reachable from this environment) | AR17: INCLUDED (+N tier): CT vs CTR rows a (rice straw) / b (wheat straw) / c (rice-straw compost). CONVENTIONAL puddled rice in all plots (residue contrast only). Row b CTR = Italian ryegrass 1963-84 then wheat straw (flag). Row c CTR = rice-straw COMPOST 20 Mg/ha (composted residue counted as CTR - author 2026-10-05; flag). NOT ENTERED: -N tier (unfertilised control as CT, rule 78); its values are in each row's Notes. Sampling depth not stated - plough layer, class 0-15 CM assumed (flag); the paper uses BD = 1 g/cm3 for its own stock calculations. Coordinates approximate (Chikugo city). Supplementary: None found - web search 2026-10-05 (publisher pages not reachable from this environment). Source file 120.pdf.
A18: 124 (companion) | B18: 124 (companion) | C18: Hoque M.A., Gathala M.K., Timsina J., Ziauddin M.A.T.M., Hossain M. & Krupnik T.J. | D18: 2023 | E18: Field Crops Research | F18: Hoque MA, Gathala MK, Timsina J, Ziauddin MATM, Hossain M & Krupnik TJ (2023) Reduced tillage and crop diversification can improve productivity and profitability of rice-based rotations of the Eastern Gangetic Plains. Field Crops Res 291:108791 | G18: https://doi.org/10.1016/j.fcr.2022.108791 | H18: Bangladesh | I18: BARI Regional Agricultural Research Station, Jamalpur (AEZ 9, Old Brahmaputra Floodplain) | J18: 24.942 | K18: 89.928 | L18: 24 deg 56' 30.68" N | M18: 89 deg 55' 40.39" E | N18: Paper | O18: ST | P18: 2013 | Q18: 2013-2016 | R18: 3 | S18: 0-3 Y | T18: LOAMY | U18: Loam (sand 47.3, silt 30.0, clay 22.7 %) | V18: 47.3 | W18: 30 | X18: 22.7 | Y18: 6.2 | AG18: Rice-wheat (row a) and rice-wheat-mungbean (row b) | AH18: BARI Gom-26 | AI18: BR-11 / BINA dhan-7 | AJ18: wheat 100; rice 81 / 68 | AM18: CA / AT ~25 cm stubble (~3 t/ha); CT ~0.7 t/ha incorporated | AO18: TREATMENTS IN PAPER (BARI RARS Jamalpur, 2013-2016, split plot, 4 reps; 6 cropping systems x 3 tillage): CA = monsoon rice transplanted into UNTILLED unpuddled soil, wheat (and mungbean) strip-tilled into ~25 cm stubble (~3 t/ha) -> MTR (as old-master 124) ; AT = PUDDLED transplanted rice, winter / spring crops strip-tilled into ~25 cm stubble with residue -> pMTR (NEW, rules 68 / 85 / 86) ; CT = puddled rice, 3-5 tillage passes for winter crops, ~0.7 t/ha stubble incorporated -> CT. R-W = row a, R-W-MB = row b; R-R, R-M, R-MB, R-M-MB not rice-wheat. | AP18: SREY, system gross margin, B:C (derived) - R-W and R-W-MB, CT / MTR / pMTR (AT added) | AQ18: Tables S1-S3 (management, residue) - not reachable | AR18: INCLUDED as companion: AT = pMTR. RE-ENTRY of old-master 124 (same paper) for the AT treatment, excluded there as a rotation mismatch and now pMTR (rules 85 / 86, author confirmed). DUPLICATE FLAG: the CT and MTR values repeat old-master 124 exactly (kept so that pMTR has its comparison in the same row) - when merging use these rows for the pMTR contrasts only. Cell values exist only as violin plots: AT digitised as the violin area-centroid (Fig. 4 raster, this batch: the same procedure reproduces the old-master CT / CA values within +/-3 US$/ha); AT system yield from the old-master Notes (Fig. 3 vector). Obs = Y3, Rep 4. System calorie and protein yields (Fig. 3) have no sheet. Supplementary Tables S1-S3 not reachable - None found - web search 2026-10-05 (publisher pages not reachable from this environment). Source file 121_real.pdf.
A19: 173 | B19: 173 | C19: Biswakarma N., Pooniya V., Zhiipao R.R., Kumar D., Shivay Y.S., Das T.K., Roy D., Das B., Choudhary A.K., Swarnalakshmi K., Govindasamy P., Lakhena K.K., Das K., Lama A., Jat R.D., Babu S., Khan S.A. & Behera B. | D19: 2023 | E19: Agriculture, Ecosystems and Environment | F19: Biswakarma N et al. (2023) Identification of a resource-efficient integrated crop management practice for the rice-wheat rotations in south Asian Indo-Gangetic Plains. Agric Ecosyst Environ 357:108675 | G19: https://doi.org/10.1016/j.agee.2023.108675 | H19: India (Delhi) | I19: ICAR-IARI research farm, New Delhi (ICM trial, est. 2015) | J19: 28.633 | K19: 77.15 | L19: 28 deg 38' N | M19: 77 deg 09' E | N19: Paper | O19: ST | P19: 2015 | Q19: 2015-16 to 2020-21; soil 2020 (after 6th rice) | R19: 6 yield years; 1 soil sampling | S19: 0-3 Y to 4-10 Y (per row) | T19: LOAMY | U19: Sandy clay loam | Z19: 4.9 | AA19: 1.52 | AB19: 5 | AC19: 46 | AF19: 642 | AG19: Rice-wheat (ICM1-6); rice-wheat-mungbean (ICM7-8) | AI19: Basmati (not named) | AJ19: rice 100, wheat 120 (100 % RF) or 75 % RF + bio-fertiliser | AK19: 21.8 / 26 | AL19: 41.5 / 33 | AM19: CA: wheat ~3, rice ~5, mungbean ~3 Mg/ha retained | AO19: TREATMENTS IN PAPER (ICAR-IARI New Delhi, est. kharif 2015, RBD 3 reps, 12.5 x 4 m plots; 8 ICM modules): ICM1 puddled TPR + CT wheat (disc + 2 cultivator), 100 % RF, no residue -> DT (annual chisel ploughing 30 cm; author 2026-10-05) ; ICM2 = ICM1 with 75 % RF + NPK bio-fertiliser + AM fungi -> DT ; ICM3 / ICM4 direct-seeded rice after chisel ploughing (30 cm) + furrow-irrigated raised-bed wheat (beds made each year after disc + 2 cultivator), 100 % / 75 % RF + bf -> CT (author 2026-10-05) ; ICM5 / ICM6 ZT-DSR with wheat residue + ZT wheat with rice residue (~3 / ~5 Mg/ha), 100 % / 75 % RF + bf -> CA ; ICM7 / ICM8 = ICM5 / ICM6 + summer mungbean (~3 Mg/ha residue knocked down with paraquat) -> CA. Chisel ploughing (30 cm, 45-HP) every year before rice in ICM1-4, laser levelling, three puddlings (ICM1-2). | AP19: WEY 6 years; RED soil rows at 0-15 / 15-30 / 30-45 cm: BD, porosity (derived), WSA >0.20 mm, GWC (derived), PR, total C, available N/P/K, ALKP, DHA, MBC, urease, SQI; carbon input / output, CER, CSI, carbon footprint | AQ19: Tables S1-S7, Figs S1-S4 - not reachable | AR19: INCLUDED (author coding): DT (ICM1/2), CT (ICM3/4), CA (ICM5-8), rows a-d. SYI radar (Fig. 2) not digitised (values not printed). AUTHOR CODING 2026-10-05: ICM1/2 (chisel 30 cm every year + puddled TPR + CT wheat) -> DT; ICM3/4 (chisel-ploughed DSR + raised-bed wheat after disc + cultivator) -> CT (flag: the paper states chisel ploughing for ICM1-4 alike); ICM5-8 -> CA. ICM2/4/6/8 use 75 % RF + bio-fertiliser + AM (rows b / d, matched fertiliser level). ICM7/8: summer MUNGBEAN third crop + its residue (rows c / d; rule 71). Supplementary Tables S1-S7 not reachable - None found - web search 2026-10-05 (publisher pages not reachable from this environment). Source file 121_now.pdf.
A20: 174 | B20: 174 | C20: Gathala M.K., Jat M.L., Saharawat Y.S., Sharma S.K., Yadvinder-Singh & Ladha J.K. | D20: 2017 | E20: Journal of Ecosystem & Ecography | F20: Gathala MK, Jat ML, Saharawat YS, Sharma SK, Yadvinder-Singh & Ladha JK (2017) Physical and chemical properties of a sandy loam soil under irrigated rice-wheat sequence in the Indo-Gangetic Plains of South Asia. J Ecosys Ecograph 7(3):246 | G20: https://doi.org/10.4172/2157-7625.1000246 | H20: India (Uttar Pradesh) | I20: IIFSR (PDCSR) research farm, Modipuram, Meerut | J20: 29.067 | K20: 77.767 | L20: 29 deg 4' N | M20: 77 deg 46' E | N20: Paper | O20: ST | P20: 2005 | Q20: 2005-06, 2006-07; soil April 2007 | R20: 1 soil sampling (after 2 cycles) | S20: 0-3 Y | T20: LOAMY | U20: Sandy loam (sand 620, silt 205, clay 165 g/kg), Typic Ustochrept | V20: 62 | W20: 20.5 | X20: 16.5 | Y20: 8.1 | Z20: 8.3 | AB20: 5 | AC20: 46 | AF20: 863 | AG20: Rice-wheat (+ Sesbania brown manure in T2/T4/T6) | AH20: PBW 343 | AI20: PHB-71 | AJ20: rice 150, wheat 120 | AK20: 26 / 26 | AL20: 50 / 50 | AM20: Rice residue ~8 Mg/ha mulch in wheat; 2.25 Mg/ha wheat stubble (T2/T4 incorporated, T6 surface) | AN20: Rice irrigated at -20 kPa (15-18 cm); wheat 5 x 60 mm | AO20: TREATMENTS IN PAPER (IIFSR Modipuram, RCBD 3 reps, 6 x 20 m plots, 2 rice-wheat cycles 2005-06 and 2006-07; wheat ZERO-TILL drill-seeded (DSW) in ALL plots): T1 CT-TPR (-S,-WR)/ZT-DSW (-RR): puddled TPR (2 cross harrowings + 2 tyne passes, puddled twice by disc harrow + planking), no Sesbania, wheat stubble removed, rice residue removed; T2 CT-TPR (+S,+WR)/ZT-DSW (+RR): as T1 + Sesbania intercrop 30 d (brown manure), 15-cm wheat stubble incorporated at puddling, ~8 Mg/ha rice residue retained as mulch (Turbo Happy Seeder); T3 CT-DSR (-S,-WR)/ZT-DSW (-RR): dry tillage (2 harrowings 12-15 cm + 2 tyne passes + planking), drill-seeded rice, no residue; T4 CT-DSR (+S,+WR)/ZT-DSW (+RR): as T3 + Sesbania + wheat stubble incorporated by dry tillage + rice residue mulch; T5 ZT-DSR (-S,-WR)/ZT-DSW (-RR); T6 ZT-DSR (+S,+WR)/ZT-DSW (+RR): wheat stubble left on surface + rice residue mulch. Rice 150-26-50 kg N-P-K + 8.75 Zn; wheat 120-26-50. | AP20: 0-15 cm EC, SOC, NH4OAc-K, MACRO (Fig. 2), MICRO (0.106-0.25 mm), WSA (derived), MWD; BD 4 layers (Fig. 1) + porosity (derived); SPR 5-45 cm (Fig. 3); steady IR (Fig. 4) - all figures digitised exactly from vector objects | AQ20: None found - web search 2026-10-05 (publisher pages not reachable from this environment) | AR20: INCLUDED: pZT (T1), pCA (T2), ZT (T3/T5) and CA (T4/T6) rows a/b. Soil temperature (Figs 6-7) and matric potential (Fig. 5) printed only as residue main effects pooled over pZT/ZT or pCA/CA treatments -> not entered (rule 65). Text: minimum soil temperature 1.12-2.21 C higher and maximum 2.2-2.8 C lower with residue in early wheat. PARTIAL CODES: T1 pZT, T2 pCA (puddled rice + ZT wheat). Rows a/b pair the rice establishment of the ZT / CA treatments (a = dry-tilled DSR T3/T4, b = zero-till DSR T5/T6); pZT / pCA repeated in both rows (rule 20, T = 2). FLAG rule 25: T3/T4 rice phase is conventionally DRY-TILLED (unpuddled) - coded ZT / CA like 'CT-DDSR fb ZT'. FLAG: residue treatments T2/T4/T6 also carry Sesbania brown manure (rule 71) and incorporated wheat stubble (T2/T4). Supplementary: None found - web search 2026-10-05 (publisher pages not reachable from this environment). Source file 123.pdf.
A21: 175 | B21: 175 | C21: Hossain M.M., Begum M. & Bell R.W. | D21: 2022 | E21: Research on World Agricultural Economy | F21: Hossain MM, Begum M & Bell RW (2022) Land use, productivity, and profitability of traditional rice-wheat system could be improved by conservation agriculture. Res World Agric Econ 3(2):48-58 (article 516) | G21: https://doi.org/10.36956/rwae.v3i2.516 | H21: Bangladesh | I21: Farmers' field, Bhungnamary village, Gouripur, Mymensingh | J21: 24.4514 | K21: 90.2411 | L21: 24.4514 N | M21: 90.2411 E | N21: Paper | O21: ST | P21: 2016 | Q21: 2016-17, 2017-18 | R21: 2 (pooled) | S21: 0-3 Y | T21: LOAMY | U21: Sandy clay loam (sand 52, silt 20, clay 28 %) | V21: 52 | W21: 20 | X21: 28 | Y21: 6.81 | AB21: 12 | AC21: 33 | AF21: 172 | AG21: Rice-wheat and rice-wheat-mungbean (cropping-system factor) | AH21: BARI Gom 26 | AI21: BRRI hybrid dhan6 | AJ21: rice 120, wheat 90, mungbean 20 | AK21: 22 / 26 / 20 | AL21: 35 / 33 / 15 | AM21: CA: 50 % anchored residue of the previous crop (height basis); TA: none | AN21: Rice rainfed; wheat 3 irrigations; mungbean 2 | AO21: TREATMENTS IN PAPER (on-farm, Bhungnamary village, Gouripur, Mymensingh; RCBD 4 reps, 9 x 5 m plots; 2016-17 and 2017-18): crop establishment TA = traditional agriculture: plough tillage (4 ploughings + cross ploughings by two-wheel tractor), puddled manual transplanting of rice, manual line sowing of wheat / mungbean, three hand weedings, previous crop residue removed; CA = pre-plant glyphosate + SINGLE (strip) tillage by Versatile Multi-crop Planter (6 x 5 cm strips at row spacing; rice transplanted into the strips after 24 h flooding - unpuddled), pre- and post-emergence herbicides, 50 % anchored residue of the previous crop; x cropping system R-W vs R-W-M (summer mungbean after wheat). | AP21: Rice / wheat grain yield, B:C (converted), tillers / spikes m-2, grains per panicle, 1000-grain weight (pooled); REY per system; growth duration | AQ21: None found - web search 2026-10-05 (publisher pages not reachable from this environment) | AR21: INCLUDED: CT (TA) vs MTR (CA, strip / single tillage + residue). No soil data in the paper. Mungbean yields, LUE, PE and Table 6 input costs not entered (no sheets). CA strip tillage + 50 % anchored residue -> MTR (rule 16); TA plough + puddling, no residue -> CT. Paper prints 'average annual rainfall 172 mm' (probably 1720 mm - entered as printed, flag). Supplementary: None found - web search 2026-10-05 (publisher pages not reachable from this environment). Source file 122_real.pdf.
A22: 176 | B22: 176 | C22: Devkota K.P., Lamers J.P.A., Manschadi A.M., Devkota M., McDonald A.J. & Vlek P.L.G. | D22: 2015 | E22: European Journal of Agronomy | F22: Devkota KP, Lamers JPA, Manschadi AM, Devkota M, McDonald AJ & Vlek PLG (2015) Comparative advantages of conservation agriculture based rice-wheat rotation systems under water and salt dynamics typical for the irrigated arid drylands in Central Asia. Eur J Agron 62:98-109 | G22: https://doi.org/10.1016/j.eja.2014.10.002 | H22: Uzbekistan | I22: Khorezm region, Urgench (ZEF/UNESCO experimental station) | J22: 41.55 | K22: 60.63 | L22: 60.050-61.390 N (printed; coordinates swapped in the paper) | M22: 41.130-42.020 E (printed) | N22: Approximate (Urgench, Khorezm; paper swaps lat / long) | O22: TEMP | P22: 2008 | Q22: 2008-2010 | R22: 2 (year-wise) | S22: 0-3 Y | T22: LOAMY | U22: Calcaric gleysol; 0-10 cm sand 23, silt 58, clay 19 % (silt loam; Table 2 of the companion) | V22: 23 | W22: 58 | X22: 19 | Y22: 5.6 | Z22: 3.6 | AA22: 1.35 | AB22: -7 | AC22: 40 | AD22: 13.4 | AF22: 100 | AG22: Rice-wheat (fallow between wheat harvest and rice) | AH22: Krasnodar-99 | AI22: Nukus-2 | AJ22: rice 250-257, wheat 124-233 | AK22: 120 / 100-140 P2O5 | AL22: 80 / 70 K2O | AM22: R50 1.5-4.1, R100 3.0-6.7 t/ha standing straw (Table 2) | AN22: DSR AWD (20 kPa at 20 cm); WSR continuous flooding; wheat furrow / flood irrigated | AO22: TREATMENTS IN PAPER (ZEF/UNESCO Khorezm project, Urgench, Uzbekistan; 2008-2010; laser-levelled, deep-ploughed once before the trial (May 2008); 400 m2 DSR plots, 2000 m2 WSR plots, 4 reps; DSR treatments 70 m from the flooded WSR): DSRB-SSW-R0 / R50 / R100: zero-till dry-seeded rice on PERMANENT raised beds (67 cm, made once in 2008), AWD irrigation (20 kPa at 20 cm), followed by wheat surface-seeded / zero-till drilled on the same beds; residue R0 = farmer harvest (3-5 cm stubble, ~95 % removed), R50 = 15-20 cm standing straw, R100 = 35-40 cm standing straw (R50 1.5-4.1, R100 3.0-6.7 t/ha); DSRF-SSW-R0 / R50 / R100: the same on the flat; WSRF-SSW-FI: conventional (dry) tillage, water-seeded rice continuously flooded (5-15 cm), wheat surface-seeded into the standing rice 17-22 d before harvest, no residue; WSRF-SSW-AWD (2009 only): as WSRF with AWD, CT non-puddled. | AP22: Gross margin and B:C (rice, wheat, system; 2 years), wheat-season ECe at 5 layers (Fig. 3, R0 vs R100) | AQ22: None found - web search 2026-10-05 (publisher pages not reachable from this environment) | AR22: INCLUDED: ZT (R0) vs CA (R50 / R100) rows a-d. PENDING (author): WSRF-SSW-FI / -AWD. Irrigation water (Fig. 1, bed vs flat pooled over residue), infiltration (Fig. 2, DSR vs fallow) and groundwater (Figs 4-5, DSR vs WSR) not entered (no code contrast). Rows a-d (rule 20, T = 4 CA treatments; ZT bed / flat repeated). Permanent beds without / with residue -> ZT / CA (rule 15). WSRF treatments left out pending the author (values in Notes). Arid irrigated drylands (<100 mm rain). Supplementary: None found - web search 2026-10-05 (publisher pages not reachable from this environment). Source file 124.pdf.
A23: 176 (companion) | B23: 176 (companion) | C23: Devkota K.P., Hoogenboom G., Boote K.J., Singh U., Lamers J.P.A., Devkota M. & Vlek P.L.G. | D23: 2015 | E23: Agricultural and Forest Meteorology | F23: Devkota KP, Hoogenboom G, Boote KJ, Singh U, Lamers JPA, Devkota M & Vlek PLG (2015) Simulating the impact of water saving irrigation and conservation agriculture practices for rice-wheat systems in the irrigated semi-arid drylands of Central Asia. Agric For Meteorol 214-215:266-280 | G23: https://doi.org/10.1016/j.agrformet.2015.08.264 | H23: Uzbekistan | I23: Khorezm region, Urgench (ZEF/UNESCO experimental station) | J23: 41.55 | K23: 60.63 | N23: As 176 | O23: TEMP | P23: 2008 | Q23: 2008-2010 (measured); 1971-2010 (simulated) | R23: 2 measured; 39 simulated | S23: 0-3 Y | T23: LOAMY | V23: 23 | W23: 58 | X23: 19 | Z23: 3.6 | AA23: 1.35 | AG23: Rice-wheat | AH23: Krasnodar-99 | AI23: Nukus-2 | AO23: TREATMENTS IN PAPER (ZEF/UNESCO Khorezm project, Urgench, Uzbekistan; 2008-2010; laser-levelled, deep-ploughed once before the trial (May 2008); 400 m2 DSR plots, 2000 m2 WSR plots, 4 reps; DSR treatments 70 m from the flooded WSR): DSRB-SSW-R0 / R50 / R100: zero-till dry-seeded rice on PERMANENT raised beds (67 cm, made once in 2008), AWD irrigation (20 kPa at 20 cm), followed by wheat surface-seeded / zero-till drilled on the same beds; residue R0 = farmer harvest (3-5 cm stubble, ~95 % removed), R50 = 15-20 cm standing straw, R100 = 35-40 cm standing straw (R50 1.5-4.1, R100 3.0-6.7 t/ha); DSRF-SSW-R0 / R50 / R100: the same on the flat; WSRF-SSW-FI: conventional (dry) tillage, water-seeded rice continuously flooded (5-15 cm), wheat surface-seeded into the standing rice 17-22 d before harvest, no residue; WSRF-SSW-AWD (2009 only): as WSRF with AWD, CT non-puddled. Simulation-only scenarios 9-11 (WSRF puddled, CT-DSR, CT-DSR + DPUS). | AP23: Measured rice and wheat grain yields 2008 and 2009 (Figs 3A / 4, vector); MODEL OUTPUT (DSSAT 1971-2010): yields, N uptake, N leached | AQ23: None found - web search 2026-10-05 (publisher pages not reachable from this environment) | AR23: COMPANION of 176. Biomass / LAI dynamics (Figs 2-3), mineral N (Fig. 5, WSR vs pooled DSR) and soil moisture (Fig. 6, one treatment) not entered (no sheet or no code contrast). Initial soil profile (Table 2): BD 1.35-1.57, SOC 0.36-0.19 %, NH4-N 5.2-6.5, NO3-N 3.9-5.3 mg/kg, Olsen P 17.6-27.9, Ex-K 76.8-98.5 mg/kg. COMPANION of 176 (same Khorezm trial, 2008-2010; rule 5). Rows a-d (rule 20, T = 4 CA treatments; ZT bed / flat repeated). Permanent beds without / with residue -> ZT / CA (rule 15). WSRF treatments left out pending the author (values in Notes). Arid irrigated drylands (<100 mm rain). Supplementary: None found - web search 2026-10-05 (publisher pages not reachable from this environment). Source file 124_real.pdf.
A24: 115 (companion) | B24: 115 (companion) | C24: Pokharel D., Jha R.K., Tiwari T.P., Gathala M.K., Shrestha H.K. & Panday D. | D24: 2018 | E24: Cogent Food & Agriculture | F24: Pokharel D, Jha RK, Tiwari TP, Gathala MK, Shrestha HK & Panday D (2018) Is conservation agriculture a potential option for cereal-based sustainable farming system in the Eastern Indo-Gangetic Plains of Nepal? Cogent Food Agric 4:1557582 | G24: https://doi.org/10.1080/23311932.2018.1557582 | H24: Nepal | I24: Sunsari district (SRFSI nodes Mahendranagar, Bhokraha, Kaptanjung, Simariya, Bhaluwa) | J24: 26.67 | K24: 87.13 | L24: 26 deg 25' to 26 deg 55' N | M24: 86 deg 55' to 87 deg 21' E | N24: Paper (district range; centre used) | O24: ST | P24: 2014 | Q24: 2015-2016 | R24: 2 (pooled) | S24: 0-3 Y | T24: LOAMY | U24: Clay loam to silty clay loam (sandy loam at Kaptanjung) | AB24: 10 | AC24: 43 | AF24: 1943 | AG24: Rice-wheat (lowland); rice-maize (upland, excluded) | AO24: TREATMENTS IN PAPER (SRFSI project, Sunsari district, Nepal; 5 nodes; 2015-2016; rice-wheat on lowland): CTTPR+CTW = conventional tillage with massive puddling and manual transplanting of rice + conventional (multiple-tillage) wheat; CTTPR+ZTW = puddled TPR + zero-till drilled wheat; ZTDSR+ZTW = zero-till direct-seeded rice + ZT wheat; UPTPR+ZTW = unpuddled mechanically (or manually) transplanted rice + ZT wheat. Residue not described in this paper (SRFSI protocol in Islam et al. 2019, old-master 115: ZT crops into 15-20 cm anchored stubble). Rice-maize system (upland) with the same rice treatments + CTM / ZTM. | AP24: Rice yield (Table 1); system grain yield, straw (derived), net profit, B:C (converted) (Table 3) | AQ24: None found - web search 2026-10-05 (publisher pages not reachable from this environment) | AR24: INCLUDED as companion of 115: CT, pCA, CA rows a/b. Survey data (Table 4), input rates (Fig. 2) and weed-control costs (Fig. 3) not entered (no sheets). COMPANION of old-master 115 (Islam S. et al. 2019, SRFSI on-farm trials incl. Sunsari, same four treatments; rule 5) - Sunsari subset, different data set (DUPLICATE FLAG for the 2015-16 seasons). Coding follows 115 with the partial code now available: CTTPR+ZTW -> pCA (excluded in 115, rules 85/86); residue retention is NOT stated in this paper - taken from 115 (rule 89, flag). Rice-maize system excluded (rule 31). Supplementary: None found - web search 2026-10-05 (publisher pages not reachable from this environment). Source file 123_real.pdf.

Sheet PARAMETERS_BY_STUDY
A1: PARAMETERS OF EACH STUDY - auto-generated from the data sheets (2026-10-05); regenerated at every build
A3: No. | B3: Serial | C3: Authors | D3: Year | E3: Journal | F3: Status | G3: Data rows | H3: No. of parameters (sheets) | I3: Parameters in this workbook (sheet: rows) | J3: Parameters extracted (Study_Info, paper-level description)
A4: 1 | B4: 164 | C4: Yadav R.L., Dwivedi B.S., Prasad K., Tomar O.K., Shurpali N.J. & Pandey P.S. | D4: 2000 | E4: Field Crops Research | F4: INCLUDED | G4: 120 | H4: 5 | I4: SOC(active C pool): 7; N: 4; P: 7; K: 7; YIELD: 95 | J4: YIELD (year-wise rice & wheat, 7 sites); SOC; available N (4 sites), P, K (final year)
A5: 2 | B5: 165 | C5: Davari M.R., Sharma S.N. & Mirzakhani M. | D5: 2012 | E5: Biological Agriculture & Horticulture | F5: INCLUDED | G5: 38 | H5: 14 | I5: BD: 2; POROSITY: 2; HC: 2; SOC(active C pool): 4; RESP: 2; P: 4; K: 4; total N: 4; MBC: 2; DHA: 2; Actinomycetes: 2; Soil microbial count: 2; Fungal count: 2; YIELD: 4 | J5: Rice, wheat, rice-equivalent yield (year-wise); SOC, Kjeldahl N, Olsen P, NH4OAc K (year-wise); BD, porosity, HC; bacteria, fungi, actinomycetes, MBC, DHA, CO2 evolution
A6: 3 | B6: 166 | C6: Das B., Chakraborty D., Singh V.K., Aggarwal P., Singh R., Dwivedi B.S. & Mishra R.P. | D6: 2014 | E6: Soil & Tillage Research | F6: INCLUDED | G6: 53 | H6: 13 | I6: MWD 1: 6; WSA: 3; MACRO: 3; MICRO: 3; macro c: 3; micro c: 3; AWC (weight basis): 6; AWC (volume basis): 6; FC (weight basis): 6; PWP (weight basis): 6; TOC: 3; cPOM-C: 3; YIELD: 2 | J6: TOC; macro/micro aggregates, WSA (derived), MWD (slaked + capillary), macro-C, micro-C, cPOM-C; aggregate FC/PWP/AWC; yields (3-yr means)
A7: 4 | B7: 167 | C7: Naz A., Rebi A., Naz R., Akbar M.U., Aslam A., Kalsom A., Niaz A., Ahmad M.I., Nawaz S., Kausar R., Ali B., Saleem M.H. & Zhou J. | D7: 2023 | E7: Land | F7: EXCLUDED | G7: 0 | H7: 0 | I7: - | J7: NONE (excluded)
A8: 5 | B8: 168 | C8: Dhaliwal J.K., Singh M.J., Sharma S., Gupta N. & Kukal S.S. | D8: 2020 | E8: Soil Research | F8: INCLUDED | G8: 27 | H8: 19 | I8: BD: 2; POROSITY: 2; MWD 1: 2; WSA: 2; MACRO: 2; MICRO: 2; IR: 1; AWC (weight basis): 1; AWC (volume basis): 1; FC (weight basis): 1; PWP (weight basis): 1; SOC(active C pool): 2; stock-SOC: 2; RESP: 1; MBC: 1; DHA: 1; ACP: 1; ALKP: 1; UREASE: 1 | J8: SOC, SOC stock, macro/micro WSA, WSA (derived), MWD, BD, porosity (derived), IR (initial + steady), FC/PWP/AWC, MBC, BSR, DHA, urease, ALP, ACP
A9: 6 | B9: 169 | C9: Singh V.K., Dwivedi B.S., Shukla A.K., Chauhan Y.S. & Yadav R.L. | D9: 2005 | E9: Field Crops Research | F9: EXCLUDED | G9: 0 | H9: 0 | I9: - | J9: NONE (excluded)
A10: 7 | B10: 23 (companion 3) | C10: Jat H.S., Datta A., Choudhary M., Yadav A.K., Choudhary V., Sharma P.C., Gathala M.K., Jat M.L. & McDonald A. | D10: 2019 | E10: Soil & Tillage Research | F10: INCLUDED | G10: 46 | H10: 11 | I10: MWD 1: 4; GMD 1: 4; WSA: 4; MACRO: 4; MICRO: 4; macro c: 4; micro c: 4; SOC(active C pool): 4; TOC: 4; PSOC: 4; YIELD: 6 | J10: WB-C, TOC, macro/micro WSA, WSA, MWD, GMD, macro-C, micro-C, POC (2013, 2015, 2 depths); REY 6 years
A11: 8 | B11: 23 (companion 4) | C11: Jat H.S., Datta A., Choudhary M., Sharma P.C., Yadav A.K., Choudhary V., Gathala M.K., Jat M.L. & McDonald A. | D11: 2019 | E11: Catena (accepted manuscript; version of record S0341816219301936) | F11: INCLUDED | G11: 25 | H11: 13 | I11: VLC(Cfrac1): 2; LC(Cfrac2): 2; LLC(Cfrac3): 2; NLC(Cfrac4): 2; stock-SOC: 2; RESP: 1; MBC: 2; MBN: 2; DHA: 2; ALKP: 2; Actinomycetes: 2; Soil microbial count: 2; Fungal count: 2 | J11: SOC stock; VL/L/LL/NL C (derived g/kg); DHA, ALP, MBC, MBN, BSR, fungi, bacteria, actinomycetes (2 depths)
A12: 9 | B12: 165 (companion) | C12: Meena A.L., Pandey R.N., Kumar D., Dotaniya M.L., Sharma V.K., Singh G., Meena B.P., Kumar A. & Bhanu C. | D12: 2020 | E12: Communications in Soil Science and Plant Analysis | F12: INCLUDED | G12: 136 | H12: 17 | I12: BD: 8; POROSITY: 8; MWD 1: 8; GMD 1: 8; HC: 8; WHC: 8; SOC(active C pool): 8; stock-SOC: 8; PH: 8; EC: 8; N: 8; P: 8; Fe(ppm): 8; Mn: 8; Cu(ppm): 8; Zn(ppm): 8; YIELD: 8 | J12: BD, porosity (derived), WHC, MWD, GMD, Ks, pH, EC, SOC, C stock, available N, P, DTPA Cu/Zn/Mn/Fe, rice grain and straw yield
A13: 10 | B13: 131 (companion) | C13: Zhang Y.-P., Li X., He H.-J., Zhou H., Geng D.-Y. & Zhang Y.-Z. | D13: 2023 | E13: Sustainability | F13: INCLUDED | G13: 50 | H13: 16 | I13: BD: 9; POROSITY: 9; MWD 1: 3; MWDA: 3; MACRO: 3; SOC(active C pool): 3; stock-SOC: 3; c sequestration rate: 1; N: 3; P: 3; K: 3; total N: 3; YIELD: 1; PANICLE-SPIKE DENSITY: 1; GRAINS PER PANICLE: 1; 1000-GRAIN WEIGHT: 1 | J13: BD (2018-20, 3 layers), porosity (derived), water-stable macro-aggregates, MWD (wet, dry), SOC, total N, alkali-N, P, K, SOC stock and sequestration (derived), rice/wheat yield and components
A14: 11 | B14: 170 | C14: Kukal S.S. & Aggarwal G.C. | D14: 2003 | E14: Soil & Tillage Research | F14: INCLUDED | G14: 49 | H14: 3 | I14: BD: 18; POROSITY: 16; PR: 15 | J14: BD per layer 0-5 ... 22-24 cm at rice harvest (red) and after wheat seedbed preparation 1996 (Fig. 1, digitised; ZT from Table 3), porosity (derived), SPR per 5-cm layer to 30 cm at both stages (Fig. 2, digitised), BD 14-20 cm 1994-95 and SPR 15-20 cm 1994-96 at rice harvest (Tables 4-5, red)
A15: 12 | B15: 15 (companion 2) | C15: Gathala M.K., Ladha J.K., Saharawat Y.S., Kumar V., Kumar V. & Sharma P.K. | D15: 2011 | E15: Soil Science Society of America Journal | F15: INCLUDED | G15: 114 | H15: 13 | I15: BD: 8; POROSITY: 8; MWD 1: 2; WSA: 2; MACRO: 12; MICRO: 2; PR: 18; IR: 12; LLWR: 4; SOIL TEMP: 40; SOC(active C pool): 2; stock-SOC: 2; YIELD: 2 | J15: BD (4 layers), porosity (derived), SPR (every 5 cm to 45 cm, digitised), WSA >0.25 mm (6 yr), water-stable aggregate size classes (7 classes, digitised) and MWD (derived), steady infiltration (6 yr), SOC 0-15 cm, SOC stock (derived), LLWR 0-5 / 6-10 cm (Fig. 5), weekly soil temperature at 5 cm (Fig. 3, 20 weeks x 0700 / 1500 h), 7-yr mean yields (duplicate flag)
A16: 13 | B16: 40 (companion) | C16: Kader M.A., Jahangir M.M.R., Islam M.R., Begum R., Nasreen S.S., Islam Md.R., Mahmud A.Al., Haque M.E., Bell R.W. & Jahiruddin M. | D16: 2022 | E16: Field Crops Research | F16: INCLUDED | G16: 47 | H16: 10 | I16: BD: 2; POROSITY: 2; SOC(active C pool): 2; stock-SOC: 2; c sequestration rate: 2; total N: 2; MBC: 2; YIELD: 15; NUE: 9; NET RETURN: 9 | J16: BD, porosity (derived), total N, SOC, MBC, SOC stock, C sequestration (derived) - 0-15 cm rows a/b; rice & wheat yields 2018-21 x 5 N rates (digitised); NUE (PFP, AE) x N; gross margin 9 yr
A17: 14 | B17: 23 (companion 5) | C17: Roy D., Datta A., Jat H.S., Choudhary M., Sharma P.C., Singh P.K. & Jat M.L. | D17: 2022 | E17: Geoderma | F17: INCLUDED | G17: 70 | H17: 22 | I17: BD: 3; POROSITY: 3; PR: 9; IR: 1; GWC: 3; SOC(active C pool): 3; stock-SOC: 3; PH: 3; EC: 3; N: 3; P: 3; K: 3; Fe(ppm): 3; Mn: 3; Cu(ppm): 3; Zn(ppm): 3; MBC: 3; DHA: 3; B-GLU: 3; ACP: 3; ALKP: 3; SQI: 3 | J17: 0-5, 5-15, 15-30 cm: BD, porosity (derived), GWC (derived), pH, EC, SOC, SOC stock, available N/P/K, DTPA Fe/Zn/Cu/Mn, MBC, DHA, ACP, ALKP, B-GLU, SQI; SPR x 9 layers (digitised); steady infiltration
A18: 15 | B18: 171 | C18: Ghimire R., Adhikari K.R., Chen Z.-S., Shah S.C. & Dahal K.R. | D18: 2012 | E18: Paddy and Water Environment | F18: INCLUDED | G18: 9 | H18: 2 | I18: SOC(active C pool): 5; stock-SOC: 4 | J18: SOC stock 0-5, 5-10, 10-15, 15-30, 30-50 cm (Table 4) -> SOC concentration (derived, BD 1.07) and cumulative stocks 0-10 / 0-15 / 0-30 / 0-50 cm
A19: 16 | B19: 172 | C19: Tirol-Padre A., Tsuchiya K., Inubushi K. & Ladha J.K. | D19: 2005 | E19: Soil Science and Plant Nutrition | F19: INCLUDED | G19: 76 | H19: 14 | I19: SOC(active C pool): 3; TC(total c): 3; WSC: 3; POXC(KMnO4-C): 3; RESP: 6; PH: 3; CEC: 3; P: 3; total N: 3; EX-K: 3; no3,nh4,PMN: 6; MBC: 6; YIELD: 28; N uptake: 3 | J19: RED soil rows (+N tier): pH, Olsen P (kg/ha, assumed depth), Ex-K, CEC, total C, organic C, total N, MBC and basal respiration (aerobic / flooded incubations), hot-water C, POXC, PMN; rice yield 12 years (Fig. 1, digitised); rice N uptake
A20: 17 | B20: 124 (companion) | C20: Hoque M.A., Gathala M.K., Timsina J., Ziauddin M.A.T.M., Hossain M. & Krupnik T.J. | D20: 2023 | E20: Field Crops Research | F20: INCLUDED | G20: 6 | H20: 3 | I20: YIELD: 2; BC ratio: 2; NET RETURN: 2 | J20: SREY, system gross margin, B:C (derived) - R-W and R-W-MB, CT / MTR / pMTR (AT added)
A21: 18 | B21: 173 | C21: Biswakarma N., Pooniya V., Zhiipao R.R., Kumar D., Shivay Y.S., Das T.K., Roy D., Das B., Choudhary A.K., Swarnalakshmi K., Govindasamy P., Lakhena K.K., Das K., Lama A., Jat R.D., Babu S., Khan S.A. & Behera B. | D21: 2023 | E21: Agriculture, Ecosystems and Environment | F21: INCLUDED | G21: 212 | H21: 20 | I21: BD: 12; POROSITY: 12; MACRO: 12; PR: 12; GWC: 12; TC(total c): 12; N: 12; P: 12; K: 12; MBC: 12; DHA: 12; ALKP: 12; UREASE: 12; YIELD: 24; SQI: 12; C input: 4; C output: 4; CSI: 4; CER: 4; GHG intensity: 4 | J21: WEY 6 years; RED soil rows at 0-15 / 15-30 / 30-45 cm: BD, porosity (derived), WSA >0.20 mm, GWC (derived), PR, total C, available N/P/K, ALKP, DHA, MBC, urease, SQI; carbon input / output, CER, CSI, carbon footprint
A22: 19 | B22: 174 | C22: Gathala M.K., Jat M.L., Saharawat Y.S., Sharma S.K., Yadvinder-Singh & Ladha J.K. | D22: 2017 | E22: Journal of Ecosystem & Ecography | F22: INCLUDED | G22: 50 | H22: 11 | I22: BD: 8; POROSITY: 8; MWD 1: 2; WSA: 2; MACRO: 2; MICRO: 2; PR: 18; IR: 2; SOC(active C pool): 2; EC: 2; K: 2 | J22: 0-15 cm EC, SOC, NH4OAc-K, MACRO (Fig. 2), MICRO (0.106-0.25 mm), WSA (derived), MWD; BD 4 layers (Fig. 1) + porosity (derived); SPR 5-45 cm (Fig. 3); steady IR (Fig. 4) - all figures digitised exactly from vector objects
A23: 20 | B23: 175 | C23: Hossain M.M., Begum M. & Bell R.W. | D23: 2022 | E23: Research on World Agricultural Economy | F23: INCLUDED | G23: 9 | H23: 6 | I23: YIELD: 3; PANICLE-SPIKE DENSITY: 1; GRAINS PER PANICLE: 1; 1000-GRAIN WEIGHT: 1; DAYS TO MATURITY: 2; BC ratio: 1 | J23: Rice / wheat grain yield, B:C (converted), tillers / spikes m-2, grains per panicle, 1000-grain weight (pooled); REY per system; growth duration
A24: 21 | B24: 176 | C24: Devkota K.P., Lamers J.P.A., Manschadi A.M., Devkota M., McDonald A.J. & Vlek P.L.G. | D24: 2015 | E24: European Journal of Agronomy | F24: INCLUDED | G24: 26 | H24: 3 | I24: EC: 10; BC ratio: 8; NET RETURN: 8 | J24: Gross margin and B:C (rice, wheat, system; 2 years), wheat-season ECe at 5 layers (Fig. 3, R0 vs R100)
A25: 22 | B25: 176 (companion) | C25: Devkota K.P., Hoogenboom G., Boote K.J., Singh U., Lamers J.P.A., Devkota M. & Vlek P.L.G. | D25: 2015 | E25: Agricultural and Forest Meteorology | F25: INCLUDED | G25: 28 | H25: 3 | I25: NO3 leaching: 8; YIELD: 12; N uptake: 8 | J25: Measured rice and wheat grain yields 2008 and 2009 (Figs 3A / 4, vector); MODEL OUTPUT (DSSAT 1971-2010): yields, N uptake, N leached
A26: 23 | B26: 115 (companion) | C26: Pokharel D., Jha R.K., Tiwari T.P., Gathala M.K., Shrestha H.K. & Panday D. | D26: 2018 | E26: Cogent Food & Agriculture | F26: INCLUDED | G26: 10 | H26: 4 | I26: YIELD: 4; SYS STRAW: 2; BC ratio: 2; NET RETURN: 2 | J26: Rice yield (Table 1); system grain yield, straw (derived), net profit, B:C (converted) (Table 3)

Sheet STUDIES_BY_PARAMETER
A1: STUDIES OF EACH PARAMETER SHEET - auto-generated (2026-10-05); 'NO DATA' = none of the entered studies reports this parameter
A3: No. | B3: Parameter sheet | C3: Unit | D3: Data rows | E3: No. of studies | F3: Studies (serial: rows)
A4: 1 | B4: BD | C4: Mg/m3 | D4: 72 | E4: 10 | F4: 168: 2; 165: 2; 131 (companion): 9; 165 (companion): 8; 15 (companion 2): 8; 40 (companion): 2; 23 (companion 5): 3; 170: 18; 173: 12; 174: 8
A5: 2 | B5: PD | C5: Mg/m3 | D5: 0 | E5: 0 | F5: NO DATA
A6: 3 | B6: POROSITY | C6: % v/v | D6: 70 | E6: 10 | F6: 168: 2; 165: 2; 131 (companion): 9; 165 (companion): 8; 15 (companion 2): 8; 40 (companion): 2; 23 (companion 5): 3; 170: 16; 173: 12; 174: 8
A7: 4 | B7: macro pore | C7: % v/v | D7: 0 | E7: 0 | F7: NO DATA
A8: 5 | B8: meso pore | C8: % v/v | D8: 0 | E8: 0 | F8: NO DATA
A9: 6 | B9: micro pore | C9: % v/v | D9: 0 | E9: 0 | F9: NO DATA
A10: 7 | B10: MWD 1 | C10: mm (wet sieving) | D10: 27 | E10: 7 | F10: 168: 2; 166: 6; 131 (companion): 3; 23 (companion 3): 4; 165 (companion): 8; 15 (companion 2): 2; 174: 2
A11: 8 | B11: MWDA | C11: mm (dry sieving) | D11: 3 | E11: 1 | F11: 131 (companion): 3
A12: 9 | B12: GMD 1 | C12: mm | D12: 12 | E12: 2 | F12: 23 (companion 3): 4; 165 (companion): 8
A13: 10 | B13: WSA | C13: g/g soil (water-stable aggregates = sum of ALL water-stable fractions > 0.053 mm; % / 100) | D13: 13 | E13: 5 | F13: 168: 2; 166: 3; 23 (companion 3): 4; 15 (companion 2): 2; 174: 2
A14: 11 | B14: MACRO | C14: % (>0.25 mm aggregates) | D14: 38 | E14: 7 | F14: 168: 2; 166: 3; 131 (companion): 3; 23 (companion 3): 4; 15 (companion 2): 12; 173: 12; 174: 2
A15: 12 | B15: MICRO | C15: % (<0.25 mm aggregates) | D15: 13 | E15: 5 | F15: 168: 2; 166: 3; 23 (companion 3): 4; 15 (companion 2): 2; 174: 2
... A140: 137 | B140: GHG intensity | C140: kg CO2-eq/kg grain (yield-scaled GWP) | D140: 4 | E140: 1 | F140: 173: 4
A141: 138 | B141: AGG-TP | D141: 0 | E141: 0 | F141: NO DATA
A142: 139 | B142: AGG-AvP | D142: 0 | E142: 0 | F142: NO DATA
A143: 140 | B143: AGG-ALKP | D143: 0 | E143: 0 | F143: NO DATA
A144: 141 | B144: AGG-PhytinP | D144: 0 | E144: 0 | F144: NO DATA
A145: 142 | B145: LLWR | C145: % v/v | D145: 4 | E145: 1 | F145: 15 (companion 2): 4
A146: 143 | B146: SOIL TEMP | C146: deg C | D146: 40 | E146: 1 | F146: 15 (companion 2): 40

Sheet Treatment_Mapping
A1: No. | B1: SERIAL NO | C1: Authors | D1: Year | E1: Paper's treatment label (verbatim) | F1: Full description from paper | G1: Rice-phase tillage | H1: Wheat-phase tillage | I1: Residue retained? | J1: Residue rate (t/ha) | K1: ASSIGNED CODE | L1: Rationale | M1: Confidence | N1: Status
A2: 164 | B2: 164 | C2: Yadav R.L. et al. | D2: 2000 | E2: Control | F2: No fertiliser or manure to either crop | G2: Puddled TPR | H2: Conventional (not described) | I2: No | K2: EXCLUDED | L2: Unfertilised control (rule 34) | M2: High | N2: EXCLUDED
A3: 164 | B3: 164 | C3: Yadav R.L. et al. | D3: 2000 | E3: 50F | F3: 50% NPK to rice, 100% to wheat | G3: Puddled TPR | H3: Conventional | I3: No | K3: EXCLUDED | L3: Sub-optimal fertiliser tier, no residue/tillage contrast | M3: High | N3: EXCLUDED
A4: 164 | B4: 164 | C4: Yadav R.L. et al. | D4: 2000 | E4: 100F | F4: 100% recommended NPK (120-26-33) to rice and wheat; all biomass removed | G4: Puddled TPR | H4: Conventional | I4: No | K4: CT | L4: Conventional rice + wheat, residue removed | M4: Medium (wheat tillage not described) | N4: INCLUDED
A5: 164 | B5: 164 | C5: Yadav R.L. et al. | D5: 2000 | E5: 50F + FYM | F5: 50% NPK + 50% N through FYM to rice; 100% NPK wheat | G5: Puddled TPR | H5: Conventional | I5: No | K5: EXCLUDED | L5: Amendment (FYM), rule 34 | M5: High | N5: EXCLUDED
A6: 164 | B6: 164 | C6: Yadav R.L. et al. | D6: 2000 | E6: 50F + CR | F6: 50% NPK + 50% N through wheat crop residue incorporated 1 month before rice; 100% NPK wheat | G6: Puddled TPR | H6: Conventional | I6: Yes (wheat straw to rice) | J6: 8.8-15.8 by site | K6: CTR | L6: Straw return with fertiliser cut to offset -> CTR FLAGGED (rule 62) | M6: Medium | N6: INCLUDED - FLAGGED
A7: 164 | B7: 164 | C7: Yadav R.L. et al. | D7: 2000 | E7: 50F + GM | F7: 50% NPK + 50% N through Sesbania green manure to rice; 100% NPK wheat | G7: Puddled TPR | H7: Conventional | I7: No (GM) | K7: EXCLUDED | L7: Green manure in a conventional system - amendment; GM only supports CA (rule 71) | M7: High | N7: EXCLUDED
A8: 165 | B8: 165 | C8: Davari M.R. et al. | D8: 2012 | E8: RW-RR | F8: Rice-wheat, residue removed (organic, FYM 60 kg N) | G8: Puddled (offset disc) | H8: Heavy disc + disk & plank x2 | I8: No | K8: CT | L8: Conventional in both phases | M8: High | N8: INCLUDED
A9: 165 | B9: 165 | C9: Davari M.R. et al. | D9: 2012 | E9: RW-RI | F9: Rice-wheat, all residue incorporated | G9: Puddled (offset disc) | H9: Heavy disc + disk & plank x2 | I9: Yes (incorporated) | J9: 14.2-16.0 Mg DM/yr | K9: CTR | L9: Conventional + residue incorporation | M9: High | N9: INCLUDED
A10: 165 | B10: 165 | C10: Davari M.R. et al. | D10: 2012 | E10: RWM-RR | F10: Rice-wheat-mungbean, residue removed | G10: Puddled (offset disc) | H10: Heavy disc + disk & plank x2 | I10: No | K10: CT | L10: Conventional; summer mungbean in both RWM treatments (flag) | M10: High | N10: INCLUDED
A11: 165 | B11: 165 | C11: Davari M.R. et al. | D11: 2012 | E11: RWM-RI | F11: Rice-wheat-mungbean, all residue incorporated | G11: Puddled (offset disc) | H11: Heavy disc + disk & plank x2 | I11: Yes (incorporated) | J11: 17.8-19.7 Mg DM/yr | K11: CTR | L11: Conventional + residue; mungbean in both (flag) | M11: High | N11: INCLUDED
A12: 166 | B12: 166 | C12: Das B. et al. | D12: 2014 | E12: T1 | F12: Unfertilised | G12: Puddled TPR | H12: Dry tillage | I12: No | K12: EXCLUDED | L12: Unfertilised control | M12: High | N12: EXCLUDED
A13: 166 | B13: 166 | C13: Das B. et al. | D13: 2014 | E13: T2 | F13: Recommended NPK (+Zn rice) through fertilisers | G13: Puddled TPR | H13: Dry tillage (conventional) | I13: No | K13: CT | L13: Conventional, residue removed | M13: High | N13: INCLUDED
A14: 166 | B14: 166 | C14: Das B. et al. | D14: 2014 | E14: T3 | F14: NPK + Zn + S | G14: Puddled TPR | H14: Dry tillage | I14: No | K14: EXCLUDED | L14: Nutrient tier (S), no residue contrast | M14: High | N14: EXCLUDED
A15: 166 | B15: 166 | C15: Das B. et al. | D15: 2014 | E15: T4 | F15: 75% NPK + 25% N via FYM (rice) | G15: Puddled TPR | H15: Dry tillage | I15: No | K15: EXCLUDED | L15: Amendment (FYM) | M15: High | N15: EXCLUDED
A16: 166 | B16: 166 | C16: Das B. et al. | D16: 2014 | E16: T5 | F16: 75% NPK + 25% N via sulphitation press mud (rice) | G16: Puddled TPR | H16: Dry tillage | I16: No | K16: EXCLUDED | L16: Amendment (press mud) | M16: High | N16: EXCLUDED
A17: 166 | B17: 166 | C17: Das B. et al. | D17: 2014 | E17: T6 | F17: 75% NPK + green gram residue before rice | G17: Puddled TPR | H17: Dry tillage | I17: Green gram residue | K17: EXCLUDED | L17: Third crop (green gram) in some treatments only (rule 30); GM only supports CA | M17: High | N17: EXCLUDED
A18: 166 | B18: 166 | C18: Das B. et al. | D18: 2014 | E18: T7 | F18: T6 + 75% NPK + 25% N via FYM (wheat) | G18: Puddled TPR | H18: Dry tillage | I18: Green gram residue | K18: EXCLUDED | L18: Third crop + FYM | M18: High | N18: EXCLUDED
A19: 166 | B19: 166 | C19: Das B. et al. | D19: 2014 | E19: T8 | F19: 75% NPK + 25% N via wheat straw (rice) and rice straw (wheat) | G19: Puddled TPR | H19: Dry tillage (straw incorporated) | I19: Yes (both crops) | J19: N-equivalent (61.5 + 47.7 Mg C over 18 yr) | K19: CTR | L19: Straw return with fertiliser cut -> CTR FLAGGED (rule 62) | M19: Medium | N19: INCLUDED - FLAGGED
A20: 167 | B20: 167 | C20: Naz A. et al. | D20: 2023 | E20: Control / NPK / GM100 / GM75 / GM50 | F20: Rice-berseem; berseem GM with 100/75/50% RDF vs NPK and control | G20: Puddled TPR | H20: No wheat (berseem) | I20: No | K20: EXCLUDED | L20: Not a rice-wheat tillage/residue study | M20: High | N20: EXCLUDED
A21: 168 | B21: 168 | C21: Dhaliwal J.K. et al. | D21: 2020 | E21: CTW-CTDSR (-M) | F21: CT wheat (disc + tyne harrow + plank) after CT dry-seeded rice, residue removed | G21: CT DSR | H21: CT | I21: No | K21: CT | L21: Conventional both phases | M21: High | N21: INCLUDED
A22: 168 | B22: 168 | C22: Dhaliwal J.K. et al. | D22: 2020 | E22: CTW+M-CTDSR | F22: As above + 7 t/ha rice residue mulch in wheat | G22: CT DSR | H22: CT | I22: Yes (surface mulch) | J22: 7 | K22: CTR | L22: Conventional + residue | M22: High | N22: INCLUDED
A23: 168 | B23: 168 | C23: Dhaliwal J.K. et al. | D23: 2020 | E23: ZTW-ZTDSR | F23: ZT wheat (Turbo Happy Seeder) after ZT DSR, residue removed | G23: ZT DSR | H23: ZT | I23: No | K23: ZT | L23: Zero till both phases, no residue | M23: High | N23: INCLUDED
A24: 168 | B24: 168 | C24: Dhaliwal J.K. et al. | D24: 2020 | E24: ZTW+M-ZTDSR | F24: ZT wheat + rice residue mulch after ZT DSR | G24: ZT DSR | H24: ZT | I24: Yes (surface mulch) | J24: 7 | K24: CA | L24: Zero till both phases + residue | M24: High | N24: INCLUDED
A25: 169 | B25: 169 | C25: Singh V.K. et al. | D25: 2005 | E25: RW / PW x N x P | F25: Rice-wheat vs pigeonpea-wheat with 0/120 kg N and 0/26 kg P to wheat | G25: Puddled TPR / pigeonpea | H25: Conventional | I25: No | K25: EXCLUDED | L25: Crop substitution + fertiliser; no tillage/residue contrast | M25: High | N25: EXCLUDED
A26: 23 (companion 3) | B26: 23 (companion 3) | C26: Jat H.S. et al. | D26: 2019 | E26: Sc1 | F26: Conventional rice-wheat, residues removed | G26: Puddled TPR | H26: CT (broadcast) | I26: No | K26: CT | L26: Conventional both phases | M26: High | N26: INCLUDED
A27: 23 (companion 3) | B27: 23 (companion 3) | C27: Jat H.S. et al. | D27: 2019 | E27: Sc2 | F27: Partial CA: puddled TPR + ZT wheat + ZT mungbean, rice stubble retained | G27: Puddled TPR | H27: ZT (drill) | I27: Yes (anchored stubble 4.1-12.7) | J27: 4.1-12.7 | K27: pCA | L27: Puddled rice + ZT wheat with residue (rule 68); mungbean flag | M27: High | N27: INCLUDED
A28: 23 (companion 3) | B28: 23 (companion 3) | C28: Jat H.S. et al. | D28: 2019 | E28: Sc3 | F28: Full CA: ZT DSR + ZT wheat + ZT mungbean, residues retained | G28: ZT DSR | H28: ZT | I28: Yes (surface) | J28: 3.7-10.2 rice | K28: CA | L28: Zero till both phases + residue; mungbean flag | M28: High | N28: INCLUDED
A29: 23 (companion 3) | B29: 23 (companion 3) | C29: Jat H.S. et al. | D29: 2019 | E29: Sc4 | F29: CA maize-wheat-mungbean | G29: - | H29: ZT | I29: Yes | K29: EXCLUDED | L29: Maize-wheat system | M29: High | N29: EXCLUDED
A30: 23 (companion 4) | B30: 23 (companion 4) | C30: Jat H.S. et al. | D30: 2019 | E30: Sc1 / Sc2 / Sc3 / Sc4 | F30: As 23 (companion 3) | G30: - | H30: - | I30: - | K30: CT / pCA / CA / EXCLUDED | L30: Same trial | M30: High | N30: INCLUDED
A31: 165 (companion) | B31: 165 (companion) | C31: Meena A.L. et al. | D31: 2020 | E31: FYM / VC | F31: Organic manure only (60 kg N/ha) | G31: Puddled TPR (project) | H31: Conventional (project) | I31: No | K31: CT | L31: Conventional, no residue | M31: Medium (tillage from Davari 2012) | N31: INCLUDED
A32: 165 (companion) | B32: 165 (companion) | C32: Meena A.L. et al. | D32: 2020 | E32: FYM + CR / VC + CR | F32: Manure + 3 t/ha preceding-crop residue | G32: Puddled TPR (project) | H32: Conventional (project) | I32: Yes (incorporated) | J32: 3 | K32: CTR | L32: Conventional + residue (row a) | M32: Medium | N32: INCLUDED
A33: 165 (companion) | B33: 165 (companion) | C33: Meena A.L. et al. | D33: 2020 | E33: FYM + CR + BF / VC + CR + BF | F33: As above + biofertilisers (BGA, PSB, Azotobacter, cellulolytic culture) | G33: Puddled TPR (project) | H33: Conventional (project) | I33: Yes (incorporated) | J33: 3 | K33: CTR | L33: Row b, biofertiliser flag (rule 20) | M33: Medium | N33: INCLUDED - FLAGGED
A34: 165 (companion) | B34: 165 (companion) | C34: Meena A.L. et al. | D34: 2020 | E34: Control | F34: No organics | G34: Puddled TPR | H34: Conventional | I34: No | K34: EXCLUDED | L34: Unfertilised control | M34: High | N34: EXCLUDED
A35: 131 (companion) | B35: 131 (companion) | C35: Zhang Y.-P. et al. | D35: 2023 | E35: CN | F35: Continuous no-till dry direct-seeded rice + no-till wheat, full straw return | G35: ZT DSR | H35: ZT | I35: Yes | J35: full | K35: CA | L35: Zero till both phases + residue | M35: High | N35: INCLUDED
A36: 131 (companion) | B36: 131 (companion) | C36: Zhang Y.-P. et al. | D36: 2023 | E36: PR | F36: Plough + rotary + puddled transplanted rice; no-till wheat; full straw return | G36: Puddled TPR (plough + rotary) | H36: ZT | I36: Yes | J36: full | K36: pCA | L36: Puddled rice + ZT wheat with residue (rule 68) | M36: High | N36: INCLUDED
A37: 131 (companion) | B37: 131 (companion) | C37: Zhang Y.-P. et al. | D37: 2023 | E37: RT | F37: No-till 2017-18, plough 2019 before rice; no-till wheat | G37: Rotational | H37: ZT | I37: Yes | J37: full | K37: EXCLUDED | L37: Alternate / rotational tillage | M37: High | N37: EXCLUDED
A38: 170 | B38: 170 | C38: Kukal S.S. & Aggarwal G.C. | D38: 2003 | E38: Medium / intensive puddling, normal depth (10-12 cm) | F38: 2 or 4 cultivator passes in flooded soil, tines fully in; CT wheat (disc + 2 cultivator) | G38: Puddled (normal depth) | H38: Conventional | I38: No | K38: CT | L38: Author 2026-10-05: normal puddling = CT | M38: High | N38: INCLUDED (author)
A39: 170 | B39: 170 | C39: Kukal S.S. & Aggarwal G.C. | D39: 2003 | E39: Medium / intensive puddling, shallow depth (5-6 cm) | F39: Tines set 4-5 cm deep; CT wheat | G39: Shallow (reduced) puddling | H39: Conventional | I39: No | K39: MT | L39: Author 2026-10-05: shallow puddling = MT (wheat CT in all - flag) | M39: Medium | N39: INCLUDED (author) - FLAG
A40: 170 | B40: 170 | C40: Kukal S.S. & Aggarwal G.C. | D40: 2003 | E40: Unpuddled | F40: Unpuddled plots in the same field, outside the randomised layout (BD only) | G40: Unpuddled (transplanted) | H40: Conventional | I40: No | K40: ZT | L40: Author 2026-10-05: unpuddled = ZT (outside layout, wheat CT - flag) | M40: Medium | N40: INCLUDED (author) - FLAG
A41: 15 (companion 2) | B41: 15 (companion 2) | C41: Gathala M.K. et al. | D41: 2011 | E41: T1 CT-TPR/CT-DSW | F41: Puddled TPR; conventional tillage + drill-seeded wheat | G41: Puddled TPR | H41: Conventional | I41: Stubble ~1 Mg/ha (incorporated) | J41: 1 | K41: CT | L41: As old-master 15 | M41: High | N41: INCLUDED
A42: 15 (companion 2) | B42: 15 (companion 2) | C42: Gathala M.K. et al. | D42: 2011 | E42: T2 CTAWD-TPR/ZT-DSW | F42: Puddled TPR with AWD; ZT drill-seeded wheat | G42: Puddled TPR (AWD) | H42: Zero tillage | I42: Stubble ~1 Mg/ha (not a treatment) | J42: 1 | K42: pZT | L42: Author 2026-10-05; AWD flag | M42: High | N42: INCLUDED (author)
A43: 15 (companion 2) | B43: 15 (companion 2) | C43: Gathala M.K. et al. | D43: 2011 | E43: T5 ZT-DSR/ZT-DSW | F43: ZT direct drill-seeded rice; ZT wheat | G43: Zero tillage DSR | H43: Zero tillage | I43: Stubble ~1 Mg/ha | J43: 1 | K43: ZT | L43: Row a (author 2026-10-05) | M43: High | N43: INCLUDED (author)
A44: 15 (companion 2) | B44: 15 (companion 2) | C44: Gathala M.K. et al. | D44: 2011 | E44: T6 ZT-TPR/ZT-DSW | F44: Zero-till plots flooded 1 d before transplanting (unpuddled); ZT wheat | G44: Zero till, unpuddled TPR | H44: Zero tillage | I44: Stubble ~1 Mg/ha | J44: 1 | K44: ZT | L44: Row b (author 2026-10-05) | M44: High | N44: INCLUDED (author)
A45: 15 (companion 2) | B45: 15 (companion 2) | C45: Gathala M.K. et al. | D45: 2011 | E45: T3 Bed-DSR/Bed-DSW | F45: Permanent raised beds, DSR; beds reshaped at wheat sowing | G45: Permanent beds (DSR) | H45: Beds reshaped (1 pass) | I45: Stubble ~1 Mg/ha | J45: 1 | K45: MT | L45: Row a; author 2026-10-05: beds = MT | M45: High | N45: INCLUDED (author)
A46: 15 (companion 2) | B46: 15 (companion 2) | C46: Gathala M.K. et al. | D46: 2011 | E46: T4 Bed-TPR/Bed-DSW | F46: Permanent raised beds, transplanted rice; beds reshaped at wheat sowing | G46: Permanent beds (TPR) | H46: Beds reshaped (1 pass) | I46: Stubble ~1 Mg/ha | J46: 1 | K46: MT | L46: Row b; author 2026-10-05: beds = MT | M46: High | N46: INCLUDED (author)
A47: 40 (companion) | B47: 40 (companion) | C47: Kader M.A. et al. | D47: 2022 | E47: CT-LR / CT-HR | F47: Puddled (4 rotary passes) TPR; 4 cross rotary passes for wheat and mungbean; 15 % / 30 % residue | G47: Puddled (rotary x4) | H47: Conventional (rotary x4) | I47: Yes (anchored) | J47: 15 / 30 % height | K47: CTR | L47: Rotary rule (>= 2 passes) + residue; rows a/b (as old-master 40) | M47: High | N47: INCLUDED
A48: 40 (companion) | B48: 40 (companion) | C48: Kader M.A. et al. | D48: 2022 | E48: ST-LR / ST-HR | F48: VMP strip tillage (4-6 cm wide, 5-6 cm deep), unpuddled TPR in strips; 15 % / 30 % residue | G48: Strip tillage, unpuddled | H48: Strip tillage | I48: Yes (anchored) | J48: 15 / 30 % height | K48: MTR | L48: Strip tillage + residue = MTR (rows a/b) | M48: High | N48: INCLUDED
A49: 23 (companion 5) | B49: 23 (companion 5) | C49: Roy D. et al. | D49: 2022 | E49: Sc1 TPR-CTW | F49: Puddled TPR; broadcast CT wheat (2 harrow + 2 cultivator); no residue | G49: Puddled TPR | H49: Conventional | I49: No | K49: CT | L49: Conventional both phases | M49: High | N49: INCLUDED
A50: 23 (companion 5) | B50: 23 (companion 5) | C50: Roy D. et al. | D50: 2022 | E50: Sc2 TPR-ZTWMb | F50: Puddled TPR; ZT wheat and mungbean (Happy Seeder); residue retained | G50: Puddled TPR | H50: Zero tillage | I50: Yes | K50: pCA | L50: Puddled rice + ZT wheat + residue (rule 68); mungbean flag | M50: High | N50: INCLUDED
A51: 23 (companion 5) | B51: 23 (companion 5) | C51: Roy D. et al. | D51: 2022 | E51: Sc3 ZTDSR-ZTWMb | F51: ZT DSR, ZT wheat, ZT mungbean; residue retained | G51: Zero tillage DSR | H51: Zero tillage | I51: Yes | K51: CA | L51: ZT both phases + residue; mungbean flag | M51: High | N51: INCLUDED
A52: 23 (companion 5) | B52: 23 (companion 5) | C52: Roy D. et al. | D52: 2022 | E52: Sc5 ZTDSR-ZTWMb + SDI | F52: As Sc3 with sub-surface drip irrigation (from 2016), 25 % less N | G52: Zero tillage DSR | H52: Zero tillage | I52: Yes | K52: EXCLUDED | L52: Irrigation/fertigation contrast with the same tillage and residue as Sc3 (old-master 23); values in Notes | M52: High | N52: EXCLUDED
A53: 23 (companion 5) | B53: 23 (companion 5) | C53: Roy D. et al. | D53: 2022 | E53: Sc4 / Sc6 | F53: ZT maize-wheat-mungbean (+ SDI) | G53: n/a - maize | H53: Zero tillage | I53: Yes | K53: EXCLUDED | L53: Maize-wheat system | M53: High | N53: EXCLUDED
A54: 171 | B54: 171 | C54: Ghimire R. et al. | D54: 2012 | E54: T1M0 | F54: Conventional tillage (plough 15-20 cm, puddled rice), no residue | G54: Puddled | H54: Conventional | I54: No (roots only) | K54: CT | L54: Conventional both phases | M54: High | N54: INCLUDED
A55: 171 | B55: 171 | C55: Ghimire R. et al. | D55: 2012 | E55: T1M1 | F55: Conventional tillage + 4 Mg/ha residue per crop | G55: Puddled | H55: Conventional | I55: Yes (incorporated) | J55: 4 per crop | K55: CTR | L55: Conventional + residue | M55: High | N55: INCLUDED
A56: 171 | B56: 171 | C56: Ghimire R. et al. | D56: 2012 | E56: T0M0 | F56: No-tillage (surface seeding of all crops), no residue | G56: No-till surface-seeded | H56: No-till | I56: No (roots only) | K56: ZT | L56: No-till both phases | M56: High | N56: INCLUDED
A57: 171 | B57: 171 | C57: Ghimire R. et al. | D57: 2012 | E57: T0M1 | F57: No-tillage + 4 Mg/ha residue per crop | G57: No-till surface-seeded | H57: No-till | I57: Yes (surface) | J57: 4 per crop | K57: CA | L57: No-till + residue | M57: High | N57: INCLUDED
A58: 172 | B58: 172 | C58: Tirol-Padre A. et al. | D58: 2005 | E58: N (urea 70 kg N/ha) | F58: Inorganic N only, no organic residue | G58: Puddled TPR | H58: Not described (conventional) | I58: No | K58: CT | L58: Residue-free reference of the +N tier | M58: High | N58: INCLUDED
A59: 172 | B59: 172 | C59: Tirol-Padre A. et al. | D59: 2005 | E59: RS + N | F59: Rice straw 10 Mg/ha incorporated at puddling + N | G59: Puddled TPR | H59: Not described | I59: Yes (incorporated) | J59: 10 | K59: CTR | L59: Row a | M59: High | N59: INCLUDED
A60: 172 | B60: 172 | C60: Tirol-Padre A. et al. | D60: 2005 | E60: WS + N | F60: Italian ryegrass 8 Mg/ha (1963-84) then wheat straw 10 / 6 Mg/ha + N | G60: Puddled TPR | H60: Not described | I60: Yes (incorporated) | J60: 6-10 | K60: CTR | L60: Row b (ryegrass period flag) | M60: Medium | N60: INCLUDED - FLAG
A61: 172 | B61: 172 | C61: Tirol-Padre A. et al. | D61: 2005 | E61: RSC + N | F61: Rice-straw compost 20 Mg/ha + N | G61: Puddled TPR | H61: Not described | I61: Composted straw (incorporated) | J61: 20 | K61: CTR | L61: Row c; author 2026-10-05: compost = CTR | M61: Medium | N61: INCLUDED (author) - FLAG
A62: 172 | B62: 172 | C62: Tirol-Padre A. et al. | D62: 2005 | E62: RSC (-N) | F62: Rice-straw compost without N | G62: Puddled TPR | H62: Not described | I62: Composted straw | J62: 20 | K62: EXCLUDED | L62: -N tier (rule 78) | M62: High | N62: EXCLUDED
A63: 172 | B63: 172 | C63: Tirol-Padre A. et al. | D63: 2005 | E63: Control / RS / WS (-N tier) | F63: No inorganic N | G63: Puddled TPR | H63: Not described | I63: - | K63: EXCLUDED | L63: Unfertilised control as CT (rule 78); values in Notes | M63: High | N63: EXCLUDED
A64: 124 (companion) | B64: 124 (companion) | C64: Hoque M.A. et al. | D64: 2023 | E64: CT | F64: Puddled TPR; 3-5 tillage passes for wheat; ~0.7 t/ha stubble incorporated | G64: Puddled | H64: Conventional | I64: Minimal (0.7 t/ha) | J64: 0.7 | K64: CT | L64: As old-master 124 | M64: High | N64: INCLUDED
A65: 124 (companion) | B65: 124 (companion) | C65: Hoque M.A. et al. | D65: 2023 | E65: CA | F65: Untilled unpuddled TPR; wheat (+ mungbean) strip-tilled into ~25 cm stubble | G65: Zero till, unpuddled | H65: Strip tillage | I65: Yes | J65: 3 | K65: MTR | L65: As old-master 124 | M65: High | N65: INCLUDED
A66: 124 (companion) | B66: 124 (companion) | C66: Hoque M.A. et al. | D66: 2023 | E66: AT | F66: Puddled TPR; winter / spring crops strip-tilled into ~25 cm stubble with residue | G66: Puddled | H66: Strip tillage | I66: Yes | J66: 3 | K66: pMTR | L66: Puddled rice + MT (strip) wheat + residue (rules 68 / 85 / 86) | M66: High | N66: INCLUDED
A67: 173 | B67: 173 | C67: Biswakarma N. et al. | D67: 2023 | E67: ICM1 / ICM2 | F67: Chisel 30 cm + puddled TPR; disc + 2 cultivator wheat; no residue; 100 % RF / 75 % RF + bf + AM | G67: Puddled (after chisel 30 cm) | H67: Conventional | I67: No | K67: DT | L67: Author 2026-10-05: annual chisel ploughing to 30 cm = deep tillage | M67: High | N67: INCLUDED (author)
A68: 173 | B68: 173 | C68: Biswakarma N. et al. | D68: 2023 | E68: ICM3 / ICM4 | F68: Chisel 30 cm + DSR; raised-bed wheat after disc + 2 cultivator; no residue | G68: Tilled DSR (unpuddled) | H68: Tilled + fresh raised beds | I68: No | K68: CT | L68: Author 2026-10-05 (flag: chisel ploughing stated for ICM1-4 alike) | M68: Medium | N68: INCLUDED (author) - FLAG
A69: 173 | B69: 173 | C69: Biswakarma N. et al. | D69: 2023 | E69: ICM5 / ICM6 | F69: ZT-DSR with wheat residue; ZT wheat with rice residue; 100 % / 75 % RF + bf | G69: Zero till DSR | H69: Zero till | I69: Yes | J69: 3 / 5 | K69: CA | L69: Rows a / b | M69: High | N69: INCLUDED
A70: 173 | B70: 173 | C70: Biswakarma N. et al. | D70: 2023 | E70: ICM7 / ICM8 | F70: As ICM5 / ICM6 + summer mungbean (residue retained) | G70: Zero till DSR | H70: Zero till | I70: Yes (+ mungbean) | J70: 3 / 5 / 3 | K70: CA | L70: Rows c / d; mungbean flag | M70: High | N70: INCLUDED - FLAG
A71: 174 | B71: 174 | C71: Gathala M.K. et al. | D71: 2017 | E71: T1 CT-TPR (-S,-WR)/ZT-DSW (-RR) | F71: Puddled TPR, no Sesbania, no residue; ZT wheat | G71: Puddled | H71: Zero till | I71: No | K71: pZT | L71: Puddled rice + ZT wheat, no residue (rule 68) | M71: High | N71: INCLUDED
A72: 174 | B72: 174 | C72: Gathala M.K. et al. | D72: 2017 | E72: T2 CT-TPR (+S,+WR)/ZT-DSW (+RR) | F72: Puddled TPR + Sesbania + wheat stubble incorporated; ZT wheat (Turbo Happy Seeder) into ~8 Mg/ha rice residue | G72: Puddled | H72: Zero till | I72: Yes | J72: 8 | K72: pCA | L72: Puddled rice + ZT wheat + residue (rule 68); Sesbania flag | M72: High | N72: INCLUDED - FLAG
A73: 174 | B73: 174 | C73: Gathala M.K. et al. | D73: 2017 | E73: T3 CT-DSR (-S,-WR)/ZT-DSW (-RR) | F73: Dry tillage (2 harrowings + 2 tyne passes + planking), drill-seeded rice; ZT wheat; no residue | G73: Dry-tilled, unpuddled DSR | H73: Zero till | I73: No | K73: ZT | L73: Row a; rule 25 (tilled unpuddled rice + ZT wheat, no residue) | M73: Medium | N73: INCLUDED - FLAG
A74: 174 | B74: 174 | C74: Gathala M.K. et al. | D74: 2017 | E74: T4 CT-DSR (+S,+WR)/ZT-DSW (+RR) | F74: As T3 + Sesbania + wheat stubble incorporated + rice residue mulch | G74: Dry-tilled, unpuddled DSR | H74: Zero till | I74: Yes | J74: 8 | K74: CA | L74: Row a; rule 25 (with residue -> CA); Sesbania flag | M74: Medium | N74: INCLUDED - FLAG
A75: 174 | B75: 174 | C75: Gathala M.K. et al. | D75: 2017 | E75: T5 ZT-DSR (-S,-WR)/ZT-DSW (-RR) | F75: Zero-till DSR + ZT wheat, no residue | G75: Zero till | H75: Zero till | I75: No | K75: ZT | L75: Row b | M75: High | N75: INCLUDED
A76: 174 | B76: 174 | C76: Gathala M.K. et al. | D76: 2017 | E76: T6 ZT-DSR (+S,+WR)/ZT-DSW (+RR) | F76: Zero-till DSR + Sesbania + surface wheat stubble; ZT wheat into rice residue mulch | G76: Zero till | H76: Zero till | I76: Yes | J76: 8 | K76: CA | L76: Row b; Sesbania flag (rule 71) | M76: High | N76: INCLUDED
A77: 175 | B77: 175 | C77: Hossain M.M. et al. | D77: 2022 | E77: TA (Traditional Agriculture) | F77: Plough tillage (4 ploughings + cross ploughings, 2WT), puddled TPR, 3 hand weedings, residue removed | G77: Puddled | H77: Conventional | I77: No | K77: CT | L77: Conventional both phases | M77: High | N77: INCLUDED
A78: 175 | B78: 175 | C78: Hossain M.M. et al. | D78: 2022 | E78: CA (Conservation Agriculture) | F78: Glyphosate + single (strip) tillage by VMP, unpuddled strip transplanting, PEH + POH, 50 % anchored residue | G78: Strip tillage, unpuddled | H78: Strip tillage (VMP) | I78: Yes (50 % anchored) | K78: MTR | L78: Rule 16: strip tillage + residue = MTR even when called CA | M78: High | N78: INCLUDED
A79: 176 | B79: 176 | C79: Devkota K.P. et al. | D79: 2015 | E79: DSRB-SSW-R0 | F79: ZT dry-seeded rice on permanent beds (AWD) + surface-seeded wheat, farmer harvest (3-5 cm stubble) | G79: Zero till (permanent beds) | H79: Zero till / surface seeded | I79: No (~95 % removed) | K79: ZT | L79: Rows a/b; permanent beds without residue = ZT (rule 15) | M79: High | N79: INCLUDED
A80: 176 | B80: 176 | C80: Devkota K.P. et al. | D80: 2015 | E80: DSRB-SSW-R50 / R100 | F80: As DSRB-R0 with 15-20 cm / 35-40 cm standing straw | G80: Zero till (permanent beds) | H80: Zero till / surface seeded | I80: Yes | J80: 1.5-6.7 | K80: CA | L80: Rows a (R50) / b (R100); permanent beds + residue = CA | M80: High | N80: INCLUDED
A81: 176 | B81: 176 | C81: Devkota K.P. et al. | D81: 2015 | E81: DSRF-SSW-R0 | F81: ZT dry-seeded rice on the flat (AWD) + surface-seeded wheat, farmer harvest | G81: Zero till | H81: Zero till / surface seeded | I81: No | K81: ZT | L81: Rows c/d | M81: High | N81: INCLUDED
A82: 176 | B82: 176 | C82: Devkota K.P. et al. | D82: 2015 | E82: DSRF-SSW-R50 / R100 | F82: As DSRF-R0 with 15-20 / 35-40 cm standing straw | G82: Zero till | H82: Zero till / surface seeded | I82: Yes | J82: 1.5-6.7 | K82: CA | L82: Rows c (R50) / d (R100) | M82: High | N82: INCLUDED
A83: 176 | B83: 176 | C83: Devkota K.P. et al. | D83: 2015 | E83: WSRF-SSW-FI / WSRF-SSW-AWD | F83: Conventional dry tillage, water-seeded rice (flooded / AWD, non-puddled) + wheat surface-seeded into standing rice, no residue | G83: Conventional dry tillage (non-puddled) | H83: Zero till / surface seeded | I83: No | K83: PENDING | L83: Author decision: pZT (rule 68, conventional rice + ZT wheat) or ZT (rule 25, tilled unpuddled rice + ZT wheat)? Values in Notes | M83: Low | N83: NOT ENTERED - ASK AUTHOR
A84: 176 (companion) | B84: 176 (companion) | C84: Devkota K.P. et al. | D84: 2015 | E84: Treatments 2-7 (DSRB / DSRF x R0 / R50 / R100) | F84: As 176 | G84: Zero till | H84: Zero till | I84: R0 no / R50, R100 yes | K84: ZT / CA | L84: As 176 rows a-d | M84: High | N84: INCLUDED
A85: 176 (companion) | B85: 176 (companion) | C85: Devkota K.P. et al. | D85: 2015 | E85: 1 WSRF-R0-FI / 8 WSRF-R0-AWD | F85: As 176 | G85: Conventional dry tillage | H85: Zero till | I85: No | K85: PENDING | L85: As 176 | M85: Low | N85: NOT ENTERED - ASK AUTHOR
A86: 176 (companion) | B86: 176 (companion) | C86: Devkota K.P. et al. | D86: 2015 | E86: 9-11 (simulation only) | F86: WSRF puddled; CT-DSR; CT-DSR + deep-placed urea | G86: - | H86: - | I86: No | K86: EXCLUDED | L86: Hypothetical model scenarios, never field-tested | M86: High | N86: EXCLUDED
A87: 115 (companion) | B87: 115 (companion) | C87: Pokharel D. et al. | D87: 2018 | E87: CTTPR+CTW | F87: Conventional tillage, puddled manual TPR + multiple-tillage wheat | G87: Puddled | H87: Conventional | I87: No | K87: CT | L87: As old-master 115 T1 | M87: High | N87: INCLUDED
A88: 115 (companion) | B88: 115 (companion) | C88: Pokharel D. et al. | D88: 2018 | E88: CTTPR+ZTW | F88: Puddled TPR + zero-till drilled wheat | G88: Puddled | H88: Zero till | I88: Yes (per 115 protocol; not stated here) | K88: pCA | L88: Excluded in 115 (mismatch); partial code now (rules 68/85); residue from 115 (rule 89, flag) | M88: Medium | N88: INCLUDED - FLAG
A89: 115 (companion) | B89: 115 (companion) | C89: Pokharel D. et al. | D89: 2018 | E89: ZTDSR+ZTW | F89: Zero-till DSR + ZT wheat | G89: Zero till | H89: Zero till | I89: Yes (per 115 protocol; not stated here) | K89: CA | L89: Row a; as 115 T3 (residue flag) | M89: Medium | N89: INCLUDED - FLAG
A90: 115 (companion) | B90: 115 (companion) | C90: Pokharel D. et al. | D90: 2018 | E90: UPTPR+ZTW | F90: Unpuddled mechanical / manual transplanting + ZT wheat | G90: Unpuddled (zero till) | H90: Zero till | I90: Yes (per 115 protocol; not stated here) | K90: CA | L90: Row b; as 115 T4; unpuddled = ZT (residue flag) | M90: Medium | N90: INCLUDED - FLAG
A91: 115 (companion) | B91: 115 (companion) | C91: Pokharel D. et al. | D91: 2018 | E91: Rice-maize: CTTPR+CTM / CTTPR+ZTM / ZTDSR+ZTM / UPTPR+ZTM | F91: Upland rice-maize system | G91: - | H91: - | I91: - | K91: EXCLUDED | L91: Rice-maize system (rule 31) | M91: High | N91: EXCLUDED

Sheet LAT_LONG
A1: No. | B1: SERIAL NO | C1: Authors | D1: Year | E1: Country | F1: Site/Location | G1: latitude (as reported) | H1: longitude (as reported) | I1: latitude | J1: longitude | K1: Coordinates source | L1: CLIMATE | M1: Notes
A2: 164 | B2: 164 | C2: Yadav R.L. et al. | D2: 2000 | E2: India (Punjab) | F2: Ludhiana | G2: 30 deg 56'N | H2: 75 deg 52'E | I2: 30.933 | J2: 75.867 | K2: Paper | L2: TEMP
A3: 164 | B3: 164 | C3: Yadav R.L. et al. | D3: 2000 | E3: India (Uttarakhand (then Uttar Pradesh)) | F3: Pantnagar | G3: 29 deg N | H3: 79 deg 5'E | I3: 29 | J3: 79.083 | K3: Paper | L3: ST | M3: GBPUAT Pantnagar ~29.02 N, 79.48 E; printed 79 deg 5'E
A4: 164 | B4: 164 | C4: Yadav R.L. et al. | D4: 2000 | E4: India (Uttar Pradesh) | F4: Kanpur | G4: 26 deg 58'N | H4: 80 deg 34'E | I4: 26.967 | J4: 80.567 | K4: Paper | L4: ST
A5: 164 | B5: 164 | C5: Yadav R.L. et al. | D5: 2000 | E5: India (Uttar Pradesh) | F5: Faizabad | G5: 26 deg 4'N | H5: 82 deg 8'E | I5: 26.067 | J5: 82.133 | K5: Paper | L5: ST | M5: Printed coords ~50 km from NDUAT Kumarganj (26.54 N, 81.84 E) - kept as printed
A6: 164 | B6: 164 | C6: Yadav R.L. et al. | D6: 2000 | E6: India (Bihar) | F6: Sabour | G6: 25 deg 14'N | H6: 87 deg 4'E | I6: 25.233 | J6: 87.067 | K6: Paper | L6: ST
A7: 164 | B7: 164 | C7: Yadav R.L. et al. | D7: 2000 | E7: India (West Bengal) | F7: Kalyani | G7: 23 deg N | H7: 89 deg E | I7: 23 | J7: 89 | K7: Paper | L7: ST | M7: Printed to whole degrees; BCKV Kalyani ~22.98 N, 88.43 E
A8: 164 | B8: 164 | C8: Yadav R.L. et al. | D8: 2000 | E8: India (Madhya Pradesh) | F8: Jabalpur | G8: 23 deg 10'N | H8: 79 deg 57'E | I8: 23.167 | J8: 79.95 | K8: Paper | L8: ST
A9: 165 | B9: 165 | C9: Davari M.R. et al. | D9: 2012 | E9: India (Delhi) | F9: IARI, New Delhi | G9: 28 deg 38'N | H9: 77 deg 11'E | I9: 28.633 | J9: 77.183 | K9: Paper | L9: ST
A10: 166 | B10: 166 | C10: Das B. et al. | D10: 2014 | E10: India (Uttar Pradesh) | F10: PDFSR Modipuram, Meerut | G10: 29 deg 4'N | H10: 77 deg 46'E | I10: 29.067 | J10: 77.767 | K10: Paper | L10: ST
A11: 167 | B11: 167 | C11: Naz A. et al. | D11: 2023 | E11: Pakistan (Punjab) | F11: Khushab / Faisalabad | K11: Not given (study excluded) | M11: EXCLUDED study
A12: 168 | B12: 168 | C12: Dhaliwal J.K. et al. | D12: 2020 | E12: India (Punjab) | F12: PAU, Ludhiana | G12: 30 deg 56'N | H12: 75 deg 52'E | I12: 30.933 | J12: 75.867 | K12: Paper | L12: TEMP
A13: 169 | B13: 169 | C13: Singh V.K. et al. | D13: 2005 | E13: India (Uttar Pradesh) | F13: PDCSR Modipuram, Meerut | K13: Not entered (study excluded) | M13: EXCLUDED study
A14: 23 (companion 3) | B14: 23 (companion 3) | C14: Jat H.S. et al. | D14: 2019 | E14: India (Haryana) | F14: ICAR-CSSRI, Karnal | G14: 29 deg 70'N | H14: 76 deg 96'E | I14: 29.7 | J14: 76.96 | K14: Paper | L14: ST | M14: Printed minutes > 59 - read as decimals (as old-master 23)
A15: 23 (companion 4) | B15: 23 (companion 4) | C15: Jat H.S. et al. | D15: 2019 | E15: India (Haryana) | F15: ICAR-CSSRI, Karnal | G15: 29 deg 70'N | H15: 76 deg 95'E | I15: 29.7 | J15: 76.95 | K15: Paper | L15: ST
A16: 165 (companion) | B16: 165 (companion) | C16: Meena A.L. et al. | D16: 2020 | E16: India (Delhi) | F16: IARI, New Delhi | G16: 28.4 N | H16: 77.1 E | I16: 28.4 | J16: 77.1 | K16: Paper | L16: ST
A17: 131 (companion) | B17: 131 (companion) | C17: Zhang Y.-P. et al. | D17: 2023 | E17: China (Shandong) | F17: Taoluo Town, Rizhao | G17: - | H17: - | I17: 35.27 | J17: 119.38 | K17: Approximate (town centre) | L17: TEMP | M17: Paper gives no coordinates
A18: 170 | B18: 170 | C18: Kukal S.S. & Aggarwal G.C. | D18: 2003 | E18: India (Punjab) | F18: PAU, Ludhiana | G18: 30 deg 56' N | H18: 75 deg 52' E | I18: 30.933 | J18: 75.867 | K18: Paper | L18: TEMP
A19: 15 (companion 2) | B19: 15 (companion 2) | C19: Gathala M.K. et al. | D19: 2011 | E19: India (Uttar Pradesh) | F19: SVBPUAT, Modipuram | G19: 29 deg 01' N | H19: 77 deg 45' E | I19: 29.017 | J19: 77.75 | K19: Paper / old-master 15 | L19: ST
A20: 40 (companion) | B20: 40 (companion) | C20: Kader M.A. et al. | D20: 2022 | E20: Bangladesh | F20: BAU farm, Mymensingh | G20: 24 deg 43.407' N | H20: 90 deg 26.22' E | I20: 24.724 | J20: 90.437 | K20: Paper | L20: ST | M20: Same as old-master 40
A21: 23 (companion 5) | B21: 23 (companion 5) | C21: Roy D. et al. | D21: 2022 | E21: India (Haryana) | F21: ICAR-CSSRI, Karnal | G21: 29 deg 42' 20.7" N | H21: 76 deg 57' 19.79" E | I21: 29.706 | J21: 76.956 | K21: Paper | L21: ST
A22: 171 | B22: 171 | C22: Ghimire R. et al. | D22: 2012 | E22: Nepal | F22: IAAS Rampur, Chitwan | G22: 27 deg 38' 49" N | H22: 84 deg 20' 45" E | I22: 27.647 | J22: 84.346 | K22: Paper | L22: ST
A23: 172 | B23: 172 | C23: Tirol-Padre A. et al. | D23: 2005 | E23: Japan | F23: Chikugo, Fukuoka | G23: - | H23: - | I23: 33.2 | J23: 130.5 | K23: Approximate (Chikugo city) | L23: TEMP | M23: Paper gives no coordinates
A24: 124 (companion) | B24: 124 (companion) | C24: Hoque M.A. et al. | D24: 2023 | E24: Bangladesh | F24: BARI RARS Jamalpur | G24: 24 deg 56' 30.68" N | H24: 89 deg 55' 40.39" E | I24: 24.942 | J24: 89.928 | K24: Paper | L24: ST | M24: Same as old-master 124
A25: 173 | B25: 173 | C25: Biswakarma N. et al. | D25: 2023 | E25: India (Delhi) | F25: ICAR-IARI, New Delhi | G25: 28 deg 38' N | H25: 77 deg 09' E | I25: 28.633 | J25: 77.15 | K25: Paper | L25: ST
A26: 174 | B26: 174 | C26: Gathala M.K. et al. | D26: 2017 | E26: India (Uttar Pradesh) | F26: IIFSR Modipuram, Meerut | G26: 29 deg 4' N | H26: 77 deg 46' E | I26: 29.067 | J26: 77.767 | K26: Paper | L26: ST
A27: 175 | B27: 175 | C27: Hossain M.M. et al. | D27: 2022 | E27: Bangladesh | F27: Bhungnamary, Gouripur, Mymensingh | G27: 24.4514 N | H27: 90.2411 E | I27: 24.4514 | J27: 90.2411 | K27: Paper | L27: ST
A28: 176 | B28: 176 | C28: Devkota K.P. et al. | D28: 2015 | E28: Uzbekistan | F28: Urgench, Khorezm | G28: 60.050-61.390 N (swapped) | H28: 41.130-42.020 E (swapped) | I28: 41.55 | J28: 60.63 | K28: Approximate (Urgench) | L28: TEMP | M28: Paper prints latitude and longitude swapped
A29: 176 (companion) | B29: 176 (companion) | C29: Devkota K.P. et al. | D29: 2015 | E29: Uzbekistan | F29: Urgench, Khorezm | G29: - | H29: - | I29: 41.55 | J29: 60.63 | K29: As 176 | L29: TEMP | M29: Same trial as 176
A30: 115 (companion) | B30: 115 (companion) | C30: Pokharel D. et al. | D30: 2018 | E30: Nepal | F30: Sunsari district | G30: 26 deg 25'-26 deg 55' N | H30: 86 deg 55'-87 deg 21' E | I30: 26.67 | J30: 87.13 | K30: Paper (range centre) | L30: ST

Sheet BD
A1: No. | B1: SERIAL NO | C1: Authors | D1: Year | E1: Journal | F1: Country | G1: Site/Location | H1: latitude | I1: longitude | J1: CLIMATE | K1: year of data collection/experiment | L1: DURATION | M1: SOIL | N1: DEPTH | O1: DEPTH (as reported in paper) | P1: BD_CA | Q1: BD_CT | R1: BD_ZT | S1: BD_DT | T1: BD_MTR | U1: BD_MT | V1: BD_CTR | W1: BD_DTR | X1: BD_pCA | Y1: BD_pZT | Z1: BD_pMT | AA1: BD_pMTR | AB1: Obs | AC1: Rep | AD1: SD | AE1: CLAY | AF1: MIN TEMP | AG1: MAX TEMP | AH1: RAIN FALL | AI1: LATT | AJ1: YEAR OF DATA (duration) | AK1: AVG T | AL1: April max temp | AM1: ph (initial) | AN1: soc (initial) | AO1: Bdi | AP1: sand | AQ1: silt | AR1: UNIT | AS1: Treatment mapping (paper's name -> code) | AT1: Crop/season of sampling | AU1: Fertilizer dose & other management | AV1: Data source | AW1: Notes/Doubts | AX1: Treatment details (from paper) | AY1: Method used (from paper) | BA1: UNIT FOR THIS SHEET:
A2: 168 | B2: 168 | C2: Dhaliwal J.K., Singh M.J., Sharma S., Gupta N. & Kukal S.S. | D2: 2020 | E2: Soil Research | F2: India (Punjab) | G2: PAU research farm, Ludhiana (DSR-wheat tillage x mulch trial of Gupta et al. 2016) | H2: 30.933 | I2: 75.867 | J2: TEMP | K2: 2016 | L2: 4-10 Y | M2: LOAMY | N2: 0-15 CM | O2: 0-15 cm | P2: 1.6 | Q2: 1.56 | R2: 1.6 | V2: 1.5 | AB2: 1 | AC2: 3 | AD2: =IF(AND(N(AB2)>0,N(AC2)>0),SQRT(2*AB2/AC2),"") -> 0.81649658 | AH2: 734 | AI2: 30.933 | AJ2: 5 | AM2: 7.4 | AR2: Mg/m3 | AS2: CTW-CTDSR (-M) -> CT ; CTW+M-CTDSR -> CTR ; ZTW-ZTDSR -> ZT ; ZTW+M-ZTDSR -> CA | AT2: RICE SEASON - soil sampled in 2016 after rice harvest (no wheat-season sampling in the paper) | AU2: Fertiliser, water and pest management as PAU recommendations (doses not printed; see Gupta et al. 2016 FCR 196:219). Wheat PBW 621, 113 kg/ha, Turbo Happy Seeder, 20 cm rows; rice PR 115 DSR 40 kg/ha, 20 cm rows. +M: 7 t/ha rice residue spread between rows after wheat sowing (2.5 t/ha left at wheat harvest). Wheat straw removed in all plots. Surface soil pH 7.4 (1:2), EC 0.31 dS/m (1:2); Typic Ustochrept, sandy loam to 120 cm. | AV2: Table 5 | AW2: RICE-SEASON DATA (RED ROW): the paper samples ONLY after the 2016 rice harvest, so values are entered under the rice-season fallback rule (rule 36). Rotation-matched: CT rice + CT wheat = CT; ZT rice + ZT wheat = ZT/CA (rice residue is the mulch factor). Supplementary: none found (web search 2026-10-05; publisher site not reachable from this environment). Source file 112_real.pdf. LSD (0-15) T 0.02, M 0.02, TxM 0.03; (15-30) T 0.03. [OBS RECOMPUTED 2026-10-05 (author rule): Y=1 (years of data in this row's series) + T=1 + D=1 -> Obs = 1; factors of 1 add nothing; supersedes any earlier Obs statement.] | AX2: TREATMENTS IN PAPER (Table 1; three-factor trial est. 2011 - only the 'absolute' CT and ZT rice and wheat combinations were studied): 1 CTW-CTDSR (-M) = conventionally tilled wheat (1 discing + 1 tyne harrowing + planking) and conventionally tilled dry-seeded rice, all rice residue removed -> CT ; 2 CTW+M-CTDSR = as 1 with ALL rice residue (7 t/ha) retained as surface mulch in wheat -> CTR ; 3 ZTW-ZTDSR = zero-till wheat (Turbo Happy Seeder) and zero-till DSR (inverted-T tyne ZT drill), residue removed -> ZT ; 4 ZTW+M-ZTDSR = as 3 with rice residue mulch -> CA. Wheat straw removed in every treatment (cut 3-5 cm above ground). RBD 3 reps; plots 9.3 x 6.5 m. | AY2: Core method (Blake & Hartge 1986), steel core 5 cm high x 5 cm i.d., 3 cores/plot | BA2: Mg/m3
A3: 168 | B3: 168 | C3: Dhaliwal J.K., Singh M.J., Sharma S., Gupta N. & Kukal S.S. | D3: 2020 | E3: Soil Research | F3: India (Punjab) | G3: PAU research farm, Ludhiana (DSR-wheat tillage x mulch trial of Gupta et al. 2016) | H3: 30.933 | I3: 75.867 | J3: TEMP | K3: 2016 | L3: 4-10 Y | M3: LOAMY | N3: 15-30 CM | O3: 15-30 cm | P3: 1.65 | Q3: 1.77 | R3: 1.67 | V3: 1.75 | AB3: 1 | AC3: 3 | AD3: =IF(AND(N(AB3)>0,N(AC3)>0),SQRT(2*AB3/AC3),"") -> 0.81649658 | AH3: 734 | AI3: 30.933 | AJ3: 5 | AM3: 7.4 | AR3: Mg/m3 | AS3: CTW-CTDSR (-M) -> CT ; CTW+M-CTDSR -> CTR ; ZTW-ZTDSR -> ZT ; ZTW+M-ZTDSR -> CA | AT3: RICE SEASON - soil sampled in 2016 after rice harvest (no wheat-season sampling in the paper) | AU3: Fertiliser, water and pest management as PAU recommendations (doses not printed; see Gupta et al. 2016 FCR 196:219). Wheat PBW 621, 113 kg/ha, Turbo Happy Seeder, 20 cm rows; rice PR 115 DSR 40 kg/ha, 20 cm rows. +M: 7 t/ha rice residue spread between rows after wheat sowing (2.5 t/ha left at wheat harvest). Wheat straw removed in all plots. Surface soil pH 7.4 (1:2), EC 0.31 dS/m (1:2); Typic Ustochrept, sandy loam to 120 cm. | AV3: Table 5 | AW3: RICE-SEASON DATA (RED ROW): the paper samples ONLY after the 2016 rice harvest, so values are entered under the rice-season fallback rule (rule 36). Rotation-matched: CT rice + CT wheat = CT; ZT rice + ZT wheat = ZT/CA (rice residue is the mulch factor). Supplementary: none found (web search 2026-10-05; publisher site not reachable from this environment). Source file 112_real.pdf. LSD (0-15) T 0.02, M 0.02, TxM 0.03; (15-30) T 0.03. [OBS RECOMPUTED 2026-10-05 (author rule): Y=1 (years of data in this row's series) + T=1 + D=1 -> Obs = 1; factors of 1 add nothing; supersedes any earlier Obs statement.] | AX3: TREATMENTS IN PAPER (Table 1; three-factor trial est. 2011 - only the 'absolute' CT and ZT rice and wheat combinations were studied): 1 CTW-CTDSR (-M) = conventionally tilled wheat (1 discing + 1 tyne harrowing + planking) and conventionally tilled dry-seeded rice, all rice residue removed -> CT ; 2 CTW+M-CTDSR = as 1 with ALL rice residue (7 t/ha) retained as surface mulch in wheat -> CTR ; 3 ZTW-ZTDSR = zero-till wheat (Turbo Happy Seeder) and zero-till DSR (inverted-T tyne ZT drill), residue removed -> ZT ; 4 ZTW+M-ZTDSR = as 3 with rice residue mulch -> CA. Wheat straw removed in every treatment (cut 3-5 cm above ground). RBD 3 reps; plots 9.3 x 6.5 m. | AY3: Core method (Blake & Hartge 1986), steel core 5 cm high x 5 cm i.d., 3 cores/plot
A4: 165 | B4: 165 | C4: Davari M.R., Sharma S.N. & Mirzakhani M. | D4: 2012 | E4: Biological Agriculture & Horticulture | F4: India (Delhi) | G4: IARI research farm, New Delhi (organic rice-based cropping systems trial) | H4: 28.633 | I4: 77.183 | J4: ST | K4: 2007-08 | L4: 0-3 Y | M4: LOAMY | N4: 0-15 CM | O4: 0-15 cm | Q4: 1.46 | V4: 1.4 | AB4: 1 | AC4: 3 | AD4: =IF(AND(N(AB4)>0,N(AC4)>0),SQRT(2*AB4/AC4),"") -> 0.81649658 | AE4: 25.4 | AI4: 28.633 | AJ4: 2 | AM4: 8.16 | AN4: 5.2 | AO4: 1.5 | AP4: 52.06 | AQ4: 22.54 | AR4: Mg/m3 | AS4: RW-RR -> CT ; RW-RI -> CTR | AT4: After completion of two cycles (June 2008, after wheat / fallow) | AU4: ORGANIC: FYM equivalent to 60 kg N/ha to rice and to wheat (FYM ~0.61% N, 22-23 C:N), no mineral fertiliser; BGA 1.5 kg/ha in rice 20 DAT; Azotobacter + PSB seed inoculation of wheat; cellulolytic fungal culture 600 g/t sprayed on residue in RI plots only. RI residue added (Mg DM/ha): RW 14.2 (2006-07), 16.0 (2007-08); RWM 17.8, 19.7. Initial soil: SCL, EC 0.79 dS/m, CEC 14.73 cmol/kg, OC 5.2 g/kg, Kjeldahl N 580 mg/kg, Olsen P 8.42, NH4OAc K 187 mg/kg, BD 1.50, FC 24.57%. | AV4: Table 9 | AW4: LSD residue 0.04. 15-30 cm values not printed (not significantly different). Rotation-matched: puddled transplanted rice + disc-tilled wheat = conventional in both phases; residue incorporated by disc -> CTR. FLAG: RI plots also received a cellulolytic culture spray (confounded with residue). Supplementary: none found (web search 2026-10-05; publisher site not reachable). Source file 113_rqal.pdf. [OBS RECOMPUTED 2026-10-05 (author rule): Y=1 (years of data in this row's series) + T=1 + D=1 -> Obs = 1; factors of 1 add nothing; supersedes any earlier Obs statement.] | AX4: TREATMENTS IN PAPER: strip-plot, 3 reps, 2006-07 and 2007-08, ORGANIC management. Rows = cropping system: RW (rice-wheat, summer fallow) and RWM (rice-wheat-mungbean, summer mungbean with Rhizobium + PSB); columns = residue: RR (entire above-ground biomass removed) and RI (all residue of each crop incorporated before the next crop: rice residue for wheat, wheat residue for rice in RW / for mungbean in RWM, mungbean residue for rice). Rice: field flooded and PUDDLED with tractor-drawn offset disc harrow, Pusa Basmati 1 transplanted 20 x 10 cm. Wheat: after rice harvest, residue (RI) + FYM incorporated with tractor-drawn heavy disc, then disked and planked twice; HD 2643 sown 3rd week Nov. RR -> CT, RI -> CTR (in both systems). | AY4: Core method (Veihmeyer & Hendrickson 1948), oven-dry 105 C 48 h
A5: 165 | B5: 165 | C5: Davari M.R., Sharma S.N. & Mirzakhani M. | D5: 2012 | E5: Biological Agriculture & Horticulture | F5: India (Delhi) | G5: IARI research farm, New Delhi (organic rice-based cropping systems trial) | H5: 28.633 | I5: 77.183 | J5: ST | K5: 2007-08 | L5: 0-3 Y | M5: LOAMY | N5: 0-15 CM | O5: 0-15 cm | Q5: 1.44 | V5: 1.38 | AB5: 1 | AC5: 3 | AD5: =IF(AND(N(AB5)>0,N(AC5)>0),SQRT(2*AB5/AC5),"") -> 0.81649658 | AE5: 25.4 | AI5: 28.633 | AJ5: 2 | AM5: 8.16 | AN5: 5.2 | AO5: 1.5 | AP5: 52.06 | AQ5: 22.54 | AR5: Mg/m3 | AS5: RWM-RR -> CT ; RWM-RI -> CTR | AT5: After completion of two cycles (June 2008, after wheat and mungbean) | AU5: ORGANIC: FYM equivalent to 60 kg N/ha to rice and to wheat (FYM ~0.61% N, 22-23 C:N), no mineral fertiliser; BGA 1.5 kg/ha in rice 20 DAT; Azotobacter + PSB seed inoculation of wheat; cellulolytic fungal culture 600 g/t sprayed on residue in RI plots only. RI residue added (Mg DM/ha): RW 14.2 (2006-07), 16.0 (2007-08); RWM 17.8, 19.7. Initial soil: SCL, EC 0.79 dS/m, CEC 14.73 cmol/kg, OC 5.2 g/kg, Kjeldahl N 580 mg/kg, Olsen P 8.42, NH4OAc K 187 mg/kg, BD 1.50, FC 24.57%. | AV5: Table 9 | AW5: LSD residue 0.04. GREEN MANURE / 3rd CROP: summer mungbean in BOTH treatments of this row (pods picked, residue incorporated in RI only). 15-30 cm values not printed (not significantly different). Rotation-matched: puddled transplanted rice + disc-tilled wheat = conventional in both phases; residue incorporated by disc -> CTR. FLAG: RI plots also received a cellulolytic culture spray (confounded with residue). Supplementary: none found (web search 2026-10-05; publisher site not reachable). Source file 113_rqal.pdf. [OBS RECOMPUTED 2026-10-05 (author rule): Y=1 (years of data in this row's series) + T=1 + D=1 -> Obs = 1; factors of 1 add nothing; supersedes any earlier Obs statement.] | AX5: TREATMENTS IN PAPER: strip-plot, 3 reps, 2006-07 and 2007-08, ORGANIC management. Rows = cropping system: RW (rice-wheat, summer fallow) and RWM (rice-wheat-mungbean, summer mungbean with Rhizobium + PSB); columns = residue: RR (entire above-ground biomass removed) and RI (all residue of each crop incorporated before the next crop: rice residue for wheat, wheat residue for rice in RW / for mungbean in RWM, mungbean residue for rice). Rice: field flooded and PUDDLED with tractor-drawn offset disc harrow, Pusa Basmati 1 transplanted 20 x 10 cm. Wheat: after rice harvest, residue (RI) + FYM incorporated with tractor-drawn heavy disc, then disked and planked twice; HD 2643 sown 3rd week Nov. RR -> CT, RI -> CTR (in both systems). | AY5: Core method (Veihmeyer & Hendrickson 1948), oven-dry 105 C 48 h
A6: 131 (companion) | B6: 131 (companion) | C6: Zhang Y.-P., Li X., He H.-J., Zhou H., Geng D.-Y. & Zhang Y.-Z. | D6: 2023 | E6: Sustainability | F6: China (Shandong) | G6: Taoluo Town, Donggang District, Rizhao, Shandong | H6: 35.27 | I6: 119.38 | J6: TEMP | K6: 2018 | L6: 0-3 Y | N6: 0-15 CM | O6: 0-10 cm | P6: 1.374 | X6: 1.395 | AB6: 3 | AC6: 3 | AD6: =IF(AND(N(AB6)>0,N(AC6)>0),SQRT(2*AB6/AC6),"") -> 1.4142136 | AH6: 916 | AI6: 35.27 | AJ6: 1 | AK6: 12.6 | AM6: 6.8 | AN6: 5.75 | AO6: 1.423 | AR6: Mg/m3 | AS6: CN (NT dry DSR + NT wheat, straw returned) -> CA ; PR (plough + rotary + puddled transplanted rice, NT wheat, straw returned) -> pCA ; RT -> EXCLUDED | AT6: Wheat season - after the 2018 wheat harvest (ring knife 100 cm3) | AU6: Rice: 600 kg/ha slow-release 25-10-10 (deep-placed at sowing in CN; at ploughing in PR) + 300 kg/ha compound 53-10-30 later; KH2PO4 0.3% foliar x2. Wheat: N 225, P2O5 180, K2O 25 kg/ha deep-placed at sowing (all). Rice Linhan 1 (125 d), 127.5 kg seed/ha in 12 cm wide belts (CN); PR transplanted 10 July. CN: intermittent / alternate wet-dry irrigation; PR: traditional flooding. Paddy soil; initial TN 0.95 g/kg, alkali-N 82.43, Olsen P 34.30, K 73.10 mg/kg (0-30 cm), BD 1.423. | AV6: Fig. 3 (digitised) | AW6: Year-wise (rule 37). DIGITISED from Fig. 3a; 2020 values reproduce the printed differences (0-10 cm RT 0.037/0.064 below CN/PR; 20-30 cm 0.056/0.051). 2017 point = before the first treated rice (all ~equal), not entered. RT (excluded) 2018-2020: 1.377/1.378/1.345. RE-ENTRY of old-master study 131 (excluded there 2026-10-04 as a rotation mismatch); re-evaluated under the PARTIAL-CA rule (rule 68): PR = puddled transplanted rice + no-till wheat with straw -> pCA, CN -> CA. FLAG: UNREPLICATED (one strip per pattern, multi-point sampling) - Rep kept 3 by rule. Coordinates approximate (Taoluo town centre; paper gives none). Texture not stated (paddy soil). Supplementary: none found. Source file 114_reqal.pdf. [OBS RECOMPUTED 2026-10-05 (author rule): Y=3 (years of data in this row's series) + T=1 + D=1 -> Obs = 3; factors of 1 add nothing; supersedes any earlier Obs statement.] | AX6: TREATMENTS IN PAPER (one 960 m2 strip per pattern, 2017-2019 rice seasons, Taoluo, Rizhao): RT = rotational tillage before rice (no-till 2017 and 2018, plough 2019; no-till dry direct-seeded rice) -> EXCLUDED (alternate tillage); CN = continuous no-till dry direct-seeded rice (wide-belt stubble seeder) 2017-2019 -> CA ; PR = plough + rotary tillage, irrigation, puddling and transplanting (30 x 12 cm) every year -> pCA. In ALL treatments wheat (Yannong 21, 187.5 kg/ha, 14 Oct) is sown WITHOUT tillage with the same seeder, and the crushed straw (<=10 cm) of the previous crop is fully returned. Before the trial: ploughing + rotary 15-18 cm, transplanting, straw removed. | AY6: Ring-knife (100 cm3) drying-weighing method
A7: 131 (companion) | B7: 131 (companion) | C7: Zhang Y.-P., Li X., He H.-J., Zhou H., Geng D.-Y. & Zhang Y.-Z. | D7: 2023 | E7: Sustainability | F7: China (Shandong) | G7: Taoluo Town, Donggang District, Rizhao, Shandong | H7: 35.27 | I7: 119.38 | J7: TEMP | K7: 2019 | L7: 0-3 Y | N7: 0-15 CM | O7: 0-10 cm | P7: 1.376 | X7: 1.397 | AB7: 3 | AC7: 3 | AD7: =IF(AND(N(AB7)>0,N(AC7)>0),SQRT(2*AB7/AC7),"") -> 1.4142136 | AH7: 916 | AI7: 35.27 | AJ7: 2 | AK7: 12.6 | AM7: 6.8 | AN7: 5.75 | AO7: 1.423 | AR7: Mg/m3 | AS7: CN (NT dry DSR + NT wheat, straw returned) -> CA ; PR (plough + rotary + puddled transplanted rice, NT wheat, straw returned) -> pCA ; RT -> EXCLUDED | AT7: Wheat season - after the 2019 wheat harvest (ring knife 100 cm3) | AU7: Rice: 600 kg/ha slow-release 25-10-10 (deep-placed at sowing in CN; at ploughing in PR) + 300 kg/ha compound 53-10-30 later; KH2PO4 0.3% foliar x2. Wheat: N 225, P2O5 180, K2O 25 kg/ha deep-placed at sowing (all). Rice Linhan 1 (125 d), 127.5 kg seed/ha in 12 cm wide belts (CN); PR transplanted 10 July. CN: intermittent / alternate wet-dry irrigation; PR: traditional flooding. Paddy soil; initial TN 0.95 g/kg, alkali-N 82.43, Olsen P 34.30, K 73.10 mg/kg (0-30 cm), BD 1.423. | AV7: Fig. 3 (digitised) | AW7: Year-wise (rule 37). DIGITISED from Fig. 3a; 2020 values reproduce the printed differences (0-10 cm RT 0.037/0.064 below CN/PR; 20-30 cm 0.056/0.051). 2017 point = before the first treated rice (all ~equal), not entered. RT (excluded) 2018-2020: 1.377/1.378/1.345. RE-ENTRY of old-master study 131 (excluded there 2026-10-04 as a rotation mismatch); re-evaluated under the PARTIAL-CA rule (rule 68): PR = puddled transplanted rice + no-till wheat with straw -> pCA, CN -> CA. FLAG: UNREPLICATED (one strip per pattern, multi-point sampling) - Rep kept 3 by rule. Coordinates approximate (Taoluo town centre; paper gives none). Texture not stated (paddy soil). Supplementary: none found. Source file 114_reqal.pdf. [OBS RECOMPUTED 2026-10-05 (author rule): Y=3 (years of data in this row's series) + T=1 + D=1 -> Obs = 3; factors of 1 add nothing; supersedes any earlier Obs statement.] | AX7: TREATMENTS IN PAPER (one 960 m2 strip per pattern, 2017-2019 rice seasons, Taoluo, Rizhao): RT = rotational tillage before rice (no-till 2017 and 2018, plough 2019; no-till dry direct-seeded rice) -> EXCLUDED (alternate tillage); CN = continuous no-till dry direct-seeded rice (wide-belt stubble seeder) 2017-2019 -> CA ; PR = plough + rotary tillage, irrigation, puddling and transplanting (30 x 12 cm) every year -> pCA. In ALL treatments wheat (Yannong 21, 187.5 kg/ha, 14 Oct) is sown WITHOUT tillage with the same seeder, and the crushed straw (<=10 cm) of the previous crop is fully returned. Before the trial: ploughing + rotary 15-18 cm, transplanting, straw removed. | AY7: Ring-knife (100 cm3) drying-weighing method
A8: 131 (companion) | B8: 131 (companion) | C8: Zhang Y.-P., Li X., He H.-J., Zhou H., Geng D.-Y. & Zhang Y.-Z. | D8: 2023 | E8: Sustainability | F8: China (Shandong) | G8: Taoluo Town, Donggang District, Rizhao, Shandong | H8: 35.27 | I8: 119.38 | J8: TEMP | K8: 2020 | L8: 0-3 Y | N8: 0-15 CM | O8: 0-10 cm | P8: 1.382 | X8: 1.408 | AB8: 3 | AC8: 3 | AD8: =IF(AND(N(AB8)>0,N(AC8)>0),SQRT(2*AB8/AC8),"") -> 1.4142136 | AH8: 916 | AI8: 35.27 | AJ8: 3 | AK8: 12.6 | AM8: 6.8 | AN8: 5.75 | AO8: 1.423 | AR8: Mg/m3 | AS8: CN (NT dry DSR + NT wheat, straw returned) -> CA ; PR (plough + rotary + puddled transplanted rice, NT wheat, straw returned) -> pCA ; RT -> EXCLUDED | AT8: Wheat season - after the 2020 wheat harvest (ring knife 100 cm3) | AU8: Rice: 600 kg/ha slow-release 25-10-10 (deep-placed at sowing in CN; at ploughing in PR) + 300 kg/ha compound 53-10-30 later; KH2PO4 0.3% foliar x2. Wheat: N 225, P2O5 180, K2O 25 kg/ha deep-placed at sowing (all). Rice Linhan 1 (125 d), 127.5 kg seed/ha in 12 cm wide belts (CN); PR transplanted 10 July. CN: intermittent / alternate wet-dry irrigation; PR: traditional flooding. Paddy soil; initial TN 0.95 g/kg, alkali-N 82.43, Olsen P 34.30, K 73.10 mg/kg (0-30 cm), BD 1.423. | AV8: Fig. 3 (digitised) | AW8: Year-wise (rule 37). DIGITISED from Fig. 3a; 2020 values reproduce the printed differences (0-10 cm RT 0.037/0.064 below CN/PR; 20-30 cm 0.056/0.051). 2017 point = before the first treated rice (all ~equal), not entered. RT (excluded) 2018-2020: 1.377/1.378/1.345. RE-ENTRY of old-master study 131 (excluded there 2026-10-04 as a rotation mismatch); re-evaluated under the PARTIAL-CA rule (rule 68): PR = puddled transplanted rice + no-till wheat with straw -> pCA, CN -> CA. FLAG: UNREPLICATED (one strip per pattern, multi-point sampling) - Rep kept 3 by rule. Coordinates approximate (Taoluo town centre; paper gives none). Texture not stated (paddy soil). Supplementary: none found. Source file 114_reqal.pdf. [OBS RECOMPUTED 2026-10-05 (author rule): Y=3 (years of data in this row's series) + T=1 + D=1 -> Obs = 3; factors of 1 add nothing; supersedes any earlier Obs statement.] | AX8: TREATMENTS IN PAPER (one 960 m2 strip per pattern, 2017-2019 rice seasons, Taoluo, Rizhao): RT = rotational tillage before rice (no-till 2017 and 2018, plough 2019; no-till dry direct-seeded rice) -> EXCLUDED (alternate tillage); CN = continuous no-till dry direct-seeded rice (wide-belt stubble seeder) 2017-2019 -> CA ; PR = plough + rotary tillage, irrigation, puddling and transplanting (30 x 12 cm) every year -> pCA. In ALL treatments wheat (Yannong 21, 187.5 kg/ha, 14 Oct) is sown WITHOUT tillage with the same seeder, and the crushed straw (<=10 cm) of the previous crop is fully returned. Before the trial: ploughing + rotary 15-18 cm, transplanting, straw removed. | AY8: Ring-knife (100 cm3) drying-weighing method
A9: 131 (companion) | B9: 131 (companion) | C9: Zhang Y.-P., Li X., He H.-J., Zhou H., Geng D.-Y. & Zhang Y.-Z. | D9: 2023 | E9: Sustainability | F9: China (Shandong) | G9: Taoluo Town, Donggang District, Rizhao, Shandong | H9: 35.27 | I9: 119.38 | J9: TEMP | K9: 2018 | L9: 0-3 Y | N9: 15-30 CM | O9: 10-20 cm | P9: 1.421 | X9: 1.434 | AB9: 5 | AC9: 3 | AD9: =IF(AND(N(AB9)>0,N(AC9)>0),SQRT(2*AB9/AC9),"") -> 1.8257419 | AH9: 916 | AI9: 35.27 | AJ9: 1 | AK9: 12.6 | AM9: 6.8 | AN9: 5.75 | AO9: 1.423 | AR9: Mg/m3 | AS9: CN (NT dry DSR + NT wheat, straw returned) -> CA ; PR (plough + rotary + puddled transplanted rice, NT wheat, straw returned) -> pCA ; RT -> EXCLUDED | AT9: Wheat season - after the 2018 wheat harvest (ring knife 100 cm3) | AU9: Rice: 600 kg/ha slow-release 25-10-10 (deep-placed at sowing in CN; at ploughing in PR) + 300 kg/ha compound 53-10-30 later; KH2PO4 0.3% foliar x2. Wheat: N 225, P2O5 180, K2O 25 kg/ha deep-placed at sowing (all). Rice Linhan 1 (125 d), 127.5 kg seed/ha in 12 cm wide belts (CN); PR transplanted 10 July. CN: intermittent / alternate wet-dry irrigation; PR: traditional flooding. Paddy soil; initial TN 0.95 g/kg, alkali-N 82.43, Olsen P 34.30, K 73.10 mg/kg (0-30 cm), BD 1.423. | AV9: Fig. 3 (digitised) | AW9: Year-wise (rule 37). DIGITISED from Fig. 3b; 2020 values reproduce the printed differences (0-10 cm RT 0.037/0.064 below CN/PR; 20-30 cm 0.056/0.051). 2017 point = before the first treated rice (all ~equal), not entered. RT (excluded) 2018-2020: 1.420/1.416/1.412. RE-ENTRY of old-master study 131 (excluded there 2026-10-04 as a rotation mismatch); re-evaluated under the PARTIAL-CA rule (rule 68): PR = puddled transplanted rice + no-till wheat with straw -> pCA, CN -> CA. FLAG: UNREPLICATED (one strip per pattern, multi-point sampling) - Rep kept 3 by rule. Coordinates approximate (Taoluo town centre; paper gives none). Texture not stated (paddy soil). Supplementary: none found. Source file 114_reqal.pdf. [OBS RECOMPUTED 2026-10-05 (author rule): Y=3 (years of data in this row's series) + T=1 + D=2 -> Obs = 5; factors of 1 add nothing; supersedes any earlier Obs statement.] | AX9: TREATMENTS IN PAPER (one 960 m2 strip per pattern, 2017-2019 rice seasons, Taoluo, Rizhao): RT = rotational tillage before rice (no-till 2017 and 2018, plough 2019; no-till dry direct-seeded rice) -> EXCLUDED (alternate tillage); CN = continuous no-till dry direct-seeded rice (wide-belt stubble seeder) 2017-2019 -> CA ; PR = plough + rotary tillage, irrigation, puddling and transplanting (30 x 12 cm) every year -> pCA. In ALL treatments wheat (Yannong 21, 187.5 kg/ha, 14 Oct) is sown WITHOUT tillage with the same seeder, and the crushed straw (<=10 cm) of the previous crop is fully returned. Before the trial: ploughing + rotary 15-18 cm, transplanting, straw removed. | AY9: Ring-knife (100 cm3) drying-weighing method
